arithmetic/HalfAdder.v
module HalfAdder (
    input a, b,
    output sum, carry
);
    
    assign sum = a ^ b;
    assign carry = a & b;

endmodule

arithmetic/FullAdder.v
`include "HalfAdder.v"

module FullAdder (
    input a, b, c,
    output sum, carry
);

    wire bAddCSum, bAddCCarry;
    wire aAddBAddCCarry;

    HalfAdder halfAdder1 (.a(b), .b(c), .sum(bAddCSum), .carry(bAddCCarry));
    HalfAdder halfAdder2 (.a(a), .b(bAddCSum), .sum(sum), .carry(aAddBAddCCarry));

    assign carry = bAddCCarry ^ aAddBAddCCarry;
endmodule

arithmetic/Adder16.v
`include "FullAdder.v"

module Adder16 (
	input [15:0] i1, i2,
	output [15:0] o
);

	wire wCarry [0:15];

	genvar gCounter;
	generate
		for (gCounter = 0; gCounter < 16; gCounter = gCounter + 1) begin
			if (gCounter == 0) begin
				HalfAdder halfAdder (.a(i1[gCounter]), .b(i2[gCounter]), .sum(o[gCounter]), .carry(wCarry[gCounter])); 
			end else begin
				FullAdder fullAdder (.a(i1[gCounter]), .b(i2[gCounter]), .c(wCarry[gCounter-1]), .sum(o[gCounter]), .carry(wCarry[gCounter]));
			end
		end
	endgenerate
	
endmodule

arithmetic/Adder16_tb.v
`include "Adder16.v"

module Adder16_tb;

    reg [15:0] i1 = 0, i2 = 0;
    wire [15:0] out;

    Adder16 adder16 (.i1(i1), .i2(i2), .o(out));

    initial begin
        $dumpfile("Adder16.vcd");
        $dumpvars(0, Adder16_tb);

        #1000 $finish;
    end

    always begin
        #1
        i1 = i1 + 1;
    end

    always begin
        #2
        i2 = i2 + 1;
    end
    
endmodule

arithmetic/Adder16.vcd
$date
	Sun Aug 27 14:10:59 2023
$end
$version
	Icarus Verilog
$end
$timescale
	1s
$end
$scope module Adder16_tb $end
$var wire 16 ! out [15:0] $end
$var reg 16 " i1 [15:0] $end
$var reg 16 # i2 [15:0] $end
$scope module adder16 $end
$var wire 16 $ i1 [15:0] $end
$var wire 16 % i2 [15:0] $end
$var wire 16 & o [15:0] $end
$scope begin genblk1[0] $end
$var parameter 2 ' gCounter $end
$scope begin genblk1 $end
$scope module halfAdder $end
$var wire 1 ( a $end
$var wire 1 ) b $end
$var wire 1 * carry $end
$var wire 1 + sum $end
$upscope $end
$upscope $end
$upscope $end
$scope begin genblk1[1] $end
$var parameter 2 , gCounter $end
$scope begin genblk1 $end
$scope module fullAdder $end
$var wire 1 - a $end
$var wire 1 . b $end
$var wire 1 * c $end
$var wire 1 / carry $end
$var wire 1 0 sum $end
$var wire 1 1 bAddCSum $end
$var wire 1 2 bAddCCarry $end
$var wire 1 3 aAddBAddCCarry $end
$scope module halfAdder1 $end
$var wire 1 . a $end
$var wire 1 * b $end
$var wire 1 2 carry $end
$var wire 1 1 sum $end
$upscope $end
$scope module halfAdder2 $end
$var wire 1 - a $end
$var wire 1 1 b $end
$var wire 1 3 carry $end
$var wire 1 0 sum $end
$upscope $end
$upscope $end
$upscope $end
$upscope $end
$scope begin genblk1[2] $end
$var parameter 3 4 gCounter $end
$scope begin genblk1 $end
$scope module fullAdder $end
$var wire 1 5 a $end
$var wire 1 6 b $end
$var wire 1 / c $end
$var wire 1 7 carry $end
$var wire 1 8 sum $end
$var wire 1 9 bAddCSum $end
$var wire 1 : bAddCCarry $end
$var wire 1 ; aAddBAddCCarry $end
$scope module halfAdder1 $end
$var wire 1 6 a $end
$var wire 1 / b $end
$var wire 1 : carry $end
$var wire 1 9 sum $end
$upscope $end
$scope module halfAdder2 $end
$var wire 1 5 a $end
$var wire 1 9 b $end
$var wire 1 ; carry $end
$var wire 1 8 sum $end
$upscope $end
$upscope $end
$upscope $end
$upscope $end
$scope begin genblk1[3] $end
$var parameter 3 < gCounter $end
$scope begin genblk1 $end
$scope module fullAdder $end
$var wire 1 = a $end
$var wire 1 > b $end
$var wire 1 7 c $end
$var wire 1 ? carry $end
$var wire 1 @ sum $end
$var wire 1 A bAddCSum $end
$var wire 1 B bAddCCarry $end
$var wire 1 C aAddBAddCCarry $end
$scope module halfAdder1 $end
$var wire 1 > a $end
$var wire 1 7 b $end
$var wire 1 B carry $end
$var wire 1 A sum $end
$upscope $end
$scope module halfAdder2 $end
$var wire 1 = a $end
$var wire 1 A b $end
$var wire 1 C carry $end
$var wire 1 @ sum $end
$upscope $end
$upscope $end
$upscope $end
$upscope $end
$scope begin genblk1[4] $end
$var parameter 4 D gCounter $end
$scope begin genblk1 $end
$scope module fullAdder $end
$var wire 1 E a $end
$var wire 1 F b $end
$var wire 1 ? c $end
$var wire 1 G carry $end
$var wire 1 H sum $end
$var wire 1 I bAddCSum $end
$var wire 1 J bAddCCarry $end
$var wire 1 K aAddBAddCCarry $end
$scope module halfAdder1 $end
$var wire 1 F a $end
$var wire 1 ? b $end
$var wire 1 J carry $end
$var wire 1 I sum $end
$upscope $end
$scope module halfAdder2 $end
$var wire 1 E a $end
$var wire 1 I b $end
$var wire 1 K carry $end
$var wire 1 H sum $end
$upscope $end
$upscope $end
$upscope $end
$upscope $end
$scope begin genblk1[5] $end
$var parameter 4 L gCounter $end
$scope begin genblk1 $end
$scope module fullAdder $end
$var wire 1 M a $end
$var wire 1 N b $end
$var wire 1 G c $end
$var wire 1 O carry $end
$var wire 1 P sum $end
$var wire 1 Q bAddCSum $end
$var wire 1 R bAddCCarry $end
$var wire 1 S aAddBAddCCarry $end
$scope module halfAdder1 $end
$var wire 1 N a $end
$var wire 1 G b $end
$var wire 1 R carry $end
$var wire 1 Q sum $end
$upscope $end
$scope module halfAdder2 $end
$var wire 1 M a $end
$var wire 1 Q b $end
$var wire 1 S carry $end
$var wire 1 P sum $end
$upscope $end
$upscope $end
$upscope $end
$upscope $end
$scope begin genblk1[6] $end
$var parameter 4 T gCounter $end
$scope begin genblk1 $end
$scope module fullAdder $end
$var wire 1 U a $end
$var wire 1 V b $end
$var wire 1 O c $end
$var wire 1 W carry $end
$var wire 1 X sum $end
$var wire 1 Y bAddCSum $end
$var wire 1 Z bAddCCarry $end
$var wire 1 [ aAddBAddCCarry $end
$scope module halfAdder1 $end
$var wire 1 V a $end
$var wire 1 O b $end
$var wire 1 Z carry $end
$var wire 1 Y sum $end
$upscope $end
$scope module halfAdder2 $end
$var wire 1 U a $end
$var wire 1 Y b $end
$var wire 1 [ carry $end
$var wire 1 X sum $end
$upscope $end
$upscope $end
$upscope $end
$upscope $end
$scope begin genblk1[7] $end
$var parameter 4 \ gCounter $end
$scope begin genblk1 $end
$scope module fullAdder $end
$var wire 1 ] a $end
$var wire 1 ^ b $end
$var wire 1 W c $end
$var wire 1 _ carry $end
$var wire 1 ` sum $end
$var wire 1 a bAddCSum $end
$var wire 1 b bAddCCarry $end
$var wire 1 c aAddBAddCCarry $end
$scope module halfAdder1 $end
$var wire 1 ^ a $end
$var wire 1 W b $end
$var wire 1 b carry $end
$var wire 1 a sum $end
$upscope $end
$scope module halfAdder2 $end
$var wire 1 ] a $end
$var wire 1 a b $end
$var wire 1 c carry $end
$var wire 1 ` sum $end
$upscope $end
$upscope $end
$upscope $end
$upscope $end
$scope begin genblk1[8] $end
$var parameter 5 d gCounter $end
$scope begin genblk1 $end
$scope module fullAdder $end
$var wire 1 e a $end
$var wire 1 f b $end
$var wire 1 _ c $end
$var wire 1 g carry $end
$var wire 1 h sum $end
$var wire 1 i bAddCSum $end
$var wire 1 j bAddCCarry $end
$var wire 1 k aAddBAddCCarry $end
$scope module halfAdder1 $end
$var wire 1 f a $end
$var wire 1 _ b $end
$var wire 1 j carry $end
$var wire 1 i sum $end
$upscope $end
$scope module halfAdder2 $end
$var wire 1 e a $end
$var wire 1 i b $end
$var wire 1 k carry $end
$var wire 1 h sum $end
$upscope $end
$upscope $end
$upscope $end
$upscope $end
$scope begin genblk1[9] $end
$var parameter 5 l gCounter $end
$scope begin genblk1 $end
$scope module fullAdder $end
$var wire 1 m a $end
$var wire 1 n b $end
$var wire 1 g c $end
$var wire 1 o carry $end
$var wire 1 p sum $end
$var wire 1 q bAddCSum $end
$var wire 1 r bAddCCarry $end
$var wire 1 s aAddBAddCCarry $end
$scope module halfAdder1 $end
$var wire 1 n a $end
$var wire 1 g b $end
$var wire 1 r carry $end
$var wire 1 q sum $end
$upscope $end
$scope module halfAdder2 $end
$var wire 1 m a $end
$var wire 1 q b $end
$var wire 1 s carry $end
$var wire 1 p sum $end
$upscope $end
$upscope $end
$upscope $end
$upscope $end
$scope begin genblk1[10] $end
$var parameter 5 t gCounter $end
$scope begin genblk1 $end
$scope module fullAdder $end
$var wire 1 u a $end
$var wire 1 v b $end
$var wire 1 o c $end
$var wire 1 w carry $end
$var wire 1 x sum $end
$var wire 1 y bAddCSum $end
$var wire 1 z bAddCCarry $end
$var wire 1 { aAddBAddCCarry $end
$scope module halfAdder1 $end
$var wire 1 v a $end
$var wire 1 o b $end
$var wire 1 z carry $end
$var wire 1 y sum $end
$upscope $end
$scope module halfAdder2 $end
$var wire 1 u a $end
$var wire 1 y b $end
$var wire 1 { carry $end
$var wire 1 x sum $end
$upscope $end
$upscope $end
$upscope $end
$upscope $end
$scope begin genblk1[11] $end
$var parameter 5 | gCounter $end
$scope begin genblk1 $end
$scope module fullAdder $end
$var wire 1 } a $end
$var wire 1 ~ b $end
$var wire 1 w c $end
$var wire 1 !" carry $end
$var wire 1 "" sum $end
$var wire 1 #" bAddCSum $end
$var wire 1 $" bAddCCarry $end
$var wire 1 %" aAddBAddCCarry $end
$scope module halfAdder1 $end
$var wire 1 ~ a $end
$var wire 1 w b $end
$var wire 1 $" carry $end
$var wire 1 #" sum $end
$upscope $end
$scope module halfAdder2 $end
$var wire 1 } a $end
$var wire 1 #" b $end
$var wire 1 %" carry $end
$var wire 1 "" sum $end
$upscope $end
$upscope $end
$upscope $end
$upscope $end
$scope begin genblk1[12] $end
$var parameter 5 &" gCounter $end
$scope begin genblk1 $end
$scope module fullAdder $end
$var wire 1 '" a $end
$var wire 1 (" b $end
$var wire 1 !" c $end
$var wire 1 )" carry $end
$var wire 1 *" sum $end
$var wire 1 +" bAddCSum $end
$var wire 1 ," bAddCCarry $end
$var wire 1 -" aAddBAddCCarry $end
$scope module halfAdder1 $end
$var wire 1 (" a $end
$var wire 1 !" b $end
$var wire 1 ," carry $end
$var wire 1 +" sum $end
$upscope $end
$scope module halfAdder2 $end
$var wire 1 '" a $end
$var wire 1 +" b $end
$var wire 1 -" carry $end
$var wire 1 *" sum $end
$upscope $end
$upscope $end
$upscope $end
$upscope $end
$scope begin genblk1[13] $end
$var parameter 5 ." gCounter $end
$scope begin genblk1 $end
$scope module fullAdder $end
$var wire 1 /" a $end
$var wire 1 0" b $end
$var wire 1 )" c $end
$var wire 1 1" carry $end
$var wire 1 2" sum $end
$var wire 1 3" bAddCSum $end
$var wire 1 4" bAddCCarry $end
$var wire 1 5" aAddBAddCCarry $end
$scope module halfAdder1 $end
$var wire 1 0" a $end
$var wire 1 )" b $end
$var wire 1 4" carry $end
$var wire 1 3" sum $end
$upscope $end
$scope module halfAdder2 $end
$var wire 1 /" a $end
$var wire 1 3" b $end
$var wire 1 5" carry $end
$var wire 1 2" sum $end
$upscope $end
$upscope $end
$upscope $end
$upscope $end
$scope begin genblk1[14] $end
$var parameter 5 6" gCounter $end
$scope begin genblk1 $end
$scope module fullAdder $end
$var wire 1 7" a $end
$var wire 1 8" b $end
$var wire 1 1" c $end
$var wire 1 9" carry $end
$var wire 1 :" sum $end
$var wire 1 ;" bAddCSum $end
$var wire 1 <" bAddCCarry $end
$var wire 1 =" aAddBAddCCarry $end
$scope module halfAdder1 $end
$var wire 1 8" a $end
$var wire 1 1" b $end
$var wire 1 <" carry $end
$var wire 1 ;" sum $end
$upscope $end
$scope module halfAdder2 $end
$var wire 1 7" a $end
$var wire 1 ;" b $end
$var wire 1 =" carry $end
$var wire 1 :" sum $end
$upscope $end
$upscope $end
$upscope $end
$upscope $end
$scope begin genblk1[15] $end
$var parameter 5 >" gCounter $end
$scope begin genblk1 $end
$scope module fullAdder $end
$var wire 1 ?" a $end
$var wire 1 @" b $end
$var wire 1 9" c $end
$var wire 1 A" carry $end
$var wire 1 B" sum $end
$var wire 1 C" bAddCSum $end
$var wire 1 D" bAddCCarry $end
$var wire 1 E" aAddBAddCCarry $end
$scope module halfAdder1 $end
$var wire 1 @" a $end
$var wire 1 9" b $end
$var wire 1 D" carry $end
$var wire 1 C" sum $end
$upscope $end
$scope module halfAdder2 $end
$var wire 1 ?" a $end
$var wire 1 C" b $end
$var wire 1 E" carry $end
$var wire 1 B" sum $end
$upscope $end
$upscope $end
$upscope $end
$upscope $end
$upscope $end
$upscope $end
$enddefinitions $end
$comment Show the parameter values. $end
$dumpall
b1111 >"
b1110 6"
b1101 ."
b1100 &"
b1011 |
b1010 t
b1001 l
b1000 d
b111 \
b110 T
b101 L
b100 D
b11 <
b10 4
b1 ,
b0 '
$end
#0
$dumpvars
0E"
0D"
0C"
0B"
0A"
0@"
0?"
0="
0<"
0;"
0:"
09"
08"
07"
05"
04"
03"
02"
01"
00"
0/"
0-"
0,"
0+"
0*"
0)"
0("
0'"
0%"
0$"
0#"
0""
0!"
0~
0}
0{
0z
0y
0x
0w
0v
0u
0s
0r
0q
0p
0o
0n
0m
0k
0j
0i
0h
0g
0f
0e
0c
0b
0a
0`
0_
0^
0]
0[
0Z
0Y
0X
0W
0V
0U
0S
0R
0Q
0P
0O
0N
0M
0K
0J
0I
0H
0G
0F
0E
0C
0B
0A
0@
0?
0>
0=
0;
0:
09
08
07
06
05
03
02
01
00
0/
0.
0-
0+
0*
0)
0(
b0 &
b0 %
b0 $
b0 #
b0 "
b0 !
$end
#1
b1 !
b1 &
1+
1(
b1 "
b1 $
#2
b11 !
b11 &
10
0(
1-
1)
b10 "
b10 $
b1 #
b1 %
#3
18
19
1/
00
13
11
b100 !
b100 &
0+
1*
1(
b11 "
b11 $
#4
0@
09
0A
10
0/
07
03
b110 !
b110 &
18
0;
0*
11
02
0(
0-
15
0)
1.
b100 "
b100 $
b10 #
b10 %
#5
b111 !
b111 &
1+
1(
b101 "
b101 $
#6
1@
1A
17
08
1;
19
1/
b1001 !
b1001 &
00
13
0(
1-
1)
b110 "
b110 $
b11 #
b11 %
#7
1@
1A
17
08
1;
19
10
03
1/
01
12
b1010 !
b1010 &
0+
1*
1(
b111 "
b111 $
#8
0A
0H
18
07
0I
00
0?
0/
0;
b1100 !
b1100 &
1@
0C
0*
01
02
19
0:
0(
0-
05
1=
0)
0.
16
b1000 "
b1000 $
b100 #
b100 %
#9
b1101 !
b1101 &
1+
1(
b1001 "
b1001 $
#10
b1111 !
b1111 &
10
0(
1-
1)
b1010 "
b1010 $
b101 #
b101 %
#11
1H
1I
1?
0@
1C
1A
08
17
09
1:
1/
00
13
11
b10000 !
b10000 &
0+
1*
1(
b1011 "
b1011 $
#12
1H
1I
1?
0@
1C
1A
1;
17
19
0:
10
0/
03
b10010 !
b10010 &
08
0*
11
02
0(
0-
15
0)
1.
b1100 "
b1100 $
b110 #
b110 %
#13
b10011 !
b10011 &
1+
1(
b1101 "
b1101 $
#14
1H
1I
1?
0@
1C
1A
18
0;
17
09
1:
1/
b10101 !
b10101 &
00
13
0(
1-
1)
b1110 "
b1110 $
b111 #
b111 %
#15
1H
1I
1?
0@
1C
1A
18
0;
17
09
1:
10
03
1/
01
12
b10110 !
b10110 &
0+
1*
1(
b1111 "
b1111 $
#16
0I
0P
08
1@
0?
0Q
00
0G
0/
07
0C
b11000 !
b11000 &
1H
0K
0*
01
02
09
0:
1A
0B
0(
0-
05
0=
1E
0)
0.
06
1>
b10000 "
b10000 $
b1000 #
b1000 %
#17
b11001 !
b11001 &
1+
1(
b10001 "
b10001 $
#18
b11011 !
b11011 &
10
0(
1-
1)
b10010 "
b10010 $
b1001 #
b1001 %
#19
18
19
1/
00
13
11
b11100 !
b11100 &
0+
1*
1(
b10011 "
b10011 $
#20
0P
0Q
0G
1H
0K
0I
1@
0?
09
1A
0B
10
0/
07
03
b11110 !
b11110 &
18
0;
0*
11
02
0(
0-
15
0)
1.
b10100 "
b10100 $
b1010 #
b1010 %
#21
b11111 !
b11111 &
1+
1(
b10101 "
b10101 $
#22
1P
1Q
1G
0H
1K
1I
0@
1?
0A
1B
17
08
1;
19
1/
b100001 !
b100001 &
00
13
0(
1-
1)
b10110 "
b10110 $
b1011 #
b1011 %
#23
1P
1Q
1G
0H
1K
1I
0@
1?
0A
1B
17
08
1;
19
10
03
1/
01
12
b100010 !
b100010 &
0+
1*
1(
b10111 "
b10111 $
#24
1P
1Q
1G
0H
1K
1I
1C
1?
1A
0B
18
07
00
0/
0;
b100100 !
b100100 &
0@
0*
01
02
19
0:
0(
0-
05
1=
0)
0.
16
b11000 "
b11000 $
b1100 #
b1100 %
#25
b100101 !
b100101 &
1+
1(
b11001 "
b11001 $
#26
b100111 !
b100111 &
10
0(
1-
1)
b11010 "
b11010 $
b1101 #
b1101 %
#27
1P
1Q
1G
0H
1K
1I
1@
0C
1?
0A
1B
08
17
09
1:
1/
00
13
11
b101000 !
b101000 &
0+
1*
1(
b11011 "
b11011 $
#28
1P
1Q
1G
0H
1K
1I
1@
0C
1?
0A
1B
1;
17
19
0:
10
0/
03
b101010 !
b101010 &
08
0*
11
02
0(
0-
15
0)
1.
b11100 "
b11100 $
b1110 #
b1110 %
#29
b101011 !
b101011 &
1+
1(
b11101 "
b11101 $
#30
1P
1Q
1G
0H
1K
1I
1@
0C
1?
0A
1B
18
0;
17
09
1:
1/
b101101 !
b101101 &
00
13
0(
1-
1)
b11110 "
b11110 $
b1111 #
b1111 %
#31
1P
1Q
1G
0H
1K
1I
1@
0C
1?
0A
1B
18
0;
17
09
1:
10
03
1/
01
12
b101110 !
b101110 &
0+
1*
1(
b11111 "
b11111 $
#32
0Q
0X
08
0@
1H
0G
0Y
00
0O
0/
07
0?
0K
b110000 !
b110000 &
1P
0S
0*
01
02
09
0:
0A
0B
1I
0J
0(
0-
05
0=
0E
1M
0)
0.
06
0>
1F
b100000 "
b100000 $
b10000 #
b10000 %
#33
b110001 !
b110001 &
1+
1(
b100001 "
b100001 $
#34
b110011 !
b110011 &
10
0(
1-
1)
b100010 "
b100010 $
b10001 #
b10001 %
#35
18
19
1/
00
13
11
b110100 !
b110100 &
0+
1*
1(
b100011 "
b100011 $
#36
0@
09
0A
10
0/
07
03
b110110 !
b110110 &
18
0;
0*
11
02
0(
0-
15
0)
1.
b100100 "
b100100 $
b10010 #
b10010 %
#37
b110111 !
b110111 &
1+
1(
b100101 "
b100101 $
#38
1@
1A
17
08
1;
19
1/
b111001 !
b111001 &
00
13
0(
1-
1)
b100110 "
b100110 $
b10011 #
b10011 %
#39
1@
1A
17
08
1;
19
10
03
1/
01
12
b111010 !
b111010 &
0+
1*
1(
b100111 "
b100111 $
#40
0X
0Y
0O
1P
0S
0Q
0A
1H
0G
18
07
1I
0J
00
0?
0/
0;
b111100 !
b111100 &
1@
0C
0*
01
02
19
0:
0(
0-
05
1=
0)
0.
16
b101000 "
b101000 $
b10100 #
b10100 %
#41
b111101 !
b111101 &
1+
1(
b101001 "
b101001 $
#42
b111111 !
b111111 &
10
0(
1-
1)
b101010 "
b101010 $
b10101 #
b10101 %
#43
1X
1Y
1O
0P
1S
1Q
0H
1G
0I
1J
1?
0@
1C
1A
08
17
09
1:
1/
00
13
11
b1000000 !
b1000000 &
0+
1*
1(
b101011 "
b101011 $
#44
1X
1Y
1O
0P
1S
1Q
0H
1G
0I
1J
1?
0@
1C
1A
1;
17
19
0:
10
0/
03
b1000010 !
b1000010 &
08
0*
11
02
0(
0-
15
0)
1.
b101100 "
b101100 $
b10110 #
b10110 %
#45
b1000011 !
b1000011 &
1+
1(
b101101 "
b101101 $
#46
1X
1Y
1O
0P
1S
1Q
0H
1G
0I
1J
1?
0@
1C
1A
18
0;
17
09
1:
1/
b1000101 !
b1000101 &
00
13
0(
1-
1)
b101110 "
b101110 $
b10111 #
b10111 %
#47
1X
1Y
1O
0P
1S
1Q
0H
1G
0I
1J
1?
0@
1C
1A
18
0;
17
09
1:
10
03
1/
01
12
b1000110 !
b1000110 &
0+
1*
1(
b101111 "
b101111 $
#48
1X
1Y
1O
0P
1S
1Q
1K
1G
1I
0J
08
1@
0?
00
0/
07
0C
b1001000 !
b1001000 &
0H
0*
01
02
09
0:
1A
0B
0(
0-
05
0=
1E
0)
0.
06
1>
b110000 "
b110000 $
b11000 #
b11000 %
#49
b1001001 !
b1001001 &
1+
1(
b110001 "
b110001 $
#50
b1001011 !
b1001011 &
10
0(
1-
1)
b110010 "
b110010 $
b11001 #
b11001 %
#51
18
19
1/
00
13
11
b1001100 !
b1001100 &
0+
1*
1(
b110011 "
b110011 $
#52
1X
1Y
1O
0P
1S
1Q
0H
1K
1G
1I
0J
1@
0?
09
1A
0B
10
0/
07
03
b1001110 !
b1001110 &
18
0;
0*
11
02
0(
0-
15
0)
1.
b110100 "
b110100 $
b11010 #
b11010 %
#53
b1001111 !
b1001111 &
1+
1(
b110101 "
b110101 $
#54
1X
1Y
1O
0P
1S
1Q
1H
0K
1G
0I
1J
0@
1?
0A
1B
17
08
1;
19
1/
b1010001 !
b1010001 &
00
13
0(
1-
1)
b110110 "
b110110 $
b11011 #
b11011 %
#55
1X
1Y
1O
0P
1S
1Q
1H
0K
1G
0I
1J
0@
1?
0A
1B
17
08
1;
19
10
03
1/
01
12
b1010010 !
b1010010 &
0+
1*
1(
b110111 "
b110111 $
#56
1X
1Y
1O
0P
1S
1Q
1H
0K
1G
0I
1J
1C
1?
1A
0B
18
07
00
0/
0;
b1010100 !
b1010100 &
0@
0*
01
02
19
0:
0(
0-
05
1=
0)
0.
16
b111000 "
b111000 $
b11100 #
b11100 %
#57
b1010101 !
b1010101 &
1+
1(
b111001 "
b111001 $
#58
b1010111 !
b1010111 &
10
0(
1-
1)
b111010 "
b111010 $
b11101 #
b11101 %
#59
1X
1Y
1O
0P
1S
1Q
1H
0K
1G
0I
1J
1@
0C
1?
0A
1B
08
17
09
1:
1/
00
13
11
b1011000 !
b1011000 &
0+
1*
1(
b111011 "
b111011 $
#60
1X
1Y
1O
0P
1S
1Q
1H
0K
1G
0I
1J
1@
0C
1?
0A
1B
1;
17
19
0:
10
0/
03
b1011010 !
b1011010 &
08
0*
11
02
0(
0-
15
0)
1.
b111100 "
b111100 $
b11110 #
b11110 %
#61
b1011011 !
b1011011 &
1+
1(
b111101 "
b111101 $
#62
1X
1Y
1O
0P
1S
1Q
1H
0K
1G
0I
1J
1@
0C
1?
0A
1B
18
0;
17
09
1:
1/
b1011101 !
b1011101 &
00
13
0(
1-
1)
b111110 "
b111110 $
b11111 #
b11111 %
#63
1X
1Y
1O
0P
1S
1Q
1H
0K
1G
0I
1J
1@
0C
1?
0A
1B
18
0;
17
09
1:
10
03
1/
01
12
b1011110 !
b1011110 &
0+
1*
1(
b111111 "
b111111 $
#64
0Y
0`
08
0@
0H
1P
0O
0a
00
0W
0/
07
0?
0G
0S
b1100000 !
b1100000 &
1X
0[
0*
01
02
09
0:
0A
0B
0I
0J
1Q
0R
0(
0-
05
0=
0E
0M
1U
0)
0.
06
0>
0F
1N
b1000000 "
b1000000 $
b100000 #
b100000 %
#65
b1100001 !
b1100001 &
1+
1(
b1000001 "
b1000001 $
#66
b1100011 !
b1100011 &
10
0(
1-
1)
b1000010 "
b1000010 $
b100001 #
b100001 %
#67
18
19
1/
00
13
11
b1100100 !
b1100100 &
0+
1*
1(
b1000011 "
b1000011 $
#68
0@
09
0A
10
0/
07
03
b1100110 !
b1100110 &
18
0;
0*
11
02
0(
0-
15
0)
1.
b1000100 "
b1000100 $
b100010 #
b100010 %
#69
b1100111 !
b1100111 &
1+
1(
b1000101 "
b1000101 $
#70
1@
1A
17
08
1;
19
1/
b1101001 !
b1101001 &
00
13
0(
1-
1)
b1000110 "
b1000110 $
b100011 #
b100011 %
#71
1@
1A
17
08
1;
19
10
03
1/
01
12
b1101010 !
b1101010 &
0+
1*
1(
b1000111 "
b1000111 $
#72
0A
0H
18
07
0I
00
0?
0/
0;
b1101100 !
b1101100 &
1@
0C
0*
01
02
19
0:
0(
0-
05
1=
0)
0.
16
b1001000 "
b1001000 $
b100100 #
b100100 %
#73
b1101101 !
b1101101 &
1+
1(
b1001001 "
b1001001 $
#74
b1101111 !
b1101111 &
10
0(
1-
1)
b1001010 "
b1001010 $
b100101 #
b100101 %
#75
1H
1I
1?
0@
1C
1A
08
17
09
1:
1/
00
13
11
b1110000 !
b1110000 &
0+
1*
1(
b1001011 "
b1001011 $
#76
1H
1I
1?
0@
1C
1A
1;
17
19
0:
10
0/
03
b1110010 !
b1110010 &
08
0*
11
02
0(
0-
15
0)
1.
b1001100 "
b1001100 $
b100110 #
b100110 %
#77
b1110011 !
b1110011 &
1+
1(
b1001101 "
b1001101 $
#78
1H
1I
1?
0@
1C
1A
18
0;
17
09
1:
1/
b1110101 !
b1110101 &
00
13
0(
1-
1)
b1001110 "
b1001110 $
b100111 #
b100111 %
#79
1H
1I
1?
0@
1C
1A
18
0;
17
09
1:
10
03
1/
01
12
b1110110 !
b1110110 &
0+
1*
1(
b1001111 "
b1001111 $
#80
0`
0a
0W
1X
0[
0Y
0I
1P
0O
08
1@
0?
1Q
0R
00
0G
0/
07
0C
b1111000 !
b1111000 &
1H
0K
0*
01
02
09
0:
1A
0B
0(
0-
05
0=
1E
0)
0.
06
1>
b1010000 "
b1010000 $
b101000 #
b101000 %
#81
b1111001 !
b1111001 &
1+
1(
b1010001 "
b1010001 $
#82
b1111011 !
b1111011 &
10
0(
1-
1)
b1010010 "
b1010010 $
b101001 #
b101001 %
#83
18
19
1/
00
13
11
b1111100 !
b1111100 &
0+
1*
1(
b1010011 "
b1010011 $
#84
0`
0a
0W
1X
0[
0Y
1P
0O
1Q
0R
0G
1H
0K
0I
1@
0?
09
1A
0B
10
0/
07
03
b1111110 !
b1111110 &
18
0;
0*
11
02
0(
0-
15
0)
1.
b1010100 "
b1010100 $
b101010 #
b101010 %
#85
b1111111 !
b1111111 &
1+
1(
b1010101 "
b1010101 $
#86
1`
1a
1W
0X
1[
1Y
0P
1O
0Q
1R
1G
0H
1K
1I
0@
1?
0A
1B
17
08
1;
19
1/
b10000001 !
b10000001 &
00
13
0(
1-
1)
b1010110 "
b1010110 $
b101011 #
b101011 %
#87
1`
1a
1W
0X
1[
1Y
0P
1O
0Q
1R
1G
0H
1K
1I
0@
1?
0A
1B
17
08
1;
19
10
03
1/
01
12
b10000010 !
b10000010 &
0+
1*
1(
b1010111 "
b1010111 $
#88
1`
1a
1W
0X
1[
1Y
0P
1O
0Q
1R
1G
0H
1K
1I
1C
1?
1A
0B
18
07
00
0/
0;
b10000100 !
b10000100 &
0@
0*
01
02
19
0:
0(
0-
05
1=
0)
0.
16
b1011000 "
b1011000 $
b101100 #
b101100 %
#89
b10000101 !
b10000101 &
1+
1(
b1011001 "
b1011001 $
#90
b10000111 !
b10000111 &
10
0(
1-
1)
b1011010 "
b1011010 $
b101101 #
b101101 %
#91
1`
1a
1W
0X
1[
1Y
0P
1O
0Q
1R
1G
0H
1K
1I
1@
0C
1?
0A
1B
08
17
09
1:
1/
00
13
11
b10001000 !
b10001000 &
0+
1*
1(
b1011011 "
b1011011 $
#92
1`
1a
1W
0X
1[
1Y
0P
1O
0Q
1R
1G
0H
1K
1I
1@
0C
1?
0A
1B
1;
17
19
0:
10
0/
03
b10001010 !
b10001010 &
08
0*
11
02
0(
0-
15
0)
1.
b1011100 "
b1011100 $
b101110 #
b101110 %
#93
b10001011 !
b10001011 &
1+
1(
b1011101 "
b1011101 $
#94
1`
1a
1W
0X
1[
1Y
0P
1O
0Q
1R
1G
0H
1K
1I
1@
0C
1?
0A
1B
18
0;
17
09
1:
1/
b10001101 !
b10001101 &
00
13
0(
1-
1)
b1011110 "
b1011110 $
b101111 #
b101111 %
#95
1`
1a
1W
0X
1[
1Y
0P
1O
0Q
1R
1G
0H
1K
1I
1@
0C
1?
0A
1B
18
0;
17
09
1:
10
03
1/
01
12
b10001110 !
b10001110 &
0+
1*
1(
b1011111 "
b1011111 $
#96
1`
1a
1W
0X
1[
1Y
1S
1O
1Q
0R
08
0@
1H
0G
00
0/
07
0?
0K
b10010000 !
b10010000 &
0P
0*
01
02
09
0:
0A
0B
1I
0J
0(
0-
05
0=
0E
1M
0)
0.
06
0>
1F
b1100000 "
b1100000 $
b110000 #
b110000 %
#97
b10010001 !
b10010001 &
1+
1(
b1100001 "
b1100001 $
#98
b10010011 !
b10010011 &
10
0(
1-
1)
b1100010 "
b1100010 $
b110001 #
b110001 %
#99
18
19
1/
00
13
11
b10010100 !
b10010100 &
0+
1*
1(
b1100011 "
b1100011 $
#100
0@
09
0A
10
0/
07
03
b10010110 !
b10010110 &
18
0;
0*
11
02
0(
0-
15
0)
1.
b1100100 "
b1100100 $
b110010 #
b110010 %
#101
b10010111 !
b10010111 &
1+
1(
b1100101 "
b1100101 $
#102
1@
1A
17
08
1;
19
1/
b10011001 !
b10011001 &
00
13
0(
1-
1)
b1100110 "
b1100110 $
b110011 #
b110011 %
#103
1@
1A
17
08
1;
19
10
03
1/
01
12
b10011010 !
b10011010 &
0+
1*
1(
b1100111 "
b1100111 $
#104
1`
1a
1W
0X
1[
1Y
0P
1S
1O
1Q
0R
0A
1H
0G
18
07
1I
0J
00
0?
0/
0;
b10011100 !
b10011100 &
1@
0C
0*
01
02
19
0:
0(
0-
05
1=
0)
0.
16
b1101000 "
b1101000 $
b110100 #
b110100 %
#105
b10011101 !
b10011101 &
1+
1(
b1101001 "
b1101001 $
#106
b10011111 !
b10011111 &
10
0(
1-
1)
b1101010 "
b1101010 $
b110101 #
b110101 %
