elementary_logic_gates/Not16.v
module Not16 (
    input [15:0] in,
    output [15:0] out
);
    
    assign out[15:0] = ~in[15:0];
endmodule

arithmetic/HalfAdder.v
module HalfAdder (
    input a, b,
    output sum, carry
);
    
    assign sum = a ^ b;
    assign carry = a & b;

endmodule

arithmetic/FullAdder.v
`include "HalfAdder.v"

module FullAdder (
    input a, b, c,
    output sum, carry
);

    wire bAddCSum, bAddCCarry;
    wire aAddBAddCCarry;

    HalfAdder halfAdder1 (.a(b), .b(c), .sum(bAddCSum), .carry(bAddCCarry));
    HalfAdder halfAdder2 (.a(a), .b(bAddCSum), .sum(sum), .carry(aAddBAddCCarry));

    assign carry = bAddCCarry ^ aAddBAddCCarry;
endmodule

arithmetic/Adder16.v
`include "FullAdder.v"

module Adder16 (
	input [15:0] i1, i2,
	output [15:0] o
);

	wire wCarry [0:15];

	genvar gCounter;
	generate
		for (gCounter = 0; gCounter < 16; gCounter = gCounter + 1) begin
			if (gCounter == 0) begin
				HalfAdder halfAdder (.a(i1[gCounter]), .b(i2[gCounter]), .sum(o[gCounter]), .carry(wCarry[gCounter])); 
			end else begin
				FullAdder fullAdder (.a(i1[gCounter]), .b(i2[gCounter]), .c(wCarry[gCounter-1]), .sum(o[gCounter]), .carry(wCarry[gCounter]));
			end
		end
	endgenerate
	
endmodule

arithmetic/ALU.v
`include "Adder16.v"
`include "../16_bit_variants/Not16.v"

module ALU (
    input wire [15:0] x, y,
    input wire zx, nx, zy, ny, f, no,
    output reg [15:0] out,
    output reg zr, ng
);

/*
zx = 1, x = 0
nx = 1, x = ~x
f => x&y / x+y
no = 1, out = ~out
*/

reg [15:0] rvProcessedX, rvProcessedY, rvCalculated;
wire [15:0] wvAddedXAndY, wvNotOut;

Adder16 adder16 (.i1(rvProcessedX), .i2(rvProcessedY), .o(wvAddedXAndY));
Not16 not16 (.in(rvCalculated), .out(wvNotOut));

always @(*) begin
    if (zx == 1) begin
        rvProcessedX = 0;
    end else begin
        rvProcessedX = x;
    end

    if (nx == 1) begin
        rvProcessedX = ~rvProcessedX;
    end else begin
        rvProcessedX = rvProcessedX;
    end

    if (zy == 1) begin
        rvProcessedY = 0;
    end else begin
        rvProcessedY = y;
    end

    if (ny == 1) begin
        rvProcessedY = ~rvProcessedY;
    end else begin
        rvProcessedY = rvProcessedY;
    end

    if (f == 0) begin
        rvCalculated = rvProcessedX & rvProcessedY;
    end else begin
        rvCalculated = wvAddedXAndY;
    end

    if (no == 0) begin
        out = rvCalculated;
    end else begin
        out = wvNotOut;
    end

    if (out == 0) begin
        zr = 1;
    end else begin
        zr = 0;
    end

    if (out[15] == 0) begin
        ng = 0;
    end else begin
        ng = 1;
    end
end
endmodule

arithmetic/ALU_tb.v
`include "ALU.v"

module ALU_tb;

    reg [15:0] x = 16'h0000, y = 16'h1111;
    reg zx = 0, nx = 0, zy = 0, ny = 0, f = 0, no = 0;
    wire [15:0] out;
    wire zr, ng;

    ALU alu (.x(x), .y(y), .zx(zx), .nx(nx), .zy(zy), .ny(ny), .f(f), .no(no), .out(out), .zr(zr), .ng(ng));

    initial begin
        $dumpfile("ALU.vcd");
        $dumpvars(0, ALU_tb);
        #1000 $finish;
    end

    always begin
        #1
        zx = ~zx;
    end

    always begin
        #2
        nx = ~nx;
    end

    always begin
        #4
        zy = ~zy;
    end
    always begin
        #8
        ny = ~ny;
    end
    always begin
        #16
        f = ~f;
    end
    always begin
        #32
        no = ~no;
    end



    
endmodule

arithmetic/ALU.vcd
$date
	Sun Aug 27 16:10:00 2023
$end
$version
	Icarus Verilog
$end
$timescale
	1s
$end
$scope module ALU_tb $end
$var wire 1 ! zr $end
$var wire 16 " out [15:0] $end
$var wire 1 # ng $end
$var reg 1 $ f $end
$var reg 1 % no $end
$var reg 1 & nx $end
$var reg 1 ' ny $end
$var reg 16 ( x [15:0] $end
$var reg 16 ) y [15:0] $end
$var reg 1 * zx $end
$var reg 1 + zy $end
$scope module alu $end
$var wire 1 $ f $end
$var wire 1 % no $end
$var wire 1 & nx $end
$var wire 1 ' ny $end
$var wire 16 , x [15:0] $end
$var wire 16 - y [15:0] $end
$var wire 1 * zx $end
$var wire 1 + zy $end
$var wire 16 . wvNotOut [15:0] $end
$var wire 16 / wvAddedXAndY [15:0] $end
$var reg 1 # ng $end
$var reg 16 0 out [15:0] $end
$var reg 16 1 rvCalculated [15:0] $end
$var reg 16 2 rvProcessedX [15:0] $end
$var reg 16 3 rvProcessedY [15:0] $end
$var reg 1 ! zr $end
$scope module adder16 $end
$var wire 16 4 i1 [15:0] $end
$var wire 16 5 i2 [15:0] $end
$var wire 16 6 o [15:0] $end
$scope begin genblk1[0] $end
$var parameter 2 7 gCounter $end
$scope begin genblk1 $end
$scope module halfAdder $end
$var wire 1 8 a $end
$var wire 1 9 b $end
$var wire 1 : carry $end
$var wire 1 ; sum $end
$upscope $end
$upscope $end
$upscope $end
$scope begin genblk1[1] $end
$var parameter 2 < gCounter $end
$scope begin genblk1 $end
$scope module fullAdder $end
$var wire 1 = a $end
$var wire 1 > b $end
$var wire 1 : c $end
$var wire 1 ? carry $end
$var wire 1 @ sum $end
$var wire 1 A bAddCSum $end
$var wire 1 B bAddCCarry $end
$var wire 1 C aAddBAddCCarry $end
$scope module halfAdder1 $end
$var wire 1 > a $end
$var wire 1 : b $end
$var wire 1 B carry $end
$var wire 1 A sum $end
$upscope $end
$scope module halfAdder2 $end
$var wire 1 = a $end
$var wire 1 A b $end
$var wire 1 C carry $end
$var wire 1 @ sum $end
$upscope $end
$upscope $end
$upscope $end
$upscope $end
$scope begin genblk1[2] $end
$var parameter 3 D gCounter $end
$scope begin genblk1 $end
$scope module fullAdder $end
$var wire 1 E a $end
$var wire 1 F b $end
$var wire 1 ? c $end
$var wire 1 G carry $end
$var wire 1 H sum $end
$var wire 1 I bAddCSum $end
$var wire 1 J bAddCCarry $end
$var wire 1 K aAddBAddCCarry $end
$scope module halfAdder1 $end
$var wire 1 F a $end
$var wire 1 ? b $end
$var wire 1 J carry $end
$var wire 1 I sum $end
$upscope $end
$scope module halfAdder2 $end
$var wire 1 E a $end
$var wire 1 I b $end
$var wire 1 K carry $end
$var wire 1 H sum $end
$upscope $end
$upscope $end
$upscope $end
$upscope $end
$scope begin genblk1[3] $end
$var parameter 3 L gCounter $end
$scope begin genblk1 $end
$scope module fullAdder $end
$var wire 1 M a $end
$var wire 1 N b $end
$var wire 1 G c $end
$var wire 1 O carry $end
$var wire 1 P sum $end
$var wire 1 Q bAddCSum $end
$var wire 1 R bAddCCarry $end
$var wire 1 S aAddBAddCCarry $end
$scope module halfAdder1 $end
$var wire 1 N a $end
$var wire 1 G b $end
$var wire 1 R carry $end
$var wire 1 Q sum $end
$upscope $end
$scope module halfAdder2 $end
$var wire 1 M a $end
$var wire 1 Q b $end
$var wire 1 S carry $end
$var wire 1 P sum $end
$upscope $end
$upscope $end
$upscope $end
$upscope $end
$scope begin genblk1[4] $end
$var parameter 4 T gCounter $end
$scope begin genblk1 $end
$scope module fullAdder $end
$var wire 1 U a $end
$var wire 1 V b $end
$var wire 1 O c $end
$var wire 1 W carry $end
$var wire 1 X sum $end
$var wire 1 Y bAddCSum $end
$var wire 1 Z bAddCCarry $end
$var wire 1 [ aAddBAddCCarry $end
$scope module halfAdder1 $end
$var wire 1 V a $end
$var wire 1 O b $end
$var wire 1 Z carry $end
$var wire 1 Y sum $end
$upscope $end
$scope module halfAdder2 $end
$var wire 1 U a $end
$var wire 1 Y b $end
$var wire 1 [ carry $end
$var wire 1 X sum $end
$upscope $end
$upscope $end
$upscope $end
$upscope $end
$scope begin genblk1[5] $end
$var parameter 4 \ gCounter $end
$scope begin genblk1 $end
$scope module fullAdder $end
$var wire 1 ] a $end
$var wire 1 ^ b $end
$var wire 1 W c $end
$var wire 1 _ carry $end
$var wire 1 ` sum $end
$var wire 1 a bAddCSum $end
$var wire 1 b bAddCCarry $end
$var wire 1 c aAddBAddCCarry $end
$scope module halfAdder1 $end
$var wire 1 ^ a $end
$var wire 1 W b $end
$var wire 1 b carry $end
$var wire 1 a sum $end
$upscope $end
$scope module halfAdder2 $end
$var wire 1 ] a $end
$var wire 1 a b $end
$var wire 1 c carry $end
$var wire 1 ` sum $end
$upscope $end
$upscope $end
$upscope $end
$upscope $end
$scope begin genblk1[6] $end
$var parameter 4 d gCounter $end
$scope begin genblk1 $end
$scope module fullAdder $end
$var wire 1 e a $end
$var wire 1 f b $end
$var wire 1 _ c $end
$var wire 1 g carry $end
$var wire 1 h sum $end
$var wire 1 i bAddCSum $end
$var wire 1 j bAddCCarry $end
$var wire 1 k aAddBAddCCarry $end
$scope module halfAdder1 $end
$var wire 1 f a $end
$var wire 1 _ b $end
$var wire 1 j carry $end
$var wire 1 i sum $end
$upscope $end
$scope module halfAdder2 $end
$var wire 1 e a $end
$var wire 1 i b $end
$var wire 1 k carry $end
$var wire 1 h sum $end
$upscope $end
$upscope $end
$upscope $end
$upscope $end
$scope begin genblk1[7] $end
$var parameter 4 l gCounter $end
$scope begin genblk1 $end
$scope module fullAdder $end
$var wire 1 m a $end
$var wire 1 n b $end
$var wire 1 g c $end
$var wire 1 o carry $end
$var wire 1 p sum $end
$var wire 1 q bAddCSum $end
$var wire 1 r bAddCCarry $end
$var wire 1 s aAddBAddCCarry $end
$scope module halfAdder1 $end
$var wire 1 n a $end
$var wire 1 g b $end
$var wire 1 r carry $end
$var wire 1 q sum $end
$upscope $end
$scope module halfAdder2 $end
$var wire 1 m a $end
$var wire 1 q b $end
$var wire 1 s carry $end
$var wire 1 p sum $end
$upscope $end
$upscope $end
$upscope $end
$upscope $end
$scope begin genblk1[8] $end
$var parameter 5 t gCounter $end
$scope begin genblk1 $end
$scope module fullAdder $end
$var wire 1 u a $end
$var wire 1 v b $end
$var wire 1 o c $end
$var wire 1 w carry $end
$var wire 1 x sum $end
$var wire 1 y bAddCSum $end
$var wire 1 z bAddCCarry $end
$var wire 1 { aAddBAddCCarry $end
$scope module halfAdder1 $end
$var wire 1 v a $end
$var wire 1 o b $end
$var wire 1 z carry $end
$var wire 1 y sum $end
$upscope $end
$scope module halfAdder2 $end
$var wire 1 u a $end
$var wire 1 y b $end
$var wire 1 { carry $end
$var wire 1 x sum $end
$upscope $end
$upscope $end
$upscope $end
$upscope $end
$scope begin genblk1[9] $end
$var parameter 5 | gCounter $end
$scope begin genblk1 $end
$scope module fullAdder $end
$var wire 1 } a $end
$var wire 1 ~ b $end
$var wire 1 w c $end
$var wire 1 !" carry $end
$var wire 1 "" sum $end
$var wire 1 #" bAddCSum $end
$var wire 1 $" bAddCCarry $end
$var wire 1 %" aAddBAddCCarry $end
$scope module halfAdder1 $end
$var wire 1 ~ a $end
$var wire 1 w b $end
$var wire 1 $" carry $end
$var wire 1 #" sum $end
$upscope $end
$scope module halfAdder2 $end
$var wire 1 } a $end
$var wire 1 #" b $end
$var wire 1 %" carry $end
$var wire 1 "" sum $end
$upscope $end
$upscope $end
$upscope $end
$upscope $end
$scope begin genblk1[10] $end
$var parameter 5 &" gCounter $end
$scope begin genblk1 $end
$scope module fullAdder $end
$var wire 1 '" a $end
$var wire 1 (" b $end
$var wire 1 !" c $end
$var wire 1 )" carry $end
$var wire 1 *" sum $end
$var wire 1 +" bAddCSum $end
$var wire 1 ," bAddCCarry $end
$var wire 1 -" aAddBAddCCarry $end
$scope module halfAdder1 $end
$var wire 1 (" a $end
$var wire 1 !" b $end
$var wire 1 ," carry $end
$var wire 1 +" sum $end
$upscope $end
$scope module halfAdder2 $end
$var wire 1 '" a $end
$var wire 1 +" b $end
$var wire 1 -" carry $end
$var wire 1 *" sum $end
$upscope $end
$upscope $end
$upscope $end
$upscope $end
$scope begin genblk1[11] $end
$var parameter 5 ." gCounter $end
$scope begin genblk1 $end
$scope module fullAdder $end
$var wire 1 /" a $end
$var wire 1 0" b $end
$var wire 1 )" c $end
$var wire 1 1" carry $end
$var wire 1 2" sum $end
$var wire 1 3" bAddCSum $end
$var wire 1 4" bAddCCarry $end
$var wire 1 5" aAddBAddCCarry $end
$scope module halfAdder1 $end
$var wire 1 0" a $end
$var wire 1 )" b $end
$var wire 1 4" carry $end
$var wire 1 3" sum $end
$upscope $end
$scope module halfAdder2 $end
$var wire 1 /" a $end
$var wire 1 3" b $end
$var wire 1 5" carry $end
$var wire 1 2" sum $end
$upscope $end
$upscope $end
$upscope $end
$upscope $end
$scope begin genblk1[12] $end
$var parameter 5 6" gCounter $end
$scope begin genblk1 $end
$scope module fullAdder $end
$var wire 1 7" a $end
$var wire 1 8" b $end
$var wire 1 1" c $end
$var wire 1 9" carry $end
$var wire 1 :" sum $end
$var wire 1 ;" bAddCSum $end
$var wire 1 <" bAddCCarry $end
$var wire 1 =" aAddBAddCCarry $end
$scope module halfAdder1 $end
$var wire 1 8" a $end
$var wire 1 1" b $end
$var wire 1 <" carry $end
$var wire 1 ;" sum $end
$upscope $end
$scope module halfAdder2 $end
$var wire 1 7" a $end
$var wire 1 ;" b $end
$var wire 1 =" carry $end
$var wire 1 :" sum $end
$upscope $end
$upscope $end
$upscope $end
$upscope $end
$scope begin genblk1[13] $end
$var parameter 5 >" gCounter $end
$scope begin genblk1 $end
$scope module fullAdder $end
$var wire 1 ?" a $end
$var wire 1 @" b $end
$var wire 1 9" c $end
$var wire 1 A" carry $end
$var wire 1 B" sum $end
$var wire 1 C" bAddCSum $end
$var wire 1 D" bAddCCarry $end
$var wire 1 E" aAddBAddCCarry $end
$scope module halfAdder1 $end
$var wire 1 @" a $end
$var wire 1 9" b $end
$var wire 1 D" carry $end
$var wire 1 C" sum $end
$upscope $end
$scope module halfAdder2 $end
$var wire 1 ?" a $end
$var wire 1 C" b $end
$var wire 1 E" carry $end
$var wire 1 B" sum $end
$upscope $end
$upscope $end
$upscope $end
$upscope $end
$scope begin genblk1[14] $end
$var parameter 5 F" gCounter $end
$scope begin genblk1 $end
$scope module fullAdder $end
$var wire 1 G" a $end
$var wire 1 H" b $end
$var wire 1 A" c $end
$var wire 1 I" carry $end
$var wire 1 J" sum $end
$var wire 1 K" bAddCSum $end
$var wire 1 L" bAddCCarry $end
$var wire 1 M" aAddBAddCCarry $end
$scope module halfAdder1 $end
$var wire 1 H" a $end
$var wire 1 A" b $end
$var wire 1 L" carry $end
$var wire 1 K" sum $end
$upscope $end
$scope module halfAdder2 $end
$var wire 1 G" a $end
$var wire 1 K" b $end
$var wire 1 M" carry $end
$var wire 1 J" sum $end
$upscope $end
$upscope $end
$upscope $end
$upscope $end
$scope begin genblk1[15] $end
$var parameter 5 N" gCounter $end
$scope begin genblk1 $end
$scope module fullAdder $end
$var wire 1 O" a $end
$var wire 1 P" b $end
$var wire 1 I" c $end
$var wire 1 Q" carry $end
$var wire 1 R" sum $end
$var wire 1 S" bAddCSum $end
$var wire 1 T" bAddCCarry $end
$var wire 1 U" aAddBAddCCarry $end
$scope module halfAdder1 $end
$var wire 1 P" a $end
$var wire 1 I" b $end
$var wire 1 T" carry $end
$var wire 1 S" sum $end
$upscope $end
$scope module halfAdder2 $end
$var wire 1 O" a $end
$var wire 1 S" b $end
$var wire 1 U" carry $end
$var wire 1 R" sum $end
$upscope $end
$upscope $end
$upscope $end
$upscope $end
$upscope $end
$scope module not16 $end
$var wire 16 V" in [15:0] $end
$var wire 16 W" out [15:0] $end
$upscope $end
$upscope $end
$upscope $end
$enddefinitions $end
$comment Show the parameter values. $end
$dumpall
b1111 N"
b1110 F"
b1101 >"
b1100 6"
b1011 ."
b1010 &"
b1001 |
b1000 t
b111 l
b110 d
b101 \
b100 T
b11 L
b10 D
b1 <
b0 7
$end
#0
$dumpvars
b1111111111111111 W"
b0 V"
0U"
0T"
0S"
0R"
0Q"
0P"
0O"
0M"
0L"
0K"
0J"
0I"
0H"
0G"
0E"
0D"
0C"
0B"
0A"
0@"
0?"
0="
0<"
1;"
1:"
09"
18"
07"
05"
04"
03"
02"
01"
00"
0/"
0-"
0,"
0+"
0*"
0)"
0("
0'"
0%"
0$"
0#"
0""
0!"
0~
0}
0{
0z
1y
1x
0w
1v
0u
0s
0r
0q
0p
0o
0n
0m
0k
0j
0i
0h
0g
0f
0e
0c
0b
0a
0`
0_
0^
0]
0[
0Z
1Y
1X
0W
1V
0U
0S
0R
0Q
0P
0O
0N
0M
0K
0J
0I
0H
0G
0F
0E
0C
0B
0A
0@
0?
0>
0=
1;
0:
19
08
b1000100010001 6
b1000100010001 5
b0 4
b1000100010001 3
b0 2
b0 1
b0 0
b1000100010001 /
b1111111111111111 .
b1000100010001 -
b0 ,
0+
0*
b1000100010001 )
b0 (
0'
0&
0%
0$
0#
b0 "
1!
$end
#1
1*
#2
0y
1z
0;"
1<"
0Y
1Z
1o
11"
1Q"
1O
1s
15"
1U"
1S
1q
13"
1S"
1Q
1g
1)"
1I"
1G
1k
1-"
1M"
1K
1i
1+"
1K"
1I
1_
1!"
1A"
1?
1c
1%"
1E"
1C
1a
1#"
1C"
1A
1W
1w
19"
0;
1:
0@
0H
0P
1X
0[
0`
0h
0p
1x
0{
0""
0*"
02"
1:"
0="
0B"
0J"
b1000100010000 /
b1000100010000 6
0R"
b1110111011101110 .
b1110111011101110 W"
18
1=
1E
1M
1U
1]
1e
1m
1u
1}
1'"
1/"
17"
1?"
1G"
1O"
0!
b1000100010001 "
b1000100010001 0
b1000100010001 1
b1000100010001 V"
b1111111111111111 2
b1111111111111111 4
0*
1&
#3
b1111111111111111 2
b1111111111111111 4
1*
#4
0a
0#"
0C"
0I
0Q
0i
0q
0+"
03"
0K"
0S"
0W
0w
09"
0A
0?
0G
0O
0_
0g
0o
0!"
0)"
01"
0A"
0I"
0Q"
0Y
0Z
0y
0z
0;"
0<"
0:
0@
0C
0H
0K
0P
0S
0X
0`
0c
0h
0k
0p
0s
0x
0""
0%"
0*"
0-"
02"
05"
0:"
0B"
0E"
0J"
0M"
b0 /
b0 6
0R"
0U"
b1111111111111111 .
b1111111111111111 W"
09
0V
0v
08"
08
0=
0E
0M
0U
0]
0e
0m
0u
0}
0'"
0/"
07"
0?"
0G"
0O"
1!
b0 "
b0 0
b0 1
b0 V"
b0 3
b0 5
b0 2
b0 4
0*
0&
1+
#5
1*
#6
1;
1@
1H
1P
1X
1`
1h
1p
1x
1""
1*"
12"
1:"
1B"
1J"
b1111111111111111 /
b1111111111111111 6
1R"
18
1=
1E
1M
1U
1]
1e
1m
1u
1}
1'"
1/"
17"
1?"
1G"
1O"
b1111111111111111 2
b1111111111111111 4
0*
1&
#7
b1111111111111111 2
b1111111111111111 4
1*
#8
1A
1I
1Q
1a
1i
1q
1#"
1+"
13"
1C"
1K"
1S"
0;
1@
1H
1P
0X
1`
1h
1p
0x
1""
1*"
12"
0:"
1B"
1J"
b1110111011101110 /
b1110111011101110 6
1R"
1>
1F
1N
1^
1f
1n
1~
1("
10"
1@"
1H"
1P"
08
0=
0E
0M
0U
0]
0e
0m
0u
0}
0'"
0/"
07"
0?"
0G"
0O"
b1110111011101110 3
b1110111011101110 5
b0 2
b0 4
0*
0&
0+
1'
#9
b1110111011101110 3
b1110111011101110 5
1*
#10
0a
1b
0#"
1$"
0C"
1D"
1W
1w
19"
1[
1{
1="
0I
1J
0Q
1R
1Y
0i
1j
0q
1r
1y
0+"
1,"
03"
14"
1;"
0K"
1L"
0S"
1T"
1?
1G
1O
1_
1g
1o
1!"
1)"
11"
1A"
1I"
1Q"
1;
0@
1C
1H
0K
1P
0S
0X
1`
0c
1h
0k
1p
0s
0x
1""
0%"
1*"
0-"
12"
05"
0:"
1B"
0E"
1J"
0M"
b1110111011101101 /
b1110111011101101 6
1R"
0U"
b1000100010001 .
b1000100010001 W"
18
1=
1E
1M
1U
1]
1e
1m
1u
1}
1'"
1/"
17"
1?"
1G"
1O"
1#
0!
b1110111011101110 "
b1110111011101110 0
b1110111011101110 1
b1110111011101110 V"
b1110111011101110 3
b1110111011101110 5
b1111111111111111 2
b1111111111111111 4
0*
1&
#11
b1110111011101110 3
b1110111011101110 5
b1111111111111111 2
b1111111111111111 4
1*
#12
0Q"
1S"
0T"
0I"
1K"
0L"
0A"
1C"
0D"
09"
01"
13"
04"
0)"
1+"
0,"
0!"
1#"
0$"
0w
0o
1q
0r
0g
1i
0j
0_
1a
0b
0W
0O
1Q
0R
0G
1I
0J
0?
1Y
0Z
1y
0z
1;"
0<"
1@
0C
1H
1P
1X
0[
1`
1h
1p
1x
0{
1""
1*"
12"
1:"
0="
1B"
1J"
b1111111111111111 /
b1111111111111111 6
1R"
b1111111111111111 .
b1111111111111111 W"
19
1V
1v
18"
08
0=
0E
0M
0U
0]
0e
0m
0u
0}
0'"
0/"
07"
0?"
0G"
0O"
0#
1!
b0 "
b0 0
b0 1
b0 V"
b1111111111111111 3
b1111111111111111 5
b0 2
b0 4
0*
0&
1+
#13
b1111111111111111 3
b1111111111111111 5
1*
#14
0I
1J
0Q
1R
0Y
1Z
0a
1b
0i
1j
0q
1r
0y
1z
0#"
1$"
0+"
1,"
03"
14"
0;"
1<"
0C"
1D"
0K"
1L"
0S"
1T"
0A
1B
1?
1G
1O
1W
1_
1g
1o
1w
1!"
1)"
11"
19"
1A"
1I"
1Q"
0;
1:
1@
0C
1H
0K
1P
0S
1X
0[
1`
0c
1h
0k
1p
0s
1x
0{
1""
0%"
1*"
0-"
12"
05"
1:"
0="
1B"
0E"
1J"
0M"
b1111111111111110 /
b1111111111111110 6
1R"
0U"
b0 .
b0 W"
18
1=
1E
1M
1U
1]
1e
1m
1u
1}
1'"
1/"
17"
1?"
1G"
1O"
1#
0!
b1111111111111111 "
b1111111111111111 0
b1111111111111111 1
b1111111111111111 V"
b1111111111111111 3
b1111111111111111 5
b1111111111111111 2
b1111111111111111 4
0*
1&
#15
b1111111111111111 3
b1111111111111111 5
b1111111111111111 2
b1111111111111111 4
1*
#16
0W
0w
09"
1Y
0Z
1y
0z
1;"
0<"
0?
0G
0O
0_
0g
0o
0!"
0)"
01"
0A"
0I"
0Q"
0#
0B
0I
0J
0Q
0R
0a
0b
0i
0j
0q
0r
0#"
0$"
0+"
0,"
03"
04"
0C"
0D"
0K"
0L"
0S"
0T"
1;
0:
0@
0H
0P
1X
0`
0h
0p
1x
0""
0*"
02"
1:"
0B"
0J"
b1000100010001 /
b1000100010001 6
0R"
b1110111011101110 .
b1110111011101110 W"
0>
0F
0N
0^
0f
0n
0~
0("
00"
0@"
0H"
0P"
08
0=
0E
0M
0U
0]
0e
0m
0u
0}
0'"
0/"
07"
0?"
0G"
0O"
b1000100010001 "
b1000100010001 0
b1000100010001 1
b1000100010001 V"
b1000100010001 3
b1000100010001 5
b0 2
b0 4
0*
0&
0+
0'
1$
#17
1*
#18
0y
1z
0;"
1<"
0Y
1Z
0!
1o
11"
1Q"
1O
1s
15"
1U"
1S
1q
13"
1S"
1Q
1g
1)"
1I"
1G
1k
1-"
1M"
1K
1i
1+"
1K"
1I
1_
1!"
1A"
1?
1c
1%"
1E"
1C
1a
1#"
1C"
b1110111011101111 .
b1110111011101111 W"
1A
1W
1w
19"
0#
b1000100010000 "
b1000100010000 0
b1000100010000 1
b1000100010000 V"
0;
1:
0@
0H
0P
1X
0[
0`
0h
0p
1x
0{
0""
0*"
02"
1:"
0="
0B"
0J"
b1000100010000 /
b1000100010000 6
0R"
18
1=
1E
1M
1U
1]
1e
1m
1u
1}
1'"
1/"
17"
1?"
1G"
1O"
b1111111111111111 2
b1111111111111111 4
0*
1&
#19
b1111111111111111 2
b1111111111111111 4
1*
#20
1!
0a
0#"
0C"
0I
0Q
0i
0q
0+"
03"
0K"
0S"
b1111111111111111 .
b1111111111111111 W"
0W
0w
09"
0A
0?
0G
0O
0_
0g
0o
0!"
0)"
01"
0A"
0I"
0#
b0 "
b0 0
b0 1
b0 V"
0Q"
0Y
0Z
0y
0z
0;"
0<"
0:
0@
0C
0H
0K
0P
0S
0X
0`
0c
0h
0k
0p
0s
0x
0""
0%"
0*"
0-"
02"
05"
0:"
0B"
0E"
0J"
0M"
b0 /
b0 6
0R"
0U"
09
0V
0v
08"
08
0=
0E
0M
0U
0]
0e
0m
0u
0}
0'"
0/"
07"
0?"
0G"
0O"
b0 3
b0 5
b0 2
b0 4
0*
0&
1+
#21
1*
#22
b0 .
b0 W"
1#
0!
b1111111111111111 "
b1111111111111111 0
b1111111111111111 1
b1111111111111111 V"
1;
1@
1H
1P
1X
1`
1h
1p
1x
1""
1*"
12"
1:"
1B"
1J"
b1111111111111111 /
b1111111111111111 6
1R"
18
1=
1E
1M
1U
1]
1e
1m
1u
1}
1'"
1/"
17"
1?"
1G"
1O"
b1111111111111111 2
b1111111111111111 4
0*
1&
#23
b1111111111111111 2
b1111111111111111 4
1*
#24
b1000100010001 .
b1000100010001 W"
1#
0!
b1110111011101110 "
b1110111011101110 0
b1110111011101110 1
b1110111011101110 V"
1A
1I
1Q
1a
1i
1q
1#"
1+"
13"
1C"
1K"
1S"
0;
1@
1H
1P
0X
1`
1h
1p
0x
1""
1*"
12"
0:"
1B"
1J"
b1110111011101110 /
b1110111011101110 6
1R"
1>
1F
1N
1^
1f
1n
1~
1("
10"
1@"
1H"
1P"
08
0=
0E
0M
0U
0]
0e
0m
0u
0}
0'"
0/"
07"
0?"
0G"
0O"
b1110111011101110 3
b1110111011101110 5
b0 2
b0 4
0*
0&
0+
1'
#25
b1110111011101110 3
b1110111011101110 5
1*
#26
0a
1b
0#"
1$"
0C"
1D"
1W
1w
19"
1[
1{
1="
0I
1J
0Q
1R
1Y
0i
1j
0q
1r
1y
0+"
1,"
03"
14"
1;"
0K"
1L"
0S"
1T"
b1000100010010 .
b1000100010010 W"
1?
1G
1O
1_
1g
1o
1!"
1)"
11"
1A"
1I"
1#
b1110111011101101 "
b1110111011101101 0
b1110111011101101 1
b1110111011101101 V"
1Q"
1;
0@
1C
1H
0K
1P
0S
0X
1`
0c
1h
0k
1p
0s
0x
1""
0%"
1*"
0-"
12"
05"
0:"
1B"
0E"
1J"
0M"
b1110111011101101 /
b1110111011101101 6
1R"
0U"
18
1=
1E
1M
1U
1]
1e
1m
1u
1}
1'"
1/"
17"
1?"
1G"
1O"
b1110111011101110 3
b1110111011101110 5
b1111111111111111 2
b1111111111111111 4
0*
1&
#27
b1110111011101110 3
b1110111011101110 5
b1111111111111111 2
b1111111111111111 4
1*
#28
0Q"
1S"
0T"
0I"
1K"
0L"
0A"
1C"
0D"
09"
01"
13"
04"
0)"
1+"
0,"
0!"
1#"
0$"
0w
0o
1q
0r
0g
1i
0j
0_
1a
0b
0W
0O
1Q
0R
0G
1I
0J
b0 .
b0 W"
0?
1#
b1111111111111111 "
b1111111111111111 0
b1111111111111111 1
b1111111111111111 V"
1Y
0Z
1y
0z
1;"
0<"
1@
0C
1H
1P
1X
0[
1`
1h
1p
1x
0{
1""
1*"
12"
1:"
0="
1B"
1J"
b1111111111111111 /
b1111111111111111 6
1R"
19
1V
1v
18"
08
0=
0E
0M
0U
0]
0e
0m
0u
0}
0'"
0/"
07"
0?"
0G"
0O"
b1111111111111111 3
b1111111111111111 5
b0 2
b0 4
0*
0&
1+
#29
b1111111111111111 3
b1111111111111111 5
1*
#30
0I
1J
0Q
1R
0Y
1Z
0a
1b
0i
1j
0q
1r
0y
1z
0#"
1$"
0+"
1,"
03"
14"
0;"
1<"
0C"
1D"
0K"
1L"
0S"
1T"
b1 .
b1 W"
0A
1B
1?
1G
1O
1W
1_
1g
1o
1w
1!"
1)"
11"
19"
1A"
1I"
1#
0!
b1111111111111110 "
b1111111111111110 0
b1111111111111110 1
b1111111111111110 V"
1Q"
0;
1:
1@
0C
1H
0K
1P
0S
1X
0[
1`
0c
1h
0k
1p
0s
1x
0{
1""
0%"
1*"
0-"
12"
05"
1:"
0="
1B"
0E"
1J"
0M"
b1111111111111110 /
b1111111111111110 6
1R"
0U"
18
1=
1E
1M
1U
1]
1e
1m
1u
1}
1'"
1/"
17"
1?"
1G"
1O"
b1111111111111111 3
b1111111111111111 5
b1111111111111111 2
b1111111111111111 4
0*
1&
#31
b1111111111111111 3
b1111111111111111 5
b1111111111111111 2
b1111111111111111 4
1*
#32
0W
0w
09"
1Y
0Z
1y
0z
1;"
0<"
0?
0G
0O
0_
0g
0o
0!"
0)"
01"
0A"
0I"
0Q"
0B
0I
0J
0Q
0R
0a
0b
0i
0j
0q
0r
0#"
0$"
0+"
0,"
03"
04"
0C"
0D"
0K"
0L"
0S"
0T"
1;
0:
0@
0H
0P
1X
0`
0h
0p
1x
0""
0*"
02"
1:"
0B"
0J"
b1000100010001 /
b1000100010001 6
0R"
b1111111111111111 .
b1111111111111111 W"
0>
0F
0N
0^
0f
0n
0~
0("
00"
0@"
0H"
0P"
08
0=
0E
0M
0U
0]
0e
0m
0u
0}
0'"
0/"
07"
0?"
0G"
0O"
1#
b1111111111111111 "
b1111111111111111 0
b0 1
b0 V"
b1000100010001 3
b1000100010001 5
b0 2
b0 4
0*
0&
0+
0'
0$
1%
#33
1*
#34
0y
1z
0;"
1<"
0Y
1Z
1o
11"
1Q"
1O
1s
15"
1U"
1S
1q
13"
1S"
1Q
1g
1)"
1I"
1G
1k
1-"
1M"
1K
1i
1+"
1K"
1I
1_
1!"
1A"
1?
1c
1%"
1E"
1C
1a
1#"
1C"
1A
1W
1w
19"
b1110111011101110 "
b1110111011101110 0
0;
1:
0@
0H
0P
1X
0[
0`
0h
0p
1x
0{
0""
0*"
02"
1:"
0="
0B"
0J"
b1000100010000 /
b1000100010000 6
0R"
b1110111011101110 .
b1110111011101110 W"
18
1=
1E
1M
1U
1]
1e
1m
1u
1}
1'"
1/"
17"
1?"
1G"
1O"
b1000100010001 1
b1000100010001 V"
b1111111111111111 2
b1111111111111111 4
0*
1&
