arithmetic/HalfAdder.v
module HalfAdder (
    input a, b,
    output sum, carry
);
    
    assign sum = a ^ b;
    assign carry = a & b;

endmodule

arithmetic/FullAdder.v
`include "HalfAdder.v"

module FullAdder (
    input a, b, c,
    output sum, carry
);

    wire bAddCSum, bAddCCarry;
    wire aAddBAddCCarry;

    HalfAdder halfAdder1 (.a(b), .b(c), .sum(bAddCSum), .carry(bAddCCarry));
    HalfAdder halfAdder2 (.a(a), .b(bAddCSum), .sum(sum), .carry(aAddBAddCCarry));

    assign carry = bAddCCarry ^ aAddBAddCCarry;
endmodule

arithmetic/FullAdder_tb.v
module FullAdder_tb;

    reg a = 0, b = 0, c = 0;
    wire sum, carry;
    
    FullAdder fullAdder (.a(a), .b(b), .c(c), .sum(sum), .carry(carry));

    initial begin
        $dumpfile("FullAdder.vcd");
        $dumpvars(0, FullAdder_tb);
        #1000 $finish;    
    end

    always begin
        #1 a = ~a;
    end

    always begin
        #2 b = ~b;
    end

    always begin
        #4 c = ~c;
    end
    
endmodule

arithmetic/FullAdder.vcd
$date
	Sat Aug 26 17:40:36 2023
$end
$version
	Icarus Verilog
$end
$timescale
	1s
$end
$scope module FullAdder_tb $end
$var wire 1 ! sum $end
$var wire 1 " carry $end
$var reg 1 # a $end
$var reg 1 $ b $end
$var reg 1 % c $end
$scope module fullAdder $end
$var wire 1 # a $end
$var wire 1 $ b $end
$var wire 1 % c $end
$var wire 1 " carry $end
$var wire 1 ! sum $end
$var wire 1 & bAddCSum $end
$var wire 1 ' bAddCCarry $end
$var wire 1 ( aAddBAddCCarry $end
$scope module halfAdder1 $end
$var wire 1 $ a $end
$var wire 1 % b $end
$var wire 1 ' carry $end
$var wire 1 & sum $end
$upscope $end
$scope module halfAdder2 $end
$var wire 1 # a $end
$var wire 1 & b $end
$var wire 1 ( carry $end
$var wire 1 ! sum $end
$upscope $end
$upscope $end
$upscope $end
$enddefinitions $end
$comment Show the parameter values. $end
$dumpall
$end
#0
$dumpvars
0(
0'
0&
0%
0$
0#
0"
0!
$end
#1
1!
1#
#2
1&
0#
1$
#3
1"
0!
1(
1#
#4
0"
1!
0(
0#
0$
1%
#5
1"
0!
1(
1#
#6
0(
0&
1'
0#
1$
#7
1!
1#
#8
0"
0!
0'
0#
0$
0%
#9
1!
1#
#10
1&
0#
1$
#11
1"
0!
1(
1#
#12
0"
1!
0(
0#
0$
1%
#13
1"
0!
1(
1#
#14
0(
0&
1'
0#
1$
#15
1!
1#
#16
0"
0!
0'
0#
0$
0%
#17
1!
1#
#18
1&
0#
1$
#19
1"
0!
1(
1#
#20
0"
1!
0(
0#
0$
1%
#21
1"
0!
1(
1#
#22
0(
0&
1'
0#
1$
#23
1!
1#
#24
0"
0!
0'
0#
0$
0%
#25
1!
1#
#26
1&
0#
1$
#27
1"
0!
1(
1#
#28
0"
1!
0(
0#
0$
1%
#29
1"
0!
1(
1#
#30
0(
0&
1'
0#
1$
#31
1!
1#
#32
0"
0!
0'
0#
0$
0%
#33
1!
1#
#34
1&
0#
1$
#35
1"
0!
1(
1#
#36
0"
1!
0(
0#
0$
1%
#37
1"
0!
1(
1#
#38
0(
0&
1'
0#
1$
#39
1!
1#
#40
0"
0!
0'
0#
0$
0%
#41
1!
1#
#42
1&
0#
1$
#43
1"
0!
1(
1#
#44
0"
1!
0(
0#
0$
1%
#45
1"
0!
1(
1#
#46
0(
0&
1'
0#
1$
#47
1!
1#
#48
0"
0!
0'
0#
0$
0%
#49
1!
1#
#50
1&
0#
1$
#51
1"
0!
1(
1#
#52
0"
1!
0(
0#
0$
1%
#53
1"
0!
1(
1#
#54
0(
0&
1'
0#
1$
#55
1!
1#
#56
0"
0!
0'
0#
0$
0%
#57
1!
1#
#58
1&
0#
1$
#59
1"
0!
1(
1#
#60
0"
1!
0(
0#
0$
1%
#61
1"
0!
1(
1#
#62
0(
0&
1'
0#
1$
#63
1!
1#
#64
0"
0!
0'
0#
0$
0%
#65
1!
1#
#66
1&
0#
1$
#67
1"
0!
1(
1#
#68
0"
1!
0(
0#
0$
1%
#69
1"
0!
1(
1#
#70
0(
0&
1'
0#
1$
#71
1!
1#
#72
0"
0!
0'
0#
0$
0%
#73
1!
1#
#74
1&
0#
1$
#75
1"
0!
1(
1#
#76
0"
1!
0(
0#
0$
1%
#77
1"
0!
1(
1#
#78
0(
0&
1'
0#
1$
#79
1!
1#
#80
0"
0!
0'
0#
0$
0%
#81
1!
1#
#82
1&
0#
1$
#83
1"
0!
1(
1#
#84
0"
1!
0(
0#
0$
1%
#85
1"
0!
1(
1#
#86
0(
0&
1'
0#
1$
#87
1!
1#
#88
0"
0!
0'
0#
0$
0%
#89
1!
1#
#90
1&
0#
1$
#91
1"
0!
1(
1#
#92
0"
1!
0(
0#
0$
1%
#93
1"
0!
1(
1#
#94
0(
0&
1'
0#
1$
#95
1!
1#
#96
0"
0!
0'
0#
0$
0%
#97
1!
1#
#98
1&
0#
1$
#99
1"
0!
1(
1#
#100
0"
1!
0(
0#
0$
1%
#101
1"
0!
1(
1#
#102
0(
0&
1'
0#
1$
#103
1!
1#
#104
0"
0!
0'
0#
0$
0%
#105
1!
1#
#106
1&
0#
1$
#107
1"
0!
1(
1#
#108
0"
1!
0(
0#
0$
1%
#109
1"
0!
1(
1#
#110
0(
0&
1'
0#
1$
#111
1!
1#
#112
0"
0!
0'
0#
0$
0%
#113
1!
1#
#114
1&
0#
1$
#115
1"
0!
1(
1#
#116
0"
1!
0(
0#
0$
1%
#117
1"
0!
1(
1#
#118
0(
0&
1'
0#
1$
#119
1!
1#
#120
0"
0!
0'
0#
0$
0%
#121
1!
1#
#122
1&
0#
1$
#123
1"
0!
1(
1#
#124
0"
1!
0(
0#
0$
1%
#125
1"
0!
1(
1#
#126
0(
0&
1'
0#
1$
#127
1!
1#
#128
0"
0!
0'
0#
0$
0%
#129
1!
1#
#130
1&
0#
1$
#131
1"
0!
1(
1#
#132
0"
1!
0(
0#
0$
1%
#133
1"
0!
1(
1#
#134
0(
0&
1'
0#
1$
#135
1!
1#
#136
0"
0!
0'
0#
0$
0%
#137
1!
1#
#138
1&
0#
1$
#139
1"
0!
1(
1#
#140
0"
1!
0(
0#
0$
1%
#141
1"
0!
1(
1#
#142
0(
0&
1'
0#
1$
#143
1!
1#
#144
0"
0!
0'
0#
0$
0%
#145
1!
1#
#146
1&
0#
1$
#147
1"
0!
1(
1#
#148
0"
1!
0(
0#
0$
1%
#149
1"
0!
1(
1#
#150
0(
0&
1'
0#
1$
#151
1!
1#
#152
0"
0!
0'
0#
0$
0%
#153
1!
1#
#154
1&
0#
1$
#155
1"
0!
1(
1#
#156
0"
1!
0(
0#
0$
1%
#157
1"
0!
1(
1#
#158
0(
0&
1'
0#
1$
#159
1!
1#
#160
0"
0!
0'
0#
0$
0%
#161
1!
1#
#162
1&
0#
1$
#163
1"
0!
1(
1#
#164
0"
1!
0(
0#
0$
1%
#165
1"
0!
1(
1#
#166
0(
0&
1'
0#
1$
#167
1!
1#
#168
0"
0!
0'
0#
0$
0%
#169
1!
1#
#170
1&
0#
1$
#171
1"
0!
1(
1#
#172
0"
1!
0(
0#
0$
1%
#173
1"
0!
1(
1#
#174
0(
0&
1'
0#
1$
#175
1!
1#
#176
0"
0!
0'
0#
0$
0%
#177
1!
1#
#178
1&
0#
1$
#179
1"
0!
1(
1#
#180
0"
1!
0(
0#
0$
1%
#181
1"
0!
1(
1#
#182
0(
0&
1'
0#
1$
#183
1!
1#
#184
0"
0!
0'
0#
0$
0%
#185
1!
1#
#186
1&
0#
1$
#187
1"
0!
1(
1#
#188
0"
1!
0(
0#
0$
1%
#189
1"
0!
1(
1#
#190
0(
0&
1'
0#
1$
#191
1!
1#
#192
0"
0!
0'
0#
0$
0%
#193
1!
1#
#194
1&
0#
1$
#195
1"
0!
1(
1#
#196
0"
1!
0(
0#
0$
1%
#197
1"
0!
1(
1#
#198
0(
0&
1'
0#
1$
#199
1!
1#
#200
0"
0!
0'
0#
0$
0%
#201
1!
1#
#202
1&
0#
1$
#203
1"
0!
1(
1#
#204
0"
1!
0(
0#
0$
1%
#205
1"
0!
1(
1#
#206
0(
0&
1'
0#
1$
#207
1!
1#
#208
0"
0!
0'
0#
0$
0%
#209
1!
1#
#210
1&
0#
1$
#211
1"
0!
1(
1#
#212
0"
1!
0(
0#
0$
1%
#213
1"
0!
1(
1#
#214
0(
0&
1'
0#
1$
#215
1!
1#
#216
0"
0!
0'
0#
0$
0%
#217
1!
1#
#218
1&
0#
1$
#219
1"
0!
1(
1#
#220
0"
1!
0(
0#
0$
1%
#221
1"
0!
1(
1#
#222
0(
0&
1'
0#
1$
#223
1!
1#
#224
0"
0!
0'
0#
0$
0%
#225
1!
1#
#226
1&
0#
1$
#227
1"
0!
1(
1#
#228
0"
1!
0(
0#
0$
1%
#229
1"
0!
1(
1#
#230
0(
0&
1'
0#
1$
#231
1!
1#
#232
0"
0!
0'
0#
0$
0%
#233
1!
1#
#234
1&
0#
1$
#235
1"
0!
1(
1#
#236
0"
1!
0(
0#
0$
1%
#237
1"
0!
1(
1#
#238
0(
0&
1'
0#
1$
#239
1!
1#
#240
0"
0!
0'
0#
0$
0%
#241
1!
1#
#242
1&
0#
1$
#243
1"
0!
1(
1#
#244
0"
1!
0(
0#
0$
1%
#245
1"
0!
1(
1#
#246
0(
0&
1'
0#
1$
#247
1!
1#
#248
0"
0!
0'
0#
0$
0%
#249
1!
1#
#250
1&
0#
1$
#251
1"
0!
1(
1#
#252
0"
1!
0(
0#
0$
1%
#253
1"
0!
1(
1#
#254
0(
0&
1'
0#
1$
#255
1!
1#
#256
0"
0!
0'
0#
0$
0%
#257
1!
1#
#258
1&
0#
1$
#259
1"
0!
1(
1#
#260
0"
1!
0(
0#
0$
1%
#261
1"
0!
1(
1#
#262
0(
0&
1'
0#
1$
#263
1!
1#
#264
0"
0!
0'
0#
0$
0%
#265
1!
1#
#266
1&
0#
1$
#267
1"
0!
1(
1#
#268
0"
1!
0(
0#
0$
1%
#269
1"
0!
1(
1#
#270
0(
0&
1'
0#
1$
#271
1!
1#
#272
0"
0!
0'
0#
0$
0%
#273
1!
1#
#274
1&
0#
1$
#275
1"
0!
1(
1#
#276
0"
1!
0(
0#
0$
1%
#277
1"
0!
1(
1#
#278
0(
0&
1'
0#
1$
#279
1!
1#
#280
0"
0!
0'
0#
0$
0%
#281
1!
1#
#282
1&
0#
1$
#283
1"
0!
1(
1#
#284
0"
1!
0(
0#
0$
1%
#285
1"
0!
1(
1#
#286
0(
0&
1'
0#
1$
#287
1!
1#
#288
0"
0!
0'
0#
0$
0%
#289
1!
1#
#290
1&
0#
1$
#291
1"
0!
1(
1#
#292
0"
1!
0(
0#
0$
1%
#293
1"
0!
1(
1#
#294
0(
0&
1'
0#
1$
#295
1!
1#
#296
0"
0!
0'
0#
0$
0%
#297
1!
1#
#298
1&
0#
1$
#299
1"
0!
1(
1#
#300
0"
1!
0(
0#
0$
1%
#301
1"
0!
1(
1#
#302
0(
0&
1'
0#
1$
#303
1!
1#
#304
0"
0!
0'
0#
0$
0%
#305
1!
1#
#306
1&
0#
1$
#307
1"
0!
1(
1#
#308
0"
1!
0(
0#
0$
1%
#309
1"
0!
1(
1#
#310
0(
0&
1'
0#
1$
#311
1!
1#
#312
0"
0!
0'
0#
0$
0%
#313
1!
1#
#314
1&
0#
1$
#315
1"
0!
1(
1#
#316
0"
1!
0(
0#
0$
1%
#317
1"
0!
1(
1#
#318
0(
0&
1'
0#
1$
#319
1!
1#
#320
0"
0!
0'
0#
0$
0%
#321
1!
1#
#322
1&
0#
1$
#323
1"
0!
1(
1#
#324
0"
1!
0(
0#
0$
1%
#325
1"
0!
1(
1#
#326
0(
0&
1'
0#
1$
#327
1!
1#
#328
0"
0!
0'
0#
0$
0%
#329
1!
1#
#330
1&
0#
1$
#331
1"
0!
1(
1#
#332
0"
1!
0(
0#
0$
1%
#333
1"
0!
1(
1#
#334
0(
0&
1'
0#
1$
#335
1!
1#
#336
0"
0!
0'
0#
0$
0%
#337
1!
1#
#338
1&
0#
1$
#339
1"
0!
1(
1#
#340
0"
1!
0(
0#
0$
1%
#341
1"
0!
1(
1#
#342
0(
0&
1'
0#
1$
#343
1!
1#
#344
0"
0!
0'
0#
0$
0%
#345
1!
1#
#346
1&
0#
1$
#347
1"
0!
1(
1#
#348
0"
1!
0(
0#
0$
1%
#349
1"
0!
1(
1#
#350
0(
0&
1'
0#
1$
#351
1!
1#
#352
0"
0!
0'
0#
0$
0%
#353
1!
1#
#354
1&
0#
1$
#355
1"
0!
1(
1#
#356
0"
1!
0(
0#
0$
1%
#357
1"
0!
1(
1#
#358
0(
0&
1'
0#
1$
#359
1!
1#
#360
0"
0!
0'
0#
0$
0%
#361
1!
1#
#362
1&
0#
1$
#363
1"
0!
1(
1#
#364
0"
1!
0(
0#
0$
1%
#365
1"
0!
1(
1#
#366
0(
0&
1'
0#
1$
#367
1!
1#
#368
0"
0!
0'
0#
0$
0%
#369
1!
1#
#370
1&
0#
1$
#371
1"
0!
1(
1#
#372
0"
1!
0(
0#
0$
1%
#373
1"
0!
1(
1#
#374
0(
0&
1'
0#
1$
#375
1!
1#
#376
0"
0!
0'
0#
0$
0%
#377
1!
1#
#378
1&
0#
1$
#379
1"
0!
1(
1#
#380
0"
1!
0(
0#
0$
1%
#381
1"
0!
1(
1#
#382
0(
0&
1'
0#
1$
#383
1!
1#
#384
0"
0!
0'
0#
0$
0%
#385
1!
1#
#386
1&
0#
1$
#387
1"
0!
1(
1#
#388
0"
1!
0(
0#
0$
1%
#389
1"
0!
1(
1#
#390
0(
0&
1'
0#
1$
#391
1!
1#
#392
0"
0!
0'
0#
0$
0%
#393
1!
1#
#394
1&
0#
1$
#395
1"
0!
1(
1#
#396
0"
1!
0(
0#
0$
1%
#397
1"
0!
1(
1#
#398
0(
0&
1'
0#
1$
#399
1!
1#
#400
0"
0!
0'
0#
0$
0%
#401
1!
1#
#402
1&
0#
1$
#403
1"
0!
1(
1#
#404
0"
1!
0(
0#
0$
1%
#405
1"
0!
1(
1#
#406
0(
0&
1'
0#
1$
#407
1!
1#
#408
0"
0!
0'
0#
0$
0%
#409
1!
1#
#410
1&
0#
1$
#411
1"
0!
1(
1#
#412
0"
1!
0(
0#
0$
1%
#413
1"
0!
1(
1#
#414
0(
0&
1'
0#
1$
#415
1!
1#
#416
0"
0!
0'
0#
0$
0%
#417
1!
1#
#418
1&
0#
1$
#419
1"
0!
1(
1#
#420
0"
1!
0(
0#
0$
1%
#421
1"
0!
1(
1#
#422
0(
0&
1'
0#
1$
#423
1!
1#
#424
0"
0!
0'
0#
0$
0%
#425
1!
1#
#426
1&
0#
1$
#427
1"
0!
1(
1#
#428
0"
1!
0(
0#
0$
1%
#429
1"
0!
1(
1#
#430
0(
0&
1'
0#
1$
#431
1!
1#
#432
0"
0!
0'
0#
0$
0%
#433
1!
1#
#434
1&
0#
1$
#435
1"
0!
1(
1#
#436
0"
1!
0(
0#
0$
1%
#437
1"
0!
1(
1#
#438
0(
0&
1'
0#
1$
#439
1!
1#
#440
0"
0!
0'
0#
0$
0%
#441
1!
1#
#442
1&
0#
1$
#443
1"
0!
1(
1#
#444
0"
1!
0(
0#
0$
1%
#445
1"
0!
1(
1#
#446
0(
0&
1'
0#
1$
#447
1!
1#
#448
0"
0!
0'
0#
0$
0%
#449
1!
1#
#450
1&
0#
1$
#451
1"
0!
1(
1#
#452
0"
1!
0(
0#
0$
1%
#453
1"
0!
1(
1#
#454
0(
0&
1'
0#
1$
#455
1!
1#
#456
0"
0!
0'
0#
0$
0%
#457
1!
1#
#458
1&
0#
1$
#459
1"
0!
1(
1#
#460
0"
1!
0(
0#
0$
1%
#461
1"
0!
1(
1#
#462
0(
0&
1'
0#
1$
#463
1!
1#
#464
0"
0!
0'
0#
0$
0%
#465
1!
1#
#466
1&
0#
1$
#467
1"
0!
1(
1#
#468
0"
1!
0(
0#
0$
1%
#469
1"
0!
1(
1#
#470
0(
0&
1'
0#
1$
#471
1!
1#
#472
0"
0!
0'
0#
0$
0%
#473
1!
1#
#474
1&
0#
1$
#475
1"
0!
1(
1#
#476
0"
1!
0(
0#
0$
1%
#477
1"
0!
1(
1#
#478
0(
0&
1'
0#
1$
#479
1!
1#
#480
0"
0!
0'
0#
0$
0%
#481
1!
1#
#482
1&
0#
1$
#483
1"
0!
1(
1#
#484
0"
1!
0(
0#
0$
1%
#485
1"
0!
1(
1#
#486
0(
0&
1'
0#
1$
#487
1!
1#
#488
0"
0!
0'
0#
0$
0%
#489
1!
1#
#490
1&
0#
1$
#491
1"
0!
1(
1#
#492
0"
1!
0(
0#
0$
1%
#493
1"
0!
1(
1#
#494
0(
0&
1'
0#
1$
#495
1!
1#
#496
0"
0!
0'
0#
0$
0%
#497
1!
1#
#498
1&
0#
1$
#499
1"
0!
1(
1#
#500
0"
1!
0(
0#
0$
1%
#501
1"
0!
1(
1#
#502
0(
0&
1'
0#
1$
#503
1!
1#
#504
0"
0!
0'
0#
0$
0%
#505
1!
1#
#506
1&
0#
1$
#507
1"
0!
1(
1#
#508
0"
1!
0(
0#
0$
1%
#509
1"
0!
1(
1#
#510
0(
0&
1'
0#
1$
#511
1!
1#
#512
0"
0!
0'
0#
0$
0%
#513
1!
1#
#514
1&
0#
1$
#515
1"
0!
1(
1#
#516
0"
1!
0(
0#
0$
1%
#517
1"
0!
1(
1#
#518
0(
0&
1'
0#
1$
#519
1!
1#
#520
0"
0!
0'
0#
0$
0%
#521
1!
1#
#522
1&
0#
1$
#523
1"
0!
1(
1#
#524
0"
1!
0(
0#
0$
1%
#525
1"
0!
1(
1#
#526
0(
0&
1'
0#
1$
#527
1!
1#
#528
0"
0!
0'
0#
0$
0%
#529
1!
1#
#530
1&
0#
1$
#531
1"
0!
1(
1#
#532
0"
1!
0(
0#
0$
1%
#533
1"
0!
1(
1#
#534
0(
0&
1'
0#
1$
#535
1!
1#
#536
0"
0!
0'
0#
0$
0%
#537
1!
1#
#538
1&
0#
1$
#539
1"
0!
1(
1#
#540
0"
1!
0(
0#
0$
1%
#541
1"
0!
1(
1#
#542
0(
0&
1'
0#
1$
#543
1!
1#
#544
0"
0!
0'
0#
0$
0%
#545
1!
1#
#546
1&
0#
1$
#547
1"
0!
1(
1#
#548
0"
1!
0(
0#
0$
1%
#549
1"
0!
1(
1#
#550
0(
0&
1'
0#
1$
#551
1!
1#
#552
0"
0!
0'
0#
0$
0%
#553
1!
1#
#554
1&
0#
1$
#555
1"
0!
1(
1#
#556
0"
1!
0(
0#
0$
1%
#557
1"
0!
1(
1#
#558
0(
0&
1'
0#
1$
#559
1!
1#
#560
0"
0!
0'
0#
0$
0%
#561
1!
1#
#562
1&
0#
1$
#563
1"
0!
1(
1#
#564
0"
1!
0(
0#
0$
1%
#565
1"
0!
1(
1#
#566
0(
0&
1'
0#
1$
#567
1!
1#
#568
0"
0!
0'
0#
0$
0%
#569
1!
1#
#570
1&
0#
1$
#571
1"
0!
1(
1#
#572
0"
1!
0(
0#
0$
1%
#573
1"
0!
1(
1#
#574
0(
0&
1'
0#
1$
#575
1!
1#
#576
0"
0!
0'
0#
0$
0%
#577
1!
1#
#578
1&
0#
1$
#579
1"
0!
1(
1#
#580
0"
1!
0(
0#
0$
1%
#581
1"
0!
1(
1#
#582
0(
0&
1'
0#
1$
#583
1!
1#
#584
0"
0!
0'
0#
0$
0%
#585
1!
1#
#586
1&
0#
1$
#587
1"
0!
1(
1#
#588
0"
1!
0(
0#
0$
1%
#589
1"
0!
1(
1#
#590
0(
0&
1'
0#
1$
#591
1!
1#
#592
0"
0!
0'
0#
0$
0%
#593
1!
1#
#594
1&
0#
1$
#595
1"
0!
1(
1#
#596
0"
1!
0(
0#
0$
1%
#597
1"
0!
1(
1#
#598
0(
0&
1'
0#
1$
#599
1!
1#
#600
0"
0!
0'
0#
0$
0%
#601
1!
1#
#602
1&
0#
1$
#603
1"
0!
1(
1#
#604
0"
1!
0(
0#
0$
1%
#605
1"
0!
1(
1#
#606
0(
0&
1'
0#
1$
#607
1!
1#
#608
0"
0!
0'
0#
0$
0%
#609
1!
1#
#610
1&
0#
1$
#611
1"
0!
1(
1#
#612
0"
1!
0(
0#
0$
1%
#613
1"
0!
1(
1#
#614
0(
0&
1'
0#
1$
#615
1!
1#
#616
0"
0!
0'
0#
0$
0%
#617
1!
1#
#618
1&
0#
1$
#619
1"
0!
1(
1#
#620
0"
1!
0(
0#
0$
1%
#621
1"
0!
1(
1#
#622
0(
0&
1'
0#
1$
#623
1!
1#
#624
0"
0!
0'
0#
0$
0%
#625
1!
1#
#626
1&
0#
1$
#627
1"
0!
1(
1#
#628
0"
1!
0(
0#
0$
1%
#629
1"
0!
1(
1#
#630
0(
0&
1'
0#
1$
#631
1!
1#
#632
0"
0!
0'
0#
0$
0%
#633
1!
1#
#634
1&
0#
1$
#635
1"
0!
1(
1#
#636
0"
1!
0(
0#
0$
1%
#637
1"
0!
1(
1#
#638
0(
0&
1'
0#
1$
#639
1!
1#
#640
0"
0!
0'
0#
0$
0%
#641
1!
1#
#642
1&
0#
1$
#643
1"
0!
1(
1#
#644
0"
1!
0(
0#
0$
1%
#645
1"
0!
1(
1#
#646
0(
0&
1'
0#
1$
#647
1!
1#
#648
0"
0!
0'
0#
0$
0%
#649
1!
1#
#650
1&
0#
1$
#651
1"
0!
1(
1#
#652
0"
1!
0(
0#
0$
1%
#653
1"
0!
1(
1#
#654
0(
0&
1'
0#
1$
#655
1!
1#
#656
0"
0!
0'
0#
0$
0%
#657
1!
1#
#658
1&
0#
1$
#659
1"
0!
1(
1#
#660
0"
1!
0(
0#
0$
1%
#661
1"
0!
1(
1#
#662
0(
0&
1'
0#
1$
#663
1!
1#
#664
0"
0!
0'
0#
0$
0%
#665
1!
1#
#666
1&
0#
1$
#667
1"
0!
1(
1#
#668
0"
1!
0(
0#
0$
1%
#669
1"
0!
1(
1#
#670
0(
0&
1'
0#
1$
#671
1!
1#
#672
0"
0!
0'
0#
0$
0%
#673
1!
1#
#674
1&
0#
1$
#675
1"
0!
1(
1#
#676
0"
1!
0(
0#
0$
1%
#677
1"
0!
1(
1#
#678
0(
0&
1'
0#
1$
#679
1!
1#
#680
0"
0!
0'
0#
0$
0%
#681
1!
1#
#682
1&
0#
1$
#683
1"
0!
1(
1#
#684
0"
1!
0(
0#
0$
1%
#685
1"
0!
1(
1#
#686
0(
0&
1'
0#
1$
#687
1!
1#
#688
0"
0!
0'
0#
0$
0%
#689
1!
1#
#690
1&
0#
1$
#691
1"
0!
1(
1#
#692
0"
1!
0(
0#
0$
1%
#693
1"
0!
1(
1#
#694
0(
0&
1'
0#
1$
#695
1!
1#
#696
0"
0!
0'
0#
0$
0%
#697
1!
1#
#698
1&
0#
1$
#699
1"
0!
1(
1#
#700
0"
1!
0(
0#
0$
1%
#701
1"
0!
1(
1#
#702
0(
0&
1'
0#
1$
#703
1!
1#
#704
0"
0!
0'
0#
0$
0%
#705
1!
1#
#706
1&
0#
1$
#707
1"
0!
1(
1#
#708
0"
1!
0(
0#
0$
1%
#709
1"
0!
1(
1#
#710
0(
0&
1'
0#
1$
#711
1!
1#
#712
0"
0!
0'
0#
0$
0%
#713
1!
1#
#714
1&
0#
1$
#715
1"
0!
1(
1#
#716
0"
1!
0(
0#
0$
1%
#717
1"
0!
1(
1#
#718
0(
0&
1'
0#
1$
#719
1!
1#
#720
0"
0!
0'
0#
0$
0%
#721
1!
1#
#722
1&
0#
1$
#723
1"
0!
1(
1#
#724
0"
1!
0(
0#
0$
1%
#725
1"
0!
1(
1#
#726
0(
0&
1'
0#
1$
#727
1!
1#
#728
0"
0!
0'
0#
0$
0%
#729
1!
1#
#730
1&
0#
1$
#731
1"
0!
1(
1#
#732
0"
1!
0(
0#
0$
1%
#733
1"
0!
1(
1#
#734
0(
0&
1'
0#
1$
#735
1!
1#
#736
0"
0!
0'
0#
0$
0%
#737
1!
1#
#738
1&
0#
1$
#739
1"
0!
1(
1#
#740
0"
1!
0(
0#
0$
1%
#741
1"
0!
1(
1#
#742
0(
0&
1'
0#
1$
#743
1!
1#
#744
0"
0!
0'
0#
0$
0%
#745
1!
1#
#746
1&
0#
1$
#747
1"
0!
1(
1#
#748
0"
1!
0(
0#
0$
1%
#749
1"
0!
1(
1#
#750
0(
0&
1'
0#
1$
#751
1!
1#
#752
0"
0!
0'
0#
0$
0%
#753
1!
1#
#754
1&
0#
1$
#755
1"
0!
1(
1#
#756
0"
1!
0(
0#
0$
1%
#757
1"
0!
1(
1#
#758
0(
0&
1'
0#
1$
#759
1!
1#
#760
0"
0!
0'
0#
0$
0%
#761
1!
1#
#762
1&
0#
1$
#763
1"
0!
1(
1#
#764
0"
1!
0(
0#
0$
1%
#765
1"
0!
1(
1#
#766
0(
0&
1'
0#
1$
#767
1!
1#
#768
0"
0!
0'
0#
0$
0%
#769
1!
1#
#770
1&
0#
1$
#771
1"
0!
1(
1#
#772
0"
1!
0(
0#
0$
1%
#773
1"
0!
1(
1#
#774
0(
0&
1'
0#
1$
#775
1!
1#
#776
0"
0!
0'
0#
0$
0%
#777
1!
1#
#778
1&
0#
1$
#779
1"
0!
1(
1#
#780
0"
1!
0(
0#
0$
1%
#781
1"
0!
1(
1#
#782
0(
0&
1'
0#
1$
#783
1!
1#
#784
0"
0!
0'
0#
0$
0%
#785
1!
1#
#786
1&
0#
1$
#787
1"
0!
1(
1#
#788
0"
1!
0(
0#
0$
1%
#789
1"
0!
1(
1#
#790
0(
0&
1'
0#
1$
#791
1!
1#
#792
0"
0!
0'
0#
0$
0%
#793
1!
1#
#794
1&
0#
1$
#795
1"
0!
1(
1#
#796
0"
1!
0(
0#
0$
1%
#797
1"
0!
1(
1#
#798
0(
0&
1'
0#
1$
#799
1!
1#
#800
0"
0!
0'
0#
0$
0%
#801
1!
1#
#802
1&
0#
1$
#803
1"
0!
1(
1#
#804
0"
1!
0(
0#
0$
1%
#805
1"
0!
1(
1#
#806
0(
0&
1'
0#
1$
#807
1!
1#
#808
0"
0!
0'
0#
0$
0%
#809
1!
1#
#810
1&
0#
1$
#811
1"
0!
1(
1#
#812
0"
1!
0(
0#
0$
1%
#813
1"
0!
1(
1#
#814
0(
0&
1'
0#
1$
#815
1!
1#
#816
0"
0!
0'
0#
0$
0%
#817
1!
1#
#818
1&
0#
1$
#819
1"
0!
1(
1#
#820
0"
1!
0(
0#
0$
1%
#821
1"
0!
1(
1#
#822
0(
0&
1'
0#
1$
#823
1!
1#
#824
0"
0!
0'
0#
0$
0%
#825
1!
1#
#826
1&
0#
1$
#827
1"
0!
1(
1#
#828
0"
1!
0(
0#
0$
1%
#829
1"
0!
1(
1#
#830
0(
0&
1'
0#
1$
#831
1!
1#
#832
0"
0!
0'
0#
0$
0%
#833
1!
1#
#834
1&
0#
1$
#835
1"
0!
1(
1#
#836
0"
1!
0(
0#
0$
1%
#837
1"
0!
1(
1#
#838
0(
0&
1'
0#
1$
#839
1!
1#
#840
0"
0!
0'
0#
0$
0%
#841
1!
1#
#842
1&
0#
1$
#843
1"
0!
1(
1#
#844
0"
1!
0(
0#
0$
1%
#845
1"
0!
1(
1#
#846
0(
0&
1'
0#
1$
#847
1!
1#
#848
0"
0!
0'
0#
0$
0%
#849
1!
1#
#850
1&
0#
1$
#851
1"
0!
1(
1#
#852
0"
1!
0(
0#
0$
1%
#853
1"
0!
1(
1#
#854
0(
0&
1'
0#
1$
#855
1!
1#
#856
0"
0!
0'
0#
0$
0%
#857
1!
1#
#858
1&
0#
1$
#859
1"
0!
1(
1#
#860
0"
1!
0(
0#
0$
1%
#861
1"
0!
1(
1#
#862
0(
0&
1'
0#
1$
#863
1!
1#
#864
0"
0!
0'
0#
0$
0%
#865
1!
1#
#866
1&
0#
1$
#867
1"
0!
1(
1#
#868
0"
1!
0(
0#
0$
1%
#869
1"
0!
1(
1#
#870
0(
0&
1'
0#
1$
#871
1!
1#
#872
0"
0!
0'
0#
0$
0%
#873
1!
1#
#874
1&
0#
1$
#875
1"
0!
1(
1#
#876
0"
1!
0(
0#
0$
1%
#877
1"
0!
1(
1#
#878
0(
0&
1'
0#
1$
#879
1!
1#
#880
0"
0!
0'
0#
0$
0%
#881
1!
1#
#882
1&
0#
1$
#883
1"
0!
1(
1#
#884
0"
1!
0(
0#
0$
1%
#885
1"
0!
1(
1#
#886
0(
0&
1'
0#
1$
#887
1!
1#
#888
0"
0!
0'
0#
0$
0%
#889
1!
1#
#890
1&
0#
1$
#891
1"
0!
1(
1#
#892
0"
1!
0(
0#
0$
1%
#893
1"
0!
1(
1#
#894
0(
0&
1'
0#
1$
#895
1!
1#
#896
0"
0!
0'
0#
0$
0%
#897
1!
1#
#898
1&
0#
1$
#899
1"
0!
1(
1#
#900
0"
1!
0(
0#
0$
1%
#901
1"
0!
1(
1#
#902
0(
0&
1'
0#
1$
#903
1!
1#
#904
0"
0!
0'
0#
0$
0%
#905
1!
1#
#906
1&
0#
1$
#907
1"
0!
1(
1#
#908
0"
1!
0(
0#
0$
1%
#909
1"
0!
1(
1#
#910
0(
0&
1'
0#
1$
#911
1!
1#
#912
0"
0!
0'
0#
0$
0%
#913
1!
1#
#914
1&
0#
1$
#915
1"
0!
1(
1#
#916
0"
1!
0(
0#
0$
1%
#917
1"
0!
1(
1#
#918
0(
0&
1'
0#
1$
#919
1!
1#
#920
0"
0!
0'
0#
0$
0%
#921
1!
1#
#922
1&
0#
1$
#923
1"
0!
1(
1#
#924
0"
1!
0(
0#
0$
1%
#925
1"
0!
1(
1#
#926
0(
0&
1'
0#
1$
#927
1!
1#
#928
0"
0!
0'
0#
0$
0%
#929
1!
1#
#930
1&
0#
1$
#931
1"
0!
1(
1#
