arithmetic/HalfAdder.v
module HalfAdder (
    input a, b,
    output sum, carry
);
    
    assign sum = a ^ b;
    assign carry = a & b;

endmodule

arithmetic/HalfAdder_tb.v
module HalfAdder_tb;
    reg a = 0, b = 0;
    wire out, carry;
    HalfAdder halfadder (a, b, out, carry);

    initial begin
        $dumpfile("HalfAdder.vcd");
        $dumpvars(0, HalfAdder_tb);
        #1000 $finish;
    end

    always begin
        #1 a = ~a;
    end

    always begin
        #2 b = ~b;
    end
    
endmodule

arithmetic/HalfAdder.vcd
$date
	Sat Aug 26 14:33:51 2023
$end
$version
	Icarus Verilog
$end
$timescale
	1s
$end
$scope module HalfAdder_tb $end
$var wire 1 ! out $end
$var wire 1 " carry $end
$var reg 1 # a $end
$var reg 1 $ b $end
$scope module halfadder $end
$var wire 1 # a $end
$var wire 1 $ b $end
$var wire 1 " carry $end
$var wire 1 ! sum $end
$upscope $end
$upscope $end
$enddefinitions $end
$comment Show the parameter values. $end
$dumpall
$end
#0
$dumpvars
0$
0#
0"
0!
$end
#1
1!
1#
#2
0#
1$
#3
0!
1"
1#
#4
0"
0#
0$
#5
1!
1#
#6
0#
1$
#7
0!
1"
1#
#8
0"
0#
0$
#9
1!
1#
#10
0#
1$
#11
0!
1"
1#
#12
0"
0#
0$
#13
1!
1#
#14
0#
1$
#15
0!
1"
1#
#16
0"
0#
0$
#17
1!
1#
#18
0#
1$
#19
0!
1"
1#
#20
0"
0#
0$
#21
1!
1#
#22
0#
1$
#23
0!
1"
1#
#24
0"
0#
0$
#25
1!
1#
#26
0#
1$
#27
0!
1"
1#
#28
0"
0#
0$
#29
1!
1#
#30
0#
1$
#31
0!
1"
1#
#32
0"
0#
0$
#33
1!
1#
#34
0#
1$
#35
0!
1"
1#
#36
0"
0#
0$
#37
1!
1#
#38
0#
1$
#39
0!
1"
1#
#40
0"
0#
0$
#41
1!
1#
#42
0#
1$
#43
0!
1"
1#
#44
0"
0#
0$
#45
1!
1#
#46
0#
1$
#47
0!
1"
1#
#48
0"
0#
0$
#49
1!
1#
#50
0#
1$
#51
0!
1"
1#
#52
0"
0#
0$
#53
1!
1#
#54
0#
1$
#55
0!
1"
1#
#56
0"
0#
0$
#57
1!
1#
#58
0#
1$
#59
0!
1"
1#
#60
0"
0#
0$
#61
1!
1#
#62
0#
1$
#63
0!
1"
1#
#64
0"
0#
0$
#65
1!
1#
#66
0#
1$
#67
0!
1"
1#
#68
0"
0#
0$
#69
1!
1#
#70
0#
1$
#71
0!
1"
1#
#72
0"
0#
0$
#73
1!
1#
#74
0#
1$
#75
0!
1"
1#
#76
0"
0#
0$
#77
1!
1#
#78
0#
1$
#79
0!
1"
1#
#80
0"
0#
0$
#81
1!
1#
#82
0#
1$
#83
0!
1"
1#
#84
0"
0#
0$
#85
1!
1#
#86
0#
1$
#87
0!
1"
1#
#88
0"
0#
0$
#89
1!
1#
#90
0#
1$
#91
0!
1"
1#
#92
0"
0#
0$
#93
1!
1#
#94
0#
1$
#95
0!
1"
1#
#96
0"
0#
0$
#97
1!
1#
#98
0#
1$
#99
0!
1"
1#
#100
0"
0#
0$
#101
1!
1#
#102
0#
1$
#103
0!
1"
1#
#104
0"
0#
0$
#105
1!
1#
#106
0#
1$
#107
0!
1"
1#
#108
0"
0#
0$
#109
1!
1#
#110
0#
1$
#111
0!
1"
1#
#112
0"
0#
0$
#113
1!
1#
#114
0#
1$
#115
0!
1"
1#
#116
0"
0#
0$
#117
1!
1#
#118
0#
1$
#119
0!
1"
1#
#120
0"
0#
0$
#121
1!
1#
#122
0#
1$
#123
0!
1"
1#
#124
0"
0#
0$
#125
1!
1#
#126
0#
1$
#127
0!
1"
1#
#128
0"
0#
0$
#129
1!
1#
#130
0#
1$
#131
0!
1"
1#
#132
0"
0#
0$
#133
1!
1#
#134
0#
1$
#135
0!
1"
1#
#136
0"
0#
0$
#137
1!
1#
#138
0#
1$
#139
0!
1"
1#
#140
0"
0#
0$
#141
1!
1#
#142
0#
1$
#143
0!
1"
1#
#144
0"
0#
0$
#145
1!
1#
#146
0#
1$
#147
0!
1"
1#
#148
0"
0#
0$
#149
1!
1#
#150
0#
1$
#151
0!
1"
1#
#152
0"
0#
0$
#153
1!
1#
#154
0#
1$
#155
0!
1"
1#
#156
0"
0#
0$
#157
1!
1#
#158
0#
1$
#159
0!
1"
1#
#160
0"
0#
0$
#161
1!
1#
#162
0#
1$
#163
0!
1"
1#
#164
0"
0#
0$
#165
1!
1#
#166
0#
1$
#167
0!
1"
1#
#168
0"
0#
0$
#169
1!
1#
#170
0#
1$
#171
0!
1"
1#
#172
0"
0#
0$
#173
1!
1#
#174
0#
1$
#175
0!
1"
1#
#176
0"
0#
0$
#177
1!
1#
#178
0#
1$
#179
0!
1"
1#
#180
0"
0#
0$
#181
1!
1#
#182
0#
1$
#183
0!
1"
1#
#184
0"
0#
0$
#185
1!
1#
#186
0#
1$
#187
0!
1"
1#
#188
0"
0#
0$
#189
1!
1#
#190
0#
1$
#191
0!
1"
1#
#192
0"
0#
0$
#193
1!
1#
#194
0#
1$
#195
0!
1"
1#
#196
0"
0#
0$
#197
1!
1#
#198
0#
1$
#199
0!
1"
1#
#200
0"
0#
0$
#201
1!
1#
#202
0#
1$
#203
0!
1"
1#
#204
0"
0#
0$
#205
1!
1#
#206
0#
1$
#207
0!
1"
1#
#208
0"
0#
0$
#209
1!
1#
#210
0#
1$
#211
0!
1"
1#
#212
0"
0#
0$
#213
1!
1#
#214
0#
1$
#215
0!
1"
1#
#216
0"
0#
0$
#217
1!
1#
#218
0#
1$
#219
0!
1"
1#
#220
0"
0#
0$
#221
1!
1#
#222
0#
1$
#223
0!
1"
1#
#224
0"
0#
0$
#225
1!
1#
#226
0#
1$
#227
0!
1"
1#
#228
0"
0#
0$
#229
1!
1#
#230
0#
1$
#231
0!
1"
1#
#232
0"
0#
0$
#233
1!
1#
#234
0#
1$
#235
0!
1"
1#
#236
0"
0#
0$
#237
1!
1#
#238
0#
1$
#239
0!
1"
1#
#240
0"
0#
0$
#241
1!
1#
#242
0#
1$
#243
0!
1"
1#
#244
0"
0#
0$
#245
1!
1#
#246
0#
1$
#247
0!
1"
1#
#248
0"
0#
0$
#249
1!
1#
#250
0#
1$
#251
0!
1"
1#
#252
0"
0#
0$
#253
1!
1#
#254
0#
1$
#255
0!
1"
1#
#256
0"
0#
0$
#257
1!
1#
#258
0#
1$
#259
0!
1"
1#
#260
0"
0#
0$
#261
1!
1#
#262
0#
1$
#263
0!
1"
1#
#264
0"
0#
0$
#265
1!
1#
#266
0#
1$
#267
0!
1"
1#
#268
0"
0#
0$
#269
1!
1#
#270
0#
1$
#271
0!
1"
1#
#272
0"
0#
0$
#273
1!
1#
#274
0#
1$
#275
0!
1"
1#
#276
0"
0#
0$
#277
1!
1#
#278
0#
1$
#279
0!
1"
1#
#280
0"
0#
0$
#281
1!
1#
#282
0#
1$
#283
0!
1"
1#
#284
0"
0#
0$
#285
1!
1#
#286
0#
1$
#287
0!
1"
1#
#288
0"
0#
0$
#289
1!
1#
#290
0#
1$
#291
0!
1"
1#
#292
0"
0#
0$
#293
1!
1#
#294
0#
1$
#295
0!
1"
1#
#296
0"
0#
0$
#297
1!
1#
#298
0#
1$
#299
0!
1"
1#
#300
0"
0#
0$
#301
1!
1#
#302
0#
1$
#303
0!
1"
1#
#304
0"
0#
0$
#305
1!
1#
#306
0#
1$
#307
0!
1"
1#
#308
0"
0#
0$
#309
1!
1#
#310
0#
1$
#311
0!
1"
1#
#312
0"
0#
0$
#313
1!
1#
#314
0#
1$
#315
0!
1"
1#
#316
0"
0#
0$
#317
1!
1#
#318
0#
1$
#319
0!
1"
1#
#320
0"
0#
0$
#321
1!
1#
#322
0#
1$
#323
0!
1"
1#
#324
0"
0#
0$
#325
1!
1#
#326
0#
1$
#327
0!
1"
1#
#328
0"
0#
0$
#329
1!
1#
#330
0#
1$
#331
0!
1"
1#
#332
0"
0#
0$
#333
1!
1#
#334
0#
1$
#335
0!
1"
1#
#336
0"
0#
0$
#337
1!
1#
#338
0#
1$
#339
0!
1"
1#
#340
0"
0#
0$
#341
1!
1#
#342
0#
1$
#343
0!
1"
1#
#344
0"
0#
0$
#345
1!
1#
#346
0#
1$
#347
0!
1"
1#
#348
0"
0#
0$
#349
1!
1#
#350
0#
1$
#351
0!
1"
1#
#352
0"
0#
0$
#353
1!
1#
#354
0#
1$
#355
0!
1"
1#
#356
0"
0#
0$
#357
1!
1#
#358
0#
1$
#359
0!
1"
1#
#360
0"
0#
0$
#361
1!
1#
#362
0#
1$
#363
0!
1"
1#
#364
0"
0#
0$
#365
1!
1#
#366
0#
1$
#367
0!
1"
1#
#368
0"
0#
0$
#369
1!
1#
#370
0#
1$
#371
0!
1"
1#
#372
0"
0#
0$
#373
1!
1#
#374
0#
1$
#375
0!
1"
1#
#376
0"
0#
0$
#377
1!
1#
#378
0#
1$
#379
0!
1"
1#
#380
0"
0#
0$
#381
1!
1#
#382
0#
1$
#383
0!
1"
1#
#384
0"
0#
0$
#385
1!
1#
#386
0#
1$
#387
0!
1"
1#
#388
0"
0#
0$
#389
1!
1#
#390
0#
1$
#391
0!
1"
1#
#392
0"
0#
0$
#393
1!
1#
#394
0#
1$
#395
0!
1"
1#
#396
0"
0#
0$
#397
1!
1#
#398
0#
1$
#399
0!
1"
1#
#400
0"
0#
0$
#401
1!
1#
#402
0#
1$
#403
0!
1"
1#
#404
0"
0#
0$
#405
1!
1#
#406
0#
1$
#407
0!
1"
1#
#408
0"
0#
0$
#409
1!
1#
#410
0#
1$
#411
0!
1"
1#
#412
0"
0#
0$
#413
1!
1#
#414
0#
1$
#415
0!
1"
1#
#416
0"
0#
0$
#417
1!
1#
#418
0#
1$
#419
0!
1"
1#
#420
0"
0#
0$
#421
1!
1#
#422
0#
1$
#423
0!
1"
1#
#424
0"
0#
0$
#425
1!
1#
#426
0#
1$
#427
0!
1"
1#
#428
0"
0#
0$
#429
1!
1#
#430
0#
1$
#431
0!
1"
1#
#432
0"
0#
0$
#433
1!
1#
#434
0#
1$
#435
0!
1"
1#
#436
0"
0#
0$
#437
1!
1#
#438
0#
1$
#439
0!
1"
1#
#440
0"
0#
0$
#441
1!
1#
#442
0#
1$
#443
0!
1"
1#
#444
0"
0#
0$
#445
1!
1#
#446
0#
1$
#447
0!
1"
1#
#448
0"
0#
0$
#449
1!
1#
#450
0#
1$
#451
0!
1"
1#
#452
0"
0#
0$
#453
1!
1#
#454
0#
1$
#455
0!
1"
1#
#456
0"
0#
0$
#457
1!
1#
#458
0#
1$
#459
0!
1"
1#
#460
0"
0#
0$
#461
1!
1#
#462
0#
1$
#463
0!
1"
1#
#464
0"
0#
0$
#465
1!
1#
#466
0#
1$
#467
0!
1"
1#
#468
0"
0#
0$
#469
1!
1#
#470
0#
1$
#471
0!
1"
1#
#472
0"
0#
0$
#473
1!
1#
#474
0#
1$
#475
0!
1"
1#
#476
0"
0#
0$
#477
1!
1#
#478
0#
1$
#479
0!
1"
1#
#480
0"
0#
0$
#481
1!
1#
#482
0#
1$
#483
0!
1"
1#
#484
0"
0#
0$
#485
1!
1#
#486
0#
1$
#487
0!
1"
1#
#488
0"
0#
0$
#489
1!
1#
#490
0#
1$
#491
0!
1"
1#
#492
0"
0#
0$
#493
1!
1#
#494
0#
1$
#495
0!
1"
1#
#496
0"
0#
0$
#497
1!
1#
#498
0#
1$
#499
0!
1"
1#
#500
0"
0#
0$
#501
1!
1#
#502
0#
1$
#503
0!
1"
1#
#504
0"
0#
0$
#505
1!
1#
#506
0#
1$
#507
0!
1"
1#
#508
0"
0#
0$
#509
1!
1#
#510
0#
1$
#511
0!
1"
1#
#512
0"
0#
0$
#513
1!
1#
#514
0#
1$
#515
0!
1"
1#
#516
0"
0#
0$
#517
1!
1#
#518
0#
1$
#519
0!
1"
1#
#520
0"
0#
0$
#521
1!
1#
#522
0#
1$
#523
0!
1"
1#
#524
0"
0#
0$
#525
1!
1#
#526
0#
1$
#527
0!
1"
1#
#528
0"
0#
0$
#529
1!
1#
#530
0#
1$
#531
0!
1"
1#
#532
0"
0#
0$
#533
1!
1#
#534
0#
1$
#535
0!
1"
1#
#536
0"
0#
0$
#537
1!
1#
#538
0#
1$
#539
0!
1"
1#
#540
0"
0#
0$
#541
1!
1#
#542
0#
1$
#543
0!
1"
1#
#544
0"
0#
0$
#545
1!
1#
#546
0#
1$
#547
0!
1"
1#
#548
0"
0#
0$
#549
1!
1#
#550
0#
1$
#551
0!
1"
1#
#552
0"
0#
0$
#553
1!
1#
#554
0#
1$
#555
0!
1"
1#
#556
0"
0#
0$
#557
1!
1#
#558
0#
1$
#559
0!
1"
1#
#560
0"
0#
0$
#561
1!
1#
#562
0#
1$
#563
0!
1"
1#
#564
0"
0#
0$
#565
1!
1#
#566
0#
1$
#567
0!
1"
1#
#568
0"
0#
0$
#569
1!
1#
#570
0#
1$
#571
0!
1"
1#
#572
0"
0#
0$
#573
1!
1#
#574
0#
1$
#575
0!
1"
1#
#576
0"
0#
0$
#577
1!
1#
#578
0#
1$
#579
0!
1"
1#
#580
0"
0#
0$
#581
1!
1#
#582
0#
1$
#583
0!
1"
1#
#584
0"
0#
0$
#585
1!
1#
#586
0#
1$
#587
0!
1"
1#
#588
0"
0#
0$
#589
1!
1#
#590
0#
1$
#591
0!
1"
1#
#592
0"
0#
0$
#593
1!
1#
#594
0#
1$
#595
0!
1"
1#
#596
0"
0#
0$
#597
1!
1#
#598
0#
1$
#599
0!
1"
1#
#600
0"
0#
0$
#601
1!
1#
#602
0#
1$
#603
0!
1"
1#
#604
0"
0#
0$
#605
1!
1#
#606
0#
1$
#607
0!
1"
1#
#608
0"
0#
0$
#609
1!
1#
#610
0#
1$
#611
0!
1"
1#
#612
0"
0#
0$
#613
1!
1#
#614
0#
1$
#615
0!
1"
1#
#616
0"
0#
0$
#617
1!
1#
#618
0#
1$
#619
0!
1"
1#
#620
0"
0#
0$
#621
1!
1#
#622
0#
1$
#623
0!
1"
1#
#624
0"
0#
0$
#625
1!
1#
#626
0#
1$
#627
0!
1"
1#
#628
0"
0#
0$
#629
1!
1#
#630
0#
1$
#631
0!
1"
1#
#632
0"
0#
0$
#633
1!
1#
#634
0#
1$
#635
0!
1"
1#
#636
0"
0#
0$
#637
1!
1#
#638
0#
1$
#639
0!
1"
1#
#640
0"
0#
0$
#641
1!
1#
#642
0#
1$
#643
0!
1"
1#
#644
0"
0#
0$
#645
1!
1#
#646
0#
1$
#647
0!
1"
1#
#648
0"
0#
0$
#649
1!
1#
#650
0#
1$
#651
0!
1"
1#
#652
0"
0#
0$
#653
1!
1#
#654
0#
1$
#655
0!
1"
1#
#656
0"
0#
0$
#657
1!
1#
#658
0#
1$
#659
0!
1"
1#
#660
0"
0#
0$
#661
1!
1#
#662
0#
1$
#663
0!
1"
1#
#664
0"
0#
0$
#665
1!
1#
#666
0#
1$
#667
0!
1"
1#
#668
0"
0#
0$
#669
1!
1#
#670
0#
1$
#671
0!
1"
1#
#672
0"
0#
0$
#673
1!
1#
#674
0#
1$
#675
0!
1"
1#
#676
0"
0#
0$
#677
1!
1#
#678
0#
1$
#679
0!
1"
1#
#680
0"
0#
0$
#681
1!
1#
#682
0#
1$
#683
0!
1"
1#
#684
0"
0#
0$
#685
1!
1#
#686
0#
1$
#687
0!
1"
1#
#688
0"
0#
0$
#689
1!
1#
#690
0#
1$
#691
0!
1"
1#
#692
0"
0#
0$
#693
1!
1#
#694
0#
1$
#695
0!
1"
1#
#696
0"
0#
0$
#697
1!
1#
#698
0#
1$
#699
0!
1"
1#
#700
0"
0#
0$
#701
1!
1#
#702
0#
1$
#703
0!
1"
1#
#704
0"
0#
0$
#705
1!
1#
#706
0#
1$
#707
0!
1"
1#
#708
0"
0#
0$
#709
1!
1#
#710
0#
1$
#711
0!
1"
1#
#712
0"
0#
0$
#713
1!
1#
#714
0#
1$
#715
0!
1"
1#
#716
0"
0#
0$
#717
1!
1#
#718
0#
1$
#719
0!
1"
1#
#720
0"
0#
0$
#721
1!
1#
#722
0#
1$
#723
0!
1"
1#
#724
0"
0#
0$
#725
1!
1#
#726
0#
1$
#727
0!
1"
1#
#728
0"
0#
0$
#729
1!
1#
#730
0#
1$
#731
0!
1"
1#
#732
0"
0#
0$
#733
1!
1#
#734
0#
1$
#735
0!
1"
1#
#736
0"
0#
0$
#737
1!
1#
#738
0#
1$
#739
0!
1"
1#
#740
0"
0#
0$
#741
1!
1#
#742
0#
1$
#743
0!
1"
1#
#744
0"
0#
0$
#745
1!
1#
#746
0#
1$
#747
0!
1"
1#
#748
0"
0#
0$
#749
1!
1#
#750
0#
1$
#751
0!
1"
1#
#752
0"
0#
0$
#753
1!
1#
#754
0#
1$
#755
0!
1"
1#
#756
0"
0#
0$
#757
1!
1#
#758
0#
1$
#759
0!
1"
1#
#760
0"
0#
0$
#761
1!
1#
#762
0#
1$
#763
0!
1"
1#
#764
0"
0#
0$
#765
1!
1#
#766
0#
1$
#767
0!
1"
1#
#768
0"
0#
0$
#769
1!
1#
#770
0#
1$
#771
0!
1"
1#
#772
0"
0#
0$
#773
1!
1#
#774
0#
1$
#775
0!
1"
1#
#776
0"
0#
0$
#777
1!
1#
#778
0#
1$
#779
0!
1"
1#
#780
0"
0#
0$
#781
1!
1#
#782
0#
1$
#783
0!
1"
1#
#784
0"
0#
0$
#785
1!
1#
#786
0#
1$
#787
0!
1"
1#
#788
0"
0#
0$
#789
1!
1#
#790
0#
1$
#791
0!
1"
1#
#792
0"
0#
0$
#793
1!
1#
#794
0#
1$
#795
0!
1"
1#
#796
0"
0#
0$
#797
1!
1#
#798
0#
1$
#799
0!
1"
1#
#800
0"
0#
0$
#801
1!
1#
#802
0#
1$
#803
0!
1"
1#
#804
0"
0#
0$
#805
1!
1#
#806
0#
1$
#807
0!
1"
1#
#808
0"
0#
0$
#809
1!
1#
#810
0#
1$
#811
0!
1"
1#
#812
0"
0#
0$
#813
1!
1#
#814
0#
1$
#815
0!
1"
1#
#816
0"
0#
0$
#817
1!
1#
#818
0#
1$
#819
0!
1"
1#
#820
0"
0#
0$
#821
1!
1#
#822
0#
1$
#823
0!
1"
1#
#824
0"
0#
0$
#825
1!
1#
#826
0#
1$
#827
0!
1"
1#
#828
0"
0#
0$
#829
1!
1#
#830
0#
1$
#831
0!
1"
1#
#832
0"
0#
0$
#833
1!
1#
#834
0#
1$
#835
0!
1"
1#
#836
0"
0#
0$
#837
1!
1#
#838
0#
1$
#839
0!
1"
1#
#840
0"
0#
0$
#841
1!
1#
#842
0#
1$
#843
0!
1"
1#
#844
0"
0#
0$
#845
1!
1#
#846
0#
1$
#847
0!
1"
1#
#848
0"
0#
0$
#849
1!
1#
#850
0#
1$
#851
0!
1"
1#
#852
0"
0#
0$
#853
1!
1#
#854
0#
1$
#855
0!
1"
1#
#856
0"
0#
0$
#857
1!
1#
#858
0#
1$
#859
0!
1"
1#
#860
0"
0#
0$
#861
1!
1#
#862
0#
1$
#863
0!
1"
1#
#864
0"
0#
0$
#865
1!
1#
#866
0#
1$
#867
0!
1"
1#
#868
0"
0#
0$
#869
1!
1#
#870
0#
1$
#871
0!
1"
1#
#872
0"
0#
0$
#873
1!
1#
#874
0#
1$
#875
0!
1"
1#
#876
0"
0#
0$
#877
1!
1#
#878
0#
1$
#879
0!
1"
1#
#880
0"
0#
0$
#881
1!
1#
#882
0#
1$
#883
0!
1"
1#
#884
0"
0#
0$
#885
1!
1#
#886
0#
1$
#887
0!
1"
1#
#888
0"
0#
0$
#889
1!
1#
#890
0#
1$
#891
0!
1"
1#
#892
0"
0#
0$
#893
1!
1#
#894
0#
1$
#895
0!
1"
1#
#896
0"
0#
0$
#897
1!
1#
#898
0#
1$
#899
0!
1"
1#
#900
0"
0#
0$
#901
1!
1#
#902
0#
1$
#903
0!
1"
1#
#904
0"
0#
0$
#905
1!
1#
#906
0#
1$
#907
0!
1"
1#
#908
0"
0#
0$
#909
1!
1#
#910
0#
1$
#911
0!
1"
1#
#912
0"
0#
0$
#913
1!
1#
#914
0#
1$
#915
0!
1"
1#
#916
0"
0#
0$
#917
1!
1#
#918
0#
1$
#919
0!
1"
1#
#920
0"
0#
0$
#921
1!
1#
#922
0#
1$
#923
0!
1"
1#
#924
0"
0#
0$
#925
1!
1#
#926
0#
1$
#927
0!
1"
1#
#928
0"
0#
0$
#929
1!
1#
#930
0#
1$
#931
0!
1"
1#
#932
0"
0#
0$
#933
1!
1#
#934
0#
1$
#935
0!
1"
1#
#936
0"
0#
0$
#937
1!
1#
#938
0#
1$
#939
0!
1"
1#
#940
0"
0#
0$
#941
1!
1#
#942
0#
1$
#943
0!
1"
1#
#944
0"
0#
0$
#945
1!
1#
#946
0#
1$
#947
0!
1"
1#
#948
0"
0#
0$
#949
1!
1#
#950
0#
1$
#951
0!
1"
1#
#952
0"
0#
0$
#953
1!
1#
#954
0#
1$
#955
0!
1"
1#
#956
0"
0#
0$
#957
1!
1#
#958
0#
1$
#959
0!
1"
1#
#960
0"
0#
0$
#961
1!
1#
#962
0#
1$
#963
0!
1"
1#
#964
0"
0#
0$
#965
1!
1#
#966
0#
1$
#967
0!
1"
1#
#968
0"
0#
0$
#969
1!
1#
#970
0#
1$
#971
0!
1"
1#
#972
0"
0#
0$
#973
1!
1#
#974
0#
1$
#975
0!
1"
1#
#976
0"
0#
0$
#977
1!
1#
#978
0#
1$
#979
0!
1"
1#
#980
0"
0#
0$
#981
1!
1#
#982
0#
1$
#983
0!
1"
1#
#984
0"
0#
0$
#985
1!
1#
#986
0#
1$
#987
0!
1"
1#
#988
0"
0#
0$
#989
1!
1#
#990
0#
1$
#991
0!
1"
1#
#992
0"
0#
0$
#993
1!
1#
#994
0#
1$
#995
0!
1"
1#
#996
0"
0#
0$
#997
1!
1#
#998
0#
1$
#999
0!
1"
1#
#1000
0"
0#
0$
