registers_and_rams/Register1.v
module Register1 (
    input in,
    input load,
    input clk,
    output reg out = 0
);

always @(posedge clk ) begin
    if (load == 1) begin
        out <= in;
    end else begin
        out <= out;
    end
end
    
endmodule

registers_and_rams/Register16.v
`include "Register1.v"

module Register16 (
    input [15:0] in,
    input load, clk,
    output [15:0] out
);

genvar registerCounter;
generate
    for (registerCounter = 0; registerCounter < 16; registerCounter = registerCounter + 1) begin
        Register1 register1 (.in(in[registerCounter]), .out(out[registerCounter]), .load(load), .clk(clk));
    end
endgenerate
    
endmodule

registers_and_rams/Register16_tb.v
`include "Register16.v"

module Register16_tb;

reg [15:0] in = 16'h0000;
reg load = 0, clk = 0;
wire [15:0] out;

Register16 register16 (.in(in), .out(out), .load(load), .clk(clk));

initial begin
    $dumpfile("Register16.vcd");
    $dumpvars(0, Register16_tb);
    #1000 $finish;
end

always begin
    #1 clk = ~clk;
end

always begin
    #2 load = ~load;
end

always begin
    #4
    if (in == 16'hffff) begin
        in <= 0; 
    end else begin
        in <= in + 1;
    end
end
    
endmodule

registers_and_rams/Register16.vcd
$date
	Sun Aug 27 19:59:57 2023
$end
$version
	Icarus Verilog
$end
$timescale
	1s
$end
$scope module Register16_tb $end
$var wire 16 ! out [15:0] $end
$var reg 1 " clk $end
$var reg 16 # in [15:0] $end
$var reg 1 $ load $end
$scope module register16 $end
$var wire 1 " clk $end
$var wire 16 % in [15:0] $end
$var wire 1 $ load $end
$var wire 16 & out [15:0] $end
$scope begin genblk1[0] $end
$var parameter 2 ' registerCounter $end
$scope module register1 $end
$var wire 1 " clk $end
$var wire 1 ( in $end
$var wire 1 $ load $end
$var reg 1 ) out $end
$upscope $end
$upscope $end
$scope begin genblk1[1] $end
$var parameter 2 * registerCounter $end
$scope module register1 $end
$var wire 1 " clk $end
$var wire 1 + in $end
$var wire 1 $ load $end
$var reg 1 , out $end
$upscope $end
$upscope $end
$scope begin genblk1[2] $end
$var parameter 3 - registerCounter $end
$scope module register1 $end
$var wire 1 " clk $end
$var wire 1 . in $end
$var wire 1 $ load $end
$var reg 1 / out $end
$upscope $end
$upscope $end
$scope begin genblk1[3] $end
$var parameter 3 0 registerCounter $end
$scope module register1 $end
$var wire 1 " clk $end
$var wire 1 1 in $end
$var wire 1 $ load $end
$var reg 1 2 out $end
$upscope $end
$upscope $end
$scope begin genblk1[4] $end
$var parameter 4 3 registerCounter $end
$scope module register1 $end
$var wire 1 " clk $end
$var wire 1 4 in $end
$var wire 1 $ load $end
$var reg 1 5 out $end
$upscope $end
$upscope $end
$scope begin genblk1[5] $end
$var parameter 4 6 registerCounter $end
$scope module register1 $end
$var wire 1 " clk $end
$var wire 1 7 in $end
$var wire 1 $ load $end
$var reg 1 8 out $end
$upscope $end
$upscope $end
$scope begin genblk1[6] $end
$var parameter 4 9 registerCounter $end
$scope module register1 $end
$var wire 1 " clk $end
$var wire 1 : in $end
$var wire 1 $ load $end
$var reg 1 ; out $end
$upscope $end
$upscope $end
$scope begin genblk1[7] $end
$var parameter 4 < registerCounter $end
$scope module register1 $end
$var wire 1 " clk $end
$var wire 1 = in $end
$var wire 1 $ load $end
$var reg 1 > out $end
$upscope $end
$upscope $end
$scope begin genblk1[8] $end
$var parameter 5 ? registerCounter $end
$scope module register1 $end
$var wire 1 " clk $end
$var wire 1 @ in $end
$var wire 1 $ load $end
$var reg 1 A out $end
$upscope $end
$upscope $end
$scope begin genblk1[9] $end
$var parameter 5 B registerCounter $end
$scope module register1 $end
$var wire 1 " clk $end
$var wire 1 C in $end
$var wire 1 $ load $end
$var reg 1 D out $end
$upscope $end
$upscope $end
$scope begin genblk1[10] $end
$var parameter 5 E registerCounter $end
$scope module register1 $end
$var wire 1 " clk $end
$var wire 1 F in $end
$var wire 1 $ load $end
$var reg 1 G out $end
$upscope $end
$upscope $end
$scope begin genblk1[11] $end
$var parameter 5 H registerCounter $end
$scope module register1 $end
$var wire 1 " clk $end
$var wire 1 I in $end
$var wire 1 $ load $end
$var reg 1 J out $end
$upscope $end
$upscope $end
$scope begin genblk1[12] $end
$var parameter 5 K registerCounter $end
$scope module register1 $end
$var wire 1 " clk $end
$var wire 1 L in $end
$var wire 1 $ load $end
$var reg 1 M out $end
$upscope $end
$upscope $end
$scope begin genblk1[13] $end
$var parameter 5 N registerCounter $end
$scope module register1 $end
$var wire 1 " clk $end
$var wire 1 O in $end
$var wire 1 $ load $end
$var reg 1 P out $end
$upscope $end
$upscope $end
$scope begin genblk1[14] $end
$var parameter 5 Q registerCounter $end
$scope module register1 $end
$var wire 1 " clk $end
$var wire 1 R in $end
$var wire 1 $ load $end
$var reg 1 S out $end
$upscope $end
$upscope $end
$scope begin genblk1[15] $end
$var parameter 5 T registerCounter $end
$scope module register1 $end
$var wire 1 " clk $end
$var wire 1 U in $end
$var wire 1 $ load $end
$var reg 1 V out $end
$upscope $end
$upscope $end
$upscope $end
$upscope $end
$enddefinitions $end
$comment Show the parameter values. $end
$dumpall
b1111 T
b1110 Q
b1101 N
b1100 K
b1011 H
b1010 E
b1001 B
b1000 ?
b111 <
b110 9
b101 6
b100 3
b11 0
b10 -
b1 *
b0 '
$end
#0
$dumpvars
xV
0U
xS
0R
xP
0O
xM
0L
xJ
0I
xG
0F
xD
0C
xA
0@
x>
0=
x;
0:
x8
07
x5
04
x2
01
x/
0.
x,
0+
x)
0(
bx &
b0 %
0$
b0 #
0"
bx !
$end
#1
1"
#2
0"
1$
#3
0V
0S
0P
0M
0J
0G
0D
0A
0>
0;
08
05
02
0/
0,
b0 !
b0 &
0)
1"
#4
1(
b1 #
b1 %
0"
0$
#5
1"
#6
0"
1$
#7
b1 !
b1 &
1)
1"
#8
0(
1+
b10 #
b10 %
0"
0$
#9
1"
#10
0"
1$
#11
1,
b10 !
b10 &
0)
1"
#12
1(
b11 #
b11 %
0"
0$
#13
1"
#14
0"
1$
#15
b11 !
b11 &
1)
1"
#16
0(
0+
1.
b100 #
b100 %
0"
0$
#17
1"
#18
0"
1$
#19
1/
0,
b100 !
b100 &
0)
1"
#20
1(
b101 #
b101 %
0"
0$
#21
1"
#22
0"
1$
#23
b101 !
b101 &
1)
1"
#24
0(
1+
b110 #
b110 %
0"
0$
#25
1"
#26
0"
1$
#27
1,
b110 !
b110 &
0)
1"
#28
1(
b111 #
b111 %
0"
0$
#29
1"
#30
0"
1$
#31
b111 !
b111 &
1)
1"
#32
0(
0+
0.
11
b1000 #
b1000 %
0"
0$
#33
1"
#34
0"
1$
#35
12
0/
0,
b1000 !
b1000 &
0)
1"
#36
1(
b1001 #
b1001 %
0"
0$
#37
1"
#38
0"
1$
#39
b1001 !
b1001 &
1)
1"
#40
0(
1+
b1010 #
b1010 %
0"
0$
#41
1"
#42
0"
1$
#43
1,
b1010 !
b1010 &
0)
1"
#44
1(
b1011 #
b1011 %
0"
0$
#45
1"
#46
0"
1$
#47
b1011 !
b1011 &
1)
1"
#48
0(
0+
1.
b1100 #
b1100 %
0"
0$
#49
1"
#50
0"
1$
#51
1/
0,
b1100 !
b1100 &
0)
1"
#52
1(
b1101 #
b1101 %
0"
0$
#53
1"
#54
0"
1$
#55
b1101 !
b1101 &
1)
1"
#56
0(
1+
b1110 #
b1110 %
0"
0$
#57
1"
#58
0"
1$
#59
1,
b1110 !
b1110 &
0)
1"
#60
1(
b1111 #
b1111 %
0"
0$
#61
1"
#62
0"
1$
#63
b1111 !
b1111 &
1)
1"
#64
0(
0+
0.
01
14
b10000 #
b10000 %
0"
0$
#65
1"
#66
0"
1$
#67
15
02
0/
0,
b10000 !
b10000 &
0)
1"
#68
1(
b10001 #
b10001 %
0"
0$
#69
1"
#70
0"
1$
#71
b10001 !
b10001 &
1)
1"
#72
0(
1+
b10010 #
b10010 %
0"
0$
#73
1"
#74
0"
1$
#75
1,
b10010 !
b10010 &
0)
1"
#76
1(
b10011 #
b10011 %
0"
0$
#77
1"
#78
0"
1$
#79
b10011 !
b10011 &
1)
1"
#80
0(
0+
1.
b10100 #
b10100 %
0"
0$
#81
1"
#82
0"
1$
#83
1/
0,
b10100 !
b10100 &
0)
1"
#84
1(
b10101 #
b10101 %
0"
0$
#85
1"
#86
0"
1$
#87
b10101 !
b10101 &
1)
1"
#88
0(
1+
b10110 #
b10110 %
0"
0$
#89
1"
#90
0"
1$
#91
1,
b10110 !
b10110 &
0)
1"
#92
1(
b10111 #
b10111 %
0"
0$
#93
1"
#94
0"
1$
#95
b10111 !
b10111 &
1)
1"
#96
0(
0+
0.
11
b11000 #
b11000 %
0"
0$
#97
1"
#98
0"
1$
#99
12
0/
0,
b11000 !
b11000 &
0)
1"
#100
1(
b11001 #
b11001 %
0"
0$
#101
1"
#102
0"
1$
#103
b11001 !
b11001 &
1)
1"
#104
0(
1+
b11010 #
b11010 %
0"
0$
#105
1"
#106
0"
1$
#107
1,
b11010 !
b11010 &
0)
1"
#108
1(
b11011 #
b11011 %
0"
0$
#109
1"
#110
0"
1$
#111
b11011 !
b11011 &
1)
1"
#112
0(
0+
1.
b11100 #
b11100 %
0"
0$
#113
1"
#114
0"
1$
#115
1/
0,
b11100 !
b11100 &
0)
1"
#116
1(
b11101 #
b11101 %
0"
0$
#117
1"
#118
0"
1$
#119
b11101 !
b11101 &
1)
1"
#120
0(
1+
b11110 #
b11110 %
0"
0$
#121
1"
#122
0"
1$
#123
1,
b11110 !
b11110 &
0)
1"
#124
1(
b11111 #
b11111 %
0"
0$
#125
1"
#126
0"
1$
#127
b11111 !
b11111 &
1)
1"
#128
0(
0+
0.
01
04
17
b100000 #
b100000 %
0"
0$
#129
1"
#130
0"
1$
#131
18
05
02
0/
0,
b100000 !
b100000 &
0)
1"
#132
1(
b100001 #
b100001 %
0"
0$
#133
1"
#134
0"
1$
#135
b100001 !
b100001 &
1)
1"
#136
0(
1+
b100010 #
b100010 %
0"
0$
#137
1"
#138
0"
1$
#139
1,
b100010 !
b100010 &
0)
1"
#140
1(
b100011 #
b100011 %
0"
0$
#141
1"
#142
0"
1$
#143
b100011 !
b100011 &
1)
1"
#144
0(
0+
1.
b100100 #
b100100 %
0"
0$
#145
1"
#146
0"
1$
#147
1/
0,
b100100 !
b100100 &
0)
1"
#148
1(
b100101 #
b100101 %
0"
0$
#149
1"
#150
0"
1$
#151
b100101 !
b100101 &
1)
1"
#152
0(
1+
b100110 #
b100110 %
0"
0$
#153
1"
#154
0"
1$
#155
1,
b100110 !
b100110 &
0)
1"
#156
1(
b100111 #
b100111 %
0"
0$
#157
1"
#158
0"
1$
#159
b100111 !
b100111 &
1)
1"
#160
0(
0+
0.
11
b101000 #
b101000 %
0"
0$
#161
1"
#162
0"
1$
#163
12
0/
0,
b101000 !
b101000 &
0)
1"
#164
1(
b101001 #
b101001 %
0"
0$
#165
1"
#166
0"
1$
#167
b101001 !
b101001 &
1)
1"
#168
0(
1+
b101010 #
b101010 %
0"
0$
#169
1"
#170
0"
1$
#171
1,
b101010 !
b101010 &
0)
1"
#172
1(
b101011 #
b101011 %
0"
0$
#173
1"
#174
0"
1$
#175
b101011 !
b101011 &
1)
1"
#176
0(
0+
1.
b101100 #
b101100 %
0"
0$
#177
1"
#178
0"
1$
#179
1/
0,
b101100 !
b101100 &
0)
1"
#180
1(
b101101 #
b101101 %
0"
0$
#181
1"
#182
0"
1$
#183
b101101 !
b101101 &
1)
1"
#184
0(
1+
b101110 #
b101110 %
0"
0$
#185
1"
#186
0"
1$
#187
1,
b101110 !
b101110 &
0)
1"
#188
1(
b101111 #
b101111 %
0"
0$
#189
1"
#190
0"
1$
#191
b101111 !
b101111 &
1)
1"
#192
0(
0+
0.
01
14
b110000 #
b110000 %
0"
0$
#193
1"
#194
0"
1$
#195
15
02
0/
0,
b110000 !
b110000 &
0)
1"
#196
1(
b110001 #
b110001 %
0"
0$
#197
1"
#198
0"
1$
#199
b110001 !
b110001 &
1)
1"
#200
0(
1+
b110010 #
b110010 %
0"
0$
#201
1"
#202
0"
1$
#203
1,
b110010 !
b110010 &
0)
1"
#204
1(
b110011 #
b110011 %
0"
0$
#205
1"
#206
0"
1$
#207
b110011 !
b110011 &
1)
1"
#208
0(
0+
1.
b110100 #
b110100 %
0"
0$
#209
1"
#210
0"
1$
#211
1/
0,
b110100 !
b110100 &
0)
1"
#212
1(
b110101 #
b110101 %
0"
0$
#213
1"
#214
0"
1$
#215
b110101 !
b110101 &
1)
1"
#216
0(
1+
b110110 #
b110110 %
0"
0$
#217
1"
#218
0"
1$
#219
1,
b110110 !
b110110 &
0)
1"
#220
1(
b110111 #
b110111 %
0"
0$
#221
1"
#222
0"
1$
#223
b110111 !
b110111 &
1)
1"
#224
0(
0+
0.
11
b111000 #
b111000 %
0"
0$
#225
1"
#226
0"
1$
#227
12
0/
0,
b111000 !
b111000 &
0)
1"
#228
1(
b111001 #
b111001 %
0"
0$
#229
1"
#230
0"
1$
#231
b111001 !
b111001 &
1)
1"
#232
0(
1+
b111010 #
b111010 %
0"
0$
#233
1"
#234
0"
1$
#235
1,
b111010 !
b111010 &
0)
1"
#236
1(
b111011 #
b111011 %
0"
0$
#237
1"
#238
0"
1$
#239
b111011 !
b111011 &
1)
1"
#240
0(
0+
1.
b111100 #
b111100 %
0"
0$
#241
1"
#242
0"
1$
#243
1/
0,
b111100 !
b111100 &
0)
1"
#244
1(
b111101 #
b111101 %
0"
0$
#245
1"
#246
0"
1$
#247
b111101 !
b111101 &
1)
1"
#248
0(
1+
b111110 #
b111110 %
0"
0$
#249
1"
#250
0"
1$
#251
1,
b111110 !
b111110 &
0)
1"
#252
1(
b111111 #
b111111 %
0"
0$
#253
1"
#254
0"
1$
#255
b111111 !
b111111 &
1)
1"
#256
0(
0+
0.
01
04
07
1:
b1000000 #
b1000000 %
0"
0$
#257
1"
#258
0"
1$
#259
1;
08
05
02
0/
0,
b1000000 !
b1000000 &
0)
1"
#260
1(
b1000001 #
b1000001 %
0"
0$
#261
1"
#262
0"
1$
#263
b1000001 !
b1000001 &
1)
1"
#264
0(
1+
b1000010 #
b1000010 %
0"
0$
#265
1"
#266
0"
1$
#267
1,
b1000010 !
b1000010 &
0)
1"
#268
1(
b1000011 #
b1000011 %
0"
0$
#269
1"
#270
0"
1$
#271
b1000011 !
b1000011 &
1)
1"
#272
0(
0+
1.
b1000100 #
b1000100 %
0"
0$
#273
1"
#274
0"
1$
#275
1/
0,
b1000100 !
b1000100 &
0)
1"
#276
1(
b1000101 #
b1000101 %
0"
0$
#277
1"
#278
0"
1$
#279
b1000101 !
b1000101 &
1)
1"
#280
0(
1+
b1000110 #
b1000110 %
0"
0$
#281
1"
#282
0"
1$
#283
1,
b1000110 !
b1000110 &
0)
1"
#284
1(
b1000111 #
b1000111 %
0"
0$
#285
1"
#286
0"
1$
#287
b1000111 !
b1000111 &
1)
1"
#288
0(
0+
0.
11
b1001000 #
b1001000 %
0"
0$
#289
1"
#290
0"
1$
#291
12
0/
0,
b1001000 !
b1001000 &
0)
1"
#292
1(
b1001001 #
b1001001 %
0"
0$
#293
1"
#294
0"
1$
#295
b1001001 !
b1001001 &
1)
1"
#296
0(
1+
b1001010 #
b1001010 %
0"
0$
#297
1"
#298
0"
1$
#299
1,
b1001010 !
b1001010 &
0)
1"
#300
1(
b1001011 #
b1001011 %
0"
0$
#301
1"
#302
0"
1$
#303
b1001011 !
b1001011 &
1)
1"
#304
0(
0+
1.
b1001100 #
b1001100 %
0"
0$
#305
1"
#306
0"
1$
#307
1/
0,
b1001100 !
b1001100 &
0)
1"
#308
1(
b1001101 #
b1001101 %
0"
0$
#309
1"
#310
0"
1$
#311
b1001101 !
b1001101 &
1)
1"
#312
0(
1+
b1001110 #
b1001110 %
0"
0$
#313
1"
#314
0"
1$
#315
1,
b1001110 !
b1001110 &
0)
1"
#316
1(
b1001111 #
b1001111 %
0"
0$
#317
1"
#318
0"
1$
#319
b1001111 !
b1001111 &
1)
1"
#320
0(
0+
0.
01
14
b1010000 #
b1010000 %
0"
0$
#321
1"
#322
0"
1$
#323
15
02
0/
0,
b1010000 !
b1010000 &
0)
1"
#324
1(
b1010001 #
b1010001 %
0"
0$
#325
1"
#326
0"
1$
#327
b1010001 !
b1010001 &
1)
1"
#328
0(
1+
b1010010 #
b1010010 %
0"
0$
#329
1"
#330
0"
1$
#331
1,
b1010010 !
b1010010 &
0)
1"
#332
1(
b1010011 #
b1010011 %
0"
0$
#333
1"
#334
0"
1$
#335
b1010011 !
b1010011 &
1)
1"
#336
0(
0+
1.
b1010100 #
b1010100 %
0"
0$
#337
1"
#338
0"
1$
#339
1/
0,
b1010100 !
b1010100 &
0)
1"
#340
1(
b1010101 #
b1010101 %
0"
0$
#341
1"
#342
0"
1$
#343
b1010101 !
b1010101 &
1)
1"
#344
0(
1+
b1010110 #
b1010110 %
0"
0$
#345
1"
#346
0"
1$
#347
1,
b1010110 !
b1010110 &
0)
1"
#348
1(
b1010111 #
b1010111 %
0"
0$
#349
1"
#350
0"
1$
#351
b1010111 !
b1010111 &
1)
1"
#352
0(
0+
0.
11
b1011000 #
b1011000 %
0"
0$
#353
1"
#354
0"
1$
#355
12
0/
0,
b1011000 !
b1011000 &
0)
1"
#356
1(
b1011001 #
b1011001 %
0"
0$
#357
1"
#358
0"
1$
#359
b1011001 !
b1011001 &
1)
1"
#360
0(
1+
b1011010 #
b1011010 %
0"
0$
#361
1"
#362
0"
1$
#363
1,
b1011010 !
b1011010 &
0)
1"
#364
1(
b1011011 #
b1011011 %
0"
0$
#365
1"
#366
0"
1$
#367
b1011011 !
b1011011 &
1)
1"
#368
0(
0+
1.
b1011100 #
b1011100 %
0"
0$
#369
1"
#370
0"
1$
#371
1/
0,
b1011100 !
b1011100 &
0)
1"
#372
1(
b1011101 #
b1011101 %
0"
0$
#373
1"
#374
0"
1$
#375
b1011101 !
b1011101 &
1)
1"
#376
0(
1+
b1011110 #
b1011110 %
0"
0$
#377
1"
#378
0"
1$
#379
1,
b1011110 !
b1011110 &
0)
1"
#380
1(
b1011111 #
b1011111 %
0"
0$
#381
1"
#382
0"
1$
#383
b1011111 !
b1011111 &
1)
1"
#384
0(
0+
0.
01
04
17
b1100000 #
b1100000 %
0"
0$
#385
1"
#386
0"
1$
#387
18
05
02
0/
0,
b1100000 !
b1100000 &
0)
1"
#388
1(
b1100001 #
b1100001 %
0"
0$
#389
1"
#390
0"
1$
#391
b1100001 !
b1100001 &
1)
1"
#392
0(
1+
b1100010 #
b1100010 %
0"
0$
#393
1"
#394
0"
1$
#395
1,
b1100010 !
b1100010 &
0)
1"
#396
1(
b1100011 #
b1100011 %
0"
0$
#397
1"
#398
0"
1$
#399
b1100011 !
b1100011 &
1)
1"
#400
0(
0+
1.
b1100100 #
b1100100 %
0"
0$
#401
1"
#402
0"
1$
#403
1/
0,
b1100100 !
b1100100 &
0)
1"
#404
1(
b1100101 #
b1100101 %
0"
0$
#405
1"
#406
0"
1$
#407
b1100101 !
b1100101 &
1)
1"
#408
0(
1+
b1100110 #
b1100110 %
0"
0$
#409
1"
#410
0"
1$
#411
1,
b1100110 !
b1100110 &
0)
1"
#412
1(
b1100111 #
b1100111 %
0"
0$
#413
1"
#414
0"
1$
#415
b1100111 !
b1100111 &
1)
1"
#416
0(
0+
0.
11
b1101000 #
b1101000 %
0"
0$
#417
1"
#418
0"
1$
#419
12
0/
0,
b1101000 !
b1101000 &
0)
1"
#420
1(
b1101001 #
b1101001 %
0"
0$
#421
1"
#422
0"
1$
#423
b1101001 !
b1101001 &
1)
1"
#424
0(
1+
b1101010 #
b1101010 %
0"
0$
#425
1"
#426
0"
1$
#427
1,
b1101010 !
b1101010 &
0)
1"
#428
1(
b1101011 #
b1101011 %
0"
0$
#429
1"
#430
0"
1$
#431
b1101011 !
b1101011 &
1)
1"
#432
0(
0+
1.
b1101100 #
b1101100 %
0"
0$
#433
1"
#434
0"
1$
#435
1/
0,
b1101100 !
b1101100 &
0)
1"
#436
1(
b1101101 #
b1101101 %
0"
0$
#437
1"
#438
0"
1$
#439
b1101101 !
b1101101 &
1)
1"
#440
0(
1+
b1101110 #
b1101110 %
0"
0$
#441
1"
#442
0"
1$
#443
1,
b1101110 !
b1101110 &
0)
1"
#444
1(
b1101111 #
b1101111 %
0"
0$
#445
1"
#446
0"
1$
#447
b1101111 !
b1101111 &
1)
1"
#448
0(
0+
0.
01
14
b1110000 #
b1110000 %
0"
0$
#449
1"
#450
0"
1$
#451
15
02
0/
0,
b1110000 !
b1110000 &
0)
1"
#452
1(
b1110001 #
b1110001 %
0"
0$
#453
1"
#454
0"
1$
#455
b1110001 !
b1110001 &
1)
1"
#456
0(
1+
b1110010 #
b1110010 %
0"
0$
#457
1"
#458
0"
1$
#459
1,
b1110010 !
b1110010 &
0)
1"
#460
1(
b1110011 #
b1110011 %
0"
0$
#461
1"
#462
0"
1$
#463
b1110011 !
b1110011 &
1)
1"
#464
0(
0+
1.
b1110100 #
b1110100 %
0"
0$
#465
1"
#466
0"
1$
#467
1/
0,
b1110100 !
b1110100 &
0)
1"
#468
1(
b1110101 #
b1110101 %
0"
0$
#469
1"
#470
0"
1$
#471
b1110101 !
b1110101 &
1)
1"
#472
0(
1+
b1110110 #
b1110110 %
0"
0$
#473
1"
#474
0"
1$
#475
1,
b1110110 !
b1110110 &
0)
1"
#476
1(
b1110111 #
b1110111 %
0"
0$
#477
1"
#478
0"
1$
#479
b1110111 !
b1110111 &
1)
1"
#480
0(
0+
0.
11
b1111000 #
b1111000 %
0"
0$
#481
1"
#482
0"
1$
#483
12
0/
0,
b1111000 !
b1111000 &
0)
1"
#484
1(
b1111001 #
b1111001 %
0"
0$
#485
1"
#486
0"
1$
#487
b1111001 !
b1111001 &
1)
1"
#488
0(
1+
b1111010 #
b1111010 %
0"
0$
#489
1"
#490
0"
1$
#491
1,
b1111010 !
b1111010 &
0)
1"
#492
1(
b1111011 #
b1111011 %
0"
0$
#493
1"
#494
0"
1$
#495
b1111011 !
b1111011 &
1)
1"
#496
0(
0+
1.
b1111100 #
b1111100 %
0"
0$
#497
1"
#498
0"
1$
#499
1/
0,
b1111100 !
b1111100 &
0)
1"
#500
1(
b1111101 #
b1111101 %
0"
0$
#501
1"
#502
0"
1$
#503
b1111101 !
b1111101 &
1)
1"
#504
0(
1+
b1111110 #
b1111110 %
0"
0$
#505
1"
#506
0"
1$
#507
1,
b1111110 !
b1111110 &
0)
1"
#508
1(
b1111111 #
b1111111 %
0"
0$
#509
1"
#510
0"
1$
#511
b1111111 !
b1111111 &
1)
1"
#512
0(
0+
0.
01
04
07
0:
1=
b10000000 #
b10000000 %
0"
0$
#513
1"
#514
0"
1$
#515
1>
0;
08
05
02
0/
0,
b10000000 !
b10000000 &
0)
1"
#516
1(
b10000001 #
b10000001 %
0"
0$
#517
1"
#518
0"
1$
#519
b10000001 !
b10000001 &
1)
1"
#520
0(
1+
b10000010 #
b10000010 %
0"
0$
#521
1"
#522
0"
1$
#523
1,
b10000010 !
b10000010 &
0)
1"
#524
1(
b10000011 #
b10000011 %
0"
0$
#525
1"
#526
0"
1$
#527
b10000011 !
b10000011 &
1)
1"
#528
0(
0+
1.
b10000100 #
b10000100 %
0"
0$
#529
1"
#530
0"
1$
#531
1/
0,
b10000100 !
b10000100 &
0)
1"
#532
1(
b10000101 #
b10000101 %
0"
0$
#533
1"
#534
0"
1$
#535
b10000101 !
b10000101 &
1)
1"
#536
0(
1+
b10000110 #
b10000110 %
0"
0$
#537
1"
#538
0"
1$
#539
1,
b10000110 !
b10000110 &
0)
1"
#540
1(
b10000111 #
b10000111 %
0"
0$
#541
1"
#542
0"
1$
#543
b10000111 !
b10000111 &
1)
1"
#544
0(
0+
0.
11
b10001000 #
b10001000 %
0"
0$
#545
1"
#546
0"
1$
#547
12
0/
0,
b10001000 !
b10001000 &
0)
1"
#548
1(
b10001001 #
b10001001 %
0"
0$
#549
1"
#550
0"
1$
#551
b10001001 !
b10001001 &
1)
1"
#552
0(
1+
b10001010 #
b10001010 %
0"
0$
#553
1"
#554
0"
1$
#555
1,
b10001010 !
b10001010 &
0)
1"
#556
1(
b10001011 #
b10001011 %
0"
0$
#557
1"
#558
0"
1$
#559
b10001011 !
b10001011 &
1)
1"
#560
0(
0+
1.
b10001100 #
b10001100 %
0"
0$
#561
1"
#562
0"
1$
#563
1/
0,
b10001100 !
b10001100 &
0)
1"
#564
1(
b10001101 #
b10001101 %
0"
0$
#565
1"
#566
0"
1$
#567
b10001101 !
b10001101 &
1)
1"
#568
0(
1+
b10001110 #
b10001110 %
0"
0$
#569
1"
#570
0"
1$
#571
1,
b10001110 !
b10001110 &
0)
1"
#572
1(
b10001111 #
b10001111 %
0"
0$
#573
1"
#574
0"
1$
#575
b10001111 !
b10001111 &
1)
1"
#576
0(
0+
0.
01
14
b10010000 #
b10010000 %
0"
0$
#577
1"
#578
0"
1$
#579
15
02
0/
0,
b10010000 !
b10010000 &
0)
1"
#580
1(
b10010001 #
b10010001 %
0"
0$
#581
1"
#582
0"
1$
#583
b10010001 !
b10010001 &
1)
1"
#584
0(
1+
b10010010 #
b10010010 %
0"
0$
#585
1"
#586
0"
1$
#587
1,
b10010010 !
b10010010 &
0)
1"
#588
1(
b10010011 #
b10010011 %
0"
0$
#589
1"
#590
0"
1$
#591
b10010011 !
b10010011 &
1)
1"
#592
0(
0+
1.
b10010100 #
b10010100 %
0"
0$
#593
1"
#594
0"
1$
#595
1/
0,
b10010100 !
b10010100 &
0)
1"
#596
1(
b10010101 #
b10010101 %
0"
0$
#597
1"
#598
0"
1$
#599
b10010101 !
b10010101 &
1)
1"
#600
0(
1+
b10010110 #
b10010110 %
0"
0$
#601
1"
#602
0"
1$
#603
1,
b10010110 !
b10010110 &
0)
1"
#604
1(
b10010111 #
b10010111 %
0"
0$
#605
1"
#606
0"
1$
#607
b10010111 !
b10010111 &
1)
1"
#608
0(
0+
0.
11
b10011000 #
b10011000 %
0"
0$
#609
1"
#610
0"
1$
#611
12
0/
0,
b10011000 !
b10011000 &
0)
1"
#612
1(
b10011001 #
b10011001 %
0"
0$
#613
1"
#614
0"
1$
#615
b10011001 !
b10011001 &
1)
1"
#616
0(
1+
b10011010 #
b10011010 %
0"
0$
#617
1"
#618
0"
1$
#619
1,
b10011010 !
b10011010 &
0)
1"
#620
1(
b10011011 #
b10011011 %
0"
0$
#621
1"
#622
0"
1$
#623
b10011011 !
b10011011 &
1)
1"
#624
0(
0+
1.
b10011100 #
b10011100 %
0"
0$
#625
1"
#626
0"
1$
#627
1/
0,
b10011100 !
b10011100 &
0)
1"
#628
1(
b10011101 #
b10011101 %
0"
0$
#629
1"
#630
0"
1$
#631
b10011101 !
b10011101 &
1)
1"
#632
0(
1+
b10011110 #
b10011110 %
0"
0$
#633
1"
#634
0"
1$
#635
1,
b10011110 !
b10011110 &
0)
1"
#636
1(
b10011111 #
b10011111 %
0"
0$
#637
1"
#638
0"
1$
#639
b10011111 !
b10011111 &
1)
1"
#640
0(
0+
0.
01
04
17
b10100000 #
b10100000 %
0"
0$
#641
1"
#642
0"
1$
#643
18
05
02
0/
0,
b10100000 !
b10100000 &
0)
1"
#644
1(
b10100001 #
b10100001 %
0"
0$
#645
1"
#646
0"
1$
#647
b10100001 !
b10100001 &
1)
1"
#648
0(
1+
b10100010 #
b10100010 %
0"
0$
#649
1"
#650
0"
1$
#651
1,
b10100010 !
b10100010 &
0)
1"
#652
1(
b10100011 #
b10100011 %
0"
0$
#653
1"
#654
0"
1$
#655
b10100011 !
b10100011 &
1)
1"
#656
0(
0+
1.
b10100100 #
b10100100 %
0"
0$
#657
1"
#658
0"
1$
#659
1/
0,
b10100100 !
b10100100 &
0)
1"
#660
1(
b10100101 #
b10100101 %
0"
0$
#661
1"
#662
0"
1$
#663
b10100101 !
b10100101 &
1)
1"
#664
0(
1+
b10100110 #
b10100110 %
0"
0$
#665
1"
#666
0"
1$
#667
1,
b10100110 !
b10100110 &
0)
1"
#668
1(
b10100111 #
b10100111 %
0"
0$
#669
1"
#670
0"
1$
#671
b10100111 !
b10100111 &
1)
1"
#672
0(
0+
0.
11
b10101000 #
b10101000 %
0"
0$
#673
1"
#674
0"
1$
#675
12
0/
0,
b10101000 !
b10101000 &
0)
1"
#676
1(
b10101001 #
b10101001 %
0"
0$
#677
1"
#678
0"
1$
#679
b10101001 !
b10101001 &
1)
1"
#680
0(
1+
b10101010 #
b10101010 %
0"
0$
#681
1"
#682
0"
1$
#683
1,
b10101010 !
b10101010 &
0)
1"
#684
1(
b10101011 #
b10101011 %
0"
0$
#685
1"
#686
0"
1$
#687
b10101011 !
b10101011 &
1)
1"
#688
0(
0+
1.
b10101100 #
b10101100 %
0"
0$
#689
1"
#690
0"
1$
#691
1/
0,
b10101100 !
b10101100 &
0)
1"
#692
1(
b10101101 #
b10101101 %
0"
0$
#693
1"
#694
0"
1$
#695
b10101101 !
b10101101 &
1)
1"
#696
0(
1+
b10101110 #
b10101110 %
0"
0$
#697
1"
#698
0"
1$
#699
1,
b10101110 !
b10101110 &
0)
1"
#700
1(
b10101111 #
b10101111 %
0"
0$
#701
1"
#702
0"
1$
#703
b10101111 !
b10101111 &
1)
1"
#704
0(
0+
0.
01
14
b10110000 #
b10110000 %
0"
0$
#705
1"
#706
0"
1$
#707
15
02
0/
0,
b10110000 !
b10110000 &
0)
1"
#708
1(
b10110001 #
b10110001 %
0"
0$
#709
1"
#710
0"
1$
#711
b10110001 !
b10110001 &
1)
1"
#712
0(
1+
b10110010 #
b10110010 %
0"
0$
#713
1"
#714
0"
1$
#715
1,
b10110010 !
b10110010 &
0)
1"
#716
1(
b10110011 #
b10110011 %
0"
0$
#717
1"
#718
0"
1$
#719
b10110011 !
b10110011 &
1)
1"
#720
0(
0+
1.
b10110100 #
b10110100 %
0"
0$
#721
1"
#722
0"
1$
