registers_and_rams/Register1.v
module Register1 (
    input in,
    input load,
    input clk,
    output reg out = 0
);

always @(posedge clk ) begin
    if (load == 1) begin
        out <= in;
    end else begin
        out <= out;
    end
end
    
endmodule

registers_and_rams/Register16.v
`include "Register1.v"

module Register16 (
    input [15:0] in,
    input load, clk,
    output [15:0] out
);

genvar registerCounter;
generate
    for (registerCounter = 0; registerCounter < 16; registerCounter = registerCounter + 1) begin : Register1to16
        Register1 register1 (.in(in[registerCounter]), .out(out[registerCounter]), .load(load), .clk(clk));
    end
endgenerate
    
endmodule

registers_and_rams/Register16_tb.v
`include "Register16.v"

module Register16_tb;

reg [15:0] in = 16'habcd;
reg load = 0, clk = 0;
wire [15:0] out;

Register16 register16 (.in(in), .out(out), .load(load), .clk(clk));

initial begin
    $dumpfile("Register16.vcd");
    $dumpvars(0, Register16_tb);
    #1000 $finish;
end

always begin
    #1 clk = ~clk;
end

always begin
    #2 load = ~load;
end

always begin
    #4
    if (in == 16'hffff) begin
        in <= 0; 
    end else begin
        in <= in + 1;
    end
end
    
endmodule

registers_and_rams/Register16.vcd
$date
	Sun Aug 27 21:45:09 2023
$end
$version
	Icarus Verilog
$end
$timescale
	1s
$end
$scope module Register16_tb $end
$var wire 16 ! out [15:0] $end
$var reg 1 " clk $end
$var reg 16 # in [15:0] $end
$var reg 1 $ load $end
$scope module register16 $end
$var wire 1 " clk $end
$var wire 16 % in [15:0] $end
$var wire 1 $ load $end
$var wire 16 & out [15:0] $end
$scope begin genblk1[0] $end
$var parameter 2 ' registerCounter $end
$scope module register1 $end
$var wire 1 " clk $end
$var wire 1 ( in $end
$var wire 1 $ load $end
$var reg 1 ) out $end
$upscope $end
$upscope $end
$scope begin genblk1[1] $end
$var parameter 2 * registerCounter $end
$scope module register1 $end
$var wire 1 " clk $end
$var wire 1 + in $end
$var wire 1 $ load $end
$var reg 1 , out $end
$upscope $end
$upscope $end
$scope begin genblk1[2] $end
$var parameter 3 - registerCounter $end
$scope module register1 $end
$var wire 1 " clk $end
$var wire 1 . in $end
$var wire 1 $ load $end
$var reg 1 / out $end
$upscope $end
$upscope $end
$scope begin genblk1[3] $end
$var parameter 3 0 registerCounter $end
$scope module register1 $end
$var wire 1 " clk $end
$var wire 1 1 in $end
$var wire 1 $ load $end
$var reg 1 2 out $end
$upscope $end
$upscope $end
$scope begin genblk1[4] $end
$var parameter 4 3 registerCounter $end
$scope module register1 $end
$var wire 1 " clk $end
$var wire 1 4 in $end
$var wire 1 $ load $end
$var reg 1 5 out $end
$upscope $end
$upscope $end
$scope begin genblk1[5] $end
$var parameter 4 6 registerCounter $end
$scope module register1 $end
$var wire 1 " clk $end
$var wire 1 7 in $end
$var wire 1 $ load $end
$var reg 1 8 out $end
$upscope $end
$upscope $end
$scope begin genblk1[6] $end
$var parameter 4 9 registerCounter $end
$scope module register1 $end
$var wire 1 " clk $end
$var wire 1 : in $end
$var wire 1 $ load $end
$var reg 1 ; out $end
$upscope $end
$upscope $end
$scope begin genblk1[7] $end
$var parameter 4 < registerCounter $end
$scope module register1 $end
$var wire 1 " clk $end
$var wire 1 = in $end
$var wire 1 $ load $end
$var reg 1 > out $end
$upscope $end
$upscope $end
$scope begin genblk1[8] $end
$var parameter 5 ? registerCounter $end
$scope module register1 $end
$var wire 1 " clk $end
$var wire 1 @ in $end
$var wire 1 $ load $end
$var reg 1 A out $end
$upscope $end
$upscope $end
$scope begin genblk1[9] $end
$var parameter 5 B registerCounter $end
$scope module register1 $end
$var wire 1 " clk $end
$var wire 1 C in $end
$var wire 1 $ load $end
$var reg 1 D out $end
$upscope $end
$upscope $end
$scope begin genblk1[10] $end
$var parameter 5 E registerCounter $end
$scope module register1 $end
$var wire 1 " clk $end
$var wire 1 F in $end
$var wire 1 $ load $end
$var reg 1 G out $end
$upscope $end
$upscope $end
$scope begin genblk1[11] $end
$var parameter 5 H registerCounter $end
$scope module register1 $end
$var wire 1 " clk $end
$var wire 1 I in $end
$var wire 1 $ load $end
$var reg 1 J out $end
$upscope $end
$upscope $end
$scope begin genblk1[12] $end
$var parameter 5 K registerCounter $end
$scope module register1 $end
$var wire 1 " clk $end
$var wire 1 L in $end
$var wire 1 $ load $end
$var reg 1 M out $end
$upscope $end
$upscope $end
$scope begin genblk1[13] $end
$var parameter 5 N registerCounter $end
$scope module register1 $end
$var wire 1 " clk $end
$var wire 1 O in $end
$var wire 1 $ load $end
$var reg 1 P out $end
$upscope $end
$upscope $end
$scope begin genblk1[14] $end
$var parameter 5 Q registerCounter $end
$scope module register1 $end
$var wire 1 " clk $end
$var wire 1 R in $end
$var wire 1 $ load $end
$var reg 1 S out $end
$upscope $end
$upscope $end
$scope begin genblk1[15] $end
$var parameter 5 T registerCounter $end
$scope module register1 $end
$var wire 1 " clk $end
$var wire 1 U in $end
$var wire 1 $ load $end
$var reg 1 V out $end
$upscope $end
$upscope $end
$upscope $end
$upscope $end
$enddefinitions $end
$comment Show the parameter values. $end
$dumpall
b1111 T
b1110 Q
b1101 N
b1100 K
b1011 H
b1010 E
b1001 B
b1000 ?
b111 <
b110 9
b101 6
b100 3
b11 0
b10 -
b1 *
b0 '
$end
#0
$dumpvars
xV
1U
xS
0R
xP
1O
xM
0L
xJ
1I
xG
0F
xD
1C
xA
1@
x>
1=
x;
1:
x8
07
x5
04
x2
11
x/
1.
x,
0+
x)
1(
bx &
b1010101111001101 %
0$
b1010101111001101 #
0"
bx !
$end
#1
1"
#2
0"
1$
#3
1V
0S
1P
0M
1J
0G
1D
1A
1>
1;
08
05
12
1/
0,
b1010101111001101 !
b1010101111001101 &
1)
1"
#4
0(
1+
b1010101111001110 #
b1010101111001110 %
0"
0$
#5
1"
#6
0"
1$
#7
1,
b1010101111001110 !
b1010101111001110 &
0)
1"
#8
1(
b1010101111001111 #
b1010101111001111 %
0"
0$
#9
1"
#10
0"
1$
#11
b1010101111001111 !
b1010101111001111 &
1)
1"
#12
0(
0+
0.
01
14
b1010101111010000 #
b1010101111010000 %
0"
0$
#13
1"
#14
0"
1$
#15
15
02
0/
0,
b1010101111010000 !
b1010101111010000 &
0)
1"
#16
1(
b1010101111010001 #
b1010101111010001 %
0"
0$
#17
1"
#18
0"
1$
#19
b1010101111010001 !
b1010101111010001 &
1)
1"
#20
0(
1+
b1010101111010010 #
b1010101111010010 %
0"
0$
#21
1"
#22
0"
1$
#23
1,
b1010101111010010 !
b1010101111010010 &
0)
1"
#24
1(
b1010101111010011 #
b1010101111010011 %
0"
0$
#25
1"
#26
0"
1$
#27
b1010101111010011 !
b1010101111010011 &
1)
1"
#28
0(
0+
1.
b1010101111010100 #
b1010101111010100 %
0"
0$
#29
1"
#30
0"
1$
#31
1/
0,
b1010101111010100 !
b1010101111010100 &
0)
1"
#32
1(
b1010101111010101 #
b1010101111010101 %
0"
0$
#33
1"
#34
0"
1$
#35
b1010101111010101 !
b1010101111010101 &
1)
1"
#36
0(
1+
b1010101111010110 #
b1010101111010110 %
0"
0$
#37
1"
#38
0"
1$
#39
1,
b1010101111010110 !
b1010101111010110 &
0)
1"
#40
1(
b1010101111010111 #
b1010101111010111 %
0"
0$
#41
1"
#42
0"
1$
#43
b1010101111010111 !
b1010101111010111 &
1)
1"
#44
0(
0+
0.
11
b1010101111011000 #
b1010101111011000 %
0"
0$
#45
1"
#46
0"
1$
#47
12
0/
0,
b1010101111011000 !
b1010101111011000 &
0)
1"
#48
1(
b1010101111011001 #
b1010101111011001 %
0"
0$
#49
1"
#50
0"
1$
#51
b1010101111011001 !
b1010101111011001 &
1)
1"
#52
0(
1+
b1010101111011010 #
b1010101111011010 %
0"
0$
#53
1"
#54
0"
1$
#55
1,
b1010101111011010 !
b1010101111011010 &
0)
1"
#56
1(
b1010101111011011 #
b1010101111011011 %
0"
0$
#57
1"
#58
0"
1$
#59
b1010101111011011 !
b1010101111011011 &
1)
1"
#60
0(
0+
1.
b1010101111011100 #
b1010101111011100 %
0"
0$
#61
1"
#62
0"
1$
#63
1/
0,
b1010101111011100 !
b1010101111011100 &
0)
1"
#64
1(
b1010101111011101 #
b1010101111011101 %
0"
0$
#65
1"
#66
0"
1$
#67
b1010101111011101 !
b1010101111011101 &
1)
1"
#68
0(
1+
b1010101111011110 #
b1010101111011110 %
0"
0$
#69
1"
#70
0"
1$
#71
1,
b1010101111011110 !
b1010101111011110 &
0)
1"
#72
1(
b1010101111011111 #
b1010101111011111 %
0"
0$
#73
1"
#74
0"
1$
#75
b1010101111011111 !
b1010101111011111 &
1)
1"
#76
0(
0+
0.
01
04
17
b1010101111100000 #
b1010101111100000 %
0"
0$
#77
1"
#78
0"
1$
#79
18
05
02
0/
0,
b1010101111100000 !
b1010101111100000 &
0)
1"
#80
1(
b1010101111100001 #
b1010101111100001 %
0"
0$
#81
1"
#82
0"
1$
#83
b1010101111100001 !
b1010101111100001 &
1)
1"
#84
0(
1+
b1010101111100010 #
b1010101111100010 %
0"
0$
#85
1"
#86
0"
1$
#87
1,
b1010101111100010 !
b1010101111100010 &
0)
1"
#88
1(
b1010101111100011 #
b1010101111100011 %
0"
0$
#89
1"
#90
0"
1$
#91
b1010101111100011 !
b1010101111100011 &
1)
1"
#92
0(
0+
1.
b1010101111100100 #
b1010101111100100 %
0"
0$
#93
1"
#94
0"
1$
#95
1/
0,
b1010101111100100 !
b1010101111100100 &
0)
1"
#96
1(
b1010101111100101 #
b1010101111100101 %
0"
0$
#97
1"
#98
0"
1$
#99
b1010101111100101 !
b1010101111100101 &
1)
1"
#100
0(
1+
b1010101111100110 #
b1010101111100110 %
0"
0$
#101
1"
#102
0"
1$
#103
1,
b1010101111100110 !
b1010101111100110 &
0)
1"
#104
1(
b1010101111100111 #
b1010101111100111 %
0"
0$
#105
1"
#106
0"
1$
#107
b1010101111100111 !
b1010101111100111 &
1)
1"
#108
0(
0+
0.
11
b1010101111101000 #
b1010101111101000 %
0"
0$
#109
1"
#110
0"
1$
#111
12
0/
0,
b1010101111101000 !
b1010101111101000 &
0)
1"
#112
1(
b1010101111101001 #
b1010101111101001 %
0"
0$
#113
1"
#114
0"
1$
#115
b1010101111101001 !
b1010101111101001 &
1)
1"
#116
0(
1+
b1010101111101010 #
b1010101111101010 %
0"
0$
#117
1"
#118
0"
1$
#119
1,
b1010101111101010 !
b1010101111101010 &
0)
1"
#120
1(
b1010101111101011 #
b1010101111101011 %
0"
0$
#121
1"
#122
0"
1$
#123
b1010101111101011 !
b1010101111101011 &
1)
1"
#124
0(
0+
1.
b1010101111101100 #
b1010101111101100 %
0"
0$
#125
1"
#126
0"
1$
#127
1/
0,
b1010101111101100 !
b1010101111101100 &
0)
1"
#128
1(
b1010101111101101 #
b1010101111101101 %
0"
0$
#129
1"
#130
0"
1$
#131
b1010101111101101 !
b1010101111101101 &
1)
1"
#132
0(
1+
b1010101111101110 #
b1010101111101110 %
0"
0$
#133
1"
#134
0"
1$
#135
1,
b1010101111101110 !
b1010101111101110 &
0)
1"
#136
1(
b1010101111101111 #
b1010101111101111 %
0"
0$
#137
1"
#138
0"
1$
#139
b1010101111101111 !
b1010101111101111 &
1)
1"
#140
0(
0+
0.
01
14
b1010101111110000 #
b1010101111110000 %
0"
0$
#141
1"
#142
0"
1$
#143
15
02
0/
0,
b1010101111110000 !
b1010101111110000 &
0)
1"
#144
1(
b1010101111110001 #
b1010101111110001 %
0"
0$
#145
1"
#146
0"
1$
#147
b1010101111110001 !
b1010101111110001 &
1)
1"
#148
0(
1+
b1010101111110010 #
b1010101111110010 %
0"
0$
#149
1"
#150
0"
1$
#151
1,
b1010101111110010 !
b1010101111110010 &
0)
1"
#152
1(
b1010101111110011 #
b1010101111110011 %
0"
0$
#153
1"
#154
0"
1$
#155
b1010101111110011 !
b1010101111110011 &
1)
1"
#156
0(
0+
1.
b1010101111110100 #
b1010101111110100 %
0"
0$
#157
1"
#158
0"
1$
#159
1/
0,
b1010101111110100 !
b1010101111110100 &
0)
1"
#160
1(
b1010101111110101 #
b1010101111110101 %
0"
0$
#161
1"
#162
0"
1$
#163
b1010101111110101 !
b1010101111110101 &
1)
1"
#164
0(
1+
b1010101111110110 #
b1010101111110110 %
0"
0$
#165
1"
#166
0"
1$
#167
1,
b1010101111110110 !
b1010101111110110 &
0)
1"
#168
1(
b1010101111110111 #
b1010101111110111 %
0"
0$
#169
1"
#170
0"
1$
#171
b1010101111110111 !
b1010101111110111 &
1)
1"
#172
0(
0+
0.
11
b1010101111111000 #
b1010101111111000 %
0"
0$
#173
1"
#174
0"
1$
#175
12
0/
0,
b1010101111111000 !
b1010101111111000 &
0)
1"
#176
1(
b1010101111111001 #
b1010101111111001 %
0"
0$
#177
1"
#178
0"
1$
#179
b1010101111111001 !
b1010101111111001 &
1)
1"
#180
0(
1+
b1010101111111010 #
b1010101111111010 %
0"
0$
#181
1"
#182
0"
1$
#183
1,
b1010101111111010 !
b1010101111111010 &
0)
1"
#184
1(
b1010101111111011 #
b1010101111111011 %
0"
0$
#185
1"
#186
0"
1$
#187
b1010101111111011 !
b1010101111111011 &
1)
1"
#188
0(
0+
1.
b1010101111111100 #
b1010101111111100 %
0"
0$
#189
1"
#190
0"
1$
#191
1/
0,
b1010101111111100 !
b1010101111111100 &
0)
1"
#192
1(
b1010101111111101 #
b1010101111111101 %
0"
0$
#193
1"
#194
0"
1$
#195
b1010101111111101 !
b1010101111111101 &
1)
1"
#196
0(
1+
b1010101111111110 #
b1010101111111110 %
0"
0$
#197
1"
#198
0"
1$
#199
1,
b1010101111111110 !
b1010101111111110 &
0)
1"
#200
1(
b1010101111111111 #
b1010101111111111 %
0"
0$
#201
1"
#202
0"
1$
#203
b1010101111111111 !
b1010101111111111 &
1)
1"
#204
0(
0+
0.
01
04
07
0:
0=
0@
0C
1F
b1010110000000000 #
b1010110000000000 %
0"
0$
#205
1"
#206
0"
1$
#207
1G
0D
0A
0>
0;
08
05
02
0/
0,
b1010110000000000 !
b1010110000000000 &
0)
1"
#208
1(
b1010110000000001 #
b1010110000000001 %
0"
0$
#209
1"
#210
0"
1$
#211
b1010110000000001 !
b1010110000000001 &
1)
1"
#212
0(
1+
b1010110000000010 #
b1010110000000010 %
0"
0$
#213
1"
#214
0"
1$
#215
1,
b1010110000000010 !
b1010110000000010 &
0)
1"
#216
1(
b1010110000000011 #
b1010110000000011 %
0"
0$
#217
1"
#218
0"
1$
#219
b1010110000000011 !
b1010110000000011 &
1)
1"
#220
0(
0+
1.
b1010110000000100 #
b1010110000000100 %
0"
0$
#221
1"
#222
0"
1$
#223
1/
0,
b1010110000000100 !
b1010110000000100 &
0)
1"
#224
1(
b1010110000000101 #
b1010110000000101 %
0"
0$
#225
1"
#226
0"
1$
#227
b1010110000000101 !
b1010110000000101 &
1)
1"
#228
0(
1+
b1010110000000110 #
b1010110000000110 %
0"
0$
#229
1"
#230
0"
1$
#231
1,
b1010110000000110 !
b1010110000000110 &
0)
1"
#232
1(
b1010110000000111 #
b1010110000000111 %
0"
0$
#233
1"
#234
0"
1$
#235
b1010110000000111 !
b1010110000000111 &
1)
1"
#236
0(
0+
0.
11
b1010110000001000 #
b1010110000001000 %
0"
0$
#237
1"
#238
0"
1$
#239
12
0/
0,
b1010110000001000 !
b1010110000001000 &
0)
1"
#240
1(
b1010110000001001 #
b1010110000001001 %
0"
0$
#241
1"
#242
0"
1$
#243
b1010110000001001 !
b1010110000001001 &
1)
1"
#244
0(
1+
b1010110000001010 #
b1010110000001010 %
0"
0$
#245
1"
#246
0"
1$
#247
1,
b1010110000001010 !
b1010110000001010 &
0)
1"
#248
1(
b1010110000001011 #
b1010110000001011 %
0"
0$
#249
1"
#250
0"
1$
#251
b1010110000001011 !
b1010110000001011 &
1)
1"
#252
0(
0+
1.
b1010110000001100 #
b1010110000001100 %
0"
0$
#253
1"
#254
0"
1$
#255
1/
0,
b1010110000001100 !
b1010110000001100 &
0)
1"
#256
1(
b1010110000001101 #
b1010110000001101 %
0"
0$
#257
1"
#258
0"
1$
#259
b1010110000001101 !
b1010110000001101 &
1)
1"
#260
0(
1+
b1010110000001110 #
b1010110000001110 %
0"
0$
#261
1"
#262
0"
1$
#263
1,
b1010110000001110 !
b1010110000001110 &
0)
1"
#264
1(
b1010110000001111 #
b1010110000001111 %
0"
0$
#265
1"
#266
0"
1$
#267
b1010110000001111 !
b1010110000001111 &
1)
1"
#268
0(
0+
0.
01
14
b1010110000010000 #
b1010110000010000 %
0"
0$
#269
1"
#270
0"
1$
#271
15
02
0/
0,
b1010110000010000 !
b1010110000010000 &
0)
1"
#272
1(
b1010110000010001 #
b1010110000010001 %
0"
0$
#273
1"
#274
0"
1$
#275
b1010110000010001 !
b1010110000010001 &
1)
1"
#276
0(
1+
b1010110000010010 #
b1010110000010010 %
0"
0$
#277
1"
#278
0"
1$
#279
1,
b1010110000010010 !
b1010110000010010 &
0)
1"
#280
1(
b1010110000010011 #
b1010110000010011 %
0"
0$
#281
1"
#282
0"
1$
#283
b1010110000010011 !
b1010110000010011 &
1)
1"
#284
0(
0+
1.
b1010110000010100 #
b1010110000010100 %
0"
0$
#285
1"
#286
0"
1$
#287
1/
0,
b1010110000010100 !
b1010110000010100 &
0)
1"
#288
1(
b1010110000010101 #
b1010110000010101 %
0"
0$
#289
1"
#290
0"
1$
#291
b1010110000010101 !
b1010110000010101 &
1)
1"
#292
0(
1+
b1010110000010110 #
b1010110000010110 %
0"
0$
#293
1"
#294
0"
1$
#295
1,
b1010110000010110 !
b1010110000010110 &
0)
1"
#296
1(
b1010110000010111 #
b1010110000010111 %
0"
0$
#297
1"
#298
0"
1$
#299
b1010110000010111 !
b1010110000010111 &
1)
1"
#300
0(
0+
0.
11
b1010110000011000 #
b1010110000011000 %
0"
0$
#301
1"
#302
0"
1$
#303
12
0/
0,
b1010110000011000 !
b1010110000011000 &
0)
1"
#304
1(
b1010110000011001 #
b1010110000011001 %
0"
0$
#305
1"
#306
0"
1$
#307
b1010110000011001 !
b1010110000011001 &
1)
1"
#308
0(
1+
b1010110000011010 #
b1010110000011010 %
0"
0$
#309
1"
#310
0"
1$
#311
1,
b1010110000011010 !
b1010110000011010 &
0)
1"
#312
1(
b1010110000011011 #
b1010110000011011 %
0"
0$
#313
1"
#314
0"
1$
#315
b1010110000011011 !
b1010110000011011 &
1)
1"
#316
0(
0+
1.
b1010110000011100 #
b1010110000011100 %
0"
0$
#317
1"
#318
0"
1$
#319
1/
0,
b1010110000011100 !
b1010110000011100 &
0)
1"
#320
1(
b1010110000011101 #
b1010110000011101 %
0"
0$
#321
1"
#322
0"
1$
#323
b1010110000011101 !
b1010110000011101 &
1)
1"
#324
0(
1+
b1010110000011110 #
b1010110000011110 %
0"
0$
#325
1"
#326
0"
1$
#327
1,
b1010110000011110 !
b1010110000011110 &
0)
1"
#328
1(
b1010110000011111 #
b1010110000011111 %
0"
0$
#329
1"
#330
0"
1$
#331
b1010110000011111 !
b1010110000011111 &
1)
1"
#332
0(
0+
0.
01
04
17
b1010110000100000 #
b1010110000100000 %
0"
0$
#333
1"
#334
0"
1$
#335
18
05
02
0/
0,
b1010110000100000 !
b1010110000100000 &
0)
1"
#336
1(
b1010110000100001 #
b1010110000100001 %
0"
0$
#337
1"
#338
0"
1$
#339
b1010110000100001 !
b1010110000100001 &
1)
1"
#340
0(
1+
b1010110000100010 #
b1010110000100010 %
0"
0$
#341
1"
#342
0"
1$
#343
1,
b1010110000100010 !
b1010110000100010 &
0)
1"
#344
1(
b1010110000100011 #
b1010110000100011 %
0"
0$
#345
1"
#346
0"
1$
#347
b1010110000100011 !
b1010110000100011 &
1)
1"
#348
0(
0+
1.
b1010110000100100 #
b1010110000100100 %
0"
0$
#349
1"
#350
0"
1$
#351
1/
0,
b1010110000100100 !
b1010110000100100 &
0)
1"
#352
1(
b1010110000100101 #
b1010110000100101 %
0"
0$
#353
1"
#354
0"
1$
#355
b1010110000100101 !
b1010110000100101 &
1)
1"
#356
0(
1+
b1010110000100110 #
b1010110000100110 %
0"
0$
#357
1"
#358
0"
1$
#359
1,
b1010110000100110 !
b1010110000100110 &
0)
1"
#360
1(
b1010110000100111 #
b1010110000100111 %
0"
0$
#361
1"
#362
0"
1$
#363
b1010110000100111 !
b1010110000100111 &
1)
1"
#364
0(
0+
0.
11
b1010110000101000 #
b1010110000101000 %
0"
0$
#365
1"
#366
0"
1$
#367
12
0/
0,
b1010110000101000 !
b1010110000101000 &
0)
1"
#368
1(
b1010110000101001 #
b1010110000101001 %
0"
0$
#369
1"
#370
0"
1$
#371
b1010110000101001 !
b1010110000101001 &
1)
1"
#372
0(
1+
b1010110000101010 #
b1010110000101010 %
0"
0$
#373
1"
#374
0"
1$
#375
1,
b1010110000101010 !
b1010110000101010 &
0)
1"
#376
1(
b1010110000101011 #
b1010110000101011 %
0"
0$
#377
1"
#378
0"
1$
#379
b1010110000101011 !
b1010110000101011 &
1)
1"
#380
0(
0+
1.
b1010110000101100 #
b1010110000101100 %
0"
0$
#381
1"
#382
0"
1$
#383
1/
0,
b1010110000101100 !
b1010110000101100 &
0)
1"
#384
1(
b1010110000101101 #
b1010110000101101 %
0"
0$
#385
1"
#386
0"
1$
#387
b1010110000101101 !
b1010110000101101 &
1)
1"
#388
0(
1+
b1010110000101110 #
b1010110000101110 %
0"
0$
#389
1"
#390
0"
1$
#391
1,
b1010110000101110 !
b1010110000101110 &
0)
1"
#392
1(
b1010110000101111 #
b1010110000101111 %
0"
0$
#393
1"
#394
0"
1$
#395
b1010110000101111 !
b1010110000101111 &
1)
1"
#396
0(
0+
0.
01
14
b1010110000110000 #
b1010110000110000 %
0"
0$
#397
1"
#398
0"
1$
#399
15
02
0/
0,
b1010110000110000 !
b1010110000110000 &
0)
1"
#400
1(
b1010110000110001 #
b1010110000110001 %
0"
0$
#401
1"
#402
0"
1$
#403
b1010110000110001 !
b1010110000110001 &
1)
1"
#404
0(
1+
b1010110000110010 #
b1010110000110010 %
0"
0$
#405
1"
#406
0"
1$
#407
1,
b1010110000110010 !
b1010110000110010 &
0)
1"
#408
1(
b1010110000110011 #
b1010110000110011 %
0"
0$
#409
1"
#410
0"
1$
#411
b1010110000110011 !
b1010110000110011 &
1)
1"
#412
0(
0+
1.
b1010110000110100 #
b1010110000110100 %
0"
0$
#413
1"
#414
0"
1$
#415
1/
0,
b1010110000110100 !
b1010110000110100 &
0)
1"
#416
1(
b1010110000110101 #
b1010110000110101 %
0"
0$
#417
1"
#418
0"
1$
#419
b1010110000110101 !
b1010110000110101 &
1)
1"
#420
0(
1+
b1010110000110110 #
b1010110000110110 %
0"
0$
#421
1"
#422
0"
1$
#423
1,
b1010110000110110 !
b1010110000110110 &
0)
1"
#424
1(
b1010110000110111 #
b1010110000110111 %
0"
0$
#425
1"
#426
0"
1$
#427
b1010110000110111 !
b1010110000110111 &
1)
1"
#428
0(
0+
0.
11
b1010110000111000 #
b1010110000111000 %
0"
0$
#429
1"
#430
0"
1$
#431
12
0/
0,
b1010110000111000 !
b1010110000111000 &
0)
1"
#432
1(
b1010110000111001 #
b1010110000111001 %
0"
0$
#433
1"
#434
0"
1$
#435
b1010110000111001 !
b1010110000111001 &
1)
1"
#436
0(
1+
b1010110000111010 #
b1010110000111010 %
0"
0$
#437
1"
#438
0"
1$
#439
1,
b1010110000111010 !
b1010110000111010 &
0)
1"
#440
1(
b1010110000111011 #
b1010110000111011 %
0"
0$
#441
1"
#442
0"
1$
#443
b1010110000111011 !
b1010110000111011 &
1)
1"
#444
0(
0+
1.
b1010110000111100 #
b1010110000111100 %
0"
0$
#445
1"
#446
0"
1$
#447
1/
0,
b1010110000111100 !
b1010110000111100 &
0)
1"
#448
1(
b1010110000111101 #
b1010110000111101 %
0"
0$
#449
1"
#450
0"
1$
#451
b1010110000111101 !
b1010110000111101 &
1)
1"
#452
0(
1+
b1010110000111110 #
b1010110000111110 %
0"
0$
#453
1"
#454
0"
1$
#455
1,
b1010110000111110 !
b1010110000111110 &
0)
1"
#456
1(
b1010110000111111 #
b1010110000111111 %
0"
0$
#457
1"
#458
0"
1$
#459
b1010110000111111 !
b1010110000111111 &
1)
1"
#460
0(
0+
0.
01
04
07
1:
b1010110001000000 #
b1010110001000000 %
0"
0$
#461
1"
#462
0"
1$
#463
1;
08
05
02
0/
0,
b1010110001000000 !
b1010110001000000 &
0)
1"
#464
1(
b1010110001000001 #
b1010110001000001 %
0"
0$
#465
1"
#466
0"
1$
#467
b1010110001000001 !
b1010110001000001 &
1)
1"
#468
0(
1+
b1010110001000010 #
b1010110001000010 %
0"
0$
#469
1"
#470
0"
1$
#471
1,
b1010110001000010 !
b1010110001000010 &
0)
1"
#472
1(
b1010110001000011 #
b1010110001000011 %
0"
0$
#473
1"
#474
0"
1$
#475
b1010110001000011 !
b1010110001000011 &
1)
1"
#476
0(
0+
1.
b1010110001000100 #
b1010110001000100 %
0"
0$
#477
1"
#478
0"
1$
#479
1/
0,
b1010110001000100 !
b1010110001000100 &
0)
1"
#480
1(
b1010110001000101 #
b1010110001000101 %
0"
0$
#481
1"
#482
0"
1$
#483
b1010110001000101 !
b1010110001000101 &
1)
1"
#484
0(
1+
b1010110001000110 #
b1010110001000110 %
0"
0$
#485
1"
#486
0"
1$
#487
1,
b1010110001000110 !
b1010110001000110 &
0)
1"
#488
1(
b1010110001000111 #
b1010110001000111 %
0"
0$
#489
1"
#490
0"
1$
#491
b1010110001000111 !
b1010110001000111 &
1)
1"
#492
0(
0+
0.
11
b1010110001001000 #
b1010110001001000 %
0"
0$
#493
1"
#494
0"
1$
#495
12
0/
0,
b1010110001001000 !
b1010110001001000 &
0)
1"
#496
1(
b1010110001001001 #
b1010110001001001 %
0"
0$
#497
1"
#498
0"
1$
#499
b1010110001001001 !
b1010110001001001 &
1)
1"
#500
0(
1+
b1010110001001010 #
b1010110001001010 %
0"
0$
#501
1"
#502
0"
1$
#503
1,
b1010110001001010 !
b1010110001001010 &
0)
1"
#504
1(
b1010110001001011 #
b1010110001001011 %
0"
0$
#505
1"
#506
0"
1$
#507
b1010110001001011 !
b1010110001001011 &
1)
1"
#508
0(
0+
1.
b1010110001001100 #
b1010110001001100 %
0"
0$
#509
1"
#510
0"
1$
#511
1/
0,
b1010110001001100 !
b1010110001001100 &
0)
1"
#512
1(
b1010110001001101 #
b1010110001001101 %
0"
0$
#513
1"
#514
0"
1$
#515
b1010110001001101 !
b1010110001001101 &
1)
1"
#516
0(
1+
b1010110001001110 #
b1010110001001110 %
0"
0$
#517
1"
#518
0"
1$
#519
1,
b1010110001001110 !
b1010110001001110 &
0)
1"
#520
1(
b1010110001001111 #
b1010110001001111 %
0"
0$
#521
1"
#522
0"
1$
#523
b1010110001001111 !
b1010110001001111 &
1)
1"
#524
0(
0+
0.
01
14
b1010110001010000 #
b1010110001010000 %
0"
0$
#525
1"
#526
0"
1$
#527
15
02
0/
0,
b1010110001010000 !
b1010110001010000 &
0)
1"
#528
1(
b1010110001010001 #
b1010110001010001 %
0"
0$
#529
1"
#530
0"
1$
#531
b1010110001010001 !
b1010110001010001 &
1)
1"
#532
0(
1+
b1010110001010010 #
b1010110001010010 %
0"
0$
#533
1"
#534
0"
1$
#535
1,
b1010110001010010 !
b1010110001010010 &
0)
1"
#536
1(
b1010110001010011 #
b1010110001010011 %
0"
0$
#537
1"
#538
0"
1$
#539
b1010110001010011 !
b1010110001010011 &
1)
1"
#540
0(
0+
1.
b1010110001010100 #
b1010110001010100 %
0"
0$
#541
1"
#542
0"
1$
#543
1/
0,
b1010110001010100 !
b1010110001010100 &
0)
1"
#544
1(
b1010110001010101 #
b1010110001010101 %
0"
0$
#545
1"
#546
0"
1$
#547
b1010110001010101 !
b1010110001010101 &
1)
1"
#548
0(
1+
b1010110001010110 #
b1010110001010110 %
0"
0$
#549
1"
#550
0"
1$
#551
1,
b1010110001010110 !
b1010110001010110 &
0)
1"
#552
1(
b1010110001010111 #
b1010110001010111 %
0"
0$
#553
1"
#554
0"
1$
#555
b1010110001010111 !
b1010110001010111 &
1)
1"
#556
0(
0+
0.
11
b1010110001011000 #
b1010110001011000 %
0"
0$
#557
1"
#558
0"
1$
#559
12
0/
0,
b1010110001011000 !
b1010110001011000 &
0)
1"
#560
1(
b1010110001011001 #
b1010110001011001 %
0"
0$
#561
1"
#562
0"
1$
#563
b1010110001011001 !
b1010110001011001 &
1)
1"
#564
0(
1+
b1010110001011010 #
b1010110001011010 %
0"
0$
#565
1"
#566
0"
1$
#567
1,
b1010110001011010 !
b1010110001011010 &
0)
1"
#568
1(
b1010110001011011 #
b1010110001011011 %
0"
0$
#569
1"
#570
0"
1$
#571
b1010110001011011 !
b1010110001011011 &
1)
1"
#572
0(
0+
1.
b1010110001011100 #
b1010110001011100 %
0"
0$
#573
1"
#574
0"
1$
#575
1/
0,
b1010110001011100 !
b1010110001011100 &
0)
1"
#576
1(
b1010110001011101 #
b1010110001011101 %
0"
0$
#577
1"
#578
0"
1$
#579
b1010110001011101 !
b1010110001011101 &
1)
1"
#580
0(
1+
b1010110001011110 #
b1010110001011110 %
0"
0$
#581
1"
#582
0"
1$
#583
1,
b1010110001011110 !
b1010110001011110 &
0)
1"
#584
1(
b1010110001011111 #
b1010110001011111 %
0"
0$
#585
1"
#586
0"
1$
#587
b1010110001011111 !
b1010110001011111 &
1)
1"
#588
0(
0+
0.
01
04
17
b1010110001100000 #
b1010110001100000 %
0"
0$
#589
1"
#590
0"
1$
#591
18
05
02
0/
0,
b1010110001100000 !
b1010110001100000 &
0)
1"
#592
1(
b1010110001100001 #
b1010110001100001 %
0"
0$
#593
1"
#594
0"
1$
#595
b1010110001100001 !
b1010110001100001 &
1)
1"
#596
0(
1+
b1010110001100010 #
b1010110001100010 %
0"
0$
#597
1"
#598
0"
1$
#599
1,
b1010110001100010 !
b1010110001100010 &
0)
1"
