registers_and_rams/Register1.v
module Register1 (
    input in,
    input load,
    input clk,
    output reg out = 0
);

always @(posedge clk ) begin
    if (load == 1) begin
        out <= in;
    end else begin
        out <= out;
    end
end
    
endmodule

registers_and_rams/Register1_tb.v
`include "Register1.v"

module Register1_tb;


reg in = 0, load = 0, clk = 0;
wire out;
Register1 register1 (.in(in), .out(out), .load(load), .clk(clk));

initial begin
    $dumpfile("Register1.vcd");
    $dumpvars(0, Register1_tb);
    #1000 $finish;
end

always begin
    #1
    clk = ~clk;
end

always begin
    #2
    load = ~load;
end

always begin
    #4
    in = ~in;
end
    
endmodule

registers_and_rams/Register1.vcd
$date
	Sun Aug 27 19:29:15 2023
$end
$version
	Icarus Verilog
$end
$timescale
	1s
$end
$scope module Register1_tb $end
$var wire 1 ! out $end
$var reg 1 " clk $end
$var reg 1 # in $end
$var reg 1 $ load $end
$scope module register1 $end
$var wire 1 " clk $end
$var wire 1 # in $end
$var wire 1 $ load $end
$var reg 1 ! out $end
$upscope $end
$upscope $end
$enddefinitions $end
$comment Show the parameter values. $end
$dumpall
$end
#0
$dumpvars
0$
0#
0"
x!
$end
#1
1"
#2
0"
1$
#3
0!
1"
#4
0"
0$
1#
#5
1"
#6
0"
1$
#7
1!
1"
#8
0"
0$
0#
#9
1"
#10
0"
1$
#11
0!
1"
#12
0"
0$
1#
#13
1"
#14
0"
1$
#15
1!
1"
#16
0"
0$
0#
#17
1"
#18
0"
1$
#19
0!
1"
#20
0"
0$
1#
#21
1"
#22
0"
1$
#23
1!
1"
#24
0"
0$
0#
#25
1"
#26
0"
1$
#27
0!
1"
#28
0"
0$
1#
#29
1"
#30
0"
1$
#31
1!
1"
#32
0"
0$
0#
#33
1"
#34
0"
1$
#35
0!
1"
#36
0"
0$
1#
#37
1"
#38
0"
1$
#39
1!
1"
#40
0"
0$
0#
#41
1"
#42
0"
1$
#43
0!
1"
#44
0"
0$
1#
#45
1"
#46
0"
1$
#47
1!
1"
#48
0"
0$
0#
#49
1"
#50
0"
1$
#51
0!
1"
#52
0"
0$
1#
#53
1"
#54
0"
1$
#55
1!
1"
#56
0"
0$
0#
#57
1"
#58
0"
1$
#59
0!
1"
#60
0"
0$
1#
#61
1"
#62
0"
1$
#63
1!
1"
#64
0"
0$
0#
#65
1"
#66
0"
1$
#67
0!
1"
#68
0"
0$
1#
#69
1"
#70
0"
1$
#71
1!
1"
#72
0"
0$
0#
#73
1"
#74
0"
1$
#75
0!
1"
#76
0"
0$
1#
#77
1"
#78
0"
1$
#79
1!
1"
#80
0"
0$
0#
#81
1"
#82
0"
1$
#83
0!
1"
#84
0"
0$
1#
#85
1"
#86
0"
1$
#87
1!
1"
#88
0"
0$
0#
#89
1"
#90
0"
1$
#91
0!
1"
#92
0"
0$
1#
#93
1"
#94
0"
1$
#95
1!
1"
#96
0"
0$
0#
#97
1"
#98
0"
1$
#99
0!
1"
#100
0"
0$
1#
#101
1"
#102
0"
1$
#103
1!
1"
#104
0"
0$
0#
#105
1"
#106
0"
1$
#107
0!
1"
#108
0"
0$
1#
#109
1"
#110
0"
1$
#111
1!
1"
#112
0"
0$
0#
#113
1"
#114
0"
1$
#115
0!
1"
#116
0"
0$
1#
#117
1"
#118
0"
1$
#119
1!
1"
#120
0"
0$
0#
#121
1"
#122
0"
1$
#123
0!
1"
#124
0"
0$
1#
#125
1"
#126
0"
1$
#127
1!
1"
#128
0"
0$
0#
#129
1"
#130
0"
1$
#131
0!
1"
#132
0"
0$
1#
#133
1"
#134
0"
1$
#135
1!
1"
#136
0"
0$
0#
#137
1"
#138
0"
1$
#139
0!
1"
#140
0"
0$
1#
#141
1"
#142
0"
1$
#143
1!
1"
#144
0"
0$
0#
#145
1"
#146
0"
1$
#147
0!
1"
#148
0"
0$
1#
#149
1"
#150
0"
1$
#151
1!
1"
#152
0"
0$
0#
#153
1"
#154
0"
1$
#155
0!
1"
#156
0"
0$
1#
#157
1"
#158
0"
1$
#159
1!
1"
#160
0"
0$
0#
#161
1"
#162
0"
1$
#163
0!
1"
#164
0"
0$
1#
#165
1"
#166
0"
1$
#167
1!
1"
#168
0"
0$
0#
#169
1"
#170
0"
1$
#171
0!
1"
#172
0"
0$
1#
#173
1"
#174
0"
1$
#175
1!
1"
#176
0"
0$
0#
#177
1"
#178
0"
1$
#179
0!
1"
#180
0"
0$
1#
#181
1"
#182
0"
1$
#183
1!
1"
#184
0"
0$
0#
#185
1"
#186
0"
1$
#187
0!
1"
#188
0"
0$
1#
#189
1"
#190
0"
1$
#191
1!
1"
#192
0"
0$
0#
#193
1"
#194
0"
1$
#195
0!
1"
#196
0"
0$
1#
#197
1"
#198
0"
1$
#199
1!
1"
#200
0"
0$
0#
#201
1"
#202
0"
1$
#203
0!
1"
#204
0"
0$
1#
#205
1"
#206
0"
1$
#207
1!
1"
#208
0"
0$
0#
#209
1"
#210
0"
1$
#211
0!
1"
#212
0"
0$
1#
#213
1"
#214
0"
1$
#215
1!
1"
#216
0"
0$
0#
#217
1"
#218
0"
1$
#219
0!
1"
#220
0"
0$
1#
#221
1"
#222
0"
1$
#223
1!
1"
#224
0"
0$
0#
#225
1"
#226
0"
1$
#227
0!
1"
#228
0"
0$
1#
#229
1"
#230
0"
1$
#231
1!
1"
#232
0"
0$
0#
#233
1"
#234
0"
1$
#235
0!
1"
#236
0"
0$
1#
#237
1"
#238
0"
1$
#239
1!
1"
#240
0"
0$
0#
#241
1"
#242
0"
1$
#243
0!
1"
#244
0"
0$
1#
#245
1"
#246
0"
1$
#247
1!
1"
#248
0"
0$
0#
#249
1"
#250
0"
1$
#251
0!
1"
#252
0"
0$
1#
#253
1"
#254
0"
1$
#255
1!
1"
#256
0"
0$
0#
#257
1"
#258
0"
1$
#259
0!
1"
#260
0"
0$
1#
#261
1"
#262
0"
1$
#263
1!
1"
#264
0"
0$
0#
#265
1"
#266
0"
1$
#267
0!
1"
#268
0"
0$
1#
#269
1"
#270
0"
1$
#271
1!
1"
#272
0"
0$
0#
#273
1"
#274
0"
1$
#275
0!
1"
#276
0"
0$
1#
#277
1"
#278
0"
1$
#279
1!
1"
#280
0"
0$
0#
#281
1"
#282
0"
1$
#283
0!
1"
#284
0"
0$
1#
#285
1"
#286
0"
1$
#287
1!
1"
#288
0"
0$
0#
#289
1"
#290
0"
1$
#291
0!
1"
#292
0"
0$
1#
#293
1"
#294
0"
1$
#295
1!
1"
#296
0"
0$
0#
#297
1"
#298
0"
1$
#299
0!
1"
#300
0"
0$
1#
#301
1"
#302
0"
1$
#303
1!
1"
#304
0"
0$
0#
#305
1"
#306
0"
1$
#307
0!
1"
#308
0"
0$
1#
#309
1"
#310
0"
1$
#311
1!
1"
#312
0"
0$
0#
#313
1"
#314
0"
1$
#315
0!
1"
#316
0"
0$
1#
#317
1"
#318
0"
1$
#319
1!
1"
#320
0"
0$
0#
#321
1"
#322
0"
1$
#323
0!
1"
#324
0"
0$
1#
#325
1"
#326
0"
1$
#327
1!
1"
#328
0"
0$
0#
#329
1"
#330
0"
1$
#331
0!
1"
#332
0"
0$
1#
#333
1"
#334
0"
1$
#335
1!
1"
#336
0"
0$
0#
#337
1"
#338
0"
1$
#339
0!
1"
#340
0"
0$
1#
#341
1"
#342
0"
1$
#343
1!
1"
#344
0"
0$
0#
#345
1"
#346
0"
1$
#347
0!
1"
#348
0"
0$
1#
#349
1"
#350
0"
1$
#351
1!
1"
#352
0"
0$
0#
#353
1"
#354
0"
1$
#355
0!
1"
#356
0"
0$
1#
#357
1"
#358
0"
1$
#359
1!
1"
#360
0"
0$
0#
#361
1"
#362
0"
1$
#363
0!
1"
#364
0"
0$
1#
#365
1"
#366
0"
1$
#367
1!
1"
#368
0"
0$
0#
#369
1"
#370
0"
1$
#371
0!
1"
#372
0"
0$
1#
#373
1"
#374
0"
1$
#375
1!
1"
#376
0"
0$
0#
#377
1"
#378
0"
1$
#379
0!
1"
#380
0"
0$
1#
#381
1"
#382
0"
1$
#383
1!
1"
#384
0"
0$
0#
#385
1"
#386
0"
1$
#387
0!
1"
#388
0"
0$
1#
#389
1"
#390
0"
1$
#391
1!
1"
#392
0"
0$
0#
#393
1"
#394
0"
1$
#395
0!
1"
#396
0"
0$
1#
#397
1"
#398
0"
1$
#399
1!
1"
#400
0"
0$
0#
#401
1"
#402
0"
1$
#403
0!
1"
#404
0"
0$
1#
#405
1"
#406
0"
1$
#407
1!
1"
#408
0"
0$
0#
#409
1"
#410
0"
1$
#411
0!
1"
#412
0"
0$
1#
#413
1"
#414
0"
1$
#415
1!
1"
#416
0"
0$
0#
#417
1"
#418
0"
1$
#419
0!
1"
#420
0"
0$
1#
#421
1"
#422
0"
1$
#423
1!
1"
#424
0"
0$
0#
#425
1"
#426
0"
1$
#427
0!
1"
#428
0"
0$
1#
#429
1"
#430
0"
1$
#431
1!
1"
#432
0"
0$
0#
#433
1"
#434
0"
1$
#435
0!
1"
#436
0"
0$
1#
#437
1"
#438
0"
1$
#439
1!
1"
#440
0"
0$
0#
#441
1"
#442
0"
1$
#443
0!
1"
#444
0"
0$
1#
#445
1"
#446
0"
1$
#447
1!
1"
#448
0"
0$
0#
#449
1"
#450
0"
1$
#451
0!
1"
#452
0"
0$
1#
#453
1"
#454
0"
1$
#455
1!
1"
#456
0"
0$
0#
#457
1"
#458
0"
1$
#459
0!
1"
#460
0"
0$
1#
#461
1"
#462
0"
1$
#463
1!
1"
#464
0"
0$
0#
#465
1"
#466
0"
1$
#467
0!
1"
#468
0"
0$
1#
#469
1"
#470
0"
1$
#471
1!
1"
#472
0"
0$
0#
#473
1"
#474
0"
1$
#475
0!
1"
#476
0"
0$
1#
#477
1"
#478
0"
1$
#479
1!
1"
#480
0"
0$
0#
#481
1"
#482
0"
1$
#483
0!
1"
#484
0"
0$
1#
#485
1"
#486
0"
1$
#487
1!
1"
#488
0"
0$
0#
#489
1"
#490
0"
1$
#491
0!
1"
#492
0"
0$
1#
#493
1"
#494
0"
1$
#495
1!
1"
#496
0"
0$
0#
#497
1"
#498
0"
1$
#499
0!
1"
#500
0"
0$
1#
#501
1"
#502
0"
1$
#503
1!
1"
#504
0"
0$
0#
#505
1"
#506
0"
1$
#507
0!
1"
#508
0"
0$
1#
#509
1"
#510
0"
1$
#511
1!
1"
#512
0"
0$
0#
#513
1"
#514
0"
1$
#515
0!
1"
#516
0"
0$
1#
#517
1"
#518
0"
1$
#519
1!
1"
#520
0"
0$
0#
#521
1"
#522
0"
1$
#523
0!
1"
#524
0"
0$
1#
#525
1"
#526
0"
1$
#527
1!
1"
#528
0"
0$
0#
#529
1"
#530
0"
1$
#531
0!
1"
#532
0"
0$
1#
#533
1"
#534
0"
1$
#535
1!
1"
#536
0"
0$
0#
#537
1"
#538
0"
1$
#539
0!
1"
#540
0"
0$
1#
#541
1"
#542
0"
1$
#543
1!
1"
#544
0"
0$
0#
#545
1"
#546
0"
1$
#547
0!
1"
#548
0"
0$
1#
#549
1"
#550
0"
1$
#551
1!
1"
#552
0"
0$
0#
#553
1"
#554
0"
1$
#555
0!
1"
#556
0"
0$
1#
#557
1"
#558
0"
1$
#559
1!
1"
#560
0"
0$
0#
#561
1"
#562
0"
1$
#563
0!
1"
#564
0"
0$
1#
#565
1"
#566
0"
1$
#567
1!
1"
#568
0"
0$
0#
#569
1"
#570
0"
1$
#571
0!
1"
#572
0"
0$
1#
#573
1"
#574
0"
1$
#575
1!
1"
#576
0"
0$
0#
#577
1"
#578
0"
1$
#579
0!
1"
#580
0"
0$
1#
#581
1"
#582
0"
1$
#583
1!
1"
#584
0"
0$
0#
#585
1"
#586
0"
1$
#587
0!
1"
#588
0"
0$
1#
#589
1"
#590
0"
1$
#591
1!
1"
#592
0"
0$
0#
#593
1"
#594
0"
1$
#595
0!
1"
#596
0"
0$
1#
#597
1"
#598
0"
1$
#599
1!
1"
#600
0"
0$
0#
#601
1"
#602
0"
1$
#603
0!
1"
#604
0"
0$
1#
#605
1"
#606
0"
1$
#607
1!
1"
#608
0"
0$
0#
#609
1"
#610
0"
1$
#611
0!
1"
#612
0"
0$
1#
#613
1"
#614
0"
1$
#615
1!
1"
#616
0"
0$
0#
#617
1"
#618
0"
1$
#619
0!
1"
#620
0"
0$
1#
#621
1"
#622
0"
1$
#623
1!
1"
#624
0"
0$
0#
#625
1"
#626
0"
1$
#627
0!
1"
#628
0"
0$
1#
#629
1"
#630
0"
1$
#631
1!
1"
#632
0"
0$
0#
#633
1"
#634
0"
1$
#635
0!
1"
#636
0"
0$
1#
#637
1"
#638
0"
1$
#639
1!
1"
#640
0"
0$
0#
#641
1"
#642
0"
1$
#643
0!
1"
#644
0"
0$
1#
#645
1"
#646
0"
1$
#647
1!
1"
#648
0"
0$
0#
#649
1"
#650
0"
1$
#651
0!
1"
#652
0"
0$
1#
#653
1"
#654
0"
1$
#655
1!
1"
#656
0"
0$
0#
#657
1"
#658
0"
1$
#659
0!
1"
#660
0"
0$
1#
#661
1"
#662
0"
1$
#663
1!
1"
#664
0"
0$
0#
#665
1"
#666
0"
1$
#667
0!
1"
#668
0"
0$
1#
#669
1"
#670
0"
1$
#671
1!
1"
#672
0"
0$
0#
#673
1"
#674
0"
1$
#675
0!
1"
#676
0"
0$
1#
#677
1"
#678
0"
1$
#679
1!
1"
#680
0"
0$
0#
#681
1"
#682
0"
1$
#683
0!
1"
#684
0"
0$
1#
#685
1"
#686
0"
1$
#687
1!
1"
#688
0"
0$
0#
#689
1"
#690
0"
1$
#691
0!
1"
#692
0"
0$
1#
#693
1"
#694
0"
1$
#695
1!
1"
#696
0"
0$
0#
#697
1"
#698
0"
1$
#699
0!
1"
#700
0"
0$
1#
#701
1"
#702
0"
1$
#703
1!
1"
#704
0"
0$
0#
#705
1"
#706
0"
1$
#707
0!
1"
#708
0"
0$
1#
#709
1"
#710
0"
1$
#711
1!
1"
#712
0"
0$
0#
#713
1"
#714
0"
1$
#715
0!
1"
#716
0"
0$
1#
#717
1"
#718
0"
1$
#719
1!
1"
#720
0"
0$
0#
#721
1"
#722
0"
1$
#723
0!
1"
#724
0"
0$
1#
#725
1"
#726
0"
1$
#727
1!
1"
#728
0"
0$
0#
#729
1"
#730
0"
1$
#731
0!
1"
#732
0"
0$
1#
#733
1"
#734
0"
1$
#735
1!
1"
#736
0"
0$
0#
#737
1"
#738
0"
1$
#739
0!
1"
#740
0"
0$
1#
#741
1"
#742
0"
1$
#743
1!
1"
#744
0"
0$
0#
#745
1"
#746
0"
1$
#747
0!
1"
#748
0"
0$
1#
#749
1"
#750
0"
1$
#751
1!
1"
#752
0"
0$
0#
#753
1"
#754
0"
1$
#755
0!
1"
#756
0"
0$
1#
#757
1"
#758
0"
1$
#759
1!
1"
#760
0"
0$
0#
#761
1"
#762
0"
1$
#763
0!
1"
#764
0"
0$
1#
#765
1"
#766
0"
1$
#767
1!
1"
#768
0"
0$
0#
#769
1"
#770
0"
1$
#771
0!
1"
#772
0"
0$
1#
#773
1"
#774
0"
1$
#775
1!
1"
#776
0"
0$
0#
#777
1"
#778
0"
1$
#779
0!
1"
#780
0"
0$
1#
#781
1"
#782
0"
1$
#783
1!
1"
#784
0"
0$
0#
#785
1"
#786
0"
1$
#787
0!
1"
#788
0"
0$
1#
#789
1"
#790
0"
1$
#791
1!
1"
#792
0"
0$
0#
#793
1"
#794
0"
1$
#795
0!
1"
#796
0"
0$
1#
#797
1"
#798
0"
1$
#799
1!
1"
#800
0"
0$
0#
#801
1"
#802
0"
1$
#803
0!
1"
#804
0"
0$
1#
#805
1"
#806
0"
1$
#807
1!
1"
#808
0"
0$
0#
#809
1"
#810
0"
1$
#811
0!
1"
#812
0"
0$
1#
#813
1"
#814
0"
1$
#815
1!
1"
#816
0"
0$
0#
#817
1"
#818
0"
1$
#819
0!
1"
#820
0"
0$
1#
#821
1"
#822
0"
1$
#823
1!
1"
#824
0"
0$
0#
#825
1"
#826
0"
1$
#827
0!
1"
#828
0"
0$
1#
#829
1"
#830
0"
1$
#831
1!
1"
#832
0"
0$
0#
#833
1"
#834
0"
1$
#835
0!
1"
#836
0"
0$
1#
#837
1"
#838
0"
1$
#839
1!
1"
#840
0"
0$
0#
#841
1"
#842
0"
1$
#843
0!
1"
#844
0"
0$
1#
#845
1"
#846
0"
1$
#847
1!
1"
#848
0"
0$
0#
#849
1"
#850
0"
1$
#851
0!
1"
#852
0"
0$
1#
#853
1"
#854
0"
1$
#855
1!
1"
#856
0"
0$
0#
#857
1"
#858
0"
1$
#859
0!
1"
#860
0"
0$
1#
#861
1"
#862
0"
1$
#863
1!
1"
#864
0"
0$
0#
#865
1"
#866
0"
1$
#867
0!
1"
#868
0"
0$
1#
#869
1"
#870
0"
1$
#871
1!
1"
#872
0"
0$
0#
#873
1"
#874
0"
1$
#875
0!
1"
#876
0"
0$
1#
#877
1"
#878
0"
1$
#879
1!
1"
#880
0"
0$
0#
#881
1"
#882
0"
1$
#883
0!
1"
#884
0"
0$
1#
#885
1"
#886
0"
1$
#887
1!
1"
#888
0"
0$
0#
#889
1"
#890
0"
1$
#891
0!
1"
#892
0"
0$
1#
#893
1"
#894
0"
1$
#895
1!
1"
#896
0"
0$
0#
#897
1"
#898
0"
1$
#899
0!
1"
#900
0"
0$
1#
#901
1"
#902
0"
1$
#903
1!
1"
#904
0"
0$
0#
#905
1"
#906
0"
1$
#907
0!
1"
#908
0"
0$
1#
#909
1"
#910
0"
1$
#911
1!
1"
#912
0"
0$
0#
#913
1"
#914
0"
1$
#915
0!
1"
#916
0"
0$
1#
#917
1"
#918
0"
1$
#919
1!
1"
#920
0"
0$
0#
#921
1"
#922
0"
1$
#923
0!
1"
#924
0"
0$
1#
#925
1"
#926
0"
1$
#927
1!
1"
#928
0"
0$
0#
#929
1"
#930
0"
1$
#931
0!
1"
#932
0"
0$
1#
#933
1"
#934
0"
1$
#935
1!
1"
#936
0"
0$
0#
#937
1"
#938
0"
1$
#939
0!
1"
#940
0"
0$
1#
#941
1"
#942
0"
1$
#943
1!
1"
#944
0"
0$
0#
#945
1"
#946
0"
1$
#947
0!
1"
#948
0"
0$
1#
#949
1"
#950
0"
1$
#951
1!
1"
#952
0"
0$
0#
#953
1"
#954
0"
1$
#955
0!
1"
#956
0"
0$
1#
#957
1"
#958
0"
1$
#959
1!
1"
#960
0"
0$
0#
#961
1"
#962
0"
1$
#963
0!
1"
#964
0"
0$
1#
#965
1"
#966
0"
1$
#967
1!
1"
#968
0"
0$
0#
#969
1"
#970
0"
1$
#971
0!
1"
#972
0"
0$
1#
#973
1"
#974
0"
1$
#975
1!
1"
#976
0"
0$
0#
#977
1"
#978
0"
1$
#979
0!
1"
#980
0"
0$
1#
#981
1"
#982
0"
1$
#983
1!
1"
#984
0"
0$
0#
#985
1"
#986
0"
1$
#987
0!
1"
#988
0"
0$
1#
#989
1"
#990
0"
1$
#991
1!
1"
#992
0"
0$
0#
#993
1"
#994
0"
1$
#995
0!
1"
#996
0"
0$
1#
#997
1"
#998
0"
1$
#999
1!
1"
#1000
0"
0$
0#
