elementary_logic_gates/DMux.v
module DMux (
    input wire a, sel,
    output reg o1, o2
);

always @(*) begin
    if (sel == 0) begin
        o1 = a;
        o2 = 0;
    end else begin
        o1 = 0;
        o2 = a;
    end
end
    
endmodule

elementary_logic_gates/DMux_tb.v
module DMux_tb;

wire o1, o2;
reg a = 0, sel = 0;
DMux dmux (.a(a), .sel(sel), .o1(o1), .o2(o2));

initial begin
    $dumpfile("DMux.vcd");
    $dumpvars(0, DMux_tb);
end

always begin
    #5 a = ~a;
end

always begin
    #20 sel = ~sel;
end

initial begin
    #100 $finish;
end
    
endmodule

elementary_logic_gates/DMux.vcd
$date
	Thu Aug 24 22:18:43 2023
$end
$version
	Icarus Verilog
$end
$timescale
	1s
$end
$scope module DMux_tb $end
$var wire 1 ! o2 $end
$var wire 1 " o1 $end
$var reg 1 # a $end
$var reg 1 $ sel $end
$scope module dmux $end
$var wire 1 # a $end
$var wire 1 $ sel $end
$var reg 1 " o1 $end
$var reg 1 ! o2 $end
$upscope $end
$upscope $end
$enddefinitions $end
$comment Show the parameter values. $end
$dumpall
$end
#0
$dumpvars
0$
0#
0"
0!
$end
#5
1"
1#
#10
0"
0#
#15
1"
1#
#20
0"
0#
1$
#25
1!
1#
#30
0!
0#
#35
1!
1#
#40
0!
0#
0$
#45
1"
1#
#50
0"
0#
#55
1"
1#
#60
0"
0#
1$
#65
1!
1#
#70
0!
0#
#75
1!
1#
#80
0!
0#
0$
#85
1"
1#
#90
0"
0#
#95
1"
1#
#100
0"
0#
1$
