elementary_logic_gates/Mux.v
module Mux (
    input wire a1,
    input wire a2,
    input wire sel,     
    output reg o
);


always @(a1 or a2 or sel) begin
    if (sel == 0)
        o = a1;
    else
        o = a2;
end
    
endmodule

elementary_logic_gates/Mux_tb.v
module Mux_tb;

reg a1 = 0, a2 = 0, sel = 0 ;
wire o;
Mux mux (a1, a2, sel, o);

initial begin
    $dumpfile("Mux.vcd");
    $dumpvars(0, Mux_tb);
    
end

always begin
    #10 a1 = ~a1;
end

always begin
    #20 a2 = ~a2;
end

always begin
    #40 sel = ~sel;
end

initial begin
    #100 $finish();
end

endmodule

elementary_logic_gates/Mux.vcd
$date
	Thu Aug 24 22:06:58 2023
$end
$version
	Icarus Verilog
$end
$timescale
	1s
$end
$scope module Mux_tb $end
$var wire 1 ! o $end
$var reg 1 " a1 $end
$var reg 1 # a2 $end
$var reg 1 $ sel $end
$scope module mux $end
$var wire 1 " a1 $end
$var wire 1 # a2 $end
$var wire 1 $ sel $end
$var reg 1 ! o $end
$upscope $end
$upscope $end
$enddefinitions $end
$comment Show the parameter values. $end
$dumpall
$end
#0
$dumpvars
0$
0#
0"
0!
$end
#10
1!
1"
#20
0!
0"
1#
#30
1!
1"
#40
0!
0"
0#
1$
#50
1"
#60
1!
0"
1#
#70
1"
#80
0!
0"
0#
0$
#90
1!
1"
#100
0!
0"
1#
