elementary_logic_gates/Not16.v
module Not16 (
    input [15:0] in,
    output [15:0] out
);
    
    assign out[15:0] = ~in[15:0];
endmodule

elementary_logic_gates/Not16_tb.v
module Not16_tb;
    reg [15:0] in = 16'b0000000000000000;
    wire [15:0] out;
    reg valid;

    Not16 notah(.in(in), .out(out));

    initial begin
        $dumpfile("Not16.vcd");
        $dumpvars(0, in, out, valid);
    end

    initial begin
        #100000 $finish;
    end

    always begin
        #1
        if (in == 16'b1111111111111111)begin
            in <= 16'b0000000000000000;
        end else begin
            in <= in + 1;
        end
    end

    always begin
        if (in == ~out)begin
            valid = 1;
        end else begin
            valid = 0;
        end
    end
    
endmodule

elementary_logic_gates/Not16.vcd
$date
	Fri Aug 25 09:47:20 2023
$end
$version
	Icarus Verilog
$end
$timescale
	1s
$end
$scope module Not16_tb $end
$var reg 16 ! in [15:0] $end
$upscope $end
$scope module Not16_tb $end
$var wire 16 " out [15:0] $end
$upscope $end
$scope module Not16_tb $end
$var reg 1 # valid $end
$upscope $end
$enddefinitions $end
$comment Show the parameter values. $end
$dumpall
$end
#0
$dumpvars
0#
b1111111111111111 "
b0 !
$end
#1
b1111111111111110 "
b1 !
1#
#2
b1111111111111101 "
b10 !
#3
b1111111111111100 "
b11 !
#4
b1111111111111011 "
b100 !
#5
b1111111111111010 "
b101 !
#6
b1111111111111001 "
b110 !
#7
b1111111111111000 "
b111 !
#8
b1111111111110111 "
b1000 !
#9
b1111111111110110 "
b1001 !
#10
b1111111111110101 "
b1010 !
#11
b1111111111110100 "
b1011 !
#12
b1111111111110011 "
b1100 !
#13
b1111111111110010 "
b1101 !
#14
b1111111111110001 "
b1110 !
#15
b1111111111110000 "
b1111 !
#16
b1111111111101111 "
b10000 !
#17
b1111111111101110 "
b10001 !
#18
b1111111111101101 "
b10010 !
#19
b1111111111101100 "
b10011 !
#20
b1111111111101011 "
b10100 !
#21
b1111111111101010 "
b10101 !
#22
b1111111111101001 "
b10110 !
#23
b1111111111101000 "
b10111 !
#24
b1111111111100111 "
b11000 !
#25
b1111111111100110 "
b11001 !
#26
b1111111111100101 "
b11010 !
#27
b1111111111100100 "
b11011 !
#28
b1111111111100011 "
b11100 !
#29
b1111111111100010 "
b11101 !
#30
b1111111111100001 "
b11110 !
#31
b1111111111100000 "
b11111 !
#32
b1111111111011111 "
b100000 !
#33
b1111111111011110 "
b100001 !
#34
b1111111111011101 "
b100010 !
#35
b1111111111011100 "
b100011 !
#36
b1111111111011011 "
b100100 !
#37
b1111111111011010 "
b100101 !
#38
b1111111111011001 "
b100110 !
#39
b1111111111011000 "
b100111 !
#40
b1111111111010111 "
b101000 !
#41
b1111111111010110 "
b101001 !
#42
b1111111111010101 "
b101010 !
#43
b1111111111010100 "
b101011 !
#44
b1111111111010011 "
b101100 !
#45
b1111111111010010 "
b101101 !
#46
b1111111111010001 "
b101110 !
#47
b1111111111010000 "
b101111 !
#48
b1111111111001111 "
b110000 !
#49
b1111111111001110 "
b110001 !
#50
b1111111111001101 "
b110010 !
#51
b1111111111001100 "
b110011 !
#52
b1111111111001011 "
b110100 !
#53
b1111111111001010 "
b110101 !
#54
b1111111111001001 "
b110110 !
#55
b1111111111001000 "
b110111 !
#56
b1111111111000111 "
b111000 !
#57
b1111111111000110 "
b111001 !
#58
b1111111111000101 "
b111010 !
#59
b1111111111000100 "
b111011 !
#60
b1111111111000011 "
b111100 !
#61
b1111111111000010 "
b111101 !
#62
b1111111111000001 "
b111110 !
#63
b1111111111000000 "
b111111 !
#64
b1111111110111111 "
b1000000 !
#65
b1111111110111110 "
b1000001 !
#66
b1111111110111101 "
b1000010 !
#67
b1111111110111100 "
b1000011 !
#68
b1111111110111011 "
b1000100 !
#69
b1111111110111010 "
b1000101 !
#70
b1111111110111001 "
b1000110 !
#71
b1111111110111000 "
b1000111 !
#72
b1111111110110111 "
b1001000 !
#73
b1111111110110110 "
b1001001 !
#74
b1111111110110101 "
b1001010 !
#75
b1111111110110100 "
b1001011 !
#76
b1111111110110011 "
b1001100 !
#77
b1111111110110010 "
b1001101 !
#78
b1111111110110001 "
b1001110 !
#79
b1111111110110000 "
b1001111 !
#80
b1111111110101111 "
b1010000 !
#81
b1111111110101110 "
b1010001 !
#82
b1111111110101101 "
b1010010 !
#83
b1111111110101100 "
b1010011 !
#84
b1111111110101011 "
b1010100 !
#85
b1111111110101010 "
b1010101 !
#86
b1111111110101001 "
b1010110 !
#87
b1111111110101000 "
b1010111 !
#88
b1111111110100111 "
b1011000 !
#89
b1111111110100110 "
b1011001 !
#90
b1111111110100101 "
b1011010 !
#91
b1111111110100100 "
b1011011 !
#92
b1111111110100011 "
b1011100 !
#93
b1111111110100010 "
b1011101 !
#94
b1111111110100001 "
b1011110 !
#95
b1111111110100000 "
b1011111 !
#96
b1111111110011111 "
b1100000 !
#97
b1111111110011110 "
b1100001 !
#98
b1111111110011101 "
b1100010 !
#99
b1111111110011100 "
b1100011 !
#100
b1111111110011011 "
b1100100 !
#101
b1111111110011010 "
b1100101 !
#102
b1111111110011001 "
b1100110 !
#103
b1111111110011000 "
b1100111 !
#104
b1111111110010111 "
b1101000 !
#105
b1111111110010110 "
b1101001 !
#106
b1111111110010101 "
b1101010 !
#107
b1111111110010100 "
b1101011 !
#108
b1111111110010011 "
b1101100 !
#109
b1111111110010010 "
b1101101 !
#110
b1111111110010001 "
b1101110 !
#111
b1111111110010000 "
b1101111 !
#112
b1111111110001111 "
b1110000 !
#113
b1111111110001110 "
b1110001 !
#114
b1111111110001101 "
b1110010 !
#115
b1111111110001100 "
b1110011 !
#116
b1111111110001011 "
b1110100 !
#117
b1111111110001010 "
b1110101 !
#118
b1111111110001001 "
b1110110 !
#119
b1111111110001000 "
b1110111 !
#120
b1111111110000111 "
b1111000 !
#121
b1111111110000110 "
b1111001 !
#122
b1111111110000101 "
b1111010 !
#123
b1111111110000100 "
b1111011 !
#124
b1111111110000011 "
b1111100 !
#125
b1111111110000010 "
b1111101 !
#126
b1111111110000001 "
b1111110 !
#127
b1111111110000000 "
b1111111 !
#128
b1111111101111111 "
b10000000 !
#129
b1111111101111110 "
b10000001 !
#130
b1111111101111101 "
b10000010 !
#131
b1111111101111100 "
b10000011 !
#132
b1111111101111011 "
b10000100 !
#133
b1111111101111010 "
b10000101 !
#134
b1111111101111001 "
b10000110 !
#135
b1111111101111000 "
b10000111 !
#136
b1111111101110111 "
b10001000 !
#137
b1111111101110110 "
b10001001 !
#138
b1111111101110101 "
b10001010 !
#139
b1111111101110100 "
b10001011 !
#140
b1111111101110011 "
b10001100 !
#141
b1111111101110010 "
b10001101 !
#142
b1111111101110001 "
b10001110 !
#143
b1111111101110000 "
b10001111 !
#144
b1111111101101111 "
b10010000 !
#145
b1111111101101110 "
b10010001 !
#146
b1111111101101101 "
b10010010 !
#147
b1111111101101100 "
b10010011 !
#148
b1111111101101011 "
b10010100 !
#149
b1111111101101010 "
b10010101 !
#150
b1111111101101001 "
b10010110 !
#151
b1111111101101000 "
b10010111 !
#152
b1111111101100111 "
b10011000 !
#153
b1111111101100110 "
b10011001 !
#154
b1111111101100101 "
b10011010 !
#155
b1111111101100100 "
b10011011 !
#156
b1111111101100011 "
b10011100 !
#157
b1111111101100010 "
b10011101 !
#158
b1111111101100001 "
b10011110 !
#159
b1111111101100000 "
b10011111 !
#160
b1111111101011111 "
b10100000 !
#161
b1111111101011110 "
b10100001 !
#162
b1111111101011101 "
b10100010 !
#163
b1111111101011100 "
b10100011 !
#164
b1111111101011011 "
b10100100 !
#165
b1111111101011010 "
b10100101 !
#166
b1111111101011001 "
b10100110 !
#167
b1111111101011000 "
b10100111 !
#168
b1111111101010111 "
b10101000 !
#169
b1111111101010110 "
b10101001 !
#170
b1111111101010101 "
b10101010 !
#171
b1111111101010100 "
b10101011 !
#172
b1111111101010011 "
b10101100 !
#173
b1111111101010010 "
b10101101 !
#174
b1111111101010001 "
b10101110 !
#175
b1111111101010000 "
b10101111 !
#176
b1111111101001111 "
b10110000 !
#177
b1111111101001110 "
b10110001 !
#178
b1111111101001101 "
b10110010 !
#179
b1111111101001100 "
b10110011 !
#180
b1111111101001011 "
b10110100 !
#181
b1111111101001010 "
b10110101 !
#182
b1111111101001001 "
b10110110 !
#183
b1111111101001000 "
b10110111 !
#184
b1111111101000111 "
b10111000 !
#185
b1111111101000110 "
b10111001 !
#186
b1111111101000101 "
b10111010 !
#187
b1111111101000100 "
b10111011 !
#188
b1111111101000011 "
b10111100 !
#189
b1111111101000010 "
b10111101 !
#190
b1111111101000001 "
b10111110 !
#191
b1111111101000000 "
b10111111 !
#192
b1111111100111111 "
b11000000 !
#193
b1111111100111110 "
b11000001 !
#194
b1111111100111101 "
b11000010 !
#195
b1111111100111100 "
b11000011 !
#196
b1111111100111011 "
b11000100 !
#197
b1111111100111010 "
b11000101 !
#198
b1111111100111001 "
b11000110 !
#199
b1111111100111000 "
b11000111 !
#200
b1111111100110111 "
b11001000 !
#201
b1111111100110110 "
b11001001 !
#202
b1111111100110101 "
b11001010 !
#203
b1111111100110100 "
b11001011 !
#204
b1111111100110011 "
b11001100 !
#205
b1111111100110010 "
b11001101 !
#206
b1111111100110001 "
b11001110 !
#207
b1111111100110000 "
b11001111 !
#208
b1111111100101111 "
b11010000 !
#209
b1111111100101110 "
b11010001 !
#210
b1111111100101101 "
b11010010 !
#211
b1111111100101100 "
b11010011 !
#212
b1111111100101011 "
b11010100 !
#213
b1111111100101010 "
b11010101 !
#214
b1111111100101001 "
b11010110 !
#215
b1111111100101000 "
b11010111 !
#216
b1111111100100111 "
b11011000 !
#217
b1111111100100110 "
b11011001 !
#218
b1111111100100101 "
b11011010 !
#219
b1111111100100100 "
b11011011 !
#220
b1111111100100011 "
b11011100 !
#221
b1111111100100010 "
b11011101 !
#222
b1111111100100001 "
b11011110 !
#223
b1111111100100000 "
b11011111 !
#224
b1111111100011111 "
b11100000 !
#225
b1111111100011110 "
b11100001 !
#226
b1111111100011101 "
b11100010 !
#227
b1111111100011100 "
b11100011 !
#228
b1111111100011011 "
b11100100 !
#229
b1111111100011010 "
b11100101 !
#230
b1111111100011001 "
b11100110 !
#231
b1111111100011000 "
b11100111 !
#232
b1111111100010111 "
b11101000 !
#233
b1111111100010110 "
b11101001 !
#234
b1111111100010101 "
b11101010 !
#235
b1111111100010100 "
b11101011 !
#236
b1111111100010011 "
b11101100 !
#237
b1111111100010010 "
b11101101 !
#238
b1111111100010001 "
b11101110 !
#239
b1111111100010000 "
b11101111 !
#240
b1111111100001111 "
b11110000 !
#241
b1111111100001110 "
b11110001 !
#242
b1111111100001101 "
b11110010 !
#243
b1111111100001100 "
b11110011 !
#244
b1111111100001011 "
b11110100 !
#245
b1111111100001010 "
b11110101 !
#246
b1111111100001001 "
b11110110 !
#247
b1111111100001000 "
b11110111 !
#248
b1111111100000111 "
b11111000 !
#249
b1111111100000110 "
b11111001 !
#250
b1111111100000101 "
b11111010 !
#251
b1111111100000100 "
b11111011 !
#252
b1111111100000011 "
b11111100 !
#253
b1111111100000010 "
b11111101 !
#254
b1111111100000001 "
b11111110 !
#255
b1111111100000000 "
b11111111 !
#256
b1111111011111111 "
b100000000 !
#257
b1111111011111110 "
b100000001 !
#258
b1111111011111101 "
b100000010 !
#259
b1111111011111100 "
b100000011 !
#260
b1111111011111011 "
b100000100 !
#261
b1111111011111010 "
b100000101 !
#262
b1111111011111001 "
b100000110 !
#263
b1111111011111000 "
b100000111 !
#264
b1111111011110111 "
b100001000 !
#265
b1111111011110110 "
b100001001 !
#266
b1111111011110101 "
b100001010 !
#267
b1111111011110100 "
b100001011 !
#268
b1111111011110011 "
b100001100 !
#269
b1111111011110010 "
b100001101 !
#270
b1111111011110001 "
b100001110 !
#271
b1111111011110000 "
b100001111 !
#272
b1111111011101111 "
b100010000 !
#273
b1111111011101110 "
b100010001 !
#274
b1111111011101101 "
b100010010 !
#275
b1111111011101100 "
b100010011 !
#276
b1111111011101011 "
b100010100 !
#277
b1111111011101010 "
b100010101 !
#278
b1111111011101001 "
b100010110 !
#279
b1111111011101000 "
b100010111 !
#280
b1111111011100111 "
b100011000 !
#281
b1111111011100110 "
b100011001 !
#282
b1111111011100101 "
b100011010 !
#283
b1111111011100100 "
b100011011 !
#284
b1111111011100011 "
b100011100 !
#285
b1111111011100010 "
b100011101 !
#286
b1111111011100001 "
b100011110 !
#287
b1111111011100000 "
b100011111 !
#288
b1111111011011111 "
b100100000 !
#289
b1111111011011110 "
b100100001 !
#290
b1111111011011101 "
b100100010 !
#291
b1111111011011100 "
b100100011 !
#292
b1111111011011011 "
b100100100 !
#293
b1111111011011010 "
b100100101 !
#294
b1111111011011001 "
b100100110 !
#295
b1111111011011000 "
b100100111 !
#296
b1111111011010111 "
b100101000 !
#297
b1111111011010110 "
b100101001 !
#298
b1111111011010101 "
b100101010 !
#299
b1111111011010100 "
b100101011 !
#300
b1111111011010011 "
b100101100 !
#301
b1111111011010010 "
b100101101 !
#302
b1111111011010001 "
b100101110 !
#303
b1111111011010000 "
b100101111 !
#304
b1111111011001111 "
b100110000 !
#305
b1111111011001110 "
b100110001 !
#306
b1111111011001101 "
b100110010 !
#307
b1111111011001100 "
b100110011 !
#308
b1111111011001011 "
b100110100 !
#309
b1111111011001010 "
b100110101 !
#310
b1111111011001001 "
b100110110 !
#311
b1111111011001000 "
b100110111 !
#312
b1111111011000111 "
b100111000 !
#313
b1111111011000110 "
b100111001 !
#314
b1111111011000101 "
b100111010 !
#315
b1111111011000100 "
b100111011 !
#316
b1111111011000011 "
b100111100 !
#317
b1111111011000010 "
b100111101 !
#318
b1111111011000001 "
b100111110 !
#319
b1111111011000000 "
b100111111 !
#320
b1111111010111111 "
b101000000 !
#321
b1111111010111110 "
b101000001 !
#322
b1111111010111101 "
b101000010 !
#323
b1111111010111100 "
b101000011 !
#324
b1111111010111011 "
b101000100 !
#325
b1111111010111010 "
b101000101 !
#326
b1111111010111001 "
b101000110 !
#327
b1111111010111000 "
b101000111 !
#328
b1111111010110111 "
b101001000 !
#329
b1111111010110110 "
b101001001 !
#330
b1111111010110101 "
b101001010 !
#331
b1111111010110100 "
b101001011 !
#332
b1111111010110011 "
b101001100 !
#333
b1111111010110010 "
b101001101 !
#334
b1111111010110001 "
b101001110 !
#335
b1111111010110000 "
b101001111 !
#336
b1111111010101111 "
b101010000 !
#337
b1111111010101110 "
b101010001 !
#338
b1111111010101101 "
b101010010 !
#339
b1111111010101100 "
b101010011 !
#340
b1111111010101011 "
b101010100 !
#341
b1111111010101010 "
b101010101 !
#342
b1111111010101001 "
b101010110 !
#343
b1111111010101000 "
b101010111 !
#344
b1111111010100111 "
b101011000 !
#345
b1111111010100110 "
b101011001 !
#346
b1111111010100101 "
b101011010 !
#347
b1111111010100100 "
b101011011 !
#348
b1111111010100011 "
b101011100 !
#349
b1111111010100010 "
b101011101 !
#350
b1111111010100001 "
b101011110 !
#351
b1111111010100000 "
b101011111 !
#352
b1111111010011111 "
b101100000 !
#353
b1111111010011110 "
b101100001 !
#354
b1111111010011101 "
b101100010 !
#355
b1111111010011100 "
b101100011 !
#356
b1111111010011011 "
b101100100 !
#357
b1111111010011010 "
b101100101 !
#358
b1111111010011001 "
b101100110 !
#359
b1111111010011000 "
b101100111 !
#360
b1111111010010111 "
b101101000 !
#361
b1111111010010110 "
b101101001 !
#362
b1111111010010101 "
b101101010 !
#363
b1111111010010100 "
b101101011 !
#364
b1111111010010011 "
b101101100 !
#365
b1111111010010010 "
b101101101 !
#366
b1111111010010001 "
b101101110 !
#367
b1111111010010000 "
b101101111 !
#368
b1111111010001111 "
b101110000 !
#369
b1111111010001110 "
b101110001 !
#370
b1111111010001101 "
b101110010 !
#371
b1111111010001100 "
b101110011 !
#372
b1111111010001011 "
b101110100 !
#373
b1111111010001010 "
b101110101 !
#374
b1111111010001001 "
b101110110 !
#375
b1111111010001000 "
b101110111 !
#376
b1111111010000111 "
b101111000 !
#377
b1111111010000110 "
b101111001 !
#378
b1111111010000101 "
b101111010 !
#379
b1111111010000100 "
b101111011 !
#380
b1111111010000011 "
b101111100 !
#381
b1111111010000010 "
b101111101 !
#382
b1111111010000001 "
b101111110 !
#383
b1111111010000000 "
b101111111 !
#384
b1111111001111111 "
b110000000 !
#385
b1111111001111110 "
b110000001 !
#386
b1111111001111101 "
b110000010 !
#387
b1111111001111100 "
b110000011 !
#388
b1111111001111011 "
b110000100 !
#389
b1111111001111010 "
b110000101 !
#390
b1111111001111001 "
b110000110 !
#391
b1111111001111000 "
b110000111 !
#392
b1111111001110111 "
b110001000 !
#393
b1111111001110110 "
b110001001 !
#394
b1111111001110101 "
b110001010 !
#395
b1111111001110100 "
b110001011 !
#396
b1111111001110011 "
b110001100 !
#397
b1111111001110010 "
b110001101 !
#398
b1111111001110001 "
b110001110 !
#399
b1111111001110000 "
b110001111 !
#400
b1111111001101111 "
b110010000 !
#401
b1111111001101110 "
b110010001 !
#402
b1111111001101101 "
b110010010 !
#403
b1111111001101100 "
b110010011 !
#404
b1111111001101011 "
b110010100 !
#405
b1111111001101010 "
b110010101 !
#406
b1111111001101001 "
b110010110 !
#407
b1111111001101000 "
b110010111 !
#408
b1111111001100111 "
b110011000 !
#409
b1111111001100110 "
b110011001 !
#410
b1111111001100101 "
b110011010 !
#411
b1111111001100100 "
b110011011 !
#412
b1111111001100011 "
b110011100 !
#413
b1111111001100010 "
b110011101 !
#414
b1111111001100001 "
b110011110 !
#415
b1111111001100000 "
b110011111 !
#416
b1111111001011111 "
b110100000 !
#417
b1111111001011110 "
b110100001 !
#418
b1111111001011101 "
b110100010 !
#419
b1111111001011100 "
b110100011 !
#420
b1111111001011011 "
b110100100 !
#421
b1111111001011010 "
b110100101 !
#422
b1111111001011001 "
b110100110 !
#423
b1111111001011000 "
b110100111 !
#424
b1111111001010111 "
b110101000 !
#425
b1111111001010110 "
b110101001 !
#426
b1111111001010101 "
b110101010 !
#427
b1111111001010100 "
b110101011 !
#428
b1111111001010011 "
b110101100 !
#429
b1111111001010010 "
b110101101 !
#430
b1111111001010001 "
b110101110 !
#431
b1111111001010000 "
b110101111 !
#432
b1111111001001111 "
b110110000 !
#433
b1111111001001110 "
b110110001 !
#434
b1111111001001101 "
b110110010 !
#435
b1111111001001100 "
b110110011 !
#436
b1111111001001011 "
b110110100 !
#437
b1111111001001010 "
b110110101 !
#438
b1111111001001001 "
b110110110 !
#439
b1111111001001000 "
b110110111 !
#440
b1111111001000111 "
b110111000 !
#441
b1111111001000110 "
b110111001 !
#442
b1111111001000101 "
b110111010 !
#443
b1111111001000100 "
b110111011 !
#444
b1111111001000011 "
b110111100 !
#445
b1111111001000010 "
b110111101 !
#446
b1111111001000001 "
b110111110 !
#447
b1111111001000000 "
b110111111 !
#448
b1111111000111111 "
b111000000 !
#449
b1111111000111110 "
b111000001 !
#450
b1111111000111101 "
b111000010 !
#451
b1111111000111100 "
b111000011 !
#452
b1111111000111011 "
b111000100 !
#453
b1111111000111010 "
b111000101 !
#454
b1111111000111001 "
b111000110 !
#455
b1111111000111000 "
b111000111 !
#456
b1111111000110111 "
b111001000 !
#457
b1111111000110110 "
b111001001 !
#458
b1111111000110101 "
b111001010 !
#459
b1111111000110100 "
b111001011 !
#460
b1111111000110011 "
b111001100 !
#461
b1111111000110010 "
b111001101 !
#462
b1111111000110001 "
b111001110 !
#463
b1111111000110000 "
b111001111 !
#464
b1111111000101111 "
b111010000 !
#465
b1111111000101110 "
b111010001 !
#466
b1111111000101101 "
b111010010 !
#467
b1111111000101100 "
b111010011 !
#468
b1111111000101011 "
b111010100 !
#469
b1111111000101010 "
b111010101 !
#470
b1111111000101001 "
b111010110 !
#471
b1111111000101000 "
b111010111 !
#472
b1111111000100111 "
b111011000 !
#473
b1111111000100110 "
b111011001 !
#474
b1111111000100101 "
b111011010 !
#475
b1111111000100100 "
b111011011 !
#476
b1111111000100011 "
b111011100 !
#477
b1111111000100010 "
b111011101 !
#478
b1111111000100001 "
b111011110 !
#479
b1111111000100000 "
b111011111 !
#480
b1111111000011111 "
b111100000 !
#481
b1111111000011110 "
b111100001 !
#482
b1111111000011101 "
b111100010 !
#483
b1111111000011100 "
b111100011 !
#484
b1111111000011011 "
b111100100 !
#485
b1111111000011010 "
b111100101 !
#486
b1111111000011001 "
b111100110 !
#487
b1111111000011000 "
b111100111 !
#488
b1111111000010111 "
b111101000 !
#489
b1111111000010110 "
b111101001 !
#490
b1111111000010101 "
b111101010 !
#491
b1111111000010100 "
b111101011 !
#492
b1111111000010011 "
b111101100 !
#493
b1111111000010010 "
b111101101 !
#494
b1111111000010001 "
b111101110 !
#495
b1111111000010000 "
b111101111 !
#496
b1111111000001111 "
b111110000 !
#497
b1111111000001110 "
b111110001 !
#498
b1111111000001101 "
b111110010 !
#499
b1111111000001100 "
b111110011 !
#500
b1111111000001011 "
b111110100 !
#501
b1111111000001010 "
b111110101 !
#502
b1111111000001001 "
b111110110 !
#503
b1111111000001000 "
b111110111 !
#504
b1111111000000111 "
b111111000 !
#505
b1111111000000110 "
b111111001 !
#506
b1111111000000101 "
b111111010 !
#507
b1111111000000100 "
b111111011 !
#508
b1111111000000011 "
b111111100 !
#509
b1111111000000010 "
b111111101 !
#510
b1111111000000001 "
b111111110 !
#511
b1111111000000000 "
b111111111 !
#512
b1111110111111111 "
b1000000000 !
#513
b1111110111111110 "
b1000000001 !
#514
b1111110111111101 "
b1000000010 !
#515
b1111110111111100 "
b1000000011 !
#516
b1111110111111011 "
b1000000100 !
#517
b1111110111111010 "
b1000000101 !
#518
b1111110111111001 "
b1000000110 !
#519
b1111110111111000 "
b1000000111 !
#520
b1111110111110111 "
b1000001000 !
#521
b1111110111110110 "
b1000001001 !
#522
b1111110111110101 "
b1000001010 !
#523
b1111110111110100 "
b1000001011 !
#524
b1111110111110011 "
b1000001100 !
#525
b1111110111110010 "
b1000001101 !
#526
b1111110111110001 "
b1000001110 !
#527
b1111110111110000 "
b1000001111 !
#528
b1111110111101111 "
b1000010000 !
#529
b1111110111101110 "
b1000010001 !
#530
b1111110111101101 "
b1000010010 !
#531
b1111110111101100 "
b1000010011 !
#532
b1111110111101011 "
b1000010100 !
#533
b1111110111101010 "
b1000010101 !
#534
b1111110111101001 "
b1000010110 !
#535
b1111110111101000 "
b1000010111 !
#536
b1111110111100111 "
b1000011000 !
#537
b1111110111100110 "
b1000011001 !
#538
b1111110111100101 "
b1000011010 !
#539
b1111110111100100 "
b1000011011 !
#540
b1111110111100011 "
b1000011100 !
#541
b1111110111100010 "
b1000011101 !
#542
b1111110111100001 "
b1000011110 !
#543
b1111110111100000 "
b1000011111 !
#544
b1111110111011111 "
b1000100000 !
#545
b1111110111011110 "
b1000100001 !
#546
b1111110111011101 "
b1000100010 !
#547
b1111110111011100 "
b1000100011 !
#548
b1111110111011011 "
b1000100100 !
#549
b1111110111011010 "
b1000100101 !
#550
b1111110111011001 "
b1000100110 !
#551
b1111110111011000 "
b1000100111 !
#552
b1111110111010111 "
b1000101000 !
#553
b1111110111010110 "
b1000101001 !
#554
b1111110111010101 "
b1000101010 !
#555
b1111110111010100 "
b1000101011 !
#556
b1111110111010011 "
b1000101100 !
#557
b1111110111010010 "
b1000101101 !
#558
b1111110111010001 "
b1000101110 !
#559
b1111110111010000 "
b1000101111 !
#560
b1111110111001111 "
b1000110000 !
#561
b1111110111001110 "
b1000110001 !
#562
b1111110111001101 "
b1000110010 !
#563
b1111110111001100 "
b1000110011 !
#564
b1111110111001011 "
b1000110100 !
#565
b1111110111001010 "
b1000110101 !
#566
b1111110111001001 "
b1000110110 !
#567
b1111110111001000 "
b1000110111 !
#568
b1111110111000111 "
b1000111000 !
#569
b1111110111000110 "
b1000111001 !
#570
b1111110111000101 "
b1000111010 !
#571
b1111110111000100 "
b1000111011 !
#572
b1111110111000011 "
b1000111100 !
#573
b1111110111000010 "
b1000111101 !
#574
b1111110111000001 "
b1000111110 !
#575
b1111110111000000 "
b1000111111 !
#576
b1111110110111111 "
b1001000000 !
#577
b1111110110111110 "
b1001000001 !
#578
b1111110110111101 "
b1001000010 !
#579
b1111110110111100 "
b1001000011 !
#580
b1111110110111011 "
b1001000100 !
#581
b1111110110111010 "
b1001000101 !
#582
b1111110110111001 "
b1001000110 !
#583
b1111110110111000 "
b1001000111 !
#584
b1111110110110111 "
b1001001000 !
#585
b1111110110110110 "
b1001001001 !
#586
b1111110110110101 "
b1001001010 !
#587
b1111110110110100 "
b1001001011 !
#588
b1111110110110011 "
b1001001100 !
#589
b1111110110110010 "
b1001001101 !
#590
b1111110110110001 "
b1001001110 !
#591
b1111110110110000 "
b1001001111 !
#592
b1111110110101111 "
b1001010000 !
#593
b1111110110101110 "
b1001010001 !
#594
b1111110110101101 "
b1001010010 !
#595
b1111110110101100 "
b1001010011 !
#596
b1111110110101011 "
b1001010100 !
#597
b1111110110101010 "
b1001010101 !
#598
b1111110110101001 "
b1001010110 !
#599
b1111110110101000 "
b1001010111 !
#600
b1111110110100111 "
b1001011000 !
#601
b1111110110100110 "
b1001011001 !
#602
b1111110110100101 "
b1001011010 !
#603
b1111110110100100 "
b1001011011 !
#604
b1111110110100011 "
b1001011100 !
#605
b1111110110100010 "
b1001011101 !
#606
b1111110110100001 "
b1001011110 !
#607
b1111110110100000 "
b1001011111 !
#608
b1111110110011111 "
b1001100000 !
#609
b1111110110011110 "
b1001100001 !
#610
b1111110110011101 "
b1001100010 !
#611
b1111110110011100 "
b1001100011 !
#612
b1111110110011011 "
b1001100100 !
#613
b1111110110011010 "
b1001100101 !
#614
b1111110110011001 "
b1001100110 !
#615
b1111110110011000 "
b1001100111 !
#616
b1111110110010111 "
b1001101000 !
#617
b1111110110010110 "
b1001101001 !
#618
b1111110110010101 "
b1001101010 !
#619
b1111110110010100 "
b1001101011 !
#620
b1111110110010011 "
b1001101100 !
#621
b1111110110010010 "
b1001101101 !
#622
b1111110110010001 "
b1001101110 !
#623
b1111110110010000 "
b1001101111 !
#624
b1111110110001111 "
b1001110000 !
#625
b1111110110001110 "
b1001110001 !
#626
b1111110110001101 "
b1001110010 !
#627
b1111110110001100 "
b1001110011 !
#628
b1111110110001011 "
b1001110100 !
#629
b1111110110001010 "
b1001110101 !
#630
b1111110110001001 "
b1001110110 !
#631
b1111110110001000 "
b1001110111 !
#632
b1111110110000111 "
b1001111000 !
#633
b1111110110000110 "
b1001111001 !
#634
b1111110110000101 "
b1001111010 !
#635
b1111110110000100 "
b1001111011 !
#636
b1111110110000011 "
b1001111100 !
#637
b1111110110000010 "
b1001111101 !
#638
b1111110110000001 "
b1001111110 !
#639
b1111110110000000 "
b1001111111 !
#640
b1111110101111111 "
b1010000000 !
#641
b1111110101111110 "
b1010000001 !
#642
b1111110101111101 "
b1010000010 !
#643
b1111110101111100 "
b1010000011 !
#644
b1111110101111011 "
b1010000100 !
#645
b1111110101111010 "
b1010000101 !
#646
b1111110101111001 "
b1010000110 !
#647
b1111110101111000 "
b1010000111 !
#648
b1111110101110111 "
b1010001000 !
#649
b1111110101110110 "
b1010001001 !
#650
b1111110101110101 "
b1010001010 !
#651
b1111110101110100 "
b1010001011 !
#652
b1111110101110011 "
b1010001100 !
#653
b1111110101110010 "
b1010001101 !
#654
b1111110101110001 "
b1010001110 !
#655
b1111110101110000 "
b1010001111 !
#656
b1111110101101111 "
b1010010000 !
#657
b1111110101101110 "
b1010010001 !
#658
b1111110101101101 "
b1010010010 !
#659
b1111110101101100 "
b1010010011 !
#660
b1111110101101011 "
b1010010100 !
#661
b1111110101101010 "
b1010010101 !
#662
b1111110101101001 "
b1010010110 !
#663
b1111110101101000 "
b1010010111 !
#664
b1111110101100111 "
b1010011000 !
#665
b1111110101100110 "
b1010011001 !
#666
b1111110101100101 "
b1010011010 !
#667
b1111110101100100 "
b1010011011 !
#668
b1111110101100011 "
b1010011100 !
#669
b1111110101100010 "
b1010011101 !
#670
b1111110101100001 "
b1010011110 !
#671
b1111110101100000 "
b1010011111 !
#672
b1111110101011111 "
b1010100000 !
#673
b1111110101011110 "
b1010100001 !
#674
b1111110101011101 "
b1010100010 !
#675
b1111110101011100 "
b1010100011 !
#676
b1111110101011011 "
b1010100100 !
#677
b1111110101011010 "
b1010100101 !
#678
b1111110101011001 "
b1010100110 !
#679
b1111110101011000 "
b1010100111 !
#680
b1111110101010111 "
b1010101000 !
#681
b1111110101010110 "
b1010101001 !
#682
b1111110101010101 "
b1010101010 !
#683
b1111110101010100 "
b1010101011 !
#684
b1111110101010011 "
b1010101100 !
#685
b1111110101010010 "
b1010101101 !
#686
b1111110101010001 "
b1010101110 !
#687
b1111110101010000 "
b1010101111 !
#688
b1111110101001111 "
b1010110000 !
#689
b1111110101001110 "
b1010110001 !
#690
b1111110101001101 "
b1010110010 !
#691
b1111110101001100 "
b1010110011 !
#692
b1111110101001011 "
b1010110100 !
#693
b1111110101001010 "
b1010110101 !
#694
b1111110101001001 "
b1010110110 !
#695
b1111110101001000 "
b1010110111 !
#696
b1111110101000111 "
b1010111000 !
#697
b1111110101000110 "
b1010111001 !
#698
b1111110101000101 "
b1010111010 !
#699
b1111110101000100 "
b1010111011 !
#700
b1111110101000011 "
b1010111100 !
#701
b1111110101000010 "
b1010111101 !
#702
b1111110101000001 "
b1010111110 !
#703
b1111110101000000 "
b1010111111 !
#704
b1111110100111111 "
b1011000000 !
#705
b1111110100111110 "
b1011000001 !
#706
b1111110100111101 "
b1011000010 !
#707
b1111110100111100 "
b1011000011 !
#708
b1111110100111011 "
b1011000100 !
#709
b1111110100111010 "
b1011000101 !
#710
b1111110100111001 "
b1011000110 !
#711
b1111110100111000 "
b1011000111 !
#712
b1111110100110111 "
b1011001000 !
#713
b1111110100110110 "
b1011001001 !
#714
b1111110100110101 "
b1011001010 !
