muti_way_variants/DMux4Way.v
module DMux4Way (
    input wire [1:0] sel,
    input wire a, b, c, d,
    output reg o
);

always @(*) begin
    case (sel)
        2'b00: o = a;
        2'b01: o = b;
        2'b10: o = c;
        2'b11: o = d; 
        default: o = 0;
    endcase
end
    
endmodule

muti_way_variants/DMux4Way_tb.v
module DMux4Way_tb;

reg [1:0] sel = 2'b00;
reg a = 0, b = 0, c = 0, d = 0;
wire o;

DMux4Way dmux4way (sel, a, b, c, d, o);

initial begin
    $dumpfile("DMux4Way.vcd");
    $dumpvars(0, DMux4Way_tb);
    #1000 $finish;
end

always begin
    #16
    if (sel == 2'b11) begin
        sel = 2'b00;
    end else begin
        sel = sel + 1;
    end
end

always begin
    #1
    a = ~a; 
end

always begin
    #2
    b = ~b;
end

always begin
    #4 
    c = ~c;
end

always begin
    #8
    d = ~d;
    
end
    
endmodule

muti_way_variants/DMux4Way.vcd
$date
	Fri Aug 25 23:00:06 2023
$end
$version
	Icarus Verilog
$end
$timescale
	1s
$end
$scope module DMux4Way_tb $end
$var wire 1 ! o $end
$var reg 1 " a $end
$var reg 1 # b $end
$var reg 1 $ c $end
$var reg 1 % d $end
$var reg 2 & sel [1:0] $end
$scope module dmux4way $end
$var wire 1 " a $end
$var wire 1 # b $end
$var wire 1 $ c $end
$var wire 1 % d $end
$var wire 2 ' sel [1:0] $end
$var reg 1 ! o $end
$upscope $end
$upscope $end
$enddefinitions $end
$comment Show the parameter values. $end
$dumpall
$end
#0
$dumpvars
b0 '
b0 &
0%
0$
0#
0"
0!
$end
#1
1!
1"
#2
0!
0"
1#
#3
1!
1"
#4
0!
0"
0#
1$
#5
1!
1"
#6
0!
0"
1#
#7
1!
1"
#8
0!
0"
0#
0$
1%
#9
1!
1"
#10
0!
0"
1#
#11
1!
1"
#12
0!
0"
0#
1$
#13
1!
1"
#14
0!
0"
1#
#15
1!
1"
#16
0!
0"
0#
0$
0%
b1 &
b1 '
#17
1"
#18
1!
0"
1#
#19
1"
#20
0!
0"
0#
1$
#21
1"
#22
1!
0"
1#
#23
1"
#24
0!
0"
0#
0$
1%
#25
1"
#26
1!
0"
1#
#27
1"
#28
0!
0"
0#
1$
#29
1"
#30
1!
0"
1#
#31
1"
#32
0!
0"
0#
0$
0%
b10 &
b10 '
#33
1"
#34
0"
1#
#35
1"
#36
1!
0"
0#
1$
#37
1"
#38
0"
1#
#39
1"
#40
0!
0"
0#
0$
1%
#41
1"
#42
0"
1#
#43
1"
#44
1!
0"
0#
1$
#45
1"
#46
0"
1#
#47
1"
#48
0!
0"
0#
0$
0%
b11 &
b11 '
#49
1"
#50
0"
1#
#51
1"
#52
0"
0#
1$
#53
1"
#54
0"
1#
#55
1"
#56
1!
0"
0#
0$
1%
#57
1"
#58
0"
1#
#59
1"
#60
0"
0#
1$
#61
1"
#62
0"
1#
#63
1"
#64
0!
0"
0#
0$
0%
b0 &
b0 '
#65
1!
1"
#66
0!
0"
1#
#67
1!
1"
#68
0!
0"
0#
1$
#69
1!
1"
#70
0!
0"
1#
#71
1!
1"
#72
0!
0"
0#
0$
1%
#73
1!
1"
#74
0!
0"
1#
#75
1!
1"
#76
0!
0"
0#
1$
#77
1!
1"
#78
0!
0"
1#
#79
1!
1"
#80
0!
0"
0#
0$
0%
b1 &
b1 '
#81
1"
#82
1!
0"
1#
#83
1"
#84
0!
0"
0#
1$
#85
1"
#86
1!
0"
1#
#87
1"
#88
0!
0"
0#
0$
1%
#89
1"
#90
1!
0"
1#
#91
1"
#92
0!
0"
0#
1$
#93
1"
#94
1!
0"
1#
#95
1"
#96
0!
0"
0#
0$
0%
b10 &
b10 '
#97
1"
#98
0"
1#
#99
1"
#100
1!
0"
0#
1$
#101
1"
#102
0"
1#
#103
1"
#104
0!
0"
0#
0$
1%
#105
1"
#106
0"
1#
#107
1"
#108
1!
0"
0#
1$
#109
1"
#110
0"
1#
#111
1"
#112
0!
0"
0#
0$
0%
b11 &
b11 '
#113
1"
#114
0"
1#
#115
1"
#116
0"
0#
1$
#117
1"
#118
0"
1#
#119
1"
#120
1!
0"
0#
0$
1%
#121
1"
#122
0"
1#
#123
1"
#124
0"
0#
1$
#125
1"
#126
0"
1#
#127
1"
#128
0!
0"
0#
0$
0%
b0 &
b0 '
#129
1!
1"
#130
0!
0"
1#
#131
1!
1"
#132
0!
0"
0#
1$
#133
1!
1"
#134
0!
0"
1#
#135
1!
1"
#136
0!
0"
0#
0$
1%
#137
1!
1"
#138
0!
0"
1#
#139
1!
1"
#140
0!
0"
0#
1$
#141
1!
1"
#142
0!
0"
1#
#143
1!
1"
#144
0!
0"
0#
0$
0%
b1 &
b1 '
#145
1"
#146
1!
0"
1#
#147
1"
#148
0!
0"
0#
1$
#149
1"
#150
1!
0"
1#
#151
1"
#152
0!
0"
0#
0$
1%
#153
1"
#154
1!
0"
1#
#155
1"
#156
0!
0"
0#
1$
#157
1"
#158
1!
0"
1#
#159
1"
#160
0!
0"
0#
0$
0%
b10 &
b10 '
#161
1"
#162
0"
1#
#163
1"
#164
1!
0"
0#
1$
#165
1"
#166
0"
1#
#167
1"
#168
0!
0"
0#
0$
1%
#169
1"
#170
0"
1#
#171
1"
#172
1!
0"
0#
1$
#173
1"
#174
0"
1#
#175
1"
#176
0!
0"
0#
0$
0%
b11 &
b11 '
#177
1"
#178
0"
1#
#179
1"
#180
0"
0#
1$
#181
1"
#182
0"
1#
#183
1"
#184
1!
0"
0#
0$
1%
#185
1"
#186
0"
1#
#187
1"
#188
0"
0#
1$
#189
1"
#190
0"
1#
#191
1"
#192
0!
0"
0#
0$
0%
b0 &
b0 '
#193
1!
1"
#194
0!
0"
1#
#195
1!
1"
#196
0!
0"
0#
1$
#197
1!
1"
#198
0!
0"
1#
#199
1!
1"
#200
0!
0"
0#
0$
1%
#201
1!
1"
#202
0!
0"
1#
#203
1!
1"
#204
0!
0"
0#
1$
#205
1!
1"
#206
0!
0"
1#
#207
1!
1"
#208
0!
0"
0#
0$
0%
b1 &
b1 '
#209
1"
#210
1!
0"
1#
#211
1"
#212
0!
0"
0#
1$
#213
1"
#214
1!
0"
1#
#215
1"
#216
0!
0"
0#
0$
1%
#217
1"
#218
1!
0"
1#
#219
1"
#220
0!
0"
0#
1$
#221
1"
#222
1!
0"
1#
#223
1"
#224
0!
0"
0#
0$
0%
b10 &
b10 '
#225
1"
#226
0"
1#
#227
1"
#228
1!
0"
0#
1$
#229
1"
#230
0"
1#
#231
1"
#232
0!
0"
0#
0$
1%
#233
1"
#234
0"
1#
#235
1"
#236
1!
0"
0#
1$
#237
1"
#238
0"
1#
#239
1"
#240
0!
0"
0#
0$
0%
b11 &
b11 '
#241
1"
#242
0"
1#
#243
1"
#244
0"
0#
1$
#245
1"
#246
0"
1#
#247
1"
#248
1!
0"
0#
0$
1%
#249
1"
#250
0"
1#
#251
1"
#252
0"
0#
1$
#253
1"
#254
0"
1#
#255
1"
#256
0!
0"
0#
0$
0%
b0 &
b0 '
#257
1!
1"
#258
0!
0"
1#
#259
1!
1"
#260
0!
0"
0#
1$
#261
1!
1"
#262
0!
0"
1#
#263
1!
1"
#264
0!
0"
0#
0$
1%
#265
1!
1"
#266
0!
0"
1#
#267
1!
1"
#268
0!
0"
0#
1$
#269
1!
1"
#270
0!
0"
1#
#271
1!
1"
#272
0!
0"
0#
0$
0%
b1 &
b1 '
#273
1"
#274
1!
0"
1#
#275
1"
#276
0!
0"
0#
1$
#277
1"
#278
1!
0"
1#
#279
1"
#280
0!
0"
0#
0$
1%
#281
1"
#282
1!
0"
1#
#283
1"
#284
0!
0"
0#
1$
#285
1"
#286
1!
0"
1#
#287
1"
#288
0!
0"
0#
0$
0%
b10 &
b10 '
#289
1"
#290
0"
1#
#291
1"
#292
1!
0"
0#
1$
#293
1"
#294
0"
1#
#295
1"
#296
0!
0"
0#
0$
1%
#297
1"
#298
0"
1#
#299
1"
#300
1!
0"
0#
1$
#301
1"
#302
0"
1#
#303
1"
#304
0!
0"
0#
0$
0%
b11 &
b11 '
#305
1"
#306
0"
1#
#307
1"
#308
0"
0#
1$
#309
1"
#310
0"
1#
#311
1"
#312
1!
0"
0#
0$
1%
#313
1"
#314
0"
1#
#315
1"
#316
0"
0#
1$
#317
1"
#318
0"
1#
#319
1"
#320
0!
0"
0#
0$
0%
b0 &
b0 '
#321
1!
1"
#322
0!
0"
1#
#323
1!
1"
#324
0!
0"
0#
1$
#325
1!
1"
#326
0!
0"
1#
#327
1!
1"
#328
0!
0"
0#
0$
1%
#329
1!
1"
#330
0!
0"
1#
#331
1!
1"
#332
0!
0"
0#
1$
#333
1!
1"
#334
0!
0"
1#
#335
1!
1"
#336
0!
0"
0#
0$
0%
b1 &
b1 '
#337
1"
#338
1!
0"
1#
#339
1"
#340
0!
0"
0#
1$
#341
1"
#342
1!
0"
1#
#343
1"
#344
0!
0"
0#
0$
1%
#345
1"
#346
1!
0"
1#
#347
1"
#348
0!
0"
0#
1$
#349
1"
#350
1!
0"
1#
#351
1"
#352
0!
0"
0#
0$
0%
b10 &
b10 '
#353
1"
#354
0"
1#
#355
1"
#356
1!
0"
0#
1$
#357
1"
#358
0"
1#
#359
1"
#360
0!
0"
0#
0$
1%
#361
1"
#362
0"
1#
#363
1"
#364
1!
0"
0#
1$
#365
1"
#366
0"
1#
#367
1"
#368
0!
0"
0#
0$
0%
b11 &
b11 '
#369
1"
#370
0"
1#
#371
1"
#372
0"
0#
1$
#373
1"
#374
0"
1#
#375
1"
#376
1!
0"
0#
0$
1%
#377
1"
#378
0"
1#
#379
1"
#380
0"
0#
1$
#381
1"
#382
0"
1#
#383
1"
#384
0!
0"
0#
0$
0%
b0 &
b0 '
#385
1!
1"
#386
0!
0"
1#
#387
1!
1"
#388
0!
0"
0#
1$
#389
1!
1"
#390
0!
0"
1#
#391
1!
1"
#392
0!
0"
0#
0$
1%
#393
1!
1"
#394
0!
0"
1#
#395
1!
1"
#396
0!
0"
0#
1$
#397
1!
1"
#398
0!
0"
1#
#399
1!
1"
#400
0!
0"
0#
0$
0%
b1 &
b1 '
#401
1"
#402
1!
0"
1#
#403
1"
#404
0!
0"
0#
1$
#405
1"
#406
1!
0"
1#
#407
1"
#408
0!
0"
0#
0$
1%
#409
1"
#410
1!
0"
1#
#411
1"
#412
0!
0"
0#
1$
#413
1"
#414
1!
0"
1#
#415
1"
#416
0!
0"
0#
0$
0%
b10 &
b10 '
#417
1"
#418
0"
1#
#419
1"
#420
1!
0"
0#
1$
#421
1"
#422
0"
1#
#423
1"
#424
0!
0"
0#
0$
1%
#425
1"
#426
0"
1#
#427
1"
#428
1!
0"
0#
1$
#429
1"
#430
0"
1#
#431
1"
#432
0!
0"
0#
0$
0%
b11 &
b11 '
#433
1"
#434
0"
1#
#435
1"
#436
0"
0#
1$
#437
1"
#438
0"
1#
#439
1"
#440
1!
0"
0#
0$
1%
#441
1"
#442
0"
1#
#443
1"
#444
0"
0#
1$
#445
1"
#446
0"
1#
#447
1"
#448
0!
0"
0#
0$
0%
b0 &
b0 '
#449
1!
1"
#450
0!
0"
1#
#451
1!
1"
#452
0!
0"
0#
1$
#453
1!
1"
#454
0!
0"
1#
#455
1!
1"
#456
0!
0"
0#
0$
1%
#457
1!
1"
#458
0!
0"
1#
#459
1!
1"
#460
0!
0"
0#
1$
#461
1!
1"
#462
0!
0"
1#
#463
1!
1"
#464
0!
0"
0#
0$
0%
b1 &
b1 '
#465
1"
#466
1!
0"
1#
#467
1"
#468
0!
0"
0#
1$
#469
1"
#470
1!
0"
1#
#471
1"
#472
0!
0"
0#
0$
1%
#473
1"
#474
1!
0"
1#
#475
1"
#476
0!
0"
0#
1$
#477
1"
#478
1!
0"
1#
#479
1"
#480
0!
0"
0#
0$
0%
b10 &
b10 '
#481
1"
#482
0"
1#
#483
1"
#484
1!
0"
0#
1$
#485
1"
#486
0"
1#
#487
1"
#488
0!
0"
0#
0$
1%
#489
1"
#490
0"
1#
#491
1"
#492
1!
0"
0#
1$
#493
1"
#494
0"
1#
#495
1"
#496
0!
0"
0#
0$
0%
b11 &
b11 '
#497
1"
#498
0"
1#
#499
1"
#500
0"
0#
1$
#501
1"
#502
0"
1#
#503
1"
#504
1!
0"
0#
0$
1%
#505
1"
#506
0"
1#
#507
1"
#508
0"
0#
1$
#509
1"
#510
0"
1#
#511
1"
#512
0!
0"
0#
0$
0%
b0 &
b0 '
#513
1!
1"
#514
0!
0"
1#
#515
1!
1"
#516
0!
0"
0#
1$
#517
1!
1"
#518
0!
0"
1#
#519
1!
1"
#520
0!
0"
0#
0$
1%
#521
1!
1"
#522
0!
0"
1#
#523
1!
1"
#524
0!
0"
0#
1$
#525
1!
1"
#526
0!
0"
1#
#527
1!
1"
#528
0!
0"
0#
0$
0%
b1 &
b1 '
#529
1"
#530
1!
0"
1#
#531
1"
#532
0!
0"
0#
1$
#533
1"
#534
1!
0"
1#
#535
1"
#536
0!
0"
0#
0$
1%
#537
1"
#538
1!
0"
1#
#539
1"
#540
0!
0"
0#
1$
#541
1"
#542
1!
0"
1#
#543
1"
#544
0!
0"
0#
0$
0%
b10 &
b10 '
#545
1"
#546
0"
1#
#547
1"
#548
1!
0"
0#
1$
#549
1"
#550
0"
1#
#551
1"
#552
0!
0"
0#
0$
1%
#553
1"
#554
0"
1#
#555
1"
#556
1!
0"
0#
1$
#557
1"
#558
0"
1#
#559
1"
#560
0!
0"
0#
0$
0%
b11 &
b11 '
#561
1"
#562
0"
1#
#563
1"
#564
0"
0#
1$
#565
1"
#566
0"
1#
#567
1"
#568
1!
0"
0#
0$
1%
#569
1"
#570
0"
1#
#571
1"
#572
0"
0#
1$
#573
1"
#574
0"
1#
#575
1"
#576
0!
0"
0#
0$
0%
b0 &
b0 '
#577
1!
1"
#578
0!
0"
1#
#579
1!
1"
#580
0!
0"
0#
1$
#581
1!
1"
#582
0!
0"
1#
#583
1!
1"
#584
0!
0"
0#
0$
1%
#585
1!
1"
#586
0!
0"
1#
#587
1!
1"
#588
0!
0"
0#
1$
#589
1!
1"
#590
0!
0"
1#
#591
1!
1"
#592
0!
0"
0#
0$
0%
b1 &
b1 '
#593
1"
#594
1!
0"
1#
#595
1"
#596
0!
0"
0#
1$
#597
1"
#598
1!
0"
1#
#599
1"
#600
0!
0"
0#
0$
1%
#601
1"
#602
1!
0"
1#
#603
1"
#604
0!
0"
0#
1$
#605
1"
#606
1!
0"
1#
#607
1"
#608
0!
0"
0#
0$
0%
b10 &
b10 '
#609
1"
#610
0"
1#
#611
1"
#612
1!
0"
0#
1$
#613
1"
#614
0"
1#
#615
1"
#616
0!
0"
0#
0$
1%
#617
1"
#618
0"
1#
#619
1"
#620
1!
0"
0#
1$
#621
1"
#622
0"
1#
#623
1"
#624
0!
0"
0#
0$
0%
b11 &
b11 '
#625
1"
#626
0"
1#
#627
1"
#628
0"
0#
1$
#629
1"
#630
0"
1#
#631
1"
#632
1!
0"
0#
0$
1%
#633
1"
#634
0"
1#
#635
1"
#636
0"
0#
1$
#637
1"
#638
0"
1#
#639
1"
#640
0!
0"
0#
0$
0%
b0 &
b0 '
#641
1!
1"
#642
0!
0"
1#
#643
1!
1"
#644
0!
0"
0#
1$
#645
1!
1"
#646
0!
0"
1#
#647
1!
1"
#648
0!
0"
0#
0$
1%
#649
1!
1"
#650
0!
0"
1#
#651
1!
1"
#652
0!
0"
0#
1$
#653
1!
1"
#654
0!
0"
1#
#655
1!
1"
#656
0!
0"
0#
0$
0%
b1 &
b1 '
#657
1"
#658
1!
0"
1#
#659
1"
#660
0!
0"
0#
1$
#661
1"
#662
1!
0"
1#
#663
1"
#664
0!
0"
0#
0$
1%
#665
1"
#666
1!
0"
1#
#667
1"
#668
0!
0"
0#
1$
#669
1"
#670
1!
0"
1#
#671
1"
#672
0!
0"
0#
0$
0%
b10 &
b10 '
#673
1"
#674
0"
1#
#675
1"
#676
1!
0"
0#
1$
#677
1"
#678
0"
1#
#679
1"
#680
0!
0"
0#
0$
1%
#681
1"
#682
0"
1#
#683
1"
#684
1!
0"
0#
1$
#685
1"
#686
0"
1#
#687
1"
#688
0!
0"
0#
0$
0%
b11 &
b11 '
#689
1"
#690
0"
1#
#691
1"
#692
0"
0#
1$
#693
1"
#694
0"
1#
#695
1"
#696
1!
0"
0#
0$
1%
#697
1"
#698
0"
1#
#699
1"
#700
0"
0#
1$
#701
1"
#702
0"
1#
#703
1"
#704
0!
0"
0#
0$
0%
b0 &
b0 '
#705
1!
1"
#706
0!
0"
1#
#707
1!
1"
#708
0!
0"
0#
1$
#709
1!
1"
#710
0!
0"
1#
#711
1!
1"
#712
0!
0"
0#
0$
1%
#713
1!
1"
#714
0!
0"
1#
#715
1!
1"
#716
0!
0"
0#
1$
#717
1!
1"
#718
0!
0"
1#
#719
1!
1"
#720
0!
0"
0#
0$
0%
b1 &
b1 '
#721
1"
#722
1!
0"
1#
#723
1"
#724
0!
0"
0#
1$
#725
1"
#726
1!
0"
1#
#727
1"
#728
0!
0"
0#
0$
1%
#729
1"
#730
1!
0"
1#
#731
1"
#732
0!
0"
0#
1$
#733
1"
#734
1!
0"
1#
#735
1"
#736
0!
0"
0#
0$
0%
b10 &
b10 '
#737
1"
#738
0"
1#
#739
1"
#740
1!
0"
0#
1$
#741
1"
#742
0"
1#
#743
1"
#744
0!
0"
0#
0$
1%
#745
1"
#746
0"
1#
#747
1"
#748
1!
0"
0#
1$
#749
1"
#750
0"
1#
#751
1"
#752
0!
0"
0#
0$
0%
b11 &
b11 '
#753
1"
#754
0"
1#
#755
1"
#756
0"
0#
1$
#757
1"
#758
0"
1#
#759
1"
#760
1!
0"
0#
0$
1%
#761
1"
#762
0"
1#
#763
1"
#764
0"
0#
1$
#765
1"
#766
0"
1#
#767
1"
#768
0!
0"
0#
0$
0%
b0 &
b0 '
#769
1!
1"
#770
0!
0"
1#
#771
1!
1"
#772
0!
0"
0#
1$
#773
1!
1"
#774
0!
0"
1#
#775
1!
1"
#776
0!
0"
0#
0$
1%
#777
1!
1"
#778
0!
0"
1#
#779
1!
1"
#780
0!
0"
0#
1$
#781
1!
1"
#782
0!
0"
1#
#783
1!
1"
#784
0!
0"
0#
0$
0%
b1 &
b1 '
#785
1"
#786
1!
0"
1#
#787
1"
#788
0!
0"
0#
1$
#789
1"
#790
1!
0"
1#
#791
1"
#792
0!
0"
0#
0$
1%
#793
1"
#794
1!
0"
1#
#795
1"
#796
0!
0"
0#
1$
#797
1"
#798
1!
0"
1#
#799
1"
#800
0!
0"
0#
0$
0%
b10 &
b10 '
#801
1"
#802
0"
1#
#803
1"
#804
1!
0"
0#
1$
#805
1"
#806
0"
1#
#807
1"
#808
0!
0"
0#
0$
1%
#809
1"
#810
0"
1#
#811
1"
#812
1!
0"
0#
1$
#813
1"
#814
0"
1#
#815
1"
#816
0!
0"
0#
0$
0%
b11 &
b11 '
#817
1"
#818
0"
1#
#819
1"
#820
0"
0#
1$
#821
1"
#822
0"
1#
#823
1"
#824
1!
0"
0#
0$
1%
#825
1"
#826
0"
1#
#827
1"
#828
0"
0#
1$
#829
1"
#830
0"
1#
#831
1"
#832
0!
0"
0#
0$
0%
b0 &
b0 '
#833
1!
1"
#834
0!
0"
1#
#835
1!
1"
#836
0!
0"
0#
1$
#837
1!
1"
#838
0!
0"
1#
#839
1!
1"
#840
0!
0"
0#
0$
1%
#841
1!
1"
#842
0!
0"
1#
#843
1!
1"
#844
0!
0"
0#
1$
#845
1!
1"
#846
0!
0"
1#
#847
1!
1"
#848
0!
0"
0#
0$
0%
b1 &
b1 '
#849
1"
#850
1!
0"
1#
#851
1"
#852
0!
0"
0#
1$
#853
1"
#854
1!
0"
1#
#855
1"
#856
0!
0"
0#
0$
1%
#857
1"
#858
1!
0"
1#
#859
1"
#860
0!
0"
0#
1$
#861
1"
#862
1!
0"
1#
#863
1"
#864
0!
0"
0#
0$
0%
b10 &
b10 '
#865
1"
#866
0"
1#
#867
1"
#868
1!
0"
0#
1$
#869
1"
#870
0"
1#
#871
1"
#872
0!
0"
0#
0$
1%
#873
1"
#874
0"
1#
#875
1"
#876
1!
0"
0#
1$
#877
1"
#878
0"
1#
#879
1"
#880
0!
0"
0#
0$
0%
b11 &
b11 '
#881
1"
#882
0"
1#
#883
1"
#884
0"
0#
1$
#885
1"
#886
0"
1#
#887
1"
#888
1!
0"
0#
0$
1%
#889
1"
#890
0"
1#
#891
1"
#892
0"
0#
1$
#893
1"
#894
0"
1#
#895
1"
#896
0!
0"
0#
0$
0%
b0 &
b0 '
#897
1!
1"
#898
0!
0"
1#
#899
1!
1"
#900
0!
0"
0#
1$
#901
1!
1"
#902
0!
0"
1#
#903
1!
1"
#904
0!
0"
0#
0$
1%
#905
1!
1"
#906
0!
0"
1#
#907
1!
1"
#908
0!
0"
0#
1$
#909
1!
1"
#910
0!
0"
1#
#911
1!
1"
#912
0!
0"
0#
0$
0%
b1 &
b1 '
#913
1"
#914
1!
0"
1#
#915
1"
#916
0!
0"
0#
1$
#917
1"
#918
1!
0"
1#
#919
1"
#920
0!
0"
0#
0$
1%
#921
1"
#922
1!
0"
1#
#923
1"
#924
0!
0"
0#
1$
#925
1"
#926
1!
0"
1#
#927
1"
#928
0!
0"
0#
0$
0%
b10 &
b10 '
#929
1"
#930
0"
1#
#931
1"
#932
1!
0"
0#
1$
#933
1"
#934
0"
1#
#935
1"
#936
0!
0"
0#
0$
1%
#937
1"
#938
0"
1#
#939
1"
#940
1!
0"
0#
1$
#941
1"
#942
0"
1#
#943
1"
#944
0!
0"
0#
0$
0%
b11 &
b11 '
#945
1"
#946
0"
1#
#947
1"
#948
0"
0#
1$
#949
1"
#950
0"
1#
#951
1"
#952
1!
0"
0#
0$
1%
#953
1"
#954
0"
1#
#955
1"
#956
0"
0#
1$
#957
1"
#958
0"
1#
#959
1"
#960
0!
0"
0#
0$
0%
b0 &
b0 '
#961
1!
1"
#962
0!
0"
1#
#963
1!
1"
#964
0!
0"
0#
1$
#965
1!
1"
#966
0!
0"
1#
#967
1!
1"
#968
0!
0"
0#
0$
1%
#969
1!
1"
#970
0!
0"
1#
#971
1!
1"
#972
0!
0"
0#
1$
#973
1!
1"
#974
0!
0"
1#
#975
1!
1"
#976
0!
0"
0#
0$
0%
b1 &
b1 '
#977
1"
#978
1!
0"
1#
#979
1"
#980
0!
0"
0#
1$
#981
1"
#982
1!
0"
1#
#983
1"
#984
0!
0"
0#
0$
1%
#985
1"
#986
1!
0"
1#
#987
1"
#988
0!
0"
0#
1$
#989
1"
#990
1!
0"
1#
#991
1"
#992
0!
0"
0#
0$
0%
b10 &
b10 '
#993
1"
#994
0"
1#
#995
1"
#996
1!
0"
0#
1$
#997
1"
#998
0"
1#
#999
1"
#1000
0!
0"
0#
0$
1%
