muti_way_variants/Mux4Way16.v
module Mux4Way16 (
    input wire [1:0] sel,
    input wire [15:0] in1,
    input wire [15:0] in2,
    input wire [15:0] in3,
    input wire [15:0] in4,
    output reg [15:0] out
);

    always @(*) begin
        if (sel == 2'b00) begin
            out = in1;
        end else if (sel == 2'b01) begin
            out = in2;
        end else if (sel == 2'b10) begin
            out = in3;
        end else if (sel == 2'b11) begin
            out = in4;
        end
    end
    
    
endmodule

muti_way_variants/Mux4Way16_tb.v
module Mux4Way16_tb;

    reg [1:0] sel = 2'b00;
    reg [15:0] in1 = 16'hdadf;
    reg [15:0] in2 = 16'haaaf;
    reg [15:0] in3 = 16'hbdef;
    reg [15:0] in4 = 16'h1245;
    wire [15:0] out;

    Mux4Way16 mux4way16(.sel(sel), .in1(in1), .in2(in2), .in3(in3), .in4(in4), .out(out));

    initial begin
        $dumpfile("Mux4Way16.vcd");
        $dumpvars(0, Mux4Way16_tb, sel);
        #1000 $finish;
    end

    always begin
        # 1
        if (sel == 2'b11) begin
            sel = 2'b00;
        end else begin
            sel = sel + 1;
        end
    end
    
endmodule

muti_way_variants/Mux4Way16.vcd
$date
	Fri Aug 25 21:39:31 2023
$end
$version
	Icarus Verilog
$end
$timescale
	1s
$end
$scope module Mux4Way16_tb $end
$var wire 16 ! out [15:0] $end
$var reg 16 " in1 [15:0] $end
$var reg 16 # in2 [15:0] $end
$var reg 16 $ in3 [15:0] $end
$var reg 16 % in4 [15:0] $end
$var reg 2 & sel [1:0] $end
$scope module mux4way16 $end
$var wire 16 ' in1 [15:0] $end
$var wire 16 ( in2 [15:0] $end
$var wire 16 ) in3 [15:0] $end
$var wire 16 * in4 [15:0] $end
$var wire 2 + sel [1:0] $end
$var reg 16 , out [15:0] $end
$upscope $end
$upscope $end
$enddefinitions $end
$comment Show the parameter values. $end
$dumpall
$end
#0
$dumpvars
b1101101011011111 ,
b0 +
b1001001000101 *
b1011110111101111 )
b1010101010101111 (
b1101101011011111 '
b0 &
b1001001000101 %
b1011110111101111 $
b1010101010101111 #
b1101101011011111 "
b1101101011011111 !
$end
#1
b1010101010101111 !
b1010101010101111 ,
b1 &
b1 +
#2
b1011110111101111 !
b1011110111101111 ,
b10 &
b10 +
#3
b1001001000101 !
b1001001000101 ,
b11 &
b11 +
#4
b1101101011011111 !
b1101101011011111 ,
b0 &
b0 +
#5
b1010101010101111 !
b1010101010101111 ,
b1 &
b1 +
#6
b1011110111101111 !
b1011110111101111 ,
b10 &
b10 +
#7
b1001001000101 !
b1001001000101 ,
b11 &
b11 +
#8
b1101101011011111 !
b1101101011011111 ,
b0 &
b0 +
#9
b1010101010101111 !
b1010101010101111 ,
b1 &
b1 +
#10
b1011110111101111 !
b1011110111101111 ,
b10 &
b10 +
#11
b1001001000101 !
b1001001000101 ,
b11 &
b11 +
#12
b1101101011011111 !
b1101101011011111 ,
b0 &
b0 +
#13
b1010101010101111 !
b1010101010101111 ,
b1 &
b1 +
#14
b1011110111101111 !
b1011110111101111 ,
b10 &
b10 +
#15
b1001001000101 !
b1001001000101 ,
b11 &
b11 +
#16
b1101101011011111 !
b1101101011011111 ,
b0 &
b0 +
#17
b1010101010101111 !
b1010101010101111 ,
b1 &
b1 +
#18
b1011110111101111 !
b1011110111101111 ,
b10 &
b10 +
#19
b1001001000101 !
b1001001000101 ,
b11 &
b11 +
#20
b1101101011011111 !
b1101101011011111 ,
b0 &
b0 +
#21
b1010101010101111 !
b1010101010101111 ,
b1 &
b1 +
#22
b1011110111101111 !
b1011110111101111 ,
b10 &
b10 +
#23
b1001001000101 !
b1001001000101 ,
b11 &
b11 +
#24
b1101101011011111 !
b1101101011011111 ,
b0 &
b0 +
#25
b1010101010101111 !
b1010101010101111 ,
b1 &
b1 +
#26
b1011110111101111 !
b1011110111101111 ,
b10 &
b10 +
#27
b1001001000101 !
b1001001000101 ,
b11 &
b11 +
#28
b1101101011011111 !
b1101101011011111 ,
b0 &
b0 +
#29
b1010101010101111 !
b1010101010101111 ,
b1 &
b1 +
#30
b1011110111101111 !
b1011110111101111 ,
b10 &
b10 +
#31
b1001001000101 !
b1001001000101 ,
b11 &
b11 +
#32
b1101101011011111 !
b1101101011011111 ,
b0 &
b0 +
#33
b1010101010101111 !
b1010101010101111 ,
b1 &
b1 +
#34
b1011110111101111 !
b1011110111101111 ,
b10 &
b10 +
#35
b1001001000101 !
b1001001000101 ,
b11 &
b11 +
#36
b1101101011011111 !
b1101101011011111 ,
b0 &
b0 +
#37
b1010101010101111 !
b1010101010101111 ,
b1 &
b1 +
#38
b1011110111101111 !
b1011110111101111 ,
b10 &
b10 +
#39
b1001001000101 !
b1001001000101 ,
b11 &
b11 +
#40
b1101101011011111 !
b1101101011011111 ,
b0 &
b0 +
#41
b1010101010101111 !
b1010101010101111 ,
b1 &
b1 +
#42
b1011110111101111 !
b1011110111101111 ,
b10 &
b10 +
#43
b1001001000101 !
b1001001000101 ,
b11 &
b11 +
#44
b1101101011011111 !
b1101101011011111 ,
b0 &
b0 +
#45
b1010101010101111 !
b1010101010101111 ,
b1 &
b1 +
#46
b1011110111101111 !
b1011110111101111 ,
b10 &
b10 +
#47
b1001001000101 !
b1001001000101 ,
b11 &
b11 +
#48
b1101101011011111 !
b1101101011011111 ,
b0 &
b0 +
#49
b1010101010101111 !
b1010101010101111 ,
b1 &
b1 +
#50
b1011110111101111 !
b1011110111101111 ,
b10 &
b10 +
#51
b1001001000101 !
b1001001000101 ,
b11 &
b11 +
#52
b1101101011011111 !
b1101101011011111 ,
b0 &
b0 +
#53
b1010101010101111 !
b1010101010101111 ,
b1 &
b1 +
#54
b1011110111101111 !
b1011110111101111 ,
b10 &
b10 +
#55
b1001001000101 !
b1001001000101 ,
b11 &
b11 +
#56
b1101101011011111 !
b1101101011011111 ,
b0 &
b0 +
#57
b1010101010101111 !
b1010101010101111 ,
b1 &
b1 +
#58
b1011110111101111 !
b1011110111101111 ,
b10 &
b10 +
#59
b1001001000101 !
b1001001000101 ,
b11 &
b11 +
#60
b1101101011011111 !
b1101101011011111 ,
b0 &
b0 +
#61
b1010101010101111 !
b1010101010101111 ,
b1 &
b1 +
#62
b1011110111101111 !
b1011110111101111 ,
b10 &
b10 +
#63
b1001001000101 !
b1001001000101 ,
b11 &
b11 +
#64
b1101101011011111 !
b1101101011011111 ,
b0 &
b0 +
#65
b1010101010101111 !
b1010101010101111 ,
b1 &
b1 +
#66
b1011110111101111 !
b1011110111101111 ,
b10 &
b10 +
#67
b1001001000101 !
b1001001000101 ,
b11 &
b11 +
#68
b1101101011011111 !
b1101101011011111 ,
b0 &
b0 +
#69
b1010101010101111 !
b1010101010101111 ,
b1 &
b1 +
#70
b1011110111101111 !
b1011110111101111 ,
b10 &
b10 +
#71
b1001001000101 !
b1001001000101 ,
b11 &
b11 +
#72
b1101101011011111 !
b1101101011011111 ,
b0 &
b0 +
#73
b1010101010101111 !
b1010101010101111 ,
b1 &
b1 +
#74
b1011110111101111 !
b1011110111101111 ,
b10 &
b10 +
#75
b1001001000101 !
b1001001000101 ,
b11 &
b11 +
#76
b1101101011011111 !
b1101101011011111 ,
b0 &
b0 +
#77
b1010101010101111 !
b1010101010101111 ,
b1 &
b1 +
#78
b1011110111101111 !
b1011110111101111 ,
b10 &
b10 +
#79
b1001001000101 !
b1001001000101 ,
b11 &
b11 +
#80
b1101101011011111 !
b1101101011011111 ,
b0 &
b0 +
#81
b1010101010101111 !
b1010101010101111 ,
b1 &
b1 +
#82
b1011110111101111 !
b1011110111101111 ,
b10 &
b10 +
#83
b1001001000101 !
b1001001000101 ,
b11 &
b11 +
#84
b1101101011011111 !
b1101101011011111 ,
b0 &
b0 +
#85
b1010101010101111 !
b1010101010101111 ,
b1 &
b1 +
#86
b1011110111101111 !
b1011110111101111 ,
b10 &
b10 +
#87
b1001001000101 !
b1001001000101 ,
b11 &
b11 +
#88
b1101101011011111 !
b1101101011011111 ,
b0 &
b0 +
#89
b1010101010101111 !
b1010101010101111 ,
b1 &
b1 +
#90
b1011110111101111 !
b1011110111101111 ,
b10 &
b10 +
#91
b1001001000101 !
b1001001000101 ,
b11 &
b11 +
#92
b1101101011011111 !
b1101101011011111 ,
b0 &
b0 +
#93
b1010101010101111 !
b1010101010101111 ,
b1 &
b1 +
#94
b1011110111101111 !
b1011110111101111 ,
b10 &
b10 +
#95
b1001001000101 !
b1001001000101 ,
b11 &
b11 +
#96
b1101101011011111 !
b1101101011011111 ,
b0 &
b0 +
#97
b1010101010101111 !
b1010101010101111 ,
b1 &
b1 +
#98
b1011110111101111 !
b1011110111101111 ,
b10 &
b10 +
#99
b1001001000101 !
b1001001000101 ,
b11 &
b11 +
#100
b1101101011011111 !
b1101101011011111 ,
b0 &
b0 +
#101
b1010101010101111 !
b1010101010101111 ,
b1 &
b1 +
#102
b1011110111101111 !
b1011110111101111 ,
b10 &
b10 +
#103
b1001001000101 !
b1001001000101 ,
b11 &
b11 +
#104
b1101101011011111 !
b1101101011011111 ,
b0 &
b0 +
#105
b1010101010101111 !
b1010101010101111 ,
b1 &
b1 +
#106
b1011110111101111 !
b1011110111101111 ,
b10 &
b10 +
#107
b1001001000101 !
b1001001000101 ,
b11 &
b11 +
#108
b1101101011011111 !
b1101101011011111 ,
b0 &
b0 +
#109
b1010101010101111 !
b1010101010101111 ,
b1 &
b1 +
#110
b1011110111101111 !
b1011110111101111 ,
b10 &
b10 +
#111
b1001001000101 !
b1001001000101 ,
b11 &
b11 +
#112
b1101101011011111 !
b1101101011011111 ,
b0 &
b0 +
#113
b1010101010101111 !
b1010101010101111 ,
b1 &
b1 +
#114
b1011110111101111 !
b1011110111101111 ,
b10 &
b10 +
#115
b1001001000101 !
b1001001000101 ,
b11 &
b11 +
#116
b1101101011011111 !
b1101101011011111 ,
b0 &
b0 +
#117
b1010101010101111 !
b1010101010101111 ,
b1 &
b1 +
#118
b1011110111101111 !
b1011110111101111 ,
b10 &
b10 +
#119
b1001001000101 !
b1001001000101 ,
b11 &
b11 +
#120
b1101101011011111 !
b1101101011011111 ,
b0 &
b0 +
#121
b1010101010101111 !
b1010101010101111 ,
b1 &
b1 +
#122
b1011110111101111 !
b1011110111101111 ,
b10 &
b10 +
#123
b1001001000101 !
b1001001000101 ,
b11 &
b11 +
#124
b1101101011011111 !
b1101101011011111 ,
b0 &
b0 +
#125
b1010101010101111 !
b1010101010101111 ,
b1 &
b1 +
#126
b1011110111101111 !
b1011110111101111 ,
b10 &
b10 +
#127
b1001001000101 !
b1001001000101 ,
b11 &
b11 +
#128
b1101101011011111 !
b1101101011011111 ,
b0 &
b0 +
#129
b1010101010101111 !
b1010101010101111 ,
b1 &
b1 +
#130
b1011110111101111 !
b1011110111101111 ,
b10 &
b10 +
#131
b1001001000101 !
b1001001000101 ,
b11 &
b11 +
#132
b1101101011011111 !
b1101101011011111 ,
b0 &
b0 +
#133
b1010101010101111 !
b1010101010101111 ,
b1 &
b1 +
#134
b1011110111101111 !
b1011110111101111 ,
b10 &
b10 +
#135
b1001001000101 !
b1001001000101 ,
b11 &
b11 +
#136
b1101101011011111 !
b1101101011011111 ,
b0 &
b0 +
#137
b1010101010101111 !
b1010101010101111 ,
b1 &
b1 +
#138
b1011110111101111 !
b1011110111101111 ,
b10 &
b10 +
#139
b1001001000101 !
b1001001000101 ,
b11 &
b11 +
#140
b1101101011011111 !
b1101101011011111 ,
b0 &
b0 +
#141
b1010101010101111 !
b1010101010101111 ,
b1 &
b1 +
#142
b1011110111101111 !
b1011110111101111 ,
b10 &
b10 +
#143
b1001001000101 !
b1001001000101 ,
b11 &
b11 +
#144
b1101101011011111 !
b1101101011011111 ,
b0 &
b0 +
#145
b1010101010101111 !
b1010101010101111 ,
b1 &
b1 +
#146
b1011110111101111 !
b1011110111101111 ,
b10 &
b10 +
#147
b1001001000101 !
b1001001000101 ,
b11 &
b11 +
#148
b1101101011011111 !
b1101101011011111 ,
b0 &
b0 +
#149
b1010101010101111 !
b1010101010101111 ,
b1 &
b1 +
#150
b1011110111101111 !
b1011110111101111 ,
b10 &
b10 +
#151
b1001001000101 !
b1001001000101 ,
b11 &
b11 +
#152
b1101101011011111 !
b1101101011011111 ,
b0 &
b0 +
#153
b1010101010101111 !
b1010101010101111 ,
b1 &
b1 +
#154
b1011110111101111 !
b1011110111101111 ,
b10 &
b10 +
#155
b1001001000101 !
b1001001000101 ,
b11 &
b11 +
#156
b1101101011011111 !
b1101101011011111 ,
b0 &
b0 +
#157
b1010101010101111 !
b1010101010101111 ,
b1 &
b1 +
#158
b1011110111101111 !
b1011110111101111 ,
b10 &
b10 +
#159
b1001001000101 !
b1001001000101 ,
b11 &
b11 +
#160
b1101101011011111 !
b1101101011011111 ,
b0 &
b0 +
#161
b1010101010101111 !
b1010101010101111 ,
b1 &
b1 +
#162
b1011110111101111 !
b1011110111101111 ,
b10 &
b10 +
#163
b1001001000101 !
b1001001000101 ,
b11 &
b11 +
#164
b1101101011011111 !
b1101101011011111 ,
b0 &
b0 +
#165
b1010101010101111 !
b1010101010101111 ,
b1 &
b1 +
#166
b1011110111101111 !
b1011110111101111 ,
b10 &
b10 +
#167
b1001001000101 !
b1001001000101 ,
b11 &
b11 +
#168
b1101101011011111 !
b1101101011011111 ,
b0 &
b0 +
#169
b1010101010101111 !
b1010101010101111 ,
b1 &
b1 +
#170
b1011110111101111 !
b1011110111101111 ,
b10 &
b10 +
#171
b1001001000101 !
b1001001000101 ,
b11 &
b11 +
#172
b1101101011011111 !
b1101101011011111 ,
b0 &
b0 +
#173
b1010101010101111 !
b1010101010101111 ,
b1 &
b1 +
#174
b1011110111101111 !
b1011110111101111 ,
b10 &
b10 +
#175
b1001001000101 !
b1001001000101 ,
b11 &
b11 +
#176
b1101101011011111 !
b1101101011011111 ,
b0 &
b0 +
#177
b1010101010101111 !
b1010101010101111 ,
b1 &
b1 +
#178
b1011110111101111 !
b1011110111101111 ,
b10 &
b10 +
#179
b1001001000101 !
b1001001000101 ,
b11 &
b11 +
#180
b1101101011011111 !
b1101101011011111 ,
b0 &
b0 +
#181
b1010101010101111 !
b1010101010101111 ,
b1 &
b1 +
#182
b1011110111101111 !
b1011110111101111 ,
b10 &
b10 +
#183
b1001001000101 !
b1001001000101 ,
b11 &
b11 +
#184
b1101101011011111 !
b1101101011011111 ,
b0 &
b0 +
#185
b1010101010101111 !
b1010101010101111 ,
b1 &
b1 +
#186
b1011110111101111 !
b1011110111101111 ,
b10 &
b10 +
#187
b1001001000101 !
b1001001000101 ,
b11 &
b11 +
#188
b1101101011011111 !
b1101101011011111 ,
b0 &
b0 +
#189
b1010101010101111 !
b1010101010101111 ,
b1 &
b1 +
#190
b1011110111101111 !
b1011110111101111 ,
b10 &
b10 +
#191
b1001001000101 !
b1001001000101 ,
b11 &
b11 +
#192
b1101101011011111 !
b1101101011011111 ,
b0 &
b0 +
#193
b1010101010101111 !
b1010101010101111 ,
b1 &
b1 +
#194
b1011110111101111 !
b1011110111101111 ,
b10 &
b10 +
#195
b1001001000101 !
b1001001000101 ,
b11 &
b11 +
#196
b1101101011011111 !
b1101101011011111 ,
b0 &
b0 +
#197
b1010101010101111 !
b1010101010101111 ,
b1 &
b1 +
#198
b1011110111101111 !
b1011110111101111 ,
b10 &
b10 +
#199
b1001001000101 !
b1001001000101 ,
b11 &
b11 +
#200
b1101101011011111 !
b1101101011011111 ,
b0 &
b0 +
#201
b1010101010101111 !
b1010101010101111 ,
b1 &
b1 +
#202
b1011110111101111 !
b1011110111101111 ,
b10 &
b10 +
#203
b1001001000101 !
b1001001000101 ,
b11 &
b11 +
#204
b1101101011011111 !
b1101101011011111 ,
b0 &
b0 +
#205
b1010101010101111 !
b1010101010101111 ,
b1 &
b1 +
#206
b1011110111101111 !
b1011110111101111 ,
b10 &
b10 +
#207
b1001001000101 !
b1001001000101 ,
b11 &
b11 +
#208
b1101101011011111 !
b1101101011011111 ,
b0 &
b0 +
#209
b1010101010101111 !
b1010101010101111 ,
b1 &
b1 +
#210
b1011110111101111 !
b1011110111101111 ,
b10 &
b10 +
#211
b1001001000101 !
b1001001000101 ,
b11 &
b11 +
#212
b1101101011011111 !
b1101101011011111 ,
b0 &
b0 +
#213
b1010101010101111 !
b1010101010101111 ,
b1 &
b1 +
#214
b1011110111101111 !
b1011110111101111 ,
b10 &
b10 +
#215
b1001001000101 !
b1001001000101 ,
b11 &
b11 +
#216
b1101101011011111 !
b1101101011011111 ,
b0 &
b0 +
#217
b1010101010101111 !
b1010101010101111 ,
b1 &
b1 +
#218
b1011110111101111 !
b1011110111101111 ,
b10 &
b10 +
#219
b1001001000101 !
b1001001000101 ,
b11 &
b11 +
#220
b1101101011011111 !
b1101101011011111 ,
b0 &
b0 +
#221
b1010101010101111 !
b1010101010101111 ,
b1 &
b1 +
#222
b1011110111101111 !
b1011110111101111 ,
b10 &
b10 +
#223
b1001001000101 !
b1001001000101 ,
b11 &
b11 +
#224
b1101101011011111 !
b1101101011011111 ,
b0 &
b0 +
#225
b1010101010101111 !
b1010101010101111 ,
b1 &
b1 +
#226
b1011110111101111 !
b1011110111101111 ,
b10 &
b10 +
#227
b1001001000101 !
b1001001000101 ,
b11 &
b11 +
#228
b1101101011011111 !
b1101101011011111 ,
b0 &
b0 +
#229
b1010101010101111 !
b1010101010101111 ,
b1 &
b1 +
#230
b1011110111101111 !
b1011110111101111 ,
b10 &
b10 +
#231
b1001001000101 !
b1001001000101 ,
b11 &
b11 +
#232
b1101101011011111 !
b1101101011011111 ,
b0 &
b0 +
#233
b1010101010101111 !
b1010101010101111 ,
b1 &
b1 +
#234
b1011110111101111 !
b1011110111101111 ,
b10 &
b10 +
#235
b1001001000101 !
b1001001000101 ,
b11 &
b11 +
#236
b1101101011011111 !
b1101101011011111 ,
b0 &
b0 +
#237
b1010101010101111 !
b1010101010101111 ,
b1 &
b1 +
#238
b1011110111101111 !
b1011110111101111 ,
b10 &
b10 +
#239
b1001001000101 !
b1001001000101 ,
b11 &
b11 +
#240
b1101101011011111 !
b1101101011011111 ,
b0 &
b0 +
#241
b1010101010101111 !
b1010101010101111 ,
b1 &
b1 +
#242
b1011110111101111 !
b1011110111101111 ,
b10 &
b10 +
#243
b1001001000101 !
b1001001000101 ,
b11 &
b11 +
#244
b1101101011011111 !
b1101101011011111 ,
b0 &
b0 +
#245
b1010101010101111 !
b1010101010101111 ,
b1 &
b1 +
#246
b1011110111101111 !
b1011110111101111 ,
b10 &
b10 +
#247
b1001001000101 !
b1001001000101 ,
b11 &
b11 +
#248
b1101101011011111 !
b1101101011011111 ,
b0 &
b0 +
#249
b1010101010101111 !
b1010101010101111 ,
b1 &
b1 +
#250
b1011110111101111 !
b1011110111101111 ,
b10 &
b10 +
#251
b1001001000101 !
b1001001000101 ,
b11 &
b11 +
#252
b1101101011011111 !
b1101101011011111 ,
b0 &
b0 +
#253
b1010101010101111 !
b1010101010101111 ,
b1 &
b1 +
#254
b1011110111101111 !
b1011110111101111 ,
b10 &
b10 +
#255
b1001001000101 !
b1001001000101 ,
b11 &
b11 +
#256
b1101101011011111 !
b1101101011011111 ,
b0 &
b0 +
#257
b1010101010101111 !
b1010101010101111 ,
b1 &
b1 +
#258
b1011110111101111 !
b1011110111101111 ,
b10 &
b10 +
#259
b1001001000101 !
b1001001000101 ,
b11 &
b11 +
#260
b1101101011011111 !
b1101101011011111 ,
b0 &
b0 +
#261
b1010101010101111 !
b1010101010101111 ,
b1 &
b1 +
#262
b1011110111101111 !
b1011110111101111 ,
b10 &
b10 +
#263
b1001001000101 !
b1001001000101 ,
b11 &
b11 +
#264
b1101101011011111 !
b1101101011011111 ,
b0 &
b0 +
#265
b1010101010101111 !
b1010101010101111 ,
b1 &
b1 +
#266
b1011110111101111 !
b1011110111101111 ,
b10 &
b10 +
#267
b1001001000101 !
b1001001000101 ,
b11 &
b11 +
#268
b1101101011011111 !
b1101101011011111 ,
b0 &
b0 +
#269
b1010101010101111 !
b1010101010101111 ,
b1 &
b1 +
#270
b1011110111101111 !
b1011110111101111 ,
b10 &
b10 +
#271
b1001001000101 !
b1001001000101 ,
b11 &
b11 +
#272
b1101101011011111 !
b1101101011011111 ,
b0 &
b0 +
#273
b1010101010101111 !
b1010101010101111 ,
b1 &
b1 +
#274
b1011110111101111 !
b1011110111101111 ,
b10 &
b10 +
#275
b1001001000101 !
b1001001000101 ,
b11 &
b11 +
#276
b1101101011011111 !
b1101101011011111 ,
b0 &
b0 +
#277
b1010101010101111 !
b1010101010101111 ,
b1 &
b1 +
#278
b1011110111101111 !
b1011110111101111 ,
b10 &
b10 +
#279
b1001001000101 !
b1001001000101 ,
b11 &
b11 +
#280
b1101101011011111 !
b1101101011011111 ,
b0 &
b0 +
#281
b1010101010101111 !
b1010101010101111 ,
b1 &
b1 +
#282
b1011110111101111 !
b1011110111101111 ,
b10 &
b10 +
#283
b1001001000101 !
b1001001000101 ,
b11 &
b11 +
#284
b1101101011011111 !
b1101101011011111 ,
b0 &
b0 +
#285
b1010101010101111 !
b1010101010101111 ,
b1 &
b1 +
#286
b1011110111101111 !
b1011110111101111 ,
b10 &
b10 +
#287
b1001001000101 !
b1001001000101 ,
b11 &
b11 +
#288
b1101101011011111 !
b1101101011011111 ,
b0 &
b0 +
#289
b1010101010101111 !
b1010101010101111 ,
b1 &
b1 +
#290
b1011110111101111 !
b1011110111101111 ,
b10 &
b10 +
#291
b1001001000101 !
b1001001000101 ,
b11 &
b11 +
#292
b1101101011011111 !
b1101101011011111 ,
b0 &
b0 +
#293
b1010101010101111 !
b1010101010101111 ,
b1 &
b1 +
#294
b1011110111101111 !
b1011110111101111 ,
b10 &
b10 +
#295
b1001001000101 !
b1001001000101 ,
b11 &
b11 +
#296
b1101101011011111 !
b1101101011011111 ,
b0 &
b0 +
#297
b1010101010101111 !
b1010101010101111 ,
b1 &
b1 +
#298
b1011110111101111 !
b1011110111101111 ,
b10 &
b10 +
#299
b1001001000101 !
b1001001000101 ,
b11 &
b11 +
#300
b1101101011011111 !
b1101101011011111 ,
b0 &
b0 +
#301
b1010101010101111 !
b1010101010101111 ,
b1 &
b1 +
#302
b1011110111101111 !
b1011110111101111 ,
b10 &
b10 +
#303
b1001001000101 !
b1001001000101 ,
b11 &
b11 +
#304
b1101101011011111 !
b1101101011011111 ,
b0 &
b0 +
#305
b1010101010101111 !
b1010101010101111 ,
b1 &
b1 +
#306
b1011110111101111 !
b1011110111101111 ,
b10 &
b10 +
#307
b1001001000101 !
b1001001000101 ,
b11 &
b11 +
#308
b1101101011011111 !
b1101101011011111 ,
b0 &
b0 +
#309
b1010101010101111 !
b1010101010101111 ,
b1 &
b1 +
#310
b1011110111101111 !
b1011110111101111 ,
b10 &
b10 +
#311
b1001001000101 !
b1001001000101 ,
b11 &
b11 +
#312
b1101101011011111 !
b1101101011011111 ,
b0 &
b0 +
#313
b1010101010101111 !
b1010101010101111 ,
b1 &
b1 +
#314
b1011110111101111 !
b1011110111101111 ,
b10 &
b10 +
#315
b1001001000101 !
b1001001000101 ,
b11 &
b11 +
#316
b1101101011011111 !
b1101101011011111 ,
b0 &
b0 +
#317
b1010101010101111 !
b1010101010101111 ,
b1 &
b1 +
#318
b1011110111101111 !
b1011110111101111 ,
b10 &
b10 +
#319
b1001001000101 !
b1001001000101 ,
b11 &
b11 +
#320
b1101101011011111 !
b1101101011011111 ,
b0 &
b0 +
#321
b1010101010101111 !
b1010101010101111 ,
b1 &
b1 +
#322
b1011110111101111 !
b1011110111101111 ,
b10 &
b10 +
#323
b1001001000101 !
b1001001000101 ,
b11 &
b11 +
#324
b1101101011011111 !
b1101101011011111 ,
b0 &
b0 +
#325
b1010101010101111 !
b1010101010101111 ,
b1 &
b1 +
#326
b1011110111101111 !
b1011110111101111 ,
b10 &
b10 +
#327
b1001001000101 !
b1001001000101 ,
b11 &
b11 +
#328
b1101101011011111 !
b1101101011011111 ,
b0 &
b0 +
#329
b1010101010101111 !
b1010101010101111 ,
b1 &
b1 +
#330
b1011110111101111 !
b1011110111101111 ,
b10 &
b10 +
#331
b1001001000101 !
b1001001000101 ,
b11 &
b11 +
#332
b1101101011011111 !
b1101101011011111 ,
b0 &
b0 +
#333
b1010101010101111 !
b1010101010101111 ,
b1 &
b1 +
#334
b1011110111101111 !
b1011110111101111 ,
b10 &
b10 +
#335
b1001001000101 !
b1001001000101 ,
b11 &
b11 +
#336
b1101101011011111 !
b1101101011011111 ,
b0 &
b0 +
#337
b1010101010101111 !
b1010101010101111 ,
b1 &
b1 +
#338
b1011110111101111 !
b1011110111101111 ,
b10 &
b10 +
#339
b1001001000101 !
b1001001000101 ,
b11 &
b11 +
#340
b1101101011011111 !
b1101101011011111 ,
b0 &
b0 +
#341
b1010101010101111 !
b1010101010101111 ,
b1 &
b1 +
#342
b1011110111101111 !
b1011110111101111 ,
b10 &
b10 +
#343
b1001001000101 !
b1001001000101 ,
b11 &
b11 +
#344
b1101101011011111 !
b1101101011011111 ,
b0 &
b0 +
#345
b1010101010101111 !
b1010101010101111 ,
b1 &
b1 +
#346
b1011110111101111 !
b1011110111101111 ,
b10 &
b10 +
#347
b1001001000101 !
b1001001000101 ,
b11 &
b11 +
#348
b1101101011011111 !
b1101101011011111 ,
b0 &
b0 +
#349
b1010101010101111 !
b1010101010101111 ,
b1 &
b1 +
#350
b1011110111101111 !
b1011110111101111 ,
b10 &
b10 +
#351
b1001001000101 !
b1001001000101 ,
b11 &
b11 +
#352
b1101101011011111 !
b1101101011011111 ,
b0 &
b0 +
#353
b1010101010101111 !
b1010101010101111 ,
b1 &
b1 +
#354
b1011110111101111 !
b1011110111101111 ,
b10 &
b10 +
#355
b1001001000101 !
b1001001000101 ,
b11 &
b11 +
#356
b1101101011011111 !
b1101101011011111 ,
b0 &
b0 +
#357
b1010101010101111 !
b1010101010101111 ,
b1 &
b1 +
#358
b1011110111101111 !
b1011110111101111 ,
b10 &
b10 +
#359
b1001001000101 !
b1001001000101 ,
b11 &
b11 +
#360
b1101101011011111 !
b1101101011011111 ,
b0 &
b0 +
#361
b1010101010101111 !
b1010101010101111 ,
b1 &
b1 +
#362
b1011110111101111 !
b1011110111101111 ,
b10 &
b10 +
#363
b1001001000101 !
b1001001000101 ,
b11 &
b11 +
#364
b1101101011011111 !
b1101101011011111 ,
b0 &
b0 +
#365
b1010101010101111 !
b1010101010101111 ,
b1 &
b1 +
#366
b1011110111101111 !
b1011110111101111 ,
b10 &
b10 +
#367
b1001001000101 !
b1001001000101 ,
b11 &
b11 +
#368
b1101101011011111 !
b1101101011011111 ,
b0 &
b0 +
#369
b1010101010101111 !
b1010101010101111 ,
b1 &
b1 +
#370
b1011110111101111 !
b1011110111101111 ,
b10 &
b10 +
#371
b1001001000101 !
b1001001000101 ,
b11 &
b11 +
#372
b1101101011011111 !
b1101101011011111 ,
b0 &
b0 +
#373
b1010101010101111 !
b1010101010101111 ,
b1 &
b1 +
#374
b1011110111101111 !
b1011110111101111 ,
b10 &
b10 +
#375
b1001001000101 !
b1001001000101 ,
b11 &
b11 +
#376
b1101101011011111 !
b1101101011011111 ,
b0 &
b0 +
#377
b1010101010101111 !
b1010101010101111 ,
b1 &
b1 +
#378
b1011110111101111 !
b1011110111101111 ,
b10 &
b10 +
#379
b1001001000101 !
b1001001000101 ,
b11 &
b11 +
#380
b1101101011011111 !
b1101101011011111 ,
b0 &
b0 +
#381
b1010101010101111 !
b1010101010101111 ,
b1 &
b1 +
#382
b1011110111101111 !
b1011110111101111 ,
b10 &
b10 +
#383
b1001001000101 !
b1001001000101 ,
b11 &
b11 +
#384
b1101101011011111 !
b1101101011011111 ,
b0 &
b0 +
#385
b1010101010101111 !
b1010101010101111 ,
b1 &
b1 +
#386
b1011110111101111 !
b1011110111101111 ,
b10 &
b10 +
#387
b1001001000101 !
b1001001000101 ,
b11 &
b11 +
#388
b1101101011011111 !
b1101101011011111 ,
b0 &
b0 +
#389
b1010101010101111 !
b1010101010101111 ,
b1 &
b1 +
#390
b1011110111101111 !
b1011110111101111 ,
b10 &
b10 +
#391
b1001001000101 !
b1001001000101 ,
b11 &
b11 +
#392
b1101101011011111 !
b1101101011011111 ,
b0 &
b0 +
#393
b1010101010101111 !
b1010101010101111 ,
b1 &
b1 +
#394
b1011110111101111 !
b1011110111101111 ,
b10 &
b10 +
#395
b1001001000101 !
b1001001000101 ,
b11 &
b11 +
#396
b1101101011011111 !
b1101101011011111 ,
b0 &
b0 +
#397
b1010101010101111 !
b1010101010101111 ,
b1 &
b1 +
#398
b1011110111101111 !
b1011110111101111 ,
b10 &
b10 +
#399
b1001001000101 !
b1001001000101 ,
b11 &
b11 +
#400
b1101101011011111 !
b1101101011011111 ,
b0 &
b0 +
#401
b1010101010101111 !
b1010101010101111 ,
b1 &
b1 +
#402
b1011110111101111 !
b1011110111101111 ,
b10 &
b10 +
#403
b1001001000101 !
b1001001000101 ,
b11 &
b11 +
#404
b1101101011011111 !
b1101101011011111 ,
b0 &
b0 +
#405
b1010101010101111 !
b1010101010101111 ,
b1 &
b1 +
#406
b1011110111101111 !
b1011110111101111 ,
b10 &
b10 +
#407
b1001001000101 !
b1001001000101 ,
b11 &
b11 +
#408
b1101101011011111 !
b1101101011011111 ,
b0 &
b0 +
#409
b1010101010101111 !
b1010101010101111 ,
b1 &
b1 +
#410
b1011110111101111 !
b1011110111101111 ,
b10 &
b10 +
#411
b1001001000101 !
b1001001000101 ,
b11 &
b11 +
#412
b1101101011011111 !
b1101101011011111 ,
b0 &
b0 +
#413
b1010101010101111 !
b1010101010101111 ,
b1 &
b1 +
#414
b1011110111101111 !
b1011110111101111 ,
b10 &
b10 +
#415
b1001001000101 !
b1001001000101 ,
b11 &
b11 +
#416
b1101101011011111 !
b1101101011011111 ,
b0 &
b0 +
