muti_way_variants/Mux8Way16.v
module Mux8Way16 (
    input wire [7:0] [15:0] in,
    input wire [2:0] sel,
    output reg [15:0] out
);
    
    always @(*) begin
        case (sel)
            3'b000: out = in[0];
            3'b001: out = in[1];
            3'b010: out = in[2];
            3'b011: out = in[3];
            3'b100: out = in[4];
            3'b101: out = in[5];
            3'b110: out = in[6];
            3'b111: out = in[7];
            default: out = 16'h0000;
        endcase
    end
endmodule

muti_way_variants/Mux8Way16_tb.v
module Mux8Way16_tb;

    reg [7:0] [15:0] in;
    reg [2:0] sel = 0;
    wire [15:0] out;

    Mux8Way16 mux8way16 (in, sel, out);

    initial begin
        in[0] = 16'haabb;
        in[1] = 16'hccdd;
        in[2] = 16'h1122;
        in[3] = 16'h3344;
        in[4] = 16'h5566;
        in[5] = 16'h7788;
        in[6] = 16'h9900;
        in[7] = 16'h0000;
        
        $dumpfile("Mux8Way16.vcd");
        $dumpvars(0, Mux8Way16_tb);
        #1000 $finish;
    end

    always begin
        #1 if (sel == 3'b111) begin
            sel = 0;
        end else begin
            sel = sel + 1;
        end
        
    end
    
endmodule

muti_way_variants/Mux8Way16.vcd
$date
	Fri Aug 25 22:01:52 2023
$end
$version
	Icarus Verilog
$end
$timescale
	1s
$end
$scope module Mux8Way16_tb $end
$var wire 16 ! out [15:0] $end
$var reg 128 " in [127:0] $end
$var reg 3 # sel [2:0] $end
$scope module mux8way16 $end
$var wire 128 $ in [127:0] $end
$var wire 3 % sel [2:0] $end
$var reg 16 & out [15:0] $end
$upscope $end
$upscope $end
$enddefinitions $end
$comment Show the parameter values. $end
$dumpall
$end
#0
$dumpvars
b1010101010111011 &
b0 %
b1001100100000000011101111000100001010101011001100011001101000100000100010010001011001100110111011010101010111011 $
b0 #
b1001100100000000011101111000100001010101011001100011001101000100000100010010001011001100110111011010101010111011 "
b1010101010111011 !
$end
#1
b1100110011011101 !
b1100110011011101 &
b1 #
b1 %
#2
b1000100100010 !
b1000100100010 &
b10 #
b10 %
#3
b11001101000100 !
b11001101000100 &
b11 #
b11 %
#4
b101010101100110 !
b101010101100110 &
b100 #
b100 %
#5
b111011110001000 !
b111011110001000 &
b101 #
b101 %
#6
b1001100100000000 !
b1001100100000000 &
b110 #
b110 %
#7
b0 !
b0 &
b111 #
b111 %
#8
b1010101010111011 !
b1010101010111011 &
b0 #
b0 %
#9
b1100110011011101 !
b1100110011011101 &
b1 #
b1 %
#10
b1000100100010 !
b1000100100010 &
b10 #
b10 %
#11
b11001101000100 !
b11001101000100 &
b11 #
b11 %
#12
b101010101100110 !
b101010101100110 &
b100 #
b100 %
#13
b111011110001000 !
b111011110001000 &
b101 #
b101 %
#14
b1001100100000000 !
b1001100100000000 &
b110 #
b110 %
#15
b0 !
b0 &
b111 #
b111 %
#16
b1010101010111011 !
b1010101010111011 &
b0 #
b0 %
#17
b1100110011011101 !
b1100110011011101 &
b1 #
b1 %
#18
b1000100100010 !
b1000100100010 &
b10 #
b10 %
#19
b11001101000100 !
b11001101000100 &
b11 #
b11 %
#20
b101010101100110 !
b101010101100110 &
b100 #
b100 %
#21
b111011110001000 !
b111011110001000 &
b101 #
b101 %
#22
b1001100100000000 !
b1001100100000000 &
b110 #
b110 %
#23
b0 !
b0 &
b111 #
b111 %
#24
b1010101010111011 !
b1010101010111011 &
b0 #
b0 %
#25
b1100110011011101 !
b1100110011011101 &
b1 #
b1 %
#26
b1000100100010 !
b1000100100010 &
b10 #
b10 %
#27
b11001101000100 !
b11001101000100 &
b11 #
b11 %
#28
b101010101100110 !
b101010101100110 &
b100 #
b100 %
#29
b111011110001000 !
b111011110001000 &
b101 #
b101 %
#30
b1001100100000000 !
b1001100100000000 &
b110 #
b110 %
#31
b0 !
b0 &
b111 #
b111 %
#32
b1010101010111011 !
b1010101010111011 &
b0 #
b0 %
#33
b1100110011011101 !
b1100110011011101 &
b1 #
b1 %
#34
b1000100100010 !
b1000100100010 &
b10 #
b10 %
#35
b11001101000100 !
b11001101000100 &
b11 #
b11 %
#36
b101010101100110 !
b101010101100110 &
b100 #
b100 %
#37
b111011110001000 !
b111011110001000 &
b101 #
b101 %
#38
b1001100100000000 !
b1001100100000000 &
b110 #
b110 %
#39
b0 !
b0 &
b111 #
b111 %
#40
b1010101010111011 !
b1010101010111011 &
b0 #
b0 %
#41
b1100110011011101 !
b1100110011011101 &
b1 #
b1 %
#42
b1000100100010 !
b1000100100010 &
b10 #
b10 %
#43
b11001101000100 !
b11001101000100 &
b11 #
b11 %
#44
b101010101100110 !
b101010101100110 &
b100 #
b100 %
#45
b111011110001000 !
b111011110001000 &
b101 #
b101 %
#46
b1001100100000000 !
b1001100100000000 &
b110 #
b110 %
#47
b0 !
b0 &
b111 #
b111 %
#48
b1010101010111011 !
b1010101010111011 &
b0 #
b0 %
#49
b1100110011011101 !
b1100110011011101 &
b1 #
b1 %
#50
b1000100100010 !
b1000100100010 &
b10 #
b10 %
#51
b11001101000100 !
b11001101000100 &
b11 #
b11 %
#52
b101010101100110 !
b101010101100110 &
b100 #
b100 %
#53
b111011110001000 !
b111011110001000 &
b101 #
b101 %
#54
b1001100100000000 !
b1001100100000000 &
b110 #
b110 %
#55
b0 !
b0 &
b111 #
b111 %
#56
b1010101010111011 !
b1010101010111011 &
b0 #
b0 %
#57
b1100110011011101 !
b1100110011011101 &
b1 #
b1 %
#58
b1000100100010 !
b1000100100010 &
b10 #
b10 %
#59
b11001101000100 !
b11001101000100 &
b11 #
b11 %
#60
b101010101100110 !
b101010101100110 &
b100 #
b100 %
#61
b111011110001000 !
b111011110001000 &
b101 #
b101 %
#62
b1001100100000000 !
b1001100100000000 &
b110 #
b110 %
#63
b0 !
b0 &
b111 #
b111 %
#64
b1010101010111011 !
b1010101010111011 &
b0 #
b0 %
#65
b1100110011011101 !
b1100110011011101 &
b1 #
b1 %
#66
b1000100100010 !
b1000100100010 &
b10 #
b10 %
#67
b11001101000100 !
b11001101000100 &
b11 #
b11 %
#68
b101010101100110 !
b101010101100110 &
b100 #
b100 %
#69
b111011110001000 !
b111011110001000 &
b101 #
b101 %
#70
b1001100100000000 !
b1001100100000000 &
b110 #
b110 %
#71
b0 !
b0 &
b111 #
b111 %
#72
b1010101010111011 !
b1010101010111011 &
b0 #
b0 %
#73
b1100110011011101 !
b1100110011011101 &
b1 #
b1 %
#74
b1000100100010 !
b1000100100010 &
b10 #
b10 %
#75
b11001101000100 !
b11001101000100 &
b11 #
b11 %
#76
b101010101100110 !
b101010101100110 &
b100 #
b100 %
#77
b111011110001000 !
b111011110001000 &
b101 #
b101 %
#78
b1001100100000000 !
b1001100100000000 &
b110 #
b110 %
#79
b0 !
b0 &
b111 #
b111 %
#80
b1010101010111011 !
b1010101010111011 &
b0 #
b0 %
#81
b1100110011011101 !
b1100110011011101 &
b1 #
b1 %
#82
b1000100100010 !
b1000100100010 &
b10 #
b10 %
#83
b11001101000100 !
b11001101000100 &
b11 #
b11 %
#84
b101010101100110 !
b101010101100110 &
b100 #
b100 %
#85
b111011110001000 !
b111011110001000 &
b101 #
b101 %
#86
b1001100100000000 !
b1001100100000000 &
b110 #
b110 %
#87
b0 !
b0 &
b111 #
b111 %
#88
b1010101010111011 !
b1010101010111011 &
b0 #
b0 %
#89
b1100110011011101 !
b1100110011011101 &
b1 #
b1 %
#90
b1000100100010 !
b1000100100010 &
b10 #
b10 %
#91
b11001101000100 !
b11001101000100 &
b11 #
b11 %
#92
b101010101100110 !
b101010101100110 &
b100 #
b100 %
#93
b111011110001000 !
b111011110001000 &
b101 #
b101 %
#94
b1001100100000000 !
b1001100100000000 &
b110 #
b110 %
#95
b0 !
b0 &
b111 #
b111 %
#96
b1010101010111011 !
b1010101010111011 &
b0 #
b0 %
#97
b1100110011011101 !
b1100110011011101 &
b1 #
b1 %
#98
b1000100100010 !
b1000100100010 &
b10 #
b10 %
#99
b11001101000100 !
b11001101000100 &
b11 #
b11 %
#100
b101010101100110 !
b101010101100110 &
b100 #
b100 %
#101
b111011110001000 !
b111011110001000 &
b101 #
b101 %
#102
b1001100100000000 !
b1001100100000000 &
b110 #
b110 %
#103
b0 !
b0 &
b111 #
b111 %
#104
b1010101010111011 !
b1010101010111011 &
b0 #
b0 %
#105
b1100110011011101 !
b1100110011011101 &
b1 #
b1 %
#106
b1000100100010 !
b1000100100010 &
b10 #
b10 %
#107
b11001101000100 !
b11001101000100 &
b11 #
b11 %
#108
b101010101100110 !
b101010101100110 &
b100 #
b100 %
#109
b111011110001000 !
b111011110001000 &
b101 #
b101 %
#110
b1001100100000000 !
b1001100100000000 &
b110 #
b110 %
#111
b0 !
b0 &
b111 #
b111 %
#112
b1010101010111011 !
b1010101010111011 &
b0 #
b0 %
#113
b1100110011011101 !
b1100110011011101 &
b1 #
b1 %
#114
b1000100100010 !
b1000100100010 &
b10 #
b10 %
#115
b11001101000100 !
b11001101000100 &
b11 #
b11 %
#116
b101010101100110 !
b101010101100110 &
b100 #
b100 %
#117
b111011110001000 !
b111011110001000 &
b101 #
b101 %
#118
b1001100100000000 !
b1001100100000000 &
b110 #
b110 %
#119
b0 !
b0 &
b111 #
b111 %
#120
b1010101010111011 !
b1010101010111011 &
b0 #
b0 %
#121
b1100110011011101 !
b1100110011011101 &
b1 #
b1 %
#122
b1000100100010 !
b1000100100010 &
b10 #
b10 %
#123
b11001101000100 !
b11001101000100 &
b11 #
b11 %
#124
b101010101100110 !
b101010101100110 &
b100 #
b100 %
#125
b111011110001000 !
b111011110001000 &
b101 #
b101 %
#126
b1001100100000000 !
b1001100100000000 &
b110 #
b110 %
#127
b0 !
b0 &
b111 #
b111 %
#128
b1010101010111011 !
b1010101010111011 &
b0 #
b0 %
#129
b1100110011011101 !
b1100110011011101 &
b1 #
b1 %
#130
b1000100100010 !
b1000100100010 &
b10 #
b10 %
#131
b11001101000100 !
b11001101000100 &
b11 #
b11 %
#132
b101010101100110 !
b101010101100110 &
b100 #
b100 %
#133
b111011110001000 !
b111011110001000 &
b101 #
b101 %
#134
b1001100100000000 !
b1001100100000000 &
b110 #
b110 %
#135
b0 !
b0 &
b111 #
b111 %
#136
b1010101010111011 !
b1010101010111011 &
b0 #
b0 %
#137
b1100110011011101 !
b1100110011011101 &
b1 #
b1 %
#138
b1000100100010 !
b1000100100010 &
b10 #
b10 %
#139
b11001101000100 !
b11001101000100 &
b11 #
b11 %
#140
b101010101100110 !
b101010101100110 &
b100 #
b100 %
#141
b111011110001000 !
b111011110001000 &
b101 #
b101 %
#142
b1001100100000000 !
b1001100100000000 &
b110 #
b110 %
#143
b0 !
b0 &
b111 #
b111 %
#144
b1010101010111011 !
b1010101010111011 &
b0 #
b0 %
#145
b1100110011011101 !
b1100110011011101 &
b1 #
b1 %
#146
b1000100100010 !
b1000100100010 &
b10 #
b10 %
#147
b11001101000100 !
b11001101000100 &
b11 #
b11 %
#148
b101010101100110 !
b101010101100110 &
b100 #
b100 %
#149
b111011110001000 !
b111011110001000 &
b101 #
b101 %
#150
b1001100100000000 !
b1001100100000000 &
b110 #
b110 %
#151
b0 !
b0 &
b111 #
b111 %
#152
b1010101010111011 !
b1010101010111011 &
b0 #
b0 %
#153
b1100110011011101 !
b1100110011011101 &
b1 #
b1 %
#154
b1000100100010 !
b1000100100010 &
b10 #
b10 %
#155
b11001101000100 !
b11001101000100 &
b11 #
b11 %
#156
b101010101100110 !
b101010101100110 &
b100 #
b100 %
#157
b111011110001000 !
b111011110001000 &
b101 #
b101 %
#158
b1001100100000000 !
b1001100100000000 &
b110 #
b110 %
#159
b0 !
b0 &
b111 #
b111 %
#160
b1010101010111011 !
b1010101010111011 &
b0 #
b0 %
#161
b1100110011011101 !
b1100110011011101 &
b1 #
b1 %
#162
b1000100100010 !
b1000100100010 &
b10 #
b10 %
#163
b11001101000100 !
b11001101000100 &
b11 #
b11 %
#164
b101010101100110 !
b101010101100110 &
b100 #
b100 %
#165
b111011110001000 !
b111011110001000 &
b101 #
b101 %
#166
b1001100100000000 !
b1001100100000000 &
b110 #
b110 %
#167
b0 !
b0 &
b111 #
b111 %
#168
b1010101010111011 !
b1010101010111011 &
b0 #
b0 %
#169
b1100110011011101 !
b1100110011011101 &
b1 #
b1 %
#170
b1000100100010 !
b1000100100010 &
b10 #
b10 %
#171
b11001101000100 !
b11001101000100 &
b11 #
b11 %
#172
b101010101100110 !
b101010101100110 &
b100 #
b100 %
#173
b111011110001000 !
b111011110001000 &
b101 #
b101 %
#174
b1001100100000000 !
b1001100100000000 &
b110 #
b110 %
#175
b0 !
b0 &
b111 #
b111 %
#176
b1010101010111011 !
b1010101010111011 &
b0 #
b0 %
#177
b1100110011011101 !
b1100110011011101 &
b1 #
b1 %
#178
b1000100100010 !
b1000100100010 &
b10 #
b10 %
#179
b11001101000100 !
b11001101000100 &
b11 #
b11 %
#180
b101010101100110 !
b101010101100110 &
b100 #
b100 %
#181
b111011110001000 !
b111011110001000 &
b101 #
b101 %
#182
b1001100100000000 !
b1001100100000000 &
b110 #
b110 %
#183
b0 !
b0 &
b111 #
b111 %
#184
b1010101010111011 !
b1010101010111011 &
b0 #
b0 %
#185
b1100110011011101 !
b1100110011011101 &
b1 #
b1 %
#186
b1000100100010 !
b1000100100010 &
b10 #
b10 %
#187
b11001101000100 !
b11001101000100 &
b11 #
b11 %
#188
b101010101100110 !
b101010101100110 &
b100 #
b100 %
#189
b111011110001000 !
b111011110001000 &
b101 #
b101 %
#190
b1001100100000000 !
b1001100100000000 &
b110 #
b110 %
#191
b0 !
b0 &
b111 #
b111 %
#192
b1010101010111011 !
b1010101010111011 &
b0 #
b0 %
#193
b1100110011011101 !
b1100110011011101 &
b1 #
b1 %
#194
b1000100100010 !
b1000100100010 &
b10 #
b10 %
#195
b11001101000100 !
b11001101000100 &
b11 #
b11 %
#196
b101010101100110 !
b101010101100110 &
b100 #
b100 %
#197
b111011110001000 !
b111011110001000 &
b101 #
b101 %
#198
b1001100100000000 !
b1001100100000000 &
b110 #
b110 %
#199
b0 !
b0 &
b111 #
b111 %
#200
b1010101010111011 !
b1010101010111011 &
b0 #
b0 %
#201
b1100110011011101 !
b1100110011011101 &
b1 #
b1 %
#202
b1000100100010 !
b1000100100010 &
b10 #
b10 %
#203
b11001101000100 !
b11001101000100 &
b11 #
b11 %
#204
b101010101100110 !
b101010101100110 &
b100 #
b100 %
#205
b111011110001000 !
b111011110001000 &
b101 #
b101 %
#206
b1001100100000000 !
b1001100100000000 &
b110 #
b110 %
#207
b0 !
b0 &
b111 #
b111 %
#208
b1010101010111011 !
b1010101010111011 &
b0 #
b0 %
#209
b1100110011011101 !
b1100110011011101 &
b1 #
b1 %
#210
b1000100100010 !
b1000100100010 &
b10 #
b10 %
#211
b11001101000100 !
b11001101000100 &
b11 #
b11 %
#212
b101010101100110 !
b101010101100110 &
b100 #
b100 %
#213
b111011110001000 !
b111011110001000 &
b101 #
b101 %
#214
b1001100100000000 !
b1001100100000000 &
b110 #
b110 %
#215
b0 !
b0 &
b111 #
b111 %
#216
b1010101010111011 !
b1010101010111011 &
b0 #
b0 %
#217
b1100110011011101 !
b1100110011011101 &
b1 #
b1 %
#218
b1000100100010 !
b1000100100010 &
b10 #
b10 %
#219
b11001101000100 !
b11001101000100 &
b11 #
b11 %
#220
b101010101100110 !
b101010101100110 &
b100 #
b100 %
#221
b111011110001000 !
b111011110001000 &
b101 #
b101 %
#222
b1001100100000000 !
b1001100100000000 &
b110 #
b110 %
#223
b0 !
b0 &
b111 #
b111 %
#224
b1010101010111011 !
b1010101010111011 &
b0 #
b0 %
#225
b1100110011011101 !
b1100110011011101 &
b1 #
b1 %
#226
b1000100100010 !
b1000100100010 &
b10 #
b10 %
#227
b11001101000100 !
b11001101000100 &
b11 #
b11 %
#228
b101010101100110 !
b101010101100110 &
b100 #
b100 %
#229
b111011110001000 !
b111011110001000 &
b101 #
b101 %
#230
b1001100100000000 !
b1001100100000000 &
b110 #
b110 %
#231
b0 !
b0 &
b111 #
b111 %
#232
b1010101010111011 !
b1010101010111011 &
b0 #
b0 %
#233
b1100110011011101 !
b1100110011011101 &
b1 #
b1 %
#234
b1000100100010 !
b1000100100010 &
b10 #
b10 %
#235
b11001101000100 !
b11001101000100 &
b11 #
b11 %
#236
b101010101100110 !
b101010101100110 &
b100 #
b100 %
#237
b111011110001000 !
b111011110001000 &
b101 #
b101 %
#238
b1001100100000000 !
b1001100100000000 &
b110 #
b110 %
#239
b0 !
b0 &
b111 #
b111 %
#240
b1010101010111011 !
b1010101010111011 &
b0 #
b0 %
#241
b1100110011011101 !
b1100110011011101 &
b1 #
b1 %
#242
b1000100100010 !
b1000100100010 &
b10 #
b10 %
#243
b11001101000100 !
b11001101000100 &
b11 #
b11 %
#244
b101010101100110 !
b101010101100110 &
b100 #
b100 %
#245
b111011110001000 !
b111011110001000 &
b101 #
b101 %
#246
b1001100100000000 !
b1001100100000000 &
b110 #
b110 %
#247
b0 !
b0 &
b111 #
b111 %
#248
b1010101010111011 !
b1010101010111011 &
b0 #
b0 %
#249
b1100110011011101 !
b1100110011011101 &
b1 #
b1 %
#250
b1000100100010 !
b1000100100010 &
b10 #
b10 %
#251
b11001101000100 !
b11001101000100 &
b11 #
b11 %
#252
b101010101100110 !
b101010101100110 &
b100 #
b100 %
#253
b111011110001000 !
b111011110001000 &
b101 #
b101 %
#254
b1001100100000000 !
b1001100100000000 &
b110 #
b110 %
#255
b0 !
b0 &
b111 #
b111 %
#256
b1010101010111011 !
b1010101010111011 &
b0 #
b0 %
#257
b1100110011011101 !
b1100110011011101 &
b1 #
b1 %
#258
b1000100100010 !
b1000100100010 &
b10 #
b10 %
#259
b11001101000100 !
b11001101000100 &
b11 #
b11 %
#260
b101010101100110 !
b101010101100110 &
b100 #
b100 %
#261
b111011110001000 !
b111011110001000 &
b101 #
b101 %
#262
b1001100100000000 !
b1001100100000000 &
b110 #
b110 %
#263
b0 !
b0 &
b111 #
b111 %
#264
b1010101010111011 !
b1010101010111011 &
b0 #
b0 %
#265
b1100110011011101 !
b1100110011011101 &
b1 #
b1 %
#266
b1000100100010 !
b1000100100010 &
b10 #
b10 %
#267
b11001101000100 !
b11001101000100 &
b11 #
b11 %
#268
b101010101100110 !
b101010101100110 &
b100 #
b100 %
#269
b111011110001000 !
b111011110001000 &
b101 #
b101 %
#270
b1001100100000000 !
b1001100100000000 &
b110 #
b110 %
#271
b0 !
b0 &
b111 #
b111 %
#272
b1010101010111011 !
b1010101010111011 &
b0 #
b0 %
#273
b1100110011011101 !
b1100110011011101 &
b1 #
b1 %
#274
b1000100100010 !
b1000100100010 &
b10 #
b10 %
#275
b11001101000100 !
b11001101000100 &
b11 #
b11 %
#276
b101010101100110 !
b101010101100110 &
b100 #
b100 %
#277
b111011110001000 !
b111011110001000 &
b101 #
b101 %
#278
b1001100100000000 !
b1001100100000000 &
b110 #
b110 %
#279
b0 !
b0 &
b111 #
b111 %
#280
b1010101010111011 !
b1010101010111011 &
b0 #
b0 %
#281
b1100110011011101 !
b1100110011011101 &
b1 #
b1 %
#282
b1000100100010 !
b1000100100010 &
b10 #
b10 %
#283
b11001101000100 !
b11001101000100 &
b11 #
b11 %
#284
b101010101100110 !
b101010101100110 &
b100 #
b100 %
#285
b111011110001000 !
b111011110001000 &
b101 #
b101 %
#286
b1001100100000000 !
b1001100100000000 &
b110 #
b110 %
#287
b0 !
b0 &
b111 #
b111 %
#288
b1010101010111011 !
b1010101010111011 &
b0 #
b0 %
#289
b1100110011011101 !
b1100110011011101 &
b1 #
b1 %
#290
b1000100100010 !
b1000100100010 &
b10 #
b10 %
#291
b11001101000100 !
b11001101000100 &
b11 #
b11 %
#292
b101010101100110 !
b101010101100110 &
b100 #
b100 %
#293
b111011110001000 !
b111011110001000 &
b101 #
b101 %
#294
b1001100100000000 !
b1001100100000000 &
b110 #
b110 %
#295
b0 !
b0 &
b111 #
b111 %
#296
b1010101010111011 !
b1010101010111011 &
b0 #
b0 %
#297
b1100110011011101 !
b1100110011011101 &
b1 #
b1 %
#298
b1000100100010 !
b1000100100010 &
b10 #
b10 %
#299
b11001101000100 !
b11001101000100 &
b11 #
b11 %
#300
b101010101100110 !
b101010101100110 &
b100 #
b100 %
#301
b111011110001000 !
b111011110001000 &
b101 #
b101 %
#302
b1001100100000000 !
b1001100100000000 &
b110 #
b110 %
#303
b0 !
b0 &
b111 #
b111 %
#304
b1010101010111011 !
b1010101010111011 &
b0 #
b0 %
#305
b1100110011011101 !
b1100110011011101 &
b1 #
b1 %
#306
b1000100100010 !
b1000100100010 &
b10 #
b10 %
#307
b11001101000100 !
b11001101000100 &
b11 #
b11 %
#308
b101010101100110 !
b101010101100110 &
b100 #
b100 %
#309
b111011110001000 !
b111011110001000 &
b101 #
b101 %
#310
b1001100100000000 !
b1001100100000000 &
b110 #
b110 %
#311
b0 !
b0 &
b111 #
b111 %
#312
b1010101010111011 !
b1010101010111011 &
b0 #
b0 %
#313
b1100110011011101 !
b1100110011011101 &
b1 #
b1 %
#314
b1000100100010 !
b1000100100010 &
b10 #
b10 %
#315
b11001101000100 !
b11001101000100 &
b11 #
b11 %
#316
b101010101100110 !
b101010101100110 &
b100 #
b100 %
#317
b111011110001000 !
b111011110001000 &
b101 #
b101 %
#318
b1001100100000000 !
b1001100100000000 &
b110 #
b110 %
#319
b0 !
b0 &
b111 #
b111 %
#320
b1010101010111011 !
b1010101010111011 &
b0 #
b0 %
#321
b1100110011011101 !
b1100110011011101 &
b1 #
b1 %
#322
b1000100100010 !
b1000100100010 &
b10 #
b10 %
#323
b11001101000100 !
b11001101000100 &
b11 #
b11 %
#324
b101010101100110 !
b101010101100110 &
b100 #
b100 %
#325
b111011110001000 !
b111011110001000 &
b101 #
b101 %
#326
b1001100100000000 !
b1001100100000000 &
b110 #
b110 %
#327
b0 !
b0 &
b111 #
b111 %
#328
b1010101010111011 !
b1010101010111011 &
b0 #
b0 %
#329
b1100110011011101 !
b1100110011011101 &
b1 #
b1 %
#330
b1000100100010 !
b1000100100010 &
b10 #
b10 %
#331
b11001101000100 !
b11001101000100 &
b11 #
b11 %
#332
b101010101100110 !
b101010101100110 &
b100 #
b100 %
#333
b111011110001000 !
b111011110001000 &
b101 #
b101 %
#334
b1001100100000000 !
b1001100100000000 &
b110 #
b110 %
#335
b0 !
b0 &
b111 #
b111 %
#336
b1010101010111011 !
b1010101010111011 &
b0 #
b0 %
#337
b1100110011011101 !
b1100110011011101 &
b1 #
b1 %
#338
b1000100100010 !
b1000100100010 &
b10 #
b10 %
#339
b11001101000100 !
b11001101000100 &
b11 #
b11 %
#340
b101010101100110 !
b101010101100110 &
b100 #
b100 %
#341
b111011110001000 !
b111011110001000 &
b101 #
b101 %
#342
b1001100100000000 !
b1001100100000000 &
b110 #
b110 %
#343
b0 !
b0 &
b111 #
b111 %
#344
b1010101010111011 !
b1010101010111011 &
b0 #
b0 %
#345
b1100110011011101 !
b1100110011011101 &
b1 #
b1 %
#346
b1000100100010 !
b1000100100010 &
b10 #
b10 %
#347
b11001101000100 !
b11001101000100 &
b11 #
b11 %
#348
b101010101100110 !
b101010101100110 &
b100 #
b100 %
#349
b111011110001000 !
b111011110001000 &
b101 #
b101 %
#350
b1001100100000000 !
b1001100100000000 &
b110 #
b110 %
#351
b0 !
b0 &
b111 #
b111 %
#352
b1010101010111011 !
b1010101010111011 &
b0 #
b0 %
#353
b1100110011011101 !
b1100110011011101 &
b1 #
b1 %
#354
b1000100100010 !
b1000100100010 &
b10 #
b10 %
#355
b11001101000100 !
b11001101000100 &
b11 #
b11 %
#356
b101010101100110 !
b101010101100110 &
b100 #
b100 %
#357
b111011110001000 !
b111011110001000 &
b101 #
b101 %
#358
b1001100100000000 !
b1001100100000000 &
b110 #
b110 %
#359
b0 !
b0 &
b111 #
b111 %
#360
b1010101010111011 !
b1010101010111011 &
b0 #
b0 %
#361
b1100110011011101 !
b1100110011011101 &
b1 #
b1 %
#362
b1000100100010 !
b1000100100010 &
b10 #
b10 %
#363
b11001101000100 !
b11001101000100 &
b11 #
b11 %
#364
b101010101100110 !
b101010101100110 &
b100 #
b100 %
#365
b111011110001000 !
b111011110001000 &
b101 #
b101 %
#366
b1001100100000000 !
b1001100100000000 &
b110 #
b110 %
#367
b0 !
b0 &
b111 #
b111 %
#368
b1010101010111011 !
b1010101010111011 &
b0 #
b0 %
#369
b1100110011011101 !
b1100110011011101 &
b1 #
b1 %
#370
b1000100100010 !
b1000100100010 &
b10 #
b10 %
#371
b11001101000100 !
b11001101000100 &
b11 #
b11 %
#372
b101010101100110 !
b101010101100110 &
b100 #
b100 %
#373
b111011110001000 !
b111011110001000 &
b101 #
b101 %
#374
b1001100100000000 !
b1001100100000000 &
b110 #
b110 %
#375
b0 !
b0 &
b111 #
b111 %
#376
b1010101010111011 !
b1010101010111011 &
b0 #
b0 %
#377
b1100110011011101 !
b1100110011011101 &
b1 #
b1 %
#378
b1000100100010 !
b1000100100010 &
b10 #
b10 %
#379
b11001101000100 !
b11001101000100 &
b11 #
b11 %
#380
b101010101100110 !
b101010101100110 &
b100 #
b100 %
#381
b111011110001000 !
b111011110001000 &
b101 #
b101 %
#382
b1001100100000000 !
b1001100100000000 &
b110 #
b110 %
#383
b0 !
b0 &
b111 #
b111 %
#384
b1010101010111011 !
b1010101010111011 &
b0 #
b0 %
#385
b1100110011011101 !
b1100110011011101 &
b1 #
b1 %
#386
b1000100100010 !
b1000100100010 &
b10 #
b10 %
#387
b11001101000100 !
b11001101000100 &
b11 #
b11 %
#388
b101010101100110 !
b101010101100110 &
b100 #
b100 %
#389
b111011110001000 !
b111011110001000 &
b101 #
b101 %
#390
b1001100100000000 !
b1001100100000000 &
b110 #
b110 %
#391
b0 !
b0 &
b111 #
b111 %
#392
b1010101010111011 !
b1010101010111011 &
b0 #
b0 %
#393
b1100110011011101 !
b1100110011011101 &
b1 #
b1 %
#394
b1000100100010 !
b1000100100010 &
b10 #
b10 %
#395
b11001101000100 !
b11001101000100 &
b11 #
b11 %
#396
b101010101100110 !
b101010101100110 &
b100 #
b100 %
#397
b111011110001000 !
b111011110001000 &
b101 #
b101 %
#398
b1001100100000000 !
b1001100100000000 &
b110 #
b110 %
#399
b0 !
b0 &
b111 #
b111 %
#400
b1010101010111011 !
b1010101010111011 &
b0 #
b0 %
#401
b1100110011011101 !
b1100110011011101 &
b1 #
b1 %
#402
b1000100100010 !
b1000100100010 &
b10 #
b10 %
#403
b11001101000100 !
b11001101000100 &
b11 #
b11 %
#404
b101010101100110 !
b101010101100110 &
b100 #
b100 %
#405
b111011110001000 !
b111011110001000 &
b101 #
b101 %
#406
b1001100100000000 !
b1001100100000000 &
b110 #
b110 %
#407
b0 !
b0 &
b111 #
b111 %
#408
b1010101010111011 !
b1010101010111011 &
b0 #
b0 %
#409
b1100110011011101 !
b1100110011011101 &
b1 #
b1 %
#410
b1000100100010 !
b1000100100010 &
b10 #
b10 %
#411
b11001101000100 !
b11001101000100 &
b11 #
b11 %
#412
b101010101100110 !
b101010101100110 &
b100 #
b100 %
#413
b111011110001000 !
b111011110001000 &
b101 #
b101 %
#414
b1001100100000000 !
b1001100100000000 &
b110 #
b110 %
#415
b0 !
b0 &
b111 #
b111 %
#416
b1010101010111011 !
b1010101010111011 &
b0 #
b0 %
#417
b1100110011011101 !
b1100110011011101 &
b1 #
b1 %
#418
b1000100100010 !
b1000100100010 &
b10 #
b10 %
#419
b11001101000100 !
b11001101000100 &
b11 #
b11 %
#420
b101010101100110 !
b101010101100110 &
b100 #
b100 %
#421
b111011110001000 !
b111011110001000 &
b101 #
b101 %
#422
b1001100100000000 !
b1001100100000000 &
b110 #
b110 %
#423
b0 !
b0 &
b111 #
b111 %
#424
b1010101010111011 !
b1010101010111011 &
b0 #
b0 %
#425
b1100110011011101 !
b1100110011011101 &
b1 #
b1 %
#426
b1000100100010 !
b1000100100010 &
b10 #
b10 %
#427
b11001101000100 !
b11001101000100 &
b11 #
b11 %
#428
b101010101100110 !
b101010101100110 &
b100 #
b100 %
#429
b111011110001000 !
b111011110001000 &
b101 #
b101 %
#430
b1001100100000000 !
b1001100100000000 &
b110 #
b110 %
#431
b0 !
b0 &
b111 #
b111 %
#432
b1010101010111011 !
b1010101010111011 &
b0 #
b0 %
#433
b1100110011011101 !
b1100110011011101 &
b1 #
b1 %
#434
b1000100100010 !
b1000100100010 &
b10 #
b10 %
#435
b11001101000100 !
b11001101000100 &
b11 #
b11 %
#436
b101010101100110 !
b101010101100110 &
b100 #
b100 %
#437
b111011110001000 !
b111011110001000 &
b101 #
b101 %
#438
b1001100100000000 !
b1001100100000000 &
b110 #
b110 %
#439
b0 !
b0 &
b111 #
b111 %
#440
b1010101010111011 !
b1010101010111011 &
b0 #
b0 %
#441
b1100110011011101 !
b1100110011011101 &
b1 #
b1 %
#442
b1000100100010 !
b1000100100010 &
b10 #
b10 %
#443
b11001101000100 !
b11001101000100 &
b11 #
b11 %
#444
b101010101100110 !
b101010101100110 &
b100 #
b100 %
#445
b111011110001000 !
b111011110001000 &
b101 #
b101 %
#446
b1001100100000000 !
b1001100100000000 &
b110 #
b110 %
#447
b0 !
b0 &
b111 #
b111 %
#448
b1010101010111011 !
b1010101010111011 &
b0 #
b0 %
#449
b1100110011011101 !
b1100110011011101 &
b1 #
b1 %
#450
b1000100100010 !
b1000100100010 &
b10 #
b10 %
#451
b11001101000100 !
b11001101000100 &
b11 #
b11 %
#452
b101010101100110 !
b101010101100110 &
b100 #
b100 %
#453
b111011110001000 !
b111011110001000 &
b101 #
b101 %
#454
b1001100100000000 !
b1001100100000000 &
b110 #
b110 %
#455
b0 !
b0 &
b111 #
b111 %
#456
b1010101010111011 !
b1010101010111011 &
b0 #
b0 %
#457
b1100110011011101 !
b1100110011011101 &
b1 #
b1 %
