16_bit_variants/Mux16.v
module Mux16(
    input wire [15:0] a1, a2,
    input wire sel,
    output reg [15:0] o
);

    always @(*) begin
        if (sel == 0) begin
            o = a1;
        end else begin
            o = a2;
        end
    end
    
endmodule

16_bit_variants/Mux16_tb.v
module Mux16_tb;
    
    reg [15:0] a1 = 16'h0000, a2 = 16'h0000;
    reg sel = 0;
    wire [15:0] o;

    Mux16 mux16(.a1(a1), .a2(a2), .sel(sel), .o(o));

    always begin
        #1
        sel = ~sel;
    end

    always begin
        #2
        if (a1 == 16'hffff) begin
            a1 = 16'h0000;
        end else begin
            a1 = a1 + 1;
        end
    end

    always begin
        #4
        if (a2 == 16'hffff) begin
            a2 = 16'h0000;
        end else begin
            a2 = a2 + 1;
        end
    end

    initial begin
        $dumpfile("Mux16.vcd");
        $dumpvars(0, Mux16_tb);
        #1000 $finish;
    end



endmodule

16_bit_variants/Mux16.vcd
$date
	Fri Aug 25 16:31:32 2023
$end
$version
	Icarus Verilog
$end
$timescale
	1s
$end
$scope module Mux16_tb $end
$var wire 16 ! o [15:0] $end
$var reg 16 " a1 [15:0] $end
$var reg 16 # a2 [15:0] $end
$var reg 1 $ sel $end
$scope module mux16 $end
$var wire 16 % a1 [15:0] $end
$var wire 16 & a2 [15:0] $end
$var wire 1 $ sel $end
$var reg 16 ' o [15:0] $end
$upscope $end
$upscope $end
$enddefinitions $end
$comment Show the parameter values. $end
$dumpall
$end
#0
$dumpvars
b0 '
b0 &
b0 %
0$
b0 #
b0 "
b0 !
$end
#1
1$
#2
b1 !
b1 '
0$
b1 "
b1 %
#3
b0 !
b0 '
1$
#4
b10 !
b10 '
0$
b10 "
b10 %
b1 #
b1 &
#5
b1 !
b1 '
1$
#6
b11 !
b11 '
0$
b11 "
b11 %
#7
b1 !
b1 '
1$
#8
b100 !
b100 '
0$
b100 "
b100 %
b10 #
b10 &
#9
b10 !
b10 '
1$
#10
b101 !
b101 '
0$
b101 "
b101 %
#11
b10 !
b10 '
1$
#12
b110 !
b110 '
0$
b110 "
b110 %
b11 #
b11 &
#13
b11 !
b11 '
1$
#14
b111 !
b111 '
0$
b111 "
b111 %
#15
b11 !
b11 '
1$
#16
b1000 !
b1000 '
0$
b1000 "
b1000 %
b100 #
b100 &
#17
b100 !
b100 '
1$
#18
b1001 !
b1001 '
0$
b1001 "
b1001 %
#19
b100 !
b100 '
1$
#20
b1010 !
b1010 '
0$
b1010 "
b1010 %
b101 #
b101 &
#21
b101 !
b101 '
1$
#22
b1011 !
b1011 '
0$
b1011 "
b1011 %
#23
b101 !
b101 '
1$
#24
b1100 !
b1100 '
0$
b1100 "
b1100 %
b110 #
b110 &
#25
b110 !
b110 '
1$
#26
b1101 !
b1101 '
0$
b1101 "
b1101 %
#27
b110 !
b110 '
1$
#28
b1110 !
b1110 '
0$
b1110 "
b1110 %
b111 #
b111 &
#29
b111 !
b111 '
1$
#30
b1111 !
b1111 '
0$
b1111 "
b1111 %
#31
b111 !
b111 '
1$
#32
b10000 !
b10000 '
0$
b10000 "
b10000 %
b1000 #
b1000 &
#33
b1000 !
b1000 '
1$
#34
b10001 !
b10001 '
0$
b10001 "
b10001 %
#35
b1000 !
b1000 '
1$
#36
b10010 !
b10010 '
0$
b10010 "
b10010 %
b1001 #
b1001 &
#37
b1001 !
b1001 '
1$
#38
b10011 !
b10011 '
0$
b10011 "
b10011 %
#39
b1001 !
b1001 '
1$
#40
b10100 !
b10100 '
0$
b10100 "
b10100 %
b1010 #
b1010 &
#41
b1010 !
b1010 '
1$
#42
b10101 !
b10101 '
0$
b10101 "
b10101 %
#43
b1010 !
b1010 '
1$
#44
b10110 !
b10110 '
0$
b10110 "
b10110 %
b1011 #
b1011 &
#45
b1011 !
b1011 '
1$
#46
b10111 !
b10111 '
0$
b10111 "
b10111 %
#47
b1011 !
b1011 '
1$
#48
b11000 !
b11000 '
0$
b11000 "
b11000 %
b1100 #
b1100 &
#49
b1100 !
b1100 '
1$
#50
b11001 !
b11001 '
0$
b11001 "
b11001 %
#51
b1100 !
b1100 '
1$
#52
b11010 !
b11010 '
0$
b11010 "
b11010 %
b1101 #
b1101 &
#53
b1101 !
b1101 '
1$
#54
b11011 !
b11011 '
0$
b11011 "
b11011 %
#55
b1101 !
b1101 '
1$
#56
b11100 !
b11100 '
0$
b11100 "
b11100 %
b1110 #
b1110 &
#57
b1110 !
b1110 '
1$
#58
b11101 !
b11101 '
0$
b11101 "
b11101 %
#59
b1110 !
b1110 '
1$
#60
b11110 !
b11110 '
0$
b11110 "
b11110 %
b1111 #
b1111 &
#61
b1111 !
b1111 '
1$
#62
b11111 !
b11111 '
0$
b11111 "
b11111 %
#63
b1111 !
b1111 '
1$
#64
b100000 !
b100000 '
0$
b100000 "
b100000 %
b10000 #
b10000 &
#65
b10000 !
b10000 '
1$
#66
b100001 !
b100001 '
0$
b100001 "
b100001 %
#67
b10000 !
b10000 '
1$
#68
b100010 !
b100010 '
0$
b100010 "
b100010 %
b10001 #
b10001 &
#69
b10001 !
b10001 '
1$
#70
b100011 !
b100011 '
0$
b100011 "
b100011 %
#71
b10001 !
b10001 '
1$
#72
b100100 !
b100100 '
0$
b100100 "
b100100 %
b10010 #
b10010 &
#73
b10010 !
b10010 '
1$
#74
b100101 !
b100101 '
0$
b100101 "
b100101 %
#75
b10010 !
b10010 '
1$
#76
b100110 !
b100110 '
0$
b100110 "
b100110 %
b10011 #
b10011 &
#77
b10011 !
b10011 '
1$
#78
b100111 !
b100111 '
0$
b100111 "
b100111 %
#79
b10011 !
b10011 '
1$
#80
b101000 !
b101000 '
0$
b101000 "
b101000 %
b10100 #
b10100 &
#81
b10100 !
b10100 '
1$
#82
b101001 !
b101001 '
0$
b101001 "
b101001 %
#83
b10100 !
b10100 '
1$
#84
b101010 !
b101010 '
0$
b101010 "
b101010 %
b10101 #
b10101 &
#85
b10101 !
b10101 '
1$
#86
b101011 !
b101011 '
0$
b101011 "
b101011 %
#87
b10101 !
b10101 '
1$
#88
b101100 !
b101100 '
0$
b101100 "
b101100 %
b10110 #
b10110 &
#89
b10110 !
b10110 '
1$
#90
b101101 !
b101101 '
0$
b101101 "
b101101 %
#91
b10110 !
b10110 '
1$
#92
b101110 !
b101110 '
0$
b101110 "
b101110 %
b10111 #
b10111 &
#93
b10111 !
b10111 '
1$
#94
b101111 !
b101111 '
0$
b101111 "
b101111 %
#95
b10111 !
b10111 '
1$
#96
b110000 !
b110000 '
0$
b110000 "
b110000 %
b11000 #
b11000 &
#97
b11000 !
b11000 '
1$
#98
b110001 !
b110001 '
0$
b110001 "
b110001 %
#99
b11000 !
b11000 '
1$
#100
b110010 !
b110010 '
0$
b110010 "
b110010 %
b11001 #
b11001 &
#101
b11001 !
b11001 '
1$
#102
b110011 !
b110011 '
0$
b110011 "
b110011 %
#103
b11001 !
b11001 '
1$
#104
b110100 !
b110100 '
0$
b110100 "
b110100 %
b11010 #
b11010 &
#105
b11010 !
b11010 '
1$
#106
b110101 !
b110101 '
0$
b110101 "
b110101 %
#107
b11010 !
b11010 '
1$
#108
b110110 !
b110110 '
0$
b110110 "
b110110 %
b11011 #
b11011 &
#109
b11011 !
b11011 '
1$
#110
b110111 !
b110111 '
0$
b110111 "
b110111 %
#111
b11011 !
b11011 '
1$
#112
b111000 !
b111000 '
0$
b111000 "
b111000 %
b11100 #
b11100 &
#113
b11100 !
b11100 '
1$
#114
b111001 !
b111001 '
0$
b111001 "
b111001 %
#115
b11100 !
b11100 '
1$
#116
b111010 !
b111010 '
0$
b111010 "
b111010 %
b11101 #
b11101 &
#117
b11101 !
b11101 '
1$
#118
b111011 !
b111011 '
0$
b111011 "
b111011 %
#119
b11101 !
b11101 '
1$
#120
b111100 !
b111100 '
0$
b111100 "
b111100 %
b11110 #
b11110 &
#121
b11110 !
b11110 '
1$
#122
b111101 !
b111101 '
0$
b111101 "
b111101 %
#123
b11110 !
b11110 '
1$
#124
b111110 !
b111110 '
0$
b111110 "
b111110 %
b11111 #
b11111 &
#125
b11111 !
b11111 '
1$
#126
b111111 !
b111111 '
0$
b111111 "
b111111 %
#127
b11111 !
b11111 '
1$
#128
b1000000 !
b1000000 '
0$
b1000000 "
b1000000 %
b100000 #
b100000 &
#129
b100000 !
b100000 '
1$
#130
b1000001 !
b1000001 '
0$
b1000001 "
b1000001 %
#131
b100000 !
b100000 '
1$
#132
b1000010 !
b1000010 '
0$
b1000010 "
b1000010 %
b100001 #
b100001 &
#133
b100001 !
b100001 '
1$
#134
b1000011 !
b1000011 '
0$
b1000011 "
b1000011 %
#135
b100001 !
b100001 '
1$
#136
b1000100 !
b1000100 '
0$
b1000100 "
b1000100 %
b100010 #
b100010 &
#137
b100010 !
b100010 '
1$
#138
b1000101 !
b1000101 '
0$
b1000101 "
b1000101 %
#139
b100010 !
b100010 '
1$
#140
b1000110 !
b1000110 '
0$
b1000110 "
b1000110 %
b100011 #
b100011 &
#141
b100011 !
b100011 '
1$
#142
b1000111 !
b1000111 '
0$
b1000111 "
b1000111 %
#143
b100011 !
b100011 '
1$
#144
b1001000 !
b1001000 '
0$
b1001000 "
b1001000 %
b100100 #
b100100 &
#145
b100100 !
b100100 '
1$
#146
b1001001 !
b1001001 '
0$
b1001001 "
b1001001 %
#147
b100100 !
b100100 '
1$
#148
b1001010 !
b1001010 '
0$
b1001010 "
b1001010 %
b100101 #
b100101 &
#149
b100101 !
b100101 '
1$
#150
b1001011 !
b1001011 '
0$
b1001011 "
b1001011 %
#151
b100101 !
b100101 '
1$
#152
b1001100 !
b1001100 '
0$
b1001100 "
b1001100 %
b100110 #
b100110 &
#153
b100110 !
b100110 '
1$
#154
b1001101 !
b1001101 '
0$
b1001101 "
b1001101 %
#155
b100110 !
b100110 '
1$
#156
b1001110 !
b1001110 '
0$
b1001110 "
b1001110 %
b100111 #
b100111 &
#157
b100111 !
b100111 '
1$
#158
b1001111 !
b1001111 '
0$
b1001111 "
b1001111 %
#159
b100111 !
b100111 '
1$
#160
b1010000 !
b1010000 '
0$
b1010000 "
b1010000 %
b101000 #
b101000 &
#161
b101000 !
b101000 '
1$
#162
b1010001 !
b1010001 '
0$
b1010001 "
b1010001 %
#163
b101000 !
b101000 '
1$
#164
b1010010 !
b1010010 '
0$
b1010010 "
b1010010 %
b101001 #
b101001 &
#165
b101001 !
b101001 '
1$
#166
b1010011 !
b1010011 '
0$
b1010011 "
b1010011 %
#167
b101001 !
b101001 '
1$
#168
b1010100 !
b1010100 '
0$
b1010100 "
b1010100 %
b101010 #
b101010 &
#169
b101010 !
b101010 '
1$
#170
b1010101 !
b1010101 '
0$
b1010101 "
b1010101 %
#171
b101010 !
b101010 '
1$
#172
b1010110 !
b1010110 '
0$
b1010110 "
b1010110 %
b101011 #
b101011 &
#173
b101011 !
b101011 '
1$
#174
b1010111 !
b1010111 '
0$
b1010111 "
b1010111 %
#175
b101011 !
b101011 '
1$
#176
b1011000 !
b1011000 '
0$
b1011000 "
b1011000 %
b101100 #
b101100 &
#177
b101100 !
b101100 '
1$
#178
b1011001 !
b1011001 '
0$
b1011001 "
b1011001 %
#179
b101100 !
b101100 '
1$
#180
b1011010 !
b1011010 '
0$
b1011010 "
b1011010 %
b101101 #
b101101 &
#181
b101101 !
b101101 '
1$
#182
b1011011 !
b1011011 '
0$
b1011011 "
b1011011 %
#183
b101101 !
b101101 '
1$
#184
b1011100 !
b1011100 '
0$
b1011100 "
b1011100 %
b101110 #
b101110 &
#185
b101110 !
b101110 '
1$
#186
b1011101 !
b1011101 '
0$
b1011101 "
b1011101 %
#187
b101110 !
b101110 '
1$
#188
b1011110 !
b1011110 '
0$
b1011110 "
b1011110 %
b101111 #
b101111 &
#189
b101111 !
b101111 '
1$
#190
b1011111 !
b1011111 '
0$
b1011111 "
b1011111 %
#191
b101111 !
b101111 '
1$
#192
b1100000 !
b1100000 '
0$
b1100000 "
b1100000 %
b110000 #
b110000 &
#193
b110000 !
b110000 '
1$
#194
b1100001 !
b1100001 '
0$
b1100001 "
b1100001 %
#195
b110000 !
b110000 '
1$
#196
b1100010 !
b1100010 '
0$
b1100010 "
b1100010 %
b110001 #
b110001 &
#197
b110001 !
b110001 '
1$
#198
b1100011 !
b1100011 '
0$
b1100011 "
b1100011 %
#199
b110001 !
b110001 '
1$
#200
b1100100 !
b1100100 '
0$
b1100100 "
b1100100 %
b110010 #
b110010 &
#201
b110010 !
b110010 '
1$
#202
b1100101 !
b1100101 '
0$
b1100101 "
b1100101 %
#203
b110010 !
b110010 '
1$
#204
b1100110 !
b1100110 '
0$
b1100110 "
b1100110 %
b110011 #
b110011 &
#205
b110011 !
b110011 '
1$
#206
b1100111 !
b1100111 '
0$
b1100111 "
b1100111 %
#207
b110011 !
b110011 '
1$
#208
b1101000 !
b1101000 '
0$
b1101000 "
b1101000 %
b110100 #
b110100 &
#209
b110100 !
b110100 '
1$
#210
b1101001 !
b1101001 '
0$
b1101001 "
b1101001 %
#211
b110100 !
b110100 '
1$
#212
b1101010 !
b1101010 '
0$
b1101010 "
b1101010 %
b110101 #
b110101 &
#213
b110101 !
b110101 '
1$
#214
b1101011 !
b1101011 '
0$
b1101011 "
b1101011 %
#215
b110101 !
b110101 '
1$
#216
b1101100 !
b1101100 '
0$
b1101100 "
b1101100 %
b110110 #
b110110 &
#217
b110110 !
b110110 '
1$
#218
b1101101 !
b1101101 '
0$
b1101101 "
b1101101 %
#219
b110110 !
b110110 '
1$
#220
b1101110 !
b1101110 '
0$
b1101110 "
b1101110 %
b110111 #
b110111 &
#221
b110111 !
b110111 '
1$
#222
b1101111 !
b1101111 '
0$
b1101111 "
b1101111 %
#223
b110111 !
b110111 '
1$
#224
b1110000 !
b1110000 '
0$
b1110000 "
b1110000 %
b111000 #
b111000 &
#225
b111000 !
b111000 '
1$
#226
b1110001 !
b1110001 '
0$
b1110001 "
b1110001 %
#227
b111000 !
b111000 '
1$
#228
b1110010 !
b1110010 '
0$
b1110010 "
b1110010 %
b111001 #
b111001 &
#229
b111001 !
b111001 '
1$
#230
b1110011 !
b1110011 '
0$
b1110011 "
b1110011 %
#231
b111001 !
b111001 '
1$
#232
b1110100 !
b1110100 '
0$
b1110100 "
b1110100 %
b111010 #
b111010 &
#233
b111010 !
b111010 '
1$
#234
b1110101 !
b1110101 '
0$
b1110101 "
b1110101 %
#235
b111010 !
b111010 '
1$
#236
b1110110 !
b1110110 '
0$
b1110110 "
b1110110 %
b111011 #
b111011 &
#237
b111011 !
b111011 '
1$
#238
b1110111 !
b1110111 '
0$
b1110111 "
b1110111 %
#239
b111011 !
b111011 '
1$
#240
b1111000 !
b1111000 '
0$
b1111000 "
b1111000 %
b111100 #
b111100 &
#241
b111100 !
b111100 '
1$
#242
b1111001 !
b1111001 '
0$
b1111001 "
b1111001 %
#243
b111100 !
b111100 '
1$
#244
b1111010 !
b1111010 '
0$
b1111010 "
b1111010 %
b111101 #
b111101 &
#245
b111101 !
b111101 '
1$
#246
b1111011 !
b1111011 '
0$
b1111011 "
b1111011 %
#247
b111101 !
b111101 '
1$
#248
b1111100 !
b1111100 '
0$
b1111100 "
b1111100 %
b111110 #
b111110 &
#249
b111110 !
b111110 '
1$
#250
b1111101 !
b1111101 '
0$
b1111101 "
b1111101 %
#251
b111110 !
b111110 '
1$
#252
b1111110 !
b1111110 '
0$
b1111110 "
b1111110 %
b111111 #
b111111 &
#253
b111111 !
b111111 '
1$
#254
b1111111 !
b1111111 '
0$
b1111111 "
b1111111 %
#255
b111111 !
b111111 '
1$
#256
b10000000 !
b10000000 '
0$
b10000000 "
b10000000 %
b1000000 #
b1000000 &
#257
b1000000 !
b1000000 '
1$
#258
b10000001 !
b10000001 '
0$
b10000001 "
b10000001 %
#259
b1000000 !
b1000000 '
1$
#260
b10000010 !
b10000010 '
0$
b10000010 "
b10000010 %
b1000001 #
b1000001 &
#261
b1000001 !
b1000001 '
1$
#262
b10000011 !
b10000011 '
0$
b10000011 "
b10000011 %
#263
b1000001 !
b1000001 '
1$
#264
b10000100 !
b10000100 '
0$
b10000100 "
b10000100 %
b1000010 #
b1000010 &
#265
b1000010 !
b1000010 '
1$
#266
b10000101 !
b10000101 '
0$
b10000101 "
b10000101 %
#267
b1000010 !
b1000010 '
1$
#268
b10000110 !
b10000110 '
0$
b10000110 "
b10000110 %
b1000011 #
b1000011 &
#269
b1000011 !
b1000011 '
1$
#270
b10000111 !
b10000111 '
0$
b10000111 "
b10000111 %
#271
b1000011 !
b1000011 '
1$
#272
b10001000 !
b10001000 '
0$
b10001000 "
b10001000 %
b1000100 #
b1000100 &
#273
b1000100 !
b1000100 '
1$
#274
b10001001 !
b10001001 '
0$
b10001001 "
b10001001 %
#275
b1000100 !
b1000100 '
1$
#276
b10001010 !
b10001010 '
0$
b10001010 "
b10001010 %
b1000101 #
b1000101 &
#277
b1000101 !
b1000101 '
1$
#278
b10001011 !
b10001011 '
0$
b10001011 "
b10001011 %
#279
b1000101 !
b1000101 '
1$
#280
b10001100 !
b10001100 '
0$
b10001100 "
b10001100 %
b1000110 #
b1000110 &
#281
b1000110 !
b1000110 '
1$
#282
b10001101 !
b10001101 '
0$
b10001101 "
b10001101 %
#283
b1000110 !
b1000110 '
1$
#284
b10001110 !
b10001110 '
0$
b10001110 "
b10001110 %
b1000111 #
b1000111 &
#285
b1000111 !
b1000111 '
1$
#286
b10001111 !
b10001111 '
0$
b10001111 "
b10001111 %
#287
b1000111 !
b1000111 '
1$
#288
b10010000 !
b10010000 '
0$
b10010000 "
b10010000 %
b1001000 #
b1001000 &
#289
b1001000 !
b1001000 '
1$
#290
b10010001 !
b10010001 '
0$
b10010001 "
b10010001 %
#291
b1001000 !
b1001000 '
1$
#292
b10010010 !
b10010010 '
0$
b10010010 "
b10010010 %
b1001001 #
b1001001 &
#293
b1001001 !
b1001001 '
1$
#294
b10010011 !
b10010011 '
0$
b10010011 "
b10010011 %
#295
b1001001 !
b1001001 '
1$
#296
b10010100 !
b10010100 '
0$
b10010100 "
b10010100 %
b1001010 #
b1001010 &
#297
b1001010 !
b1001010 '
1$
#298
b10010101 !
b10010101 '
0$
b10010101 "
b10010101 %
#299
b1001010 !
b1001010 '
1$
#300
b10010110 !
b10010110 '
0$
b10010110 "
b10010110 %
b1001011 #
b1001011 &
#301
b1001011 !
b1001011 '
1$
#302
b10010111 !
b10010111 '
0$
b10010111 "
b10010111 %
#303
b1001011 !
b1001011 '
1$
#304
b10011000 !
b10011000 '
0$
b10011000 "
b10011000 %
b1001100 #
b1001100 &
#305
b1001100 !
b1001100 '
1$
#306
b10011001 !
b10011001 '
0$
b10011001 "
b10011001 %
#307
b1001100 !
b1001100 '
1$
#308
b10011010 !
b10011010 '
0$
b10011010 "
b10011010 %
b1001101 #
b1001101 &
#309
b1001101 !
b1001101 '
1$
#310
b10011011 !
b10011011 '
0$
b10011011 "
b10011011 %
#311
b1001101 !
b1001101 '
1$
#312
b10011100 !
b10011100 '
0$
b10011100 "
b10011100 %
b1001110 #
b1001110 &
#313
b1001110 !
b1001110 '
1$
#314
b10011101 !
b10011101 '
0$
b10011101 "
b10011101 %
#315
b1001110 !
b1001110 '
1$
#316
b10011110 !
b10011110 '
0$
b10011110 "
b10011110 %
b1001111 #
b1001111 &
#317
b1001111 !
b1001111 '
1$
#318
b10011111 !
b10011111 '
0$
b10011111 "
b10011111 %
#319
b1001111 !
b1001111 '
1$
#320
b10100000 !
b10100000 '
0$
b10100000 "
b10100000 %
b1010000 #
b1010000 &
#321
b1010000 !
b1010000 '
1$
#322
b10100001 !
b10100001 '
0$
b10100001 "
b10100001 %
#323
b1010000 !
b1010000 '
1$
#324
b10100010 !
b10100010 '
0$
b10100010 "
b10100010 %
b1010001 #
b1010001 &
#325
b1010001 !
b1010001 '
1$
#326
b10100011 !
b10100011 '
0$
b10100011 "
b10100011 %
#327
b1010001 !
b1010001 '
1$
#328
b10100100 !
b10100100 '
0$
b10100100 "
b10100100 %
b1010010 #
b1010010 &
#329
b1010010 !
b1010010 '
1$
#330
b10100101 !
b10100101 '
0$
b10100101 "
b10100101 %
#331
b1010010 !
b1010010 '
1$
#332
b10100110 !
b10100110 '
0$
b10100110 "
b10100110 %
b1010011 #
b1010011 &
#333
b1010011 !
b1010011 '
1$
#334
b10100111 !
b10100111 '
0$
b10100111 "
b10100111 %
#335
b1010011 !
b1010011 '
1$
#336
b10101000 !
b10101000 '
0$
b10101000 "
b10101000 %
b1010100 #
b1010100 &
#337
b1010100 !
b1010100 '
1$
#338
b10101001 !
b10101001 '
0$
b10101001 "
b10101001 %
#339
b1010100 !
b1010100 '
1$
#340
b10101010 !
b10101010 '
0$
b10101010 "
b10101010 %
b1010101 #
b1010101 &
#341
b1010101 !
b1010101 '
1$
#342
b10101011 !
b10101011 '
0$
b10101011 "
b10101011 %
#343
b1010101 !
b1010101 '
1$
#344
b10101100 !
b10101100 '
0$
b10101100 "
b10101100 %
b1010110 #
b1010110 &
#345
b1010110 !
b1010110 '
1$
#346
b10101101 !
b10101101 '
0$
b10101101 "
b10101101 %
#347
b1010110 !
b1010110 '
1$
#348
b10101110 !
b10101110 '
0$
b10101110 "
b10101110 %
b1010111 #
b1010111 &
#349
b1010111 !
b1010111 '
1$
#350
b10101111 !
b10101111 '
0$
b10101111 "
b10101111 %
#351
b1010111 !
b1010111 '
1$
#352
b10110000 !
b10110000 '
0$
b10110000 "
b10110000 %
b1011000 #
b1011000 &
#353
b1011000 !
b1011000 '
1$
#354
b10110001 !
b10110001 '
0$
b10110001 "
b10110001 %
#355
b1011000 !
b1011000 '
1$
#356
b10110010 !
b10110010 '
0$
b10110010 "
b10110010 %
b1011001 #
b1011001 &
#357
b1011001 !
b1011001 '
1$
#358
b10110011 !
b10110011 '
0$
b10110011 "
b10110011 %
#359
b1011001 !
b1011001 '
1$
#360
b10110100 !
b10110100 '
0$
b10110100 "
b10110100 %
b1011010 #
b1011010 &
#361
b1011010 !
b1011010 '
1$
#362
b10110101 !
b10110101 '
0$
b10110101 "
b10110101 %
#363
b1011010 !
b1011010 '
1$
#364
b10110110 !
b10110110 '
0$
b10110110 "
b10110110 %
b1011011 #
b1011011 &
#365
b1011011 !
b1011011 '
1$
#366
b10110111 !
b10110111 '
0$
b10110111 "
b10110111 %
#367
b1011011 !
b1011011 '
1$
#368
b10111000 !
b10111000 '
0$
b10111000 "
b10111000 %
b1011100 #
b1011100 &
#369
b1011100 !
b1011100 '
1$
#370
b10111001 !
b10111001 '
0$
b10111001 "
b10111001 %
#371
b1011100 !
b1011100 '
1$
#372
b10111010 !
b10111010 '
0$
b10111010 "
b10111010 %
b1011101 #
b1011101 &
#373
b1011101 !
b1011101 '
1$
#374
b10111011 !
b10111011 '
0$
b10111011 "
b10111011 %
#375
b1011101 !
b1011101 '
1$
#376
b10111100 !
b10111100 '
0$
b10111100 "
b10111100 %
b1011110 #
b1011110 &
#377
b1011110 !
b1011110 '
1$
#378
b10111101 !
b10111101 '
0$
b10111101 "
b10111101 %
#379
b1011110 !
b1011110 '
1$
#380
b10111110 !
b10111110 '
0$
b10111110 "
b10111110 %
b1011111 #
b1011111 &
#381
b1011111 !
b1011111 '
1$
#382
b10111111 !
b10111111 '
0$
b10111111 "
b10111111 %
#383
b1011111 !
b1011111 '
1$
#384
b11000000 !
b11000000 '
0$
b11000000 "
b11000000 %
b1100000 #
b1100000 &
#385
b1100000 !
b1100000 '
1$
#386
b11000001 !
b11000001 '
0$
b11000001 "
b11000001 %
#387
b1100000 !
b1100000 '
1$
#388
b11000010 !
b11000010 '
0$
b11000010 "
b11000010 %
b1100001 #
b1100001 &
#389
b1100001 !
b1100001 '
1$
#390
b11000011 !
b11000011 '
0$
b11000011 "
b11000011 %
#391
b1100001 !
b1100001 '
1$
#392
b11000100 !
b11000100 '
0$
b11000100 "
b11000100 %
b1100010 #
b1100010 &
#393
b1100010 !
b1100010 '
1$
#394
b11000101 !
b11000101 '
0$
b11000101 "
b11000101 %
#395
b1100010 !
b1100010 '
1$
#396
b11000110 !
b11000110 '
0$
b11000110 "
b11000110 %
b1100011 #
b1100011 &
#397
b1100011 !
b1100011 '
1$
#398
b11000111 !
b11000111 '
0$
b11000111 "
b11000111 %
#399
b1100011 !
b1100011 '
1$
#400
b11001000 !
b11001000 '
0$
b11001000 "
b11001000 %
b1100100 #
b1100100 &
#401
b1100100 !
b1100100 '
1$
#402
b11001001 !
b11001001 '
0$
b11001001 "
b11001001 %
#403
b1100100 !
b1100100 '
1$
#404
b11001010 !
b11001010 '
0$
b11001010 "
b11001010 %
b1100101 #
b1100101 &
#405
b1100101 !
b1100101 '
1$
#406
b11001011 !
b11001011 '
0$
b11001011 "
b11001011 %
#407
b1100101 !
b1100101 '
1$
#408
b11001100 !
b11001100 '
0$
b11001100 "
b11001100 %
b1100110 #
b1100110 &
#409
b1100110 !
b1100110 '
1$
#410
b11001101 !
b11001101 '
0$
b11001101 "
b11001101 %
#411
b1100110 !
b1100110 '
1$
#412
b11001110 !
b11001110 '
0$
b11001110 "
b11001110 %
b1100111 #
b1100111 &
#413
b1100111 !
b1100111 '
1$
#414
b11001111 !
b11001111 '
0$
b11001111 "
b11001111 %
#415
b1100111 !
b1100111 '
1$
#416
b11010000 !
b11010000 '
0$
b11010000 "
b11010000 %
b1101000 #
b1101000 &
#417
b1101000 !
b1101000 '
1$
#418
b11010001 !
b11010001 '
0$
b11010001 "
b11010001 %
#419
b1101000 !
b1101000 '
1$
#420
b11010010 !
b11010010 '
0$
b11010010 "
b11010010 %
b1101001 #
b1101001 &
#421
b1101001 !
b1101001 '
1$
#422
b11010011 !
b11010011 '
0$
b11010011 "
b11010011 %
#423
b1101001 !
b1101001 '
1$
#424
b11010100 !
b11010100 '
0$
b11010100 "
b11010100 %
b1101010 #
b1101010 &
#425
b1101010 !
b1101010 '
1$
#426
b11010101 !
b11010101 '
0$
b11010101 "
b11010101 %
#427
b1101010 !
b1101010 '
1$
#428
b11010110 !
b11010110 '
0$
b11010110 "
b11010110 %
b1101011 #
b1101011 &
#429
b1101011 !
b1101011 '
1$
#430
b11010111 !
b11010111 '
0$
b11010111 "
b11010111 %
#431
b1101011 !
b1101011 '
1$
#432
b11011000 !
b11011000 '
0$
b11011000 "
b11011000 %
b1101100 #
b1101100 &
#433
b1101100 !
b1101100 '
1$
#434
b11011001 !
b11011001 '
0$
b11011001 "
b11011001 %
#435
b1101100 !
b1101100 '
1$
#436
b11011010 !
b11011010 '
0$
b11011010 "
b11011010 %
b1101101 #
b1101101 &
#437
b1101101 !
b1101101 '
1$
#438
b11011011 !
b11011011 '
0$
b11011011 "
b11011011 %
#439
b1101101 !
b1101101 '
1$
#440
b11011100 !
b11011100 '
0$
b11011100 "
b11011100 %
b1101110 #
b1101110 &
#441
b1101110 !
b1101110 '
1$
#442
b11011101 !
b11011101 '
0$
b11011101 "
b11011101 %
#443
b1101110 !
b1101110 '
1$
#444
b11011110 !
b11011110 '
0$
b11011110 "
b11011110 %
b1101111 #
b1101111 &
#445
b1101111 !
b1101111 '
1$
#446
b11011111 !
b11011111 '
0$
b11011111 "
b11011111 %
#447
b1101111 !
b1101111 '
1$
#448
b11100000 !
b11100000 '
0$
b11100000 "
b11100000 %
b1110000 #
b1110000 &
#449
b1110000 !
b1110000 '
1$
#450
b11100001 !
b11100001 '
0$
b11100001 "
b11100001 %
#451
b1110000 !
b1110000 '
1$
#452
b11100010 !
b11100010 '
0$
b11100010 "
b11100010 %
b1110001 #
b1110001 &
#453
b1110001 !
b1110001 '
1$
#454
b11100011 !
b11100011 '
0$
b11100011 "
b11100011 %
#455
b1110001 !
b1110001 '
1$
#456
b11100100 !
b11100100 '
0$
b11100100 "
b11100100 %
b1110010 #
b1110010 &
#457
b1110010 !
b1110010 '
1$
#458
b11100101 !
b11100101 '
0$
b11100101 "
b11100101 %
#459
b1110010 !
b1110010 '
1$
#460
b11100110 !
b11100110 '
0$
b11100110 "
b11100110 %
b1110011 #
b1110011 &
#461
b1110011 !
b1110011 '
1$
#462
b11100111 !
b11100111 '
0$
b11100111 "
b11100111 %
#463
b1110011 !
b1110011 '
1$
#464
b11101000 !
b11101000 '
0$
b11101000 "
b11101000 %
b1110100 #
b1110100 &
#465
b1110100 !
b1110100 '
1$
#466
b11101001 !
b11101001 '
0$
b11101001 "
b11101001 %
#467
b1110100 !
b1110100 '
1$
#468
b11101010 !
b11101010 '
0$
b11101010 "
b11101010 %
b1110101 #
b1110101 &
#469
b1110101 !
b1110101 '
1$
#470
b11101011 !
b11101011 '
0$
b11101011 "
b11101011 %
#471
b1110101 !
b1110101 '
1$
#472
b11101100 !
b11101100 '
0$
b11101100 "
b11101100 %
b1110110 #
b1110110 &
#473
b1110110 !
b1110110 '
1$
#474
b11101101 !
b11101101 '
0$
b11101101 "
b11101101 %
#475
b1110110 !
b1110110 '
1$
#476
b11101110 !
b11101110 '
0$
b11101110 "
b11101110 %
b1110111 #
b1110111 &
#477
b1110111 !
b1110111 '
1$
#478
b11101111 !
b11101111 '
0$
b11101111 "
b11101111 %
#479
b1110111 !
b1110111 '
1$
#480
b11110000 !
b11110000 '
0$
b11110000 "
b11110000 %
b1111000 #
b1111000 &
#481
b1111000 !
b1111000 '
1$
#482
b11110001 !
b11110001 '
0$
b11110001 "
b11110001 %
#483
b1111000 !
b1111000 '
1$
#484
b11110010 !
b11110010 '
0$
b11110010 "
b11110010 %
b1111001 #
b1111001 &
#485
b1111001 !
b1111001 '
1$
#486
b11110011 !
b11110011 '
0$
b11110011 "
b11110011 %
#487
b1111001 !
b1111001 '
1$
#488
b11110100 !
b11110100 '
0$
b11110100 "
b11110100 %
b1111010 #
b1111010 &
#489
b1111010 !
b1111010 '
1$
#490
b11110101 !
b11110101 '
0$
b11110101 "
b11110101 %
