elementary_logic_gates/Or16.v
module Or16 (
    input wire [15:0] in1, in2,
    output wire [15:0] out
);
    assign out = in1 | in2;
    
endmodule

elementary_logic_gates/Or16_tb.v
module Or16_tb;
    reg [15:0] in1 = 16'h0000, in2 = 16'h0000;
    wire [15:0] out;

    Or16 dctime (.in1(in1), .in2(in2), .out(out));

    initial begin
        $dumpfile("Or16.vcd");
        $dumpvars(0, Or16_tb);
    end

    always begin
        #1
        if (in1 == 16'hffff) begin
            in1 = 16'h0000;
        end else begin
            in1 = in1 + 1;
        end
    end

    always begin
        #2
        if (in2 == 16'hffff) begin
            in2 = 16'h0000;
        end else begin
            in2 = in2 + 1;
        end
    end

    initial begin
        #1000 $finish;
    end
    
endmodule

16_bit_variants/Or16.vcd
$date
	Fri Aug 25 13:54:54 2023
$end
$version
	Icarus Verilog
$end
$timescale
	1s
$end
$scope module Or16_tb $end
$var wire 16 ! out [15:0] $end
$var reg 16 " in1 [15:0] $end
$var reg 16 # in2 [15:0] $end
$scope module dctime $end
$var wire 16 $ in1 [15:0] $end
$var wire 16 % in2 [15:0] $end
$var wire 16 & out [15:0] $end
$upscope $end
$upscope $end
$enddefinitions $end
$comment Show the parameter values. $end
$dumpall
$end
#0
$dumpvars
b0 &
b0 %
b0 $
b0 #
b0 "
b0 !
$end
#1
b1 !
b1 &
b1 "
b1 $
#2
b11 !
b11 &
b10 "
b10 $
b1 #
b1 %
#3
b11 "
b11 $
#4
b110 !
b110 &
b100 "
b100 $
b10 #
b10 %
#5
b111 !
b111 &
b101 "
b101 $
#6
b110 "
b110 $
b11 #
b11 %
#7
b111 "
b111 $
#8
b1100 !
b1100 &
b1000 "
b1000 $
b100 #
b100 %
#9
b1101 !
b1101 &
b1001 "
b1001 $
#10
b1111 !
b1111 &
b1010 "
b1010 $
b101 #
b101 %
#11
b1011 "
b1011 $
#12
b1110 !
b1110 &
b1100 "
b1100 $
b110 #
b110 %
#13
b1111 !
b1111 &
b1101 "
b1101 $
#14
b1110 "
b1110 $
b111 #
b111 %
#15
b1111 "
b1111 $
#16
b11000 !
b11000 &
b10000 "
b10000 $
b1000 #
b1000 %
#17
b11001 !
b11001 &
b10001 "
b10001 $
#18
b11011 !
b11011 &
b10010 "
b10010 $
b1001 #
b1001 %
#19
b10011 "
b10011 $
#20
b11110 !
b11110 &
b10100 "
b10100 $
b1010 #
b1010 %
#21
b11111 !
b11111 &
b10101 "
b10101 $
#22
b10110 "
b10110 $
b1011 #
b1011 %
#23
b10111 "
b10111 $
#24
b11100 !
b11100 &
b11000 "
b11000 $
b1100 #
b1100 %
#25
b11101 !
b11101 &
b11001 "
b11001 $
#26
b11111 !
b11111 &
b11010 "
b11010 $
b1101 #
b1101 %
#27
b11011 "
b11011 $
#28
b11110 !
b11110 &
b11100 "
b11100 $
b1110 #
b1110 %
#29
b11111 !
b11111 &
b11101 "
b11101 $
#30
b11110 "
b11110 $
b1111 #
b1111 %
#31
b11111 "
b11111 $
#32
b110000 !
b110000 &
b100000 "
b100000 $
b10000 #
b10000 %
#33
b110001 !
b110001 &
b100001 "
b100001 $
#34
b110011 !
b110011 &
b100010 "
b100010 $
b10001 #
b10001 %
#35
b100011 "
b100011 $
#36
b110110 !
b110110 &
b100100 "
b100100 $
b10010 #
b10010 %
#37
b110111 !
b110111 &
b100101 "
b100101 $
#38
b100110 "
b100110 $
b10011 #
b10011 %
#39
b100111 "
b100111 $
#40
b111100 !
b111100 &
b101000 "
b101000 $
b10100 #
b10100 %
#41
b111101 !
b111101 &
b101001 "
b101001 $
#42
b111111 !
b111111 &
b101010 "
b101010 $
b10101 #
b10101 %
#43
b101011 "
b101011 $
#44
b111110 !
b111110 &
b101100 "
b101100 $
b10110 #
b10110 %
#45
b111111 !
b111111 &
b101101 "
b101101 $
#46
b101110 "
b101110 $
b10111 #
b10111 %
#47
b101111 "
b101111 $
#48
b111000 !
b111000 &
b110000 "
b110000 $
b11000 #
b11000 %
#49
b111001 !
b111001 &
b110001 "
b110001 $
#50
b111011 !
b111011 &
b110010 "
b110010 $
b11001 #
b11001 %
#51
b110011 "
b110011 $
#52
b111110 !
b111110 &
b110100 "
b110100 $
b11010 #
b11010 %
#53
b111111 !
b111111 &
b110101 "
b110101 $
#54
b110110 "
b110110 $
b11011 #
b11011 %
#55
b110111 "
b110111 $
#56
b111100 !
b111100 &
b111000 "
b111000 $
b11100 #
b11100 %
#57
b111101 !
b111101 &
b111001 "
b111001 $
#58
b111111 !
b111111 &
b111010 "
b111010 $
b11101 #
b11101 %
#59
b111011 "
b111011 $
#60
b111110 !
b111110 &
b111100 "
b111100 $
b11110 #
b11110 %
#61
b111111 !
b111111 &
b111101 "
b111101 $
#62
b111110 "
b111110 $
b11111 #
b11111 %
#63
b111111 "
b111111 $
#64
b1100000 !
b1100000 &
b1000000 "
b1000000 $
b100000 #
b100000 %
#65
b1100001 !
b1100001 &
b1000001 "
b1000001 $
#66
b1100011 !
b1100011 &
b1000010 "
b1000010 $
b100001 #
b100001 %
#67
b1000011 "
b1000011 $
#68
b1100110 !
b1100110 &
b1000100 "
b1000100 $
b100010 #
b100010 %
#69
b1100111 !
b1100111 &
b1000101 "
b1000101 $
#70
b1000110 "
b1000110 $
b100011 #
b100011 %
#71
b1000111 "
b1000111 $
#72
b1101100 !
b1101100 &
b1001000 "
b1001000 $
b100100 #
b100100 %
#73
b1101101 !
b1101101 &
b1001001 "
b1001001 $
#74
b1101111 !
b1101111 &
b1001010 "
b1001010 $
b100101 #
b100101 %
#75
b1001011 "
b1001011 $
#76
b1101110 !
b1101110 &
b1001100 "
b1001100 $
b100110 #
b100110 %
#77
b1101111 !
b1101111 &
b1001101 "
b1001101 $
#78
b1001110 "
b1001110 $
b100111 #
b100111 %
#79
b1001111 "
b1001111 $
#80
b1111000 !
b1111000 &
b1010000 "
b1010000 $
b101000 #
b101000 %
#81
b1111001 !
b1111001 &
b1010001 "
b1010001 $
#82
b1111011 !
b1111011 &
b1010010 "
b1010010 $
b101001 #
b101001 %
#83
b1010011 "
b1010011 $
#84
b1111110 !
b1111110 &
b1010100 "
b1010100 $
b101010 #
b101010 %
#85
b1111111 !
b1111111 &
b1010101 "
b1010101 $
#86
b1010110 "
b1010110 $
b101011 #
b101011 %
#87
b1010111 "
b1010111 $
#88
b1111100 !
b1111100 &
b1011000 "
b1011000 $
b101100 #
b101100 %
#89
b1111101 !
b1111101 &
b1011001 "
b1011001 $
#90
b1111111 !
b1111111 &
b1011010 "
b1011010 $
b101101 #
b101101 %
#91
b1011011 "
b1011011 $
#92
b1111110 !
b1111110 &
b1011100 "
b1011100 $
b101110 #
b101110 %
#93
b1111111 !
b1111111 &
b1011101 "
b1011101 $
#94
b1011110 "
b1011110 $
b101111 #
b101111 %
#95
b1011111 "
b1011111 $
#96
b1110000 !
b1110000 &
b1100000 "
b1100000 $
b110000 #
b110000 %
#97
b1110001 !
b1110001 &
b1100001 "
b1100001 $
#98
b1110011 !
b1110011 &
b1100010 "
b1100010 $
b110001 #
b110001 %
#99
b1100011 "
b1100011 $
#100
b1110110 !
b1110110 &
b1100100 "
b1100100 $
b110010 #
b110010 %
#101
b1110111 !
b1110111 &
b1100101 "
b1100101 $
#102
b1100110 "
b1100110 $
b110011 #
b110011 %
#103
b1100111 "
b1100111 $
#104
b1111100 !
b1111100 &
b1101000 "
b1101000 $
b110100 #
b110100 %
#105
b1111101 !
b1111101 &
b1101001 "
b1101001 $
#106
b1111111 !
b1111111 &
b1101010 "
b1101010 $
b110101 #
b110101 %
#107
b1101011 "
b1101011 $
#108
b1111110 !
b1111110 &
b1101100 "
b1101100 $
b110110 #
b110110 %
#109
b1111111 !
b1111111 &
b1101101 "
b1101101 $
#110
b1101110 "
b1101110 $
b110111 #
b110111 %
#111
b1101111 "
b1101111 $
#112
b1111000 !
b1111000 &
b1110000 "
b1110000 $
b111000 #
b111000 %
#113
b1111001 !
b1111001 &
b1110001 "
b1110001 $
#114
b1111011 !
b1111011 &
b1110010 "
b1110010 $
b111001 #
b111001 %
#115
b1110011 "
b1110011 $
#116
b1111110 !
b1111110 &
b1110100 "
b1110100 $
b111010 #
b111010 %
#117
b1111111 !
b1111111 &
b1110101 "
b1110101 $
#118
b1110110 "
b1110110 $
b111011 #
b111011 %
#119
b1110111 "
b1110111 $
#120
b1111100 !
b1111100 &
b1111000 "
b1111000 $
b111100 #
b111100 %
#121
b1111101 !
b1111101 &
b1111001 "
b1111001 $
#122
b1111111 !
b1111111 &
b1111010 "
b1111010 $
b111101 #
b111101 %
#123
b1111011 "
b1111011 $
#124
b1111110 !
b1111110 &
b1111100 "
b1111100 $
b111110 #
b111110 %
#125
b1111111 !
b1111111 &
b1111101 "
b1111101 $
#126
b1111110 "
b1111110 $
b111111 #
b111111 %
#127
b1111111 "
b1111111 $
#128
b11000000 !
b11000000 &
b10000000 "
b10000000 $
b1000000 #
b1000000 %
#129
b11000001 !
b11000001 &
b10000001 "
b10000001 $
#130
b11000011 !
b11000011 &
b10000010 "
b10000010 $
b1000001 #
b1000001 %
#131
b10000011 "
b10000011 $
#132
b11000110 !
b11000110 &
b10000100 "
b10000100 $
b1000010 #
b1000010 %
#133
b11000111 !
b11000111 &
b10000101 "
b10000101 $
#134
b10000110 "
b10000110 $
b1000011 #
b1000011 %
#135
b10000111 "
b10000111 $
#136
b11001100 !
b11001100 &
b10001000 "
b10001000 $
b1000100 #
b1000100 %
#137
b11001101 !
b11001101 &
b10001001 "
b10001001 $
#138
b11001111 !
b11001111 &
b10001010 "
b10001010 $
b1000101 #
b1000101 %
#139
b10001011 "
b10001011 $
#140
b11001110 !
b11001110 &
b10001100 "
b10001100 $
b1000110 #
b1000110 %
#141
b11001111 !
b11001111 &
b10001101 "
b10001101 $
#142
b10001110 "
b10001110 $
b1000111 #
b1000111 %
#143
b10001111 "
b10001111 $
#144
b11011000 !
b11011000 &
b10010000 "
b10010000 $
b1001000 #
b1001000 %
#145
b11011001 !
b11011001 &
b10010001 "
b10010001 $
#146
b11011011 !
b11011011 &
b10010010 "
b10010010 $
b1001001 #
b1001001 %
#147
b10010011 "
b10010011 $
#148
b11011110 !
b11011110 &
b10010100 "
b10010100 $
b1001010 #
b1001010 %
#149
b11011111 !
b11011111 &
b10010101 "
b10010101 $
#150
b10010110 "
b10010110 $
b1001011 #
b1001011 %
#151
b10010111 "
b10010111 $
#152
b11011100 !
b11011100 &
b10011000 "
b10011000 $
b1001100 #
b1001100 %
#153
b11011101 !
b11011101 &
b10011001 "
b10011001 $
#154
b11011111 !
b11011111 &
b10011010 "
b10011010 $
b1001101 #
b1001101 %
#155
b10011011 "
b10011011 $
#156
b11011110 !
b11011110 &
b10011100 "
b10011100 $
b1001110 #
b1001110 %
#157
b11011111 !
b11011111 &
b10011101 "
b10011101 $
#158
b10011110 "
b10011110 $
b1001111 #
b1001111 %
#159
b10011111 "
b10011111 $
#160
b11110000 !
b11110000 &
b10100000 "
b10100000 $
b1010000 #
b1010000 %
#161
b11110001 !
b11110001 &
b10100001 "
b10100001 $
#162
b11110011 !
b11110011 &
b10100010 "
b10100010 $
b1010001 #
b1010001 %
#163
b10100011 "
b10100011 $
#164
b11110110 !
b11110110 &
b10100100 "
b10100100 $
b1010010 #
b1010010 %
#165
b11110111 !
b11110111 &
b10100101 "
b10100101 $
#166
b10100110 "
b10100110 $
b1010011 #
b1010011 %
#167
b10100111 "
b10100111 $
#168
b11111100 !
b11111100 &
b10101000 "
b10101000 $
b1010100 #
b1010100 %
#169
b11111101 !
b11111101 &
b10101001 "
b10101001 $
#170
b11111111 !
b11111111 &
b10101010 "
b10101010 $
b1010101 #
b1010101 %
#171
b10101011 "
b10101011 $
#172
b11111110 !
b11111110 &
b10101100 "
b10101100 $
b1010110 #
b1010110 %
#173
b11111111 !
b11111111 &
b10101101 "
b10101101 $
#174
b10101110 "
b10101110 $
b1010111 #
b1010111 %
#175
b10101111 "
b10101111 $
#176
b11111000 !
b11111000 &
b10110000 "
b10110000 $
b1011000 #
b1011000 %
#177
b11111001 !
b11111001 &
b10110001 "
b10110001 $
#178
b11111011 !
b11111011 &
b10110010 "
b10110010 $
b1011001 #
b1011001 %
#179
b10110011 "
b10110011 $
#180
b11111110 !
b11111110 &
b10110100 "
b10110100 $
b1011010 #
b1011010 %
#181
b11111111 !
b11111111 &
b10110101 "
b10110101 $
#182
b10110110 "
b10110110 $
b1011011 #
b1011011 %
#183
b10110111 "
b10110111 $
#184
b11111100 !
b11111100 &
b10111000 "
b10111000 $
b1011100 #
b1011100 %
#185
b11111101 !
b11111101 &
b10111001 "
b10111001 $
#186
b11111111 !
b11111111 &
b10111010 "
b10111010 $
b1011101 #
b1011101 %
#187
b10111011 "
b10111011 $
#188
b11111110 !
b11111110 &
b10111100 "
b10111100 $
b1011110 #
b1011110 %
#189
b11111111 !
b11111111 &
b10111101 "
b10111101 $
#190
b10111110 "
b10111110 $
b1011111 #
b1011111 %
#191
b10111111 "
b10111111 $
#192
b11100000 !
b11100000 &
b11000000 "
b11000000 $
b1100000 #
b1100000 %
#193
b11100001 !
b11100001 &
b11000001 "
b11000001 $
#194
b11100011 !
b11100011 &
b11000010 "
b11000010 $
b1100001 #
b1100001 %
#195
b11000011 "
b11000011 $
#196
b11100110 !
b11100110 &
b11000100 "
b11000100 $
b1100010 #
b1100010 %
#197
b11100111 !
b11100111 &
b11000101 "
b11000101 $
#198
b11000110 "
b11000110 $
b1100011 #
b1100011 %
#199
b11000111 "
b11000111 $
#200
b11101100 !
b11101100 &
b11001000 "
b11001000 $
b1100100 #
b1100100 %
#201
b11101101 !
b11101101 &
b11001001 "
b11001001 $
#202
b11101111 !
b11101111 &
b11001010 "
b11001010 $
b1100101 #
b1100101 %
#203
b11001011 "
b11001011 $
#204
b11101110 !
b11101110 &
b11001100 "
b11001100 $
b1100110 #
b1100110 %
#205
b11101111 !
b11101111 &
b11001101 "
b11001101 $
#206
b11001110 "
b11001110 $
b1100111 #
b1100111 %
#207
b11001111 "
b11001111 $
#208
b11111000 !
b11111000 &
b11010000 "
b11010000 $
b1101000 #
b1101000 %
#209
b11111001 !
b11111001 &
b11010001 "
b11010001 $
#210
b11111011 !
b11111011 &
b11010010 "
b11010010 $
b1101001 #
b1101001 %
#211
b11010011 "
b11010011 $
#212
b11111110 !
b11111110 &
b11010100 "
b11010100 $
b1101010 #
b1101010 %
#213
b11111111 !
b11111111 &
b11010101 "
b11010101 $
#214
b11010110 "
b11010110 $
b1101011 #
b1101011 %
#215
b11010111 "
b11010111 $
#216
b11111100 !
b11111100 &
b11011000 "
b11011000 $
b1101100 #
b1101100 %
#217
b11111101 !
b11111101 &
b11011001 "
b11011001 $
#218
b11111111 !
b11111111 &
b11011010 "
b11011010 $
b1101101 #
b1101101 %
#219
b11011011 "
b11011011 $
#220
b11111110 !
b11111110 &
b11011100 "
b11011100 $
b1101110 #
b1101110 %
#221
b11111111 !
b11111111 &
b11011101 "
b11011101 $
#222
b11011110 "
b11011110 $
b1101111 #
b1101111 %
#223
b11011111 "
b11011111 $
#224
b11110000 !
b11110000 &
b11100000 "
b11100000 $
b1110000 #
b1110000 %
#225
b11110001 !
b11110001 &
b11100001 "
b11100001 $
#226
b11110011 !
b11110011 &
b11100010 "
b11100010 $
b1110001 #
b1110001 %
#227
b11100011 "
b11100011 $
#228
b11110110 !
b11110110 &
b11100100 "
b11100100 $
b1110010 #
b1110010 %
#229
b11110111 !
b11110111 &
b11100101 "
b11100101 $
#230
b11100110 "
b11100110 $
b1110011 #
b1110011 %
#231
b11100111 "
b11100111 $
#232
b11111100 !
b11111100 &
b11101000 "
b11101000 $
b1110100 #
b1110100 %
#233
b11111101 !
b11111101 &
b11101001 "
b11101001 $
#234
b11111111 !
b11111111 &
b11101010 "
b11101010 $
b1110101 #
b1110101 %
#235
b11101011 "
b11101011 $
#236
b11111110 !
b11111110 &
b11101100 "
b11101100 $
b1110110 #
b1110110 %
#237
b11111111 !
b11111111 &
b11101101 "
b11101101 $
#238
b11101110 "
b11101110 $
b1110111 #
b1110111 %
#239
b11101111 "
b11101111 $
#240
b11111000 !
b11111000 &
b11110000 "
b11110000 $
b1111000 #
b1111000 %
#241
b11111001 !
b11111001 &
b11110001 "
b11110001 $
#242
b11111011 !
b11111011 &
b11110010 "
b11110010 $
b1111001 #
b1111001 %
#243
b11110011 "
b11110011 $
#244
b11111110 !
b11111110 &
b11110100 "
b11110100 $
b1111010 #
b1111010 %
#245
b11111111 !
b11111111 &
b11110101 "
b11110101 $
#246
b11110110 "
b11110110 $
b1111011 #
b1111011 %
#247
b11110111 "
b11110111 $
#248
b11111100 !
b11111100 &
b11111000 "
b11111000 $
b1111100 #
b1111100 %
#249
b11111101 !
b11111101 &
b11111001 "
b11111001 $
#250
b11111111 !
b11111111 &
b11111010 "
b11111010 $
b1111101 #
b1111101 %
#251
b11111011 "
b11111011 $
#252
b11111110 !
b11111110 &
b11111100 "
b11111100 $
b1111110 #
b1111110 %
#253
b11111111 !
b11111111 &
b11111101 "
b11111101 $
#254
b11111110 "
b11111110 $
b1111111 #
b1111111 %
#255
b11111111 "
b11111111 $
#256
b110000000 !
b110000000 &
b100000000 "
b100000000 $
b10000000 #
b10000000 %
#257
b110000001 !
b110000001 &
b100000001 "
b100000001 $
#258
b110000011 !
b110000011 &
b100000010 "
b100000010 $
b10000001 #
b10000001 %
#259
b100000011 "
b100000011 $
#260
b110000110 !
b110000110 &
b100000100 "
b100000100 $
b10000010 #
b10000010 %
#261
b110000111 !
b110000111 &
b100000101 "
b100000101 $
#262
b100000110 "
b100000110 $
b10000011 #
b10000011 %
#263
b100000111 "
b100000111 $
#264
b110001100 !
b110001100 &
b100001000 "
b100001000 $
b10000100 #
b10000100 %
#265
b110001101 !
b110001101 &
b100001001 "
b100001001 $
#266
b110001111 !
b110001111 &
b100001010 "
b100001010 $
b10000101 #
b10000101 %
#267
b100001011 "
b100001011 $
#268
b110001110 !
b110001110 &
b100001100 "
b100001100 $
b10000110 #
b10000110 %
#269
b110001111 !
b110001111 &
b100001101 "
b100001101 $
#270
b100001110 "
b100001110 $
b10000111 #
b10000111 %
#271
b100001111 "
b100001111 $
#272
b110011000 !
b110011000 &
b100010000 "
b100010000 $
b10001000 #
b10001000 %
#273
b110011001 !
b110011001 &
b100010001 "
b100010001 $
#274
b110011011 !
b110011011 &
b100010010 "
b100010010 $
b10001001 #
b10001001 %
#275
b100010011 "
b100010011 $
#276
b110011110 !
b110011110 &
b100010100 "
b100010100 $
b10001010 #
b10001010 %
#277
b110011111 !
b110011111 &
b100010101 "
b100010101 $
#278
b100010110 "
b100010110 $
b10001011 #
b10001011 %
#279
b100010111 "
b100010111 $
#280
b110011100 !
b110011100 &
b100011000 "
b100011000 $
b10001100 #
b10001100 %
#281
b110011101 !
b110011101 &
b100011001 "
b100011001 $
#282
b110011111 !
b110011111 &
b100011010 "
b100011010 $
b10001101 #
b10001101 %
#283
b100011011 "
b100011011 $
#284
b110011110 !
b110011110 &
b100011100 "
b100011100 $
b10001110 #
b10001110 %
#285
b110011111 !
b110011111 &
b100011101 "
b100011101 $
#286
b100011110 "
b100011110 $
b10001111 #
b10001111 %
#287
b100011111 "
b100011111 $
#288
b110110000 !
b110110000 &
b100100000 "
b100100000 $
b10010000 #
b10010000 %
#289
b110110001 !
b110110001 &
b100100001 "
b100100001 $
#290
b110110011 !
b110110011 &
b100100010 "
b100100010 $
b10010001 #
b10010001 %
#291
b100100011 "
b100100011 $
#292
b110110110 !
b110110110 &
b100100100 "
b100100100 $
b10010010 #
b10010010 %
#293
b110110111 !
b110110111 &
b100100101 "
b100100101 $
#294
b100100110 "
b100100110 $
b10010011 #
b10010011 %
#295
b100100111 "
b100100111 $
#296
b110111100 !
b110111100 &
b100101000 "
b100101000 $
b10010100 #
b10010100 %
#297
b110111101 !
b110111101 &
b100101001 "
b100101001 $
#298
b110111111 !
b110111111 &
b100101010 "
b100101010 $
b10010101 #
b10010101 %
#299
b100101011 "
b100101011 $
#300
b110111110 !
b110111110 &
b100101100 "
b100101100 $
b10010110 #
b10010110 %
#301
b110111111 !
b110111111 &
b100101101 "
b100101101 $
#302
b100101110 "
b100101110 $
b10010111 #
b10010111 %
#303
b100101111 "
b100101111 $
#304
b110111000 !
b110111000 &
b100110000 "
b100110000 $
b10011000 #
b10011000 %
#305
b110111001 !
b110111001 &
b100110001 "
b100110001 $
#306
b110111011 !
b110111011 &
b100110010 "
b100110010 $
b10011001 #
b10011001 %
#307
b100110011 "
b100110011 $
#308
b110111110 !
b110111110 &
b100110100 "
b100110100 $
b10011010 #
b10011010 %
#309
b110111111 !
b110111111 &
b100110101 "
b100110101 $
#310
b100110110 "
b100110110 $
b10011011 #
b10011011 %
#311
b100110111 "
b100110111 $
#312
b110111100 !
b110111100 &
b100111000 "
b100111000 $
b10011100 #
b10011100 %
#313
b110111101 !
b110111101 &
b100111001 "
b100111001 $
#314
b110111111 !
b110111111 &
b100111010 "
b100111010 $
b10011101 #
b10011101 %
#315
b100111011 "
b100111011 $
#316
b110111110 !
b110111110 &
b100111100 "
b100111100 $
b10011110 #
b10011110 %
#317
b110111111 !
b110111111 &
b100111101 "
b100111101 $
#318
b100111110 "
b100111110 $
b10011111 #
b10011111 %
#319
b100111111 "
b100111111 $
#320
b111100000 !
b111100000 &
b101000000 "
b101000000 $
b10100000 #
b10100000 %
#321
b111100001 !
b111100001 &
b101000001 "
b101000001 $
#322
b111100011 !
b111100011 &
b101000010 "
b101000010 $
b10100001 #
b10100001 %
#323
b101000011 "
b101000011 $
#324
b111100110 !
b111100110 &
b101000100 "
b101000100 $
b10100010 #
b10100010 %
#325
b111100111 !
b111100111 &
b101000101 "
b101000101 $
#326
b101000110 "
b101000110 $
b10100011 #
b10100011 %
#327
b101000111 "
b101000111 $
#328
b111101100 !
b111101100 &
b101001000 "
b101001000 $
b10100100 #
b10100100 %
#329
b111101101 !
b111101101 &
b101001001 "
b101001001 $
#330
b111101111 !
b111101111 &
b101001010 "
b101001010 $
b10100101 #
b10100101 %
#331
b101001011 "
b101001011 $
#332
b111101110 !
b111101110 &
b101001100 "
b101001100 $
b10100110 #
b10100110 %
#333
b111101111 !
b111101111 &
b101001101 "
b101001101 $
#334
b101001110 "
b101001110 $
b10100111 #
b10100111 %
#335
b101001111 "
b101001111 $
#336
b111111000 !
b111111000 &
b101010000 "
b101010000 $
b10101000 #
b10101000 %
#337
b111111001 !
b111111001 &
b101010001 "
b101010001 $
#338
b111111011 !
b111111011 &
b101010010 "
b101010010 $
b10101001 #
b10101001 %
#339
b101010011 "
b101010011 $
#340
b111111110 !
b111111110 &
b101010100 "
b101010100 $
b10101010 #
b10101010 %
#341
b111111111 !
b111111111 &
b101010101 "
b101010101 $
#342
b101010110 "
b101010110 $
b10101011 #
b10101011 %
#343
b101010111 "
b101010111 $
#344
b111111100 !
b111111100 &
b101011000 "
b101011000 $
b10101100 #
b10101100 %
#345
b111111101 !
b111111101 &
b101011001 "
b101011001 $
#346
b111111111 !
b111111111 &
b101011010 "
b101011010 $
b10101101 #
b10101101 %
#347
b101011011 "
b101011011 $
#348
b111111110 !
b111111110 &
b101011100 "
b101011100 $
b10101110 #
b10101110 %
#349
b111111111 !
b111111111 &
b101011101 "
b101011101 $
#350
b101011110 "
b101011110 $
b10101111 #
b10101111 %
#351
b101011111 "
b101011111 $
#352
b111110000 !
b111110000 &
b101100000 "
b101100000 $
b10110000 #
b10110000 %
#353
b111110001 !
b111110001 &
b101100001 "
b101100001 $
#354
b111110011 !
b111110011 &
b101100010 "
b101100010 $
b10110001 #
b10110001 %
#355
b101100011 "
b101100011 $
#356
b111110110 !
b111110110 &
b101100100 "
b101100100 $
b10110010 #
b10110010 %
#357
b111110111 !
b111110111 &
b101100101 "
b101100101 $
#358
b101100110 "
b101100110 $
b10110011 #
b10110011 %
#359
b101100111 "
b101100111 $
#360
b111111100 !
b111111100 &
b101101000 "
b101101000 $
b10110100 #
b10110100 %
#361
b111111101 !
b111111101 &
b101101001 "
b101101001 $
#362
b111111111 !
b111111111 &
b101101010 "
b101101010 $
b10110101 #
b10110101 %
#363
b101101011 "
b101101011 $
#364
b111111110 !
b111111110 &
b101101100 "
b101101100 $
b10110110 #
b10110110 %
#365
b111111111 !
b111111111 &
b101101101 "
b101101101 $
#366
b101101110 "
b101101110 $
b10110111 #
b10110111 %
#367
b101101111 "
b101101111 $
#368
b111111000 !
b111111000 &
b101110000 "
b101110000 $
b10111000 #
b10111000 %
#369
b111111001 !
b111111001 &
b101110001 "
b101110001 $
#370
b111111011 !
b111111011 &
b101110010 "
b101110010 $
b10111001 #
b10111001 %
#371
b101110011 "
b101110011 $
#372
b111111110 !
b111111110 &
b101110100 "
b101110100 $
b10111010 #
b10111010 %
#373
b111111111 !
b111111111 &
b101110101 "
b101110101 $
#374
b101110110 "
b101110110 $
b10111011 #
b10111011 %
#375
b101110111 "
b101110111 $
#376
b111111100 !
b111111100 &
b101111000 "
b101111000 $
b10111100 #
b10111100 %
#377
b111111101 !
b111111101 &
b101111001 "
b101111001 $
#378
b111111111 !
b111111111 &
b101111010 "
b101111010 $
b10111101 #
b10111101 %
#379
b101111011 "
b101111011 $
#380
b111111110 !
b111111110 &
b101111100 "
b101111100 $
b10111110 #
b10111110 %
#381
b111111111 !
b111111111 &
b101111101 "
b101111101 $
#382
b101111110 "
b101111110 $
b10111111 #
b10111111 %
#383
b101111111 "
b101111111 $
#384
b111000000 !
b111000000 &
b110000000 "
b110000000 $
b11000000 #
b11000000 %
#385
b111000001 !
b111000001 &
b110000001 "
b110000001 $
#386
b111000011 !
b111000011 &
b110000010 "
b110000010 $
b11000001 #
b11000001 %
#387
b110000011 "
b110000011 $
#388
b111000110 !
b111000110 &
b110000100 "
b110000100 $
b11000010 #
b11000010 %
#389
b111000111 !
b111000111 &
b110000101 "
b110000101 $
#390
b110000110 "
b110000110 $
b11000011 #
b11000011 %
#391
b110000111 "
b110000111 $
#392
b111001100 !
b111001100 &
b110001000 "
b110001000 $
b11000100 #
b11000100 %
#393
b111001101 !
b111001101 &
b110001001 "
b110001001 $
#394
b111001111 !
b111001111 &
b110001010 "
b110001010 $
b11000101 #
b11000101 %
#395
b110001011 "
b110001011 $
#396
b111001110 !
b111001110 &
b110001100 "
b110001100 $
b11000110 #
b11000110 %
#397
b111001111 !
b111001111 &
b110001101 "
b110001101 $
#398
b110001110 "
b110001110 $
b11000111 #
b11000111 %
#399
b110001111 "
b110001111 $
#400
b111011000 !
b111011000 &
b110010000 "
b110010000 $
b11001000 #
b11001000 %
#401
b111011001 !
b111011001 &
b110010001 "
b110010001 $
#402
b111011011 !
b111011011 &
b110010010 "
b110010010 $
b11001001 #
b11001001 %
#403
b110010011 "
b110010011 $
#404
b111011110 !
b111011110 &
b110010100 "
b110010100 $
b11001010 #
b11001010 %
#405
b111011111 !
b111011111 &
b110010101 "
b110010101 $
#406
b110010110 "
b110010110 $
b11001011 #
b11001011 %
#407
b110010111 "
b110010111 $
#408
b111011100 !
b111011100 &
b110011000 "
b110011000 $
b11001100 #
b11001100 %
#409
b111011101 !
b111011101 &
b110011001 "
b110011001 $
#410
b111011111 !
b111011111 &
b110011010 "
b110011010 $
b11001101 #
b11001101 %
#411
b110011011 "
b110011011 $
#412
b111011110 !
b111011110 &
b110011100 "
b110011100 $
b11001110 #
b11001110 %
#413
b111011111 !
b111011111 &
b110011101 "
b110011101 $
#414
b110011110 "
b110011110 $
b11001111 #
b11001111 %
#415
b110011111 "
b110011111 $
#416
b111110000 !
b111110000 &
b110100000 "
b110100000 $
b11010000 #
b11010000 %
#417
b111110001 !
b111110001 &
b110100001 "
b110100001 $
#418
b111110011 !
b111110011 &
b110100010 "
b110100010 $
b11010001 #
b11010001 %
#419
b110100011 "
b110100011 $
#420
b111110110 !
b111110110 &
b110100100 "
b110100100 $
b11010010 #
b11010010 %
#421
b111110111 !
b111110111 &
b110100101 "
b110100101 $
#422
b110100110 "
b110100110 $
b11010011 #
b11010011 %
#423
b110100111 "
b110100111 $
#424
b111111100 !
b111111100 &
b110101000 "
b110101000 $
b11010100 #
b11010100 %
#425
b111111101 !
b111111101 &
b110101001 "
b110101001 $
#426
b111111111 !
b111111111 &
b110101010 "
b110101010 $
b11010101 #
b11010101 %
#427
b110101011 "
b110101011 $
#428
b111111110 !
b111111110 &
b110101100 "
b110101100 $
b11010110 #
b11010110 %
#429
b111111111 !
b111111111 &
b110101101 "
b110101101 $
#430
b110101110 "
b110101110 $
b11010111 #
b11010111 %
#431
b110101111 "
b110101111 $
#432
b111111000 !
b111111000 &
b110110000 "
b110110000 $
b11011000 #
b11011000 %
#433
b111111001 !
b111111001 &
b110110001 "
b110110001 $
#434
b111111011 !
b111111011 &
b110110010 "
b110110010 $
b11011001 #
b11011001 %
#435
b110110011 "
b110110011 $
#436
b111111110 !
b111111110 &
b110110100 "
b110110100 $
b11011010 #
b11011010 %
#437
b111111111 !
b111111111 &
b110110101 "
b110110101 $
#438
b110110110 "
b110110110 $
b11011011 #
b11011011 %
#439
b110110111 "
b110110111 $
#440
b111111100 !
b111111100 &
b110111000 "
b110111000 $
b11011100 #
b11011100 %
#441
b111111101 !
b111111101 &
b110111001 "
b110111001 $
#442
b111111111 !
b111111111 &
b110111010 "
b110111010 $
b11011101 #
b11011101 %
#443
b110111011 "
b110111011 $
#444
b111111110 !
b111111110 &
b110111100 "
b110111100 $
b11011110 #
b11011110 %
#445
b111111111 !
b111111111 &
b110111101 "
b110111101 $
#446
b110111110 "
b110111110 $
b11011111 #
b11011111 %
#447
b110111111 "
b110111111 $
#448
b111100000 !
b111100000 &
b111000000 "
b111000000 $
b11100000 #
b11100000 %
#449
b111100001 !
b111100001 &
b111000001 "
b111000001 $
